Workbook

Sheet Final Calculation Sheet
B1: MSTC LIMITED - COMBINED BID SHEET (Auctions 21977, 21978, 21979, 21980)
A3: Quantity | B3: Lot Name | C3: Rate | D3: Bid Sheet | E3: Unit | F3: Lot No. | G3: Buyer | H3: Mat. Value | I3: GST | J3: Mat. Value + GST | K3: TCS | L3: TDS u/s 194(O) | M3: Service Charge to MSTC | N3: TDS u/s 194(H) | O3: Net Service Charge (post TDS 194H) | P3: Service charge to MSTC | Q3: GST TDS Rate | R3: GST TDS | S3: Total Receivables in Cash | T3: Security Deposit (Expected) | U3: Security Deposit (Received) | V3: Date of Receipt | W3: Final Payment (Expected) | X3: Final Payment (Received) | Y3: Date of Receipt | Z3: LPP Expected | AA3: LPP Received | AB3: Date of Recepit of LPP | AC3: Total Received | AD3: Outstanding | AE3: Invoice No. | AF3: SAP Document | AG3: Doc./Invoice Date
A4: 669 | B4: SCRAP COPPER OF T/F WINDING (Oil impregnated paper insulated T/F winding) | C4: 1181 | D4: 21980 | E4: KG | F4: 1763 | G4: AL HAMD TRADE CORPORATION | H4: 790089 | I4: =ROUND(H4*18%,0) | J4: =+H4+I4 | K4: =ROUND((H4+I4)*2%,0) | L4: =H4*0.1% | M4: =H4*2.25%*118% | N4: =H4*2.25%*2% | O4: =M4-N4 | P4: =ROUND(O4+L4,0) | Q4: 0.02 | R4: =ROUND(H4*Q4,0) | S4: =ROUND(H4*117.65%-R4,0) | T4: =ROUND(H4*25%,0) | U4: 197522 | V4: 24.08.2026 | W4: =ROUND(H4*92.65%-R4,0) | X4: 716216 | Y4: 18.08.2026 | Z4: =IF(OR(Y4="",Y4=0),H4*0.0118*CEILING((TODAY()-DATE(2026,8,22))/7,1),IF(DATE(VALUE(RIGHT(Y4,4)),VALUE(MID(Y4,4,2)),VALUE(LEFT(Y4,2)))<=DATE(2026,8,24),0,H4*0.0118*CEILING((DATE(VALUE(RIGHT(Y4,4)),VALUE(MID(Y4,4,2)),VALUE(LEFT(Y4,2)))-DATE(2026,8,22))/7,1))) | AC4: =U4+X4+AA4 | AD4: =S4-AC4 | AE4: DR2640100029 | AF4: 1800003271 | AG4: 24.08.2026
A5: 270 | B5: Scrap of Empty oil drum | C5: 580 | D5: 21977 | E5: NO | F5: 1874 | G5: NATIONAL ENTERPRISES | H5: 156600 | I5: =ROUND(H5*18%,0) | J5: =+H5+I5 | K5: =ROUND((H5+I5)*2%,0) | L5: =H5*0.1% | M5: =H5*2.25%*118% | N5: =H5*2.25%*2% | O5: =M5-N5 | P5: =ROUND(O5+L5,0) | Q5: 0 | R5: =ROUND(H5*Q5,0) | S5: =ROUND(H5*117.65%-R5,0) | T5: =ROUND(H5*25%,0) | U5: =+T5 | V5: 13.08.2026 | W5: =ROUND(H5*92.65%-R5,0) | X5: 145090 | Y5: 24.08.2026 | Z5: =IF(OR(Y5="",Y5=0),H5*0.0118*CEILING((TODAY()-DATE(2026,8,22))/7,1),IF(DATE(VALUE(RIGHT(Y5,4)),VALUE(MID(Y5,4,2)),VALUE(LEFT(Y5,2)))<=DATE(2026,8,24),0,H5*0.0118*CEILING((DATE(VALUE(RIGHT(Y5,4)),VALUE(MID(Y5,4,2)),VALUE(LEFT(Y5,2)))-DATE(2026,8,22))/7,1))) | AC5: =U5+X5+AA5 | AD5: =S5-AC5 | AE5: DR2640100030 | AF5: 1800003302 | AG5: 27.08.2026
A6: 28 | B6: Scrap of Copper of faulty AC compressor | C6: 1456 | D6: 21977 | E6: KG | F6: 1875 | G6: F R KHANS ENTERPRISES | H6: 40768 | I6: =ROUND(H6*18%,0) | J6: =+H6+I6 | K6: =ROUND((H6+I6)*2%,0) | L6: =H6*0.1% | M6: =H6*2.25%*118% | N6: =H6*2.25%*2% | O6: =M6-N6 | P6: =ROUND(O6+L6,0) | Q6: 0 | R6: =ROUND(H6*Q6,0) | S6: =ROUND(H6*117.65%-R6,0) | T6: =ROUND(H6*25%,0) | U6: 10192 | V6: 11.08.2026 | W6: =ROUND(H6*92.65%-R6,0) | X6: =+W6+R6 | Y6: 20.08.2026 | Z6: =IF(OR(Y6="",Y6=0),H6*0.0118*CEILING((TODAY()-DATE(2026,8,22))/7,1),IF(DATE(VALUE(RIGHT(Y6,4)),VALUE(MID(Y6,4,2)),VALUE(LEFT(Y6,2)))<=DATE(2026,8,24),0,H6*0.0118*CEILING((DATE(VALUE(RIGHT(Y6,4)),VALUE(MID(Y6,4,2)),VALUE(LEFT(Y6,2)))-DATE(2026,8,22))/7,1))) | AC6: =U6+X6+AA6 | AD6: =S6-AC6 | AE6: DR2640100047 | AF6: 1800003346 | AG6: 27.08.2026
A7: 3000 | B7: Scrap of MS (extracted from equip cage and empty Sf6 gas cylinder) | C7: 66 | D7: 21977 | E7: KG | F7: 1876 | G7: F R KHANS ENTERPRISES | H7: 198000 | I7: =ROUND(H7*18%,0) | J7: =+H7+I7 | K7: =ROUND((H7+I7)*2%,0) | L7: =H7*0.1% | M7: =H7*2.25%*118% | N7: =H7*2.25%*2% | O7: =M7-N7 | P7: =ROUND(O7+L7,0) | Q7: 0 | R7: =ROUND(H7*Q7,0) | S7: =ROUND(H7*117.65%-R7,0) | T7: =ROUND(H7*25%,0) | U7: 49500 | V7: 11.08.2026 | W7: =ROUND(H7*92.65%-R7,0) | X7: =+W7+R7-1 | Y7: 20.08.2026 | Z7: =IF(OR(Y7="",Y7=0),H7*0.0118*CEILING((TODAY()-DATE(2026,8,22))/7,1),IF(DATE(VALUE(RIGHT(Y7,4)),VALUE(MID(Y7,4,2)),VALUE(LEFT(Y7,2)))<=DATE(2026,8,24),0,H7*0.0118*CEILING((DATE(VALUE(RIGHT(Y7,4)),VALUE(MID(Y7,4,2)),VALUE(LEFT(Y7,2)))-DATE(2026,8,22))/7,1))) | AC7: =U7+X7+AA7 | AD7: =S7-AC7 | AE7: DR2640100048 | AF7: 1800003347 | AG7: 27.08.2026
A8: 7253 | B8: SCRAP ACSR CONDUCTORS (Conductor Pieces) | C8: 227 | D8: 21980 | E8: KG | F8: 1923 | G8: OMKAR STEELS | H8: 1646431 | I8: =ROUND(H8*18%,0) | J8: =+H8+I8 | K8: =ROUND((H8+I8)*2%,0) | L8: =H8*0.1% | M8: =H8*2.25%*118% | N8: =H8*2.25%*2% | O8: =M8-N8 | P8: =ROUND(O8+L8,0) | Q8: 0.02 | R8: =ROUND(H8*Q8,0) | S8: =ROUND(H8*117.65%-R8,0) | T8: =ROUND(H8*25%,0) | U8: =+T8 | V8: 14.08.2026 | W8: =ROUND(H8*92.65%-R8,0) | X8: 1492490 | Y8: 24.08.2026 | Z8: =IF(OR(Y8="",Y8=0),H8*0.0118*CEILING((TODAY()-DATE(2026,8,22))/7,1),IF(DATE(VALUE(RIGHT(Y8,4)),VALUE(MID(Y8,4,2)),VALUE(LEFT(Y8,2)))<=DATE(2026,8,24),0,H8*0.0118*CEILING((DATE(VALUE(RIGHT(Y8,4)),VALUE(MID(Y8,4,2)),VALUE(LEFT(Y8,2)))-DATE(2026,8,22))/7,1))) | AC8: =U8+X8+AA8 | AD8: =S8-AC8 | AE8: DR2640100045 | AF8: 1800003315 | AG8: 27.08.2026
A9: 1 | B9: Scrap Power Transformer | C9: 2787314 | D9: 21977 | E9: NO | F9: 1976 | G9: SHAR JAHAN TRADERS | H9: 2787314 | I9: =ROUND(H9*18%,0) | J9: =+H9+I9 | K9: =ROUND((H9+I9)*2%,0) | L9: =H9*0.1% | M9: =H9*2.25%*118% | N9: =H9*2.25%*2% | O9: =M9-N9 | P9: =ROUND(O9+L9,0) | Q9: 0 | R9: =ROUND(H9*Q9,0) | S9: =ROUND(H9*117.65%-R9,0) | T9: =ROUND(H9*25%,0) | U9: =+T9 | V9: 13.08.2026 | W9: =ROUND(H9*92.65%-R9,0) | X9: 2582447.1 | Y9: 13.08.2026 | Z9: =IF(OR(Y9="",Y9=0),H9*0.0118*CEILING((TODAY()-DATE(2026,8,22))/7,1),IF(DATE(VALUE(RIGHT(Y9,4)),VALUE(MID(Y9,4,2)),VALUE(LEFT(Y9,2)))<=DATE(2026,8,24),0,H9*0.0118*CEILING((DATE(VALUE(RIGHT(Y9,4)),VALUE(MID(Y9,4,2)),VALUE(LEFT(Y9,2)))-DATE(2026,8,22))/7,1))) | AC9: =U9+X9+AA9 | AD9: =S9-AC9 | AE9: DR2640100023 | AF9: 1800003194 | AG9: 17.08.2026
A10: 4 | B10: Scrap of 132 KV CT | C10: 51511 | D10: 21977 | E10: NO | F10: 2002 | G10: NATIONAL ENTERPRISES | H10: 206044 | I10: =ROUND(H10*18%,0) | J10: =+H10+I10 | K10: =ROUND((H10+I10)*2%,0) | L10: =H10*0.1% | M10: =H10*2.25%*118% | N10: =H10*2.25%*2% | O10: =M10-N10 | P10: =ROUND(O10+L10,0) | Q10: 0 | R10: =ROUND(H10*Q10,0) | S10: =ROUND(H10*117.65%-R10,0) | T10: =ROUND(H10*25%,0) | U10: =+T10 | V10: 13.08.2026 | W10: =ROUND(H10*92.65%-R10,0) | X10: 190900 | Y10: 24.08.2026 | Z10: =IF(OR(Y10="",Y10=0),H10*0.0118*CEILING((TODAY()-DATE(2026,8,22))/7,1),IF(DATE(VALUE(RIGHT(Y10,4)),VALUE(MID(Y10,4,2)),VALUE(LEFT(Y10,2)))<=DATE(2026,8,24),0,H10*0.0118*CEILING((DATE(VALUE(RIGHT(Y10,4)),VALUE(MID(Y10,4,2)),VALUE(LEFT(Y10,2)))-DATE(2026,8,22))/7,1))) | AC10: =U10+X10+AA10 | AD10: =S10-AC10 | AE10: DR2640100031 | AF10: 1800003303 | AG10: 27.08.2026
A11: 1 | B11: Scrap of 145 KV CB | C11: 65007 | D11: 21977 | E11: NO | F11: 2003 | G11: NATIONAL ENTERPRISES | H11: 65007 | I11: =ROUND(H11*18%,0) | J11: =+H11+I11 | K11: =ROUND((H11+I11)*2%,0) | L11: =H11*0.1% | M11: =H11*2.25%*118% | N11: =H11*2.25%*2% | O11: =M11-N11 | P11: =ROUND(O11+L11,0) | Q11: 0 | R11: =ROUND(H11*Q11,0) | S11: =ROUND(H11*117.65%-R11,0) | T11: =ROUND(H11*25%,0) | U11: =+T11 | V11: 13.08.2026 | W11: =ROUND(H11*92.65%-R11,0) | X11: 60229 | Y11: 24.08.2026 | Z11: =IF(OR(Y11="",Y11=0),H11*0.0118*CEILING((TODAY()-DATE(2026,8,22))/7,1),IF(DATE(VALUE(RIGHT(Y11,4)),VALUE(MID(Y11,4,2)),VALUE(LEFT(Y11,2)))<=DATE(2026,8,24),0,H11*0.0118*CEILING((DATE(VALUE(RIGHT(Y11,4)),VALUE(MID(Y11,4,2)),VALUE(LEFT(Y11,2)))-DATE(2026,8,22))/7,1))) | AC11: =U11+X11+AA11 | AD11: =S11-AC11 | AE11: DR2640100032 | AF11: 1800003304 | AG11: 27.08.2026
A12: 1 | B12: Scrap of 220KV CT | C12: 70006 | D12: 21977 | E12: NO | F12: 2005 | G12: NATIONAL ENTERPRISES | H12: 70006 | I12: =ROUND(H12*18%,0) | J12: =+H12+I12 | K12: =ROUND((H12+I12)*2%,0) | L12: =H12*0.1% | M12: =H12*2.25%*118% | N12: =H12*2.25%*2% | O12: =M12-N12 | P12: =ROUND(O12+L12,0) | Q12: 0 | R12: =ROUND(H12*Q12,0) | S12: =ROUND(H12*117.65%-R12,0) | T12: =ROUND(H12*25%,0) | U12: =+T12 | V12: 13.08.2026 | W12: =ROUND(H12*92.65%-R12,0) | X12: 64859 | Y12: 24.08.2026 | Z12: =IF(OR(Y12="",Y12=0),H12*0.0118*CEILING((TODAY()-DATE(2026,8,22))/7,1),IF(DATE(VALUE(RIGHT(Y12,4)),VALUE(MID(Y12,4,2)),VALUE(LEFT(Y12,2)))<=DATE(2026,8,24),0,H12*0.0118*CEILING((DATE(VALUE(RIGHT(Y12,4)),VALUE(MID(Y12,4,2)),VALUE(LEFT(Y12,2)))-DATE(2026,8,22))/7,1))) | AC12: =U12+X12+AA12 | AD12: =S12-AC12 | AE12: DR2640100033 | AF12: 1800003305 | AG12: 27.08.2026
A13: 25 | B13: Scrap of empty oil drums | C13: 700 | D13: 21977 | E13: NO | F13: 2006 | G13: STERLING ENTERPRISES | H13: 17500 | I13: =ROUND(H13*18%,0) | J13: =+H13+I13 | K13: =ROUND((H13+I13)*2%,0) | L13: =H13*0.1% | M13: =H13*2.25%*118% | N13: =H13*2.25%*2% | O13: =M13-N13 | P13: =ROUND(O13+L13,0) | Q13: 0 | R13: =ROUND(H13*Q13,0) | S13: =ROUND(H13*117.65%-R13,0) | T13: =ROUND(H13*25%,0) | U13: 4375 | V13: 11.08.2026 | W13: =ROUND(H13*92.65%-R13,0) | X13: 16214 | Y13: 11.08.2026 | Z13: =IF(OR(Y13="",Y13=0),H13*0.0118*CEILING((TODAY()-DATE(2026,8,22))/7,1),IF(DATE(VALUE(RIGHT(Y13,4)),VALUE(MID(Y13,4,2)),VALUE(LEFT(Y13,2)))<=DATE(2026,8,24),0,H13*0.0118*CEILING((DATE(VALUE(RIGHT(Y13,4)),VALUE(MID(Y13,4,2)),VALUE(LEFT(Y13,2)))-DATE(2026,8,22))/7,1))) | AC13: =U13+X13+AA13 | AD13: =S13-AC13 | AE13: DR2640100018 | AF13: 1800003156 | AG13: 14.08.2026
A14: 1 | B14: SCRAP POWER TRANSFORMER | C14: 3857116 | D14: 21977 | E14: NO | F14: 2007 | G14: SHAR JAHAN TRADERS | H14: 3857116 | I14: =ROUND(H14*18%,0) | J14: =+H14+I14 | K14: =ROUND((H14+I14)*2%,0) | L14: =H14*0.1% | M14: =H14*2.25%*118% | N14: =H14*2.25%*2% | O14: =M14-N14 | P14: =ROUND(O14+L14,0) | Q14: 0 | R14: =ROUND(H14*Q14,0) | S14: =ROUND(H14*117.65%-R14,0) | T14: =ROUND(H14*25%,0) | U14: =+T14 | V14: 13.08.2026 | W14: =ROUND(H14*92.65%-R14,0) | X14: 3573618.9 | Y14: 13.08.2026 | Z14: =IF(OR(Y14="",Y14=0),H14*0.0118*CEILING((TODAY()-DATE(2026,8,22))/7,1),IF(DATE(VALUE(RIGHT(Y14,4)),VALUE(MID(Y14,4,2)),VALUE(LEFT(Y14,2)))<=DATE(2026,8,24),0,H14*0.0118*CEILING((DATE(VALUE(RIGHT(Y14,4)),VALUE(MID(Y14,4,2)),VALUE(LEFT(Y14,2)))-DATE(2026,8,22))/7,1))) | AC14: =U14+X14+AA14 | AD14: =S14-AC14 | AE14: DR2640100024 | AF14: 1800003196 | AG14: 17.08.2026
A15: 250 | B15: Scrap of empty oil Druam | C15: 543 | D15: 21977 | E15: NO | F15: 2008 | G15: HIND TRADERS | H15: 135750 | I15: =ROUND(H15*18%,0) | J15: =+H15+I15 | K15: =ROUND((H15+I15)*2%,0) | L15: =H15*0.1% | M15: =H15*2.25%*118% | N15: =H15*2.25%*2% | O15: =M15-N15 | P15: =ROUND(O15+L15,0) | Q15: 0 | R15: =ROUND(H15*Q15,0) | S15: =ROUND(H15*117.65%-R15,0) | T15: =ROUND(H15*25%,0) | U15: 33938 | V15: 14.08.2026 | W15: =ROUND(H15*92.65%-R15,0) | X15: 125772 | Y15: 18.08.2026 | Z15: =IF(OR(Y15="",Y15=0),H15*0.0118*CEILING((TODAY()-DATE(2026,8,22))/7,1),IF(DATE(VALUE(RIGHT(Y15,4)),VALUE(MID(Y15,4,2)),VALUE(LEFT(Y15,2)))<=DATE(2026,8,24),0,H15*0.0118*CEILING((DATE(VALUE(RIGHT(Y15,4)),VALUE(MID(Y15,4,2)),VALUE(LEFT(Y15,2)))-DATE(2026,8,22))/7,1))) | AC15: =U15+X15+AA15 | AD15: =S15-AC15 | AE15: DR2640100026 | AF15: 1800003247 | AG15: 20.08.2026
A16: 22 | B16: Scrap of empty oil Barrel | C16: 700 | D16: 21977 | E16: NO | F16: 2011 | G16: STERLING ENTERPRISES | H16: 15400 | I16: =ROUND(H16*18%,0) | J16: =+H16+I16 | K16: =ROUND((H16+I16)*2%,0) | L16: =H16*0.1% | M16: =H16*2.25%*118% | N16: =H16*2.25%*2% | O16: =M16-N16 | P16: =ROUND(O16+L16,0) | Q16: 0 | R16: =ROUND(H16*Q16,0) | S16: =ROUND(H16*117.65%-R16,0) | T16: =ROUND(H16*25%,0) | U16: 3850 | V16: 11.08.2026 | W16: =ROUND(H16*92.65%-R16,0) | X16: 14267 | Y16: 11.08.2026 | Z16: =IF(OR(Y16="",Y16=0),H16*0.0118*CEILING((TODAY()-DATE(2026,8,22))/7,1),IF(DATE(VALUE(RIGHT(Y16,4)),VALUE(MID(Y16,4,2)),VALUE(LEFT(Y16,2)))<=DATE(2026,8,24),0,H16*0.0118*CEILING((DATE(VALUE(RIGHT(Y16,4)),VALUE(MID(Y16,4,2)),VALUE(LEFT(Y16,2)))-DATE(2026,8,22))/7,1))) | AC16: =U16+X16+AA16 | AD16: =S16-AC16 | AE16: DR2640100019 | AF16: 1800003157 | AG16: 14.08.2026
A17: 100 | B17: Scrap of empty oil Barrels | C17: 710 | D17: 21978 | E17: NO | F17: 2015 | G17: STERLING ENTERPRISES | H17: 71000 | I17: =ROUND(H17*18%,0) | J17: =+H17+I17 | K17: =ROUND((H17+I17)*2%,0) | L17: =H17*0.1% | M17: =H17*2.25%*118% | N17: =H17*2.25%*2% | O17: =M17-N17 | P17: =ROUND(O17+L17,0) | Q17: 0 | R17: =ROUND(H17*Q17,0) | S17: =ROUND(H17*117.65%-R17,0) | T17: =ROUND(H17*25%,0) | U17: 17750 | V17: 11.08.2026 | W17: =ROUND(H17*92.65%-R17,0) | X17: =+W17 | Y17: 11.08.2026 | Z17: =IF(OR(Y17="",Y17=0),H17*0.0118*CEILING((TODAY()-DATE(2026,8,22))/7,1),IF(DATE(VALUE(RIGHT(Y17,4)),VALUE(MID(Y17,4,2)),VALUE(LEFT(Y17,2)))<=DATE(2026,8,24),0,H17*0.0118*CEILING((DATE(VALUE(RIGHT(Y17,4)),VALUE(MID(Y17,4,2)),VALUE(LEFT(Y17,2)))-DATE(2026,8,22))/7,1))) | AC17: =U17+X17+AA17 | AD17: =S17-AC17 | AE17: DR2640100020 | AF17: 1800003158 | AG17: 14.08.2026
A18: 1 | B18: Scrap of 220 KV Circuit Breaker | C18: 220001 | D18: 21978 | E18: NO | F18: 2018 | G18: NATIONAL ENTERPRISES | H18: 220001 | I18: =ROUND(H18*18%,0) | J18: =+H18+I18 | K18: =ROUND((H18+I18)*2%,0) | L18: =H18*0.1% | M18: =H18*2.25%*118% | N18: =H18*2.25%*2% | O18: =M18-N18 | P18: =ROUND(O18+L18,0) | Q18: 0 | R18: =ROUND(H18*Q18,0) | S18: =ROUND(H18*117.65%-R18,0) | T18: =ROUND(H18*25%,0) | U18: =+T18 | V18: 13.08.2026 | W18: =ROUND(H18*92.65%-R18,0) | X18: 203831 | Y18: 24.08.2026 | Z18: =IF(OR(Y18="",Y18=0),H18*0.0118*CEILING((TODAY()-DATE(2026,8,22))/7,1),IF(DATE(VALUE(RIGHT(Y18,4)),VALUE(MID(Y18,4,2)),VALUE(LEFT(Y18,2)))<=DATE(2026,8,24),0,H18*0.0118*CEILING((DATE(VALUE(RIGHT(Y18,4)),VALUE(MID(Y18,4,2)),VALUE(LEFT(Y18,2)))-DATE(2026,8,22))/7,1))) | AC18: =U18+X18+AA18 | AD18: =S18-AC18 | AE18: DR2640100034 | AF18: 1800003306 | AG18: 27.08.2026
A19: 1 | B19: Scrap of 220 KV Circuit Breaker | C19: 210001 | D19: 21978 | E19: NO | F19: 2019 | G19: NATIONAL ENTERPRISES | H19: 210001 | I19: =ROUND(H19*18%,0) | J19: =+H19+I19 | K19: =ROUND((H19+I19)*2%,0) | L19: =H19*0.1% | M19: =H19*2.25%*118% | N19: =H19*2.25%*2% | O19: =M19-N19 | P19: =ROUND(O19+L19,0) | Q19: 0 | R19: =ROUND(H19*Q19,0) | S19: =ROUND(H19*117.65%-R19,0) | T19: =ROUND(H19*25%,0) | U19: =+T19 | V19: 13.08.2026 | W19: =ROUND(H19*92.65%-R19,0) | X19: 194566 | Y19: 24.08.2026 | Z19: =IF(OR(Y19="",Y19=0),H19*0.0118*CEILING((TODAY()-DATE(2026,8,22))/7,1),IF(DATE(VALUE(RIGHT(Y19,4)),VALUE(MID(Y19,4,2)),VALUE(LEFT(Y19,2)))<=DATE(2026,8,24),0,H19*0.0118*CEILING((DATE(VALUE(RIGHT(Y19,4)),VALUE(MID(Y19,4,2)),VALUE(LEFT(Y19,2)))-DATE(2026,8,22))/7,1))) | AC19: =U19+X19+AA19 | AD19: =S19-AC19 | AE19: DR2640100035 | AF19: 1800003307 | AG19: 27.08.2026
A20: 3500 | B20: SCRAP 80MM² AAAC EARTHWIRE | C20: 333 | D20: 21978 | E20: KG | F20: 2020 | G20: OMKAR STEELS | H20: 1165500 | I20: =ROUND(H20*18%,0) | J20: =+H20+I20 | K20: =ROUND((H20+I20)*2%,0) | L20: =H20*0.1% | M20: =H20*2.25%*118% | N20: =H20*2.25%*2% | O20: =M20-N20 | P20: =ROUND(O20+L20,0) | Q20: 0.02 | R20: =ROUND(H20*Q20,0) | S20: =ROUND(H20*117.65%-R20,0) | T20: =ROUND(H20*25%,0) | U20: 291375 | V20: 10.08.2026 | W20: =ROUND(H20*92.65%-R20,0) | X20: 1056525 | Y20: 10.08.2026 | Z20: =IF(OR(Y20="",Y20=0),H20*0.0118*CEILING((TODAY()-DATE(2026,8,22))/7,1),IF(DATE(VALUE(RIGHT(Y20,4)),VALUE(MID(Y20,4,2)),VALUE(LEFT(Y20,2)))<=DATE(2026,8,24),0,H20*0.0118*CEILING((DATE(VALUE(RIGHT(Y20,4)),VALUE(MID(Y20,4,2)),VALUE(LEFT(Y20,2)))-DATE(2026,8,22))/7,1))) | AC20: =U20+X20+AA20 | AD20: =S20-AC20 | AE20: DR2640100017 | AF20: 1800003065 | AG20: 12.08.2026
A21: 3 | B21: Scrap of 132 KV CT | C21: 110200 | D21: 21978 | E21: NO | F21: 2022 | G21: NATIONAL SCRAP AND BUILDING MATERIAL SUPPLIER | H21: 330600 | I21: =ROUND(H21*18%,0) | J21: =+H21+I21 | K21: =ROUND((H21+I21)*2%,0) | L21: =H21*0.1% | M21: =H21*2.25%*118% | N21: =H21*2.25%*2% | O21: =M21-N21 | P21: =ROUND(O21+L21,0) | Q21: 0 | R21: =ROUND(H21*Q21,0) | S21: =ROUND(H21*117.65%-R21,0) | T21: =ROUND(H21*25%,0) | U21: =+T21 | V21: 14.08.2026 | W21: =ROUND(H21*92.65%-R21,0) | X21: 306301 | Y21: 21.08.2026 | Z21: =IF(OR(Y21="",Y21=0),H21*0.0118*CEILING((TODAY()-DATE(2026,8,22))/7,1),IF(DATE(VALUE(RIGHT(Y21,4)),VALUE(MID(Y21,4,2)),VALUE(LEFT(Y21,2)))<=DATE(2026,8,24),0,H21*0.0118*CEILING((DATE(VALUE(RIGHT(Y21,4)),VALUE(MID(Y21,4,2)),VALUE(LEFT(Y21,2)))-DATE(2026,8,22))/7,1))) | AC21: =U21+X21+AA21 | AD21: =S21-AC21 | AE21: DR2640100028 | AF21: 1800003269 | AG21: 24.08.2026
A22: 3 | B22: Scrap of 132 KV CT | C22: 83743 | D22: 21978 | E22: NO | F22: 2023 | G22: NATIONAL ENTERPRISES | H22: 251229 | I22: =ROUND(H22*18%,0) | J22: =+H22+I22 | K22: =ROUND((H22+I22)*2%,0) | L22: =H22*0.1% | M22: =H22*2.25%*118% | N22: =H22*2.25%*2% | O22: =M22-N22 | P22: =ROUND(O22+L22,0) | Q22: 0 | R22: =ROUND(H22*Q22,0) | S22: =ROUND(H22*117.65%-R22,0) | T22: =ROUND(H22*25%,0) | U22: =+T22 | V22: 13.08.2026 | W22: =ROUND(H22*92.65%-R22,0) | X22: 232764 | Y22: 24.08.2026 | Z22: =IF(OR(Y22="",Y22=0),H22*0.0118*CEILING((TODAY()-DATE(2026,8,22))/7,1),IF(DATE(VALUE(RIGHT(Y22,4)),VALUE(MID(Y22,4,2)),VALUE(LEFT(Y22,2)))<=DATE(2026,8,24),0,H22*0.0118*CEILING((DATE(VALUE(RIGHT(Y22,4)),VALUE(MID(Y22,4,2)),VALUE(LEFT(Y22,2)))-DATE(2026,8,22))/7,1))) | AC22: =U22+X22+AA22 | AD22: =S22-AC22 | AE22: DR2640100044 | AF22: 1800003308 | AG22: 27.08.2026
A23: 90 | B23: Scrap of empty oil Barrels | C23: 700 | D23: 21978 | E23: NO | F23: 2025 | G23: STERLING ENTERPRISES | H23: 63000 | I23: =ROUND(H23*18%,0) | J23: =+H23+I23 | K23: =ROUND((H23+I23)*2%,0) | L23: =H23*0.1% | M23: =H23*2.25%*118% | N23: =H23*2.25%*2% | O23: =M23-N23 | P23: =ROUND(O23+L23,0) | Q23: 0 | R23: =ROUND(H23*Q23,0) | S23: =ROUND(H23*117.65%-R23,0) | T23: =ROUND(H23*25%,0) | U23: 15750 | V23: 11.08.2026 | W23: =ROUND(H23*92.65%-R23,0) | X23: 58418 | Y23: 11.08.2026 | Z23: =IF(OR(Y23="",Y23=0),H23*0.0118*CEILING((TODAY()-DATE(2026,8,22))/7,1),IF(DATE(VALUE(RIGHT(Y23,4)),VALUE(MID(Y23,4,2)),VALUE(LEFT(Y23,2)))<=DATE(2026,8,24),0,H23*0.0118*CEILING((DATE(VALUE(RIGHT(Y23,4)),VALUE(MID(Y23,4,2)),VALUE(LEFT(Y23,2)))-DATE(2026,8,22))/7,1))) | AC23: =U23+X23+AA23 | AD23: =S23-AC23 | AE23: DR2640100021 | AF23: 1800003160 | AG23: 14.08.2026
A24: 1 | B24: Scrap of 132 KV CT | C24: 50003 | D24: 21978 | E24: NO | F24: 2027 | G24: NATIONAL ENTERPRISES | H24: 50003 | I24: =ROUND(H24*18%,0) | J24: =+H24+I24 | K24: =ROUND((H24+I24)*2%,0) | L24: =H24*0.1% | M24: =H24*2.25%*118% | N24: =H24*2.25%*2% | O24: =M24-N24 | P24: =ROUND(O24+L24,0) | Q24: 0 | R24: =ROUND(H24*Q24,0) | S24: =ROUND(H24*117.65%-R24,0) | T24: =ROUND(H24*25%,0) | U24: =+T24 | V24: 13.08.2026 | W24: =ROUND(H24*92.65%-R24,0) | X24: 46328 | Y24: 24.08.2026 | Z24: =IF(OR(Y24="",Y24=0),H24*0.0118*CEILING((TODAY()-DATE(2026,8,22))/7,1),IF(DATE(VALUE(RIGHT(Y24,4)),VALUE(MID(Y24,4,2)),VALUE(LEFT(Y24,2)))<=DATE(2026,8,24),0,H24*0.0118*CEILING((DATE(VALUE(RIGHT(Y24,4)),VALUE(MID(Y24,4,2)),VALUE(LEFT(Y24,2)))-DATE(2026,8,22))/7,1))) | AC24: =U24+X24+AA24 | AD24: =S24-AC24 | AE24: DR2640100036 | AF24: 1800003309 | AG24: 27.08.2026
A25: 1000 | B25: Scrap Empty Oil Drum/ Barrel | C25: 517 | D25: 21978 | E25: NO | F25: 2033 | G25: WATAN SCRAP TRADERS | H25: 517000 | I25: =ROUND(H25*18%,0) | J25: =+H25+I25 | K25: =ROUND((H25+I25)*2%,0) | L25: =H25*0.1% | M25: =H25*2.25%*118% | N25: =H25*2.25%*2% | O25: =M25-N25 | P25: =ROUND(O25+L25,0) | Q25: 0 | R25: =ROUND(H25*Q25,0) | S25: =ROUND(H25*117.65%-R25,0) | T25: =ROUND(H25*25%,0) | U25: 129250 | V25: 14.08.2026 | W25: =ROUND(H25*92.65%-R25,0) | X25: 479001 | Y25: 21.08.2026 | Z25: =IF(OR(Y25="",Y25=0),H25*0.0118*CEILING((TODAY()-DATE(2026,8,22))/7,1),IF(DATE(VALUE(RIGHT(Y25,4)),VALUE(MID(Y25,4,2)),VALUE(LEFT(Y25,2)))<=DATE(2026,8,24),0,H25*0.0118*CEILING((DATE(VALUE(RIGHT(Y25,4)),VALUE(MID(Y25,4,2)),VALUE(LEFT(Y25,2)))-DATE(2026,8,22))/7,1))) | AC25: =U25+X25+AA25 | AD25: =S25-AC25 | AE25: DR2640100042 | AF25: 1800003317 | AG25: 27.08.2026
A26: 2 | B26: Scrap of 132 KV Wave Trap | C26: 14001 | D26: 21978 | E26: NO | F26: 2035 | G26: NATIONAL ENTERPRISES | H26: 28002 | I26: =ROUND(H26*18%,0) | J26: =+H26+I26 | K26: =ROUND((H26+I26)*2%,0) | L26: =H26*0.1% | M26: =H26*2.25%*118% | N26: =H26*2.25%*2% | O26: =M26-N26 | P26: =ROUND(O26+L26,0) | Q26: 0 | R26: =ROUND(H26*Q26,0) | S26: =ROUND(H26*117.65%-R26,0) | T26: =ROUND(H26*25%,0) | U26: =+T26 | V26: 13.08.2026 | W26: =ROUND(H26*92.65%-R26,0) | X26: 25943 | Y26: 24.08.2026 | Z26: =IF(OR(Y26="",Y26=0),H26*0.0118*CEILING((TODAY()-DATE(2026,8,22))/7,1),IF(DATE(VALUE(RIGHT(Y26,4)),VALUE(MID(Y26,4,2)),VALUE(LEFT(Y26,2)))<=DATE(2026,8,24),0,H26*0.0118*CEILING((DATE(VALUE(RIGHT(Y26,4)),VALUE(MID(Y26,4,2)),VALUE(LEFT(Y26,2)))-DATE(2026,8,22))/7,1))) | AC26: =U26+X26+AA26 | AD26: =S26-AC26 | AE26: DR2640100037 | AF26: 1800003310 | AG26: 27.08.2026
A27: 8.2 | B27: Mix Scrap (Tower angles & 0.2 ACSR Condutor pieces) | C27: 67000 | D27: 21978 | E27: MT | F27: 2036 | G27: M I SCRAP TRADERS | H27: 549400 | I27: =ROUND(H27*18%,0) | J27: =+H27+I27 | K27: =ROUND((H27+I27)*2%,0) | L27: =H27*0.1% | M27: =H27*2.25%*118% | N27: =H27*2.25%*2% | O27: =M27-N27 | P27: =ROUND(O27+L27,0) | Q27: 0.02 | R27: =ROUND(H27*Q27,0) | S27: =ROUND(H27*117.65%-R27,0) | T27: =ROUND(H27*25%,0) | U27: 137350 | V27: 14.08.2026 | W27: =ROUND(H27*92.65%-R27,0) | Y27: 0 | Z27: =IF(OR(Y27="",Y27=0),H27*0.0118*CEILING((TODAY()-DATE(2026,8,22))/7,1),IF(DATE(VALUE(RIGHT(Y27,4)),VALUE(MID(Y27,4,2)),VALUE(LEFT(Y27,2)))<=DATE(2026,8,24),0,H27*0.0118*CEILING((DATE(VALUE(RIGHT(Y27,4)),VALUE(MID(Y27,4,2)),VALUE(LEFT(Y27,2)))-DATE(2026,8,22))/7,1))) | AC27: =U27+X27+AA27 | AD27: =S27-AC27
A28: 50 | B28: Scrap of empty oil Barrels | C28: 531 | D28: 21978 | E28: NO | F28: 2037 | G28: WATAN SCRAP TRADERS | H28: 26550 | I28: =ROUND(H28*18%,0) | J28: =+H28+I28 | K28: =ROUND((H28+I28)*2%,0) | L28: =H28*0.1% | M28: =H28*2.25%*118% | N28: =H28*2.25%*2% | O28: =M28-N28 | P28: =ROUND(O28+L28,0) | Q28: 0 | R28: =ROUND(H28*Q28,0) | S28: =ROUND(H28*117.65%-R28,0) | T28: =ROUND(H28*25%,0) | U28: 6638 | V28: 14.08.2026 | W28: =ROUND(H28*92.65%-R28,0) | X28: 24598 | Y28: 21.08.2026 | Z28: =IF(OR(Y28="",Y28=0),H28*0.0118*CEILING((TODAY()-DATE(2026,8,22))/7,1),IF(DATE(VALUE(RIGHT(Y28,4)),VALUE(MID(Y28,4,2)),VALUE(LEFT(Y28,2)))<=DATE(2026,8,24),0,H28*0.0118*CEILING((DATE(VALUE(RIGHT(Y28,4)),VALUE(MID(Y28,4,2)),VALUE(LEFT(Y28,2)))-DATE(2026,8,22))/7,1))) | AC28: =U28+X28+AA28 | AD28: =S28-AC28 | AE28: DR2640100043 | AF28: 1800003318 | AG28: 27.08.2026
A29: 3 | B29: Scrap of 33 KV CT | C29: 90002 | D29: 21978 | E29: NO | F29: 2040 | G29: STERLING ENTERPRISES | H29: 270006 | I29: =ROUND(H29*18%,0) | J29: =+H29+I29 | K29: =ROUND((H29+I29)*2%,0) | L29: =H29*0.1% | M29: =H29*2.25%*118% | N29: =H29*2.25%*2% | O29: =M29-N29 | P29: =ROUND(O29+L29,0) | Q29: 0 | R29: =ROUND(H29*Q29,0) | S29: =ROUND(H29*117.65%-R29,0) | T29: =ROUND(H29*25%,0) | U29: 67502 | V29: 11.08.2026 | W29: =ROUND(H29*92.65%-R29,0) | Y29: 0 | Z29: =IF(OR(Y29="",Y29=0),H29*0.0118*CEILING((TODAY()-DATE(2026,8,22))/7,1),IF(DATE(VALUE(RIGHT(Y29,4)),VALUE(MID(Y29,4,2)),VALUE(LEFT(Y29,2)))<=DATE(2026,8,24),0,H29*0.0118*CEILING((DATE(VALUE(RIGHT(Y29,4)),VALUE(MID(Y29,4,2)),VALUE(LEFT(Y29,2)))-DATE(2026,8,22))/7,1))) | AC29: =U29+X29+AA29 | AD29: =S29-AC29
A30: 5 | B30: Scrap of 132 KV CT | C30: 80000 | D30: 21979 | E30: NO | F30: 2043 | G30: NATIONAL ENTERPRISES | H30: 400000 | I30: =ROUND(H30*18%,0) | J30: =+H30+I30 | K30: =ROUND((H30+I30)*2%,0) | L30: =H30*0.1% | M30: =H30*2.25%*118% | N30: =H30*2.25%*2% | O30: =M30-N30 | P30: =ROUND(O30+L30,0) | Q30: 0 | R30: =ROUND(H30*Q30,0) | S30: =ROUND(H30*117.65%-R30,0) | T30: =ROUND(H30*25%,0) | U30: =+T30 | V30: 13.08.2026 | W30: =ROUND(H30*92.65%-R30,0) | X30: 370600 | Y30: 24.08.2026 | Z30: =IF(OR(Y30="",Y30=0),H30*0.0118*CEILING((TODAY()-DATE(2026,8,22))/7,1),IF(DATE(VALUE(RIGHT(Y30,4)),VALUE(MID(Y30,4,2)),VALUE(LEFT(Y30,2)))<=DATE(2026,8,24),0,H30*0.0118*CEILING((DATE(VALUE(RIGHT(Y30,4)),VALUE(MID(Y30,4,2)),VALUE(LEFT(Y30,2)))-DATE(2026,8,22))/7,1))) | AC30: =U30+X30+AA30 | AD30: =S30-AC30 | AE30: DR2640100038 | AF30: 1800003311 | AG30: 27.08.2026
A31: 670 | B31: Scrap of AAAC Earth wire | C31: 309 | D31: 21979 | E31: KG | F31: 2046 | G31: SAHARA ENTERPRISES | H31: 207030 | I31: =ROUND(H31*18%,0) | J31: =+H31+I31 | K31: =ROUND((H31+I31)*2%,0) | L31: =H31*0.1% | M31: =H31*2.25%*118% | N31: =H31*2.25%*2% | O31: =M31-N31 | P31: =ROUND(O31+L31,0) | Q31: 0 | R31: =ROUND(H31*Q31,0) | S31: =ROUND(H31*117.65%-R31,0) | T31: =ROUND(H31*25%,0) | U31: 51758 | V31: 11.08.2026 | W31: =ROUND(H31*92.65%-R31,0) | X31: 191812 | Y31: 21.08.2026 | Z31: =IF(OR(Y31="",Y31=0),H31*0.0118*CEILING((TODAY()-DATE(2026,8,22))/7,1),IF(DATE(VALUE(RIGHT(Y31,4)),VALUE(MID(Y31,4,2)),VALUE(LEFT(Y31,2)))<=DATE(2026,8,24),0,H31*0.0118*CEILING((DATE(VALUE(RIGHT(Y31,4)),VALUE(MID(Y31,4,2)),VALUE(LEFT(Y31,2)))-DATE(2026,8,22))/7,1))) | AC31: =U31+X31+AA31 | AD31: =S31-AC31 | AE31: DR2640100041 | AF31: 1800003316 | AG31: 27.08.2026
A32: 2 | B32: Scrap of 220 KV CT | C32: 80006 | D32: 21979 | E32: NO | F32: 2055 | G32: NATIONAL ENTERPRISES | H32: 160012 | I32: =ROUND(H32*18%,0) | J32: =+H32+I32 | K32: =ROUND((H32+I32)*2%,0) | L32: =H32*0.1% | M32: =H32*2.25%*118% | N32: =H32*2.25%*2% | O32: =M32-N32 | P32: =ROUND(O32+L32,0) | Q32: 0 | R32: =ROUND(H32*Q32,0) | S32: =ROUND(H32*117.65%-R32,0) | T32: =ROUND(H32*25%,0) | U32: =+T32 | V32: 13.08.2026 | W32: =ROUND(H32*92.65%-R32,0) | X32: 148251 | Y32: 24.08.2026 | Z32: =IF(OR(Y32="",Y32=0),H32*0.0118*CEILING((TODAY()-DATE(2026,8,22))/7,1),IF(DATE(VALUE(RIGHT(Y32,4)),VALUE(MID(Y32,4,2)),VALUE(LEFT(Y32,2)))<=DATE(2026,8,24),0,H32*0.0118*CEILING((DATE(VALUE(RIGHT(Y32,4)),VALUE(MID(Y32,4,2)),VALUE(LEFT(Y32,2)))-DATE(2026,8,22))/7,1))) | AC32: =U32+X32+AA32 | AD32: =S32-AC32 | AE32: DR2640100039 | AF32: 1800003312 | AG32: 27.08.2026
A33: 1 | B33: Scrap of 33 KV GCB | C33: 29502 | D33: 21979 | E33: NO | F33: 2059 | G33: NATIONAL ENTERPRISES | H33: 29502 | I33: =ROUND(H33*18%,0) | J33: =+H33+I33 | K33: =ROUND((H33+I33)*2%,0) | L33: =H33*0.1% | M33: =H33*2.25%*118% | N33: =H33*2.25%*2% | O33: =M33-N33 | P33: =ROUND(O33+L33,0) | Q33: 0 | R33: =ROUND(H33*Q33,0) | S33: =ROUND(H33*117.65%-R33,0) | T33: =ROUND(H33*25%,0) | U33: =+T33 | V33: 13.08.2026 | W33: =ROUND(H33*92.65%-R33,0) | X33: 27332 | Y33: 24.08.2026 | Z33: =IF(OR(Y33="",Y33=0),H33*0.0118*CEILING((TODAY()-DATE(2026,8,22))/7,1),IF(DATE(VALUE(RIGHT(Y33,4)),VALUE(MID(Y33,4,2)),VALUE(LEFT(Y33,2)))<=DATE(2026,8,24),0,H33*0.0118*CEILING((DATE(VALUE(RIGHT(Y33,4)),VALUE(MID(Y33,4,2)),VALUE(LEFT(Y33,2)))-DATE(2026,8,22))/7,1))) | AC33: =U33+X33+AA33 | AD33: =S33-AC33 | AE33: DR2640100046 | AF33: 1800003313 | AG33: 27.08.2026
A34: 30 | B34: Scrap of Empty oil Barrels | C34: 702 | D34: 21979 | E34: NO | F34: 2062 | G34: STERLING ENTERPRISES | H34: 21060 | I34: =ROUND(H34*18%,0) | J34: =+H34+I34 | K34: =ROUND((H34+I34)*2%,0) | L34: =H34*0.1% | M34: =H34*2.25%*118% | N34: =H34*2.25%*2% | O34: =M34-N34 | P34: =ROUND(O34+L34,0) | Q34: 0 | R34: =ROUND(H34*Q34,0) | S34: =ROUND(H34*117.65%-R34,0) | T34: =ROUND(H34*25%,0) | U34: 5265 | V34: 11.08.2026 | W34: =ROUND(H34*92.65%-R34,0) | X34: 19512 | Y34: 11.08.2026 | Z34: =IF(OR(Y34="",Y34=0),H34*0.0118*CEILING((TODAY()-DATE(2026,8,22))/7,1),IF(DATE(VALUE(RIGHT(Y34,4)),VALUE(MID(Y34,4,2)),VALUE(LEFT(Y34,2)))<=DATE(2026,8,24),0,H34*0.0118*CEILING((DATE(VALUE(RIGHT(Y34,4)),VALUE(MID(Y34,4,2)),VALUE(LEFT(Y34,2)))-DATE(2026,8,22))/7,1))) | AC34: =U34+X34+AA34 | AD34: =S34-AC34 | AE34: DR2640100022 | AF34: 1800003161 | AG34: 14.08.2026
A35: 150 | B35: Scrap of empty oil drums | C35: 571 | D35: 21980 | E35: NO | F35: 2067 | G35: WATAN SCRAP TRADERS | H35: 85650 | I35: =ROUND(H35*18%,0) | J35: =+H35+I35 | K35: =ROUND((H35+I35)*2%,0) | L35: =H35*0.1% | M35: =H35*2.25%*118% | N35: =H35*2.25%*2% | O35: =M35-N35 | P35: =ROUND(O35+L35,0) | Q35: 0 | R35: =ROUND(H35*Q35,0) | S35: =ROUND(H35*117.65%-R35,0) | T35: =ROUND(H35*25%,0) | U35: 21413 | V35: 14.08.2026 | W35: =ROUND(H35*92.65%-R35,0) | X35: 79354 | Y35: 20.08.2026 | Z35: =IF(OR(Y35="",Y35=0),H35*0.0118*CEILING((TODAY()-DATE(2026,8,22))/7,1),IF(DATE(VALUE(RIGHT(Y35,4)),VALUE(MID(Y35,4,2)),VALUE(LEFT(Y35,2)))<=DATE(2026,8,24),0,H35*0.0118*CEILING((DATE(VALUE(RIGHT(Y35,4)),VALUE(MID(Y35,4,2)),VALUE(LEFT(Y35,2)))-DATE(2026,8,22))/7,1))) | AC35: =U35+X35+AA35 | AD35: =S35-AC35 | AE35: DR2640100027 | AF35: 1800003248 | AG35: 20.08.2026
A36: 1 | B36: Scrap of 33 KV CB | C36: 54000 | D36: 21980 | E36: NO | F36: 2069 | G36: STERLING ENTERPRISES | H36: 54000 | I36: =ROUND(H36*18%,0) | J36: =+H36+I36 | K36: =ROUND((H36+I36)*2%,0) | L36: =H36*0.1% | M36: =H36*2.25%*118% | N36: =H36*2.25%*2% | O36: =M36-N36 | P36: =ROUND(O36+L36,0) | Q36: 0 | R36: =ROUND(H36*Q36,0) | S36: =ROUND(H36*117.65%-R36,0) | T36: =ROUND(H36*25%,0) | U36: 13500 | V36: 11.08.2026 | W36: =ROUND(H36*92.65%-R36,0) | Y36: 0 | Z36: =IF(OR(Y36="",Y36=0),H36*0.0118*CEILING((TODAY()-DATE(2026,8,22))/7,1),IF(DATE(VALUE(RIGHT(Y36,4)),VALUE(MID(Y36,4,2)),VALUE(LEFT(Y36,2)))<=DATE(2026,8,24),0,H36*0.0118*CEILING((DATE(VALUE(RIGHT(Y36,4)),VALUE(MID(Y36,4,2)),VALUE(LEFT(Y36,2)))-DATE(2026,8,22))/7,1))) | AC36: =U36+X36+AA36 | AD36: =S36-AC36
A37: 3 | B37: Scrap of 66 KV Isolater | C37: 25001 | D37: 21980 | E37: NO | F37: 2071 | G37: NATIONAL ENTERPRISES | H37: 75003 | I37: =ROUND(H37*18%,0) | J37: =+H37+I37 | K37: =ROUND((H37+I37)*2%,0) | L37: =H37*0.1% | M37: =H37*2.25%*118% | N37: =H37*2.25%*2% | O37: =M37-N37 | P37: =ROUND(O37+L37,0) | Q37: 0 | R37: =ROUND(H37*Q37,0) | S37: =ROUND(H37*117.65%-R37,0) | T37: =ROUND(H37*25%,0) | U37: =+T37 | V37: 13.08.2026 | W37: =ROUND(H37*92.65%-R37,0) | X37: 69491 | Y37: 24.08.2026 | Z37: =IF(OR(Y37="",Y37=0),H37*0.0118*CEILING((TODAY()-DATE(2026,8,22))/7,1),IF(DATE(VALUE(RIGHT(Y37,4)),VALUE(MID(Y37,4,2)),VALUE(LEFT(Y37,2)))<=DATE(2026,8,24),0,H37*0.0118*CEILING((DATE(VALUE(RIGHT(Y37,4)),VALUE(MID(Y37,4,2)),VALUE(LEFT(Y37,2)))-DATE(2026,8,22))/7,1))) | AC37: =U37+X37+AA37 | AD37: =S37-AC37 | AE37: DR2640100040 | AF37: 1800003314 | AG37: 27.08.2026
A38: 3 | B38: Scrap of 132 KV CT | C38: 70001 | D38: 21980 | E38: NO | F38: 2086 | G38: KASHYAP TRADING CO | H38: 210003 | I38: =ROUND(H38*18%,0) | J38: =+H38+I38 | K38: =ROUND((H38+I38)*2%,0) | L38: =H38*0.1% | M38: =H38*2.25%*118% | N38: =H38*2.25%*2% | O38: =M38-N38 | P38: =ROUND(O38+L38,0) | Q38: 0 | R38: =ROUND(H38*Q38,0) | S38: =ROUND(H38*117.65%-R38,0) | T38: =ROUND(H38*25%,0) | U38: 52501 | V38: 17.08.2026 | W38: =ROUND(H38*92.65%-R38,0) | X38: 194568 | Y38: 17.08.2026 | Z38: =IF(OR(Y38="",Y38=0),H38*0.0118*CEILING((TODAY()-DATE(2026,8,22))/7,1),IF(DATE(VALUE(RIGHT(Y38,4)),VALUE(MID(Y38,4,2)),VALUE(LEFT(Y38,2)))<=DATE(2026,8,24),0,H38*0.0118*CEILING((DATE(VALUE(RIGHT(Y38,4)),VALUE(MID(Y38,4,2)),VALUE(LEFT(Y38,2)))-DATE(2026,8,22))/7,1))) | AC38: =U38+X38+AA38 | AD38: =S38-AC38 | AE38: DR2640100025 | AF38: 1800003226 | AG38: 19.08.2026
A39: 2 | B39: Scrap of 66 kv TBC C & R Panel | C39: 15006 | D39: 21980 | E39: NO | F39: 2089 | G39: S M ENTERPRISES | H39: 30012 | I39: =ROUND(H39*18%,0) | J39: =+H39+I39 | K39: =ROUND((H39+I39)*2%,0) | L39: =H39*0.1% | M39: =H39*2.25%*118% | N39: =H39*2.25%*2% | O39: =M39-N39 | P39: =ROUND(O39+L39,0) | Q39: 0 | R39: =ROUND(H39*Q39,0) | S39: =ROUND(H39*117.65%-R39,0) | T39: =ROUND(H39*25%,0) | U39: 7503 | V39: 14.08.2026 | W39: =ROUND(H39*92.65%-R39,0) | X39: 27806 | Y39: 01.09.2026 | Z39: =IF(OR(Y39="",Y39=0),H39*0.0118*CEILING((TODAY()-DATE(2026,8,22))/7,1),IF(DATE(VALUE(RIGHT(Y39,4)),VALUE(MID(Y39,4,2)),VALUE(LEFT(Y39,2)))<=DATE(2026,8,24),0,H39*0.0118*CEILING((DATE(VALUE(RIGHT(Y39,4)),VALUE(MID(Y39,4,2)),VALUE(LEFT(Y39,2)))-DATE(2026,8,22))/7,1))) | AA39: 708 | AB39: 01.09.2026 | AC39: =U39+X39+AA39 | AD39: =S39-AC39
A40: 3 | B40: Scrap of 132 KV CT | C40: 40003 | D40: 21980 | E40: NO | F40: 2091 | G40: S M ENTERPRISES | H40: 120009 | I40: =ROUND(H40*18%,0) | J40: =+H40+I40 | K40: =ROUND((H40+I40)*2%,0) | L40: =H40*0.1% | M40: =H40*2.25%*118% | N40: =H40*2.25%*2% | O40: =M40-N40 | P40: =ROUND(O40+L40,0) | Q40: 0 | R40: =ROUND(H40*Q40,0) | S40: =ROUND(H40*117.65%-R40,0) | T40: =ROUND(H40*25%,0) | U40: 30002 | V40: 14.08.2026 | W40: =ROUND(H40*92.65%-R40,0) | X40: 111189 | Y40: 01.09.2026 | Z40: =IF(OR(Y40="",Y40=0),H40*0.0118*CEILING((TODAY()-DATE(2026,8,22))/7,1),IF(DATE(VALUE(RIGHT(Y40,4)),VALUE(MID(Y40,4,2)),VALUE(LEFT(Y40,2)))<=DATE(2026,8,24),0,H40*0.0118*CEILING((DATE(VALUE(RIGHT(Y40,4)),VALUE(MID(Y40,4,2)),VALUE(LEFT(Y40,2)))-DATE(2026,8,22))/7,1))) | AA40: 2832 | AB40: 01.09.2026 | AC40: =U40+X40+AA40 | AD40: =S40-AC40
H41: =SUM(H4:H40) | I41: =SUM(I4:I40) | J41: =SUM(J4:J40) | K41: =SUM(K4:K40) | L41: =SUM(L4:L40) | M41: =SUM(M4:M40) | N41: =SUM(N4:N40) | O41: =SUM(O4:O40) | P41: =SUM(P4:P40) | R41: =SUM(R4:R40) | S41: =SUM(S4:S40) | T41: =SUM(T4:T40) | U41: =SUM(U4:U40) | W41: =SUM(W4:W40) | X41: =SUM(X4:X40) | Z41: =SUM(Z4:Z40) | AA41: =SUM(AA4:AA40) | AC41: =SUM(AC4:AC40) | AD41: =SUM(AD4:AD40)
H42: =+H41 | I42: =ROUND(H42*18%,0) | J42: =+H42+I42 | K42: =ROUND((H42+I42)*2%,0) | L42: =ROUND(H42*0.1%,0) | M42: =ROUND(H42*2.25%*118%,0) | N42: =ROUND(H42*2.25%*2%,0) | O42: =ROUND(M42-N42,0) | P42: =ROUND(O42+L42,0) | R42: =+R41 | S42: =H42*117.65%-R42 | U42: =+T41-U41 | X42: =+W41-X41
U43: Bal SD O/s | X43: Bal FP O/s

Sheet Collapsible - Lots Across
A1: MSTC LIMITED • BUYER × LOT COLLAPSIBLE VIEW (fields ↓ rows | lots → columns)
A2: Auctions 21977 • 21978 • 21979 • 21980 — every figure below is a live link to 'Final Calculation Sheet'
A3: HOW TO USE ▶ the − / + buttons in the grey margin on the LEFT fold a whole buyer (outer level) or a single section such as FINANCIALS (inner level) • the − / + above column O folds all lot columns away and keeps only the buyer totals • the 1 2 3 buttons at the top left expand everything again • a colour coded buyer index with totals and jump links sits at the bottom of this sheet
A5: FIELD ▸ BUYER | LOT → | B5: LOT 1 | C5: LOT 2 | D5: LOT 3 | E5: LOT 4 | F5: LOT 5 | G5: LOT 6 | H5: LOT 7 | I5: LOT 8 | J5: LOT 9 | K5: LOT 10 | L5: LOT 11 | M5: LOT 12 | N5: LOT 13 | O5: BUYER TOTAL
A6: ="▼ AL HAMD TRADE CORPORATION • "&COUNTIF('Final Calculation Sheet'!$G$4:$G$1000,"AL HAMD TRADE CORPORATION")&" LOT(S) • MAT. VALUE ₹"&TEXT(SUMIF('Final Calculation Sheet'!$G$4:$G$1000,"AL HAMD TRADE CORPORATION",'Final Calculation Sheet'!$H$4:$H$1000),"#,##0")&" • RECEIVED ₹"&TEXT(SUMIF('Final Calculation Sheet'!$G$4:$G$1000,"AL HAMD TRADE CORPORATION",'Final Calculation Sheet'!$AC$4:$AC$1000),"#,##0")&" • OUTSTANDING ₹"&TEXT(SUMIF('Final Calculation Sheet'!$G$4:$G$1000,"AL HAMD TRADE CORPORATION",'Final Calculation Sheet'!$AD$4:$AD$1000),"#,##0")
A7: Lot No. → | B7: =IF('Final Calculation Sheet'!$F$4="","",'Final Calculation Sheet'!$F$4) | O7: TOTAL
A8: ▸ LOT INFORMATION
A9: Lot No. | B9: =IF('Final Calculation Sheet'!$F$4="","",'Final Calculation Sheet'!$F$4) | O9: –
A10: Lot Name | B10: =IF('Final Calculation Sheet'!$B$4="","",'Final Calculation Sheet'!$B$4) | O10: –
A11: Bid Sheet / Auction | B11: =IF('Final Calculation Sheet'!$D$4="","",'Final Calculation Sheet'!$D$4) | O11: –
A12: Quantity | B12: =IF('Final Calculation Sheet'!$A$4="","",'Final Calculation Sheet'!$A$4) | O12: =SUM(B12:N12)
A13: Unit | B13: =IF('Final Calculation Sheet'!$E$4="","",'Final Calculation Sheet'!$E$4) | O13: –
A14: Rate (₹) | B14: =IF('Final Calculation Sheet'!$C$4="","",'Final Calculation Sheet'!$C$4) | O14: –
A15: ▸ FINANCIALS
A16: Mat. Value (₹) | B16: =IF('Final Calculation Sheet'!$H$4="","",'Final Calculation Sheet'!$H$4) | O16: =SUM(B16:N16)
A17: GST @ 18% (₹) | B17: =IF('Final Calculation Sheet'!$I$4="","",'Final Calculation Sheet'!$I$4) | O17: =SUM(B17:N17)
A18: Mat. Value + GST (₹) | B18: =IF('Final Calculation Sheet'!$J$4="","",'Final Calculation Sheet'!$J$4) | O18: =SUM(B18:N18)
A19: TCS @ 2% (₹) | B19: =IF('Final Calculation Sheet'!$K$4="","",'Final Calculation Sheet'!$K$4) | O19: =SUM(B19:N19)
A20: TDS u/s 194(O) (₹) | B20: =IF('Final Calculation Sheet'!$L$4="","",'Final Calculation Sheet'!$L$4) | O20: =SUM(B20:N20)
A21: Service Charge gross (₹) | B21: =IF('Final Calculation Sheet'!$M$4="","",'Final Calculation Sheet'!$M$4) | O21: =SUM(B21:N21)
A22: TDS u/s 194(H) (₹) | B22: =IF('Final Calculation Sheet'!$N$4="","",'Final Calculation Sheet'!$N$4) | O22: =SUM(B22:N22)
A23: Net Service Charge (₹) | B23: =IF('Final Calculation Sheet'!$O$4="","",'Final Calculation Sheet'!$O$4) | O23: =SUM(B23:N23)
A24: Svc Charge to MSTC (₹) | B24: =IF('Final Calculation Sheet'!$P$4="","",'Final Calculation Sheet'!$P$4) | O24: =SUM(B24:N24)
A25: GST TDS Rate | B25: =IF('Final Calculation Sheet'!$Q$4="","",'Final Calculation Sheet'!$Q$4) | O25: –
A26: GST TDS (₹) | B26: =IF('Final Calculation Sheet'!$R$4="","",'Final Calculation Sheet'!$R$4) | O26: =SUM(B26:N26)
A27: Total Receivables (₹) | B27: =IF('Final Calculation Sheet'!$S$4="","",'Final Calculation Sheet'!$S$4) | O27: =SUM(B27:N27)
A28: ▸ SECURITY DEPOSIT
A29: SD Expected (₹) | B29: =IF('Final Calculation Sheet'!$T$4="","",'Final Calculation Sheet'!$T$4) | O29: =SUM(B29:N29)
A30: SD Received (₹) | B30: =IF('Final Calculation Sheet'!$U$4="","",'Final Calculation Sheet'!$U$4) | O30: =SUM(B30:N30)
A31: SD Receipt Date | B31: =IF('Final Calculation Sheet'!$V$4="","",'Final Calculation Sheet'!$V$4) | O31: –
A32: ▸ FINAL PAYMENT
A33: FP Expected (₹) | B33: =IF('Final Calculation Sheet'!$W$4="","",'Final Calculation Sheet'!$W$4) | O33: =SUM(B33:N33)
A34: FP Received (₹) | B34: =IF('Final Calculation Sheet'!$X$4="","",'Final Calculation Sheet'!$X$4) | O34: =SUM(B34:N34)
A35: FP Receipt Date | B35: =IF('Final Calculation Sheet'!$Y$4="","",'Final Calculation Sheet'!$Y$4) | O35: –
A36: ▸ LPP
A37: LPP Expected (₹) | B37: =IF('Final Calculation Sheet'!$Z$4="","",'Final Calculation Sheet'!$Z$4) | O37: =SUM(B37:N37)
A38: LPP Received (₹) | B38: =IF('Final Calculation Sheet'!$AA$4="","",'Final Calculation Sheet'!$AA$4) | O38: =SUM(B38:N38)
A39: LPP Receipt Date | B39: =IF('Final Calculation Sheet'!$AB$4="","",'Final Calculation Sheet'!$AB$4) | O39: –
A40: ▸ SUMMARY
A41: Total Received (₹) | B41: =IF('Final Calculation Sheet'!$AC$4="","",'Final Calculation Sheet'!$AC$4) | O41: =SUM(B41:N41)
A42: Outstanding (₹) | B42: =IF('Final Calculation Sheet'!$AD$4="","",'Final Calculation Sheet'!$AD$4) | O42: =SUM(B42:N42)
A43: Payment Status | B43: =IF('Final Calculation Sheet'!$AD$4="","",IF('Final Calculation Sheet'!$AD$4<=0,"SETTLED","OUTSTANDING")) | O43: –
A44: ▸ DOCUMENT
A45: Invoice No. | B45: =IF('Final Calculation Sheet'!$AE$4="","",'Final Calculation Sheet'!$AE$4) | O45: –
A46: SAP Document | B46: =IF('Final Calculation Sheet'!$AF$4="","",'Final Calculation Sheet'!$AF$4) | O46: –
A47: Doc./Invoice Date | B47: =IF('Final Calculation Sheet'!$AG$4="","",'Final Calculation Sheet'!$AG$4) | O47: –
A49: ="▼ F R KHANS ENTERPRISES • "&COUNTIF('Final Calculation Sheet'!$G$4:$G$1000,"F R KHANS ENTERPRISES")&" LOT(S) • MAT. VALUE ₹"&TEXT(SUMIF('Final Calculation Sheet'!$G$4:$G$1000,"F R KHANS ENTERPRISES",'Final Calculation Sheet'!$H$4:$H$1000),"#,##0")&" • RECEIVED ₹"&TEXT(SUMIF('Final Calculation Sheet'!$G$4:$G$1000,"F R KHANS ENTERPRISES",'Final Calculation Sheet'!$AC$4:$AC$1000),"#,##0")&" • OUTSTANDING ₹"&TEXT(SUMIF('Final Calculation Sheet'!$G$4:$G$1000,"F R KHANS ENTERPRISES",'Final Calculation Sheet'!$AD$4:$AD$1000),"#,##0")
A50: Lot No. → | B50: =IF('Final Calculation Sheet'!$F$6="","",'Final Calculation Sheet'!$F$6) | C50: =IF('Final Calculation Sheet'!$F$7="","",'Final Calculation Sheet'!$F$7) | O50: TOTAL
A51: ▸ LOT INFORMATION
A52: Lot No. | B52: =IF('Final Calculation Sheet'!$F$6="","",'Final Calculation Sheet'!$F$6) | C52: =IF('Final Calculation Sheet'!$F$7="","",'Final Calculation Sheet'!$F$7) | O52: –
A53: Lot Name | B53: =IF('Final Calculation Sheet'!$B$6="","",'Final Calculation Sheet'!$B$6) | C53: =IF('Final Calculation Sheet'!$B$7="","",'Final Calculation Sheet'!$B$7) | O53: –
A54: Bid Sheet / Auction | B54: =IF('Final Calculation Sheet'!$D$6="","",'Final Calculation Sheet'!$D$6) | C54: =IF('Final Calculation Sheet'!$D$7="","",'Final Calculation Sheet'!$D$7) | O54: –
A55: Quantity | B55: =IF('Final Calculation Sheet'!$A$6="","",'Final Calculation Sheet'!$A$6) | C55: =IF('Final Calculation Sheet'!$A$7="","",'Final Calculation Sheet'!$A$7) | O55: =SUM(B55:N55)
A56: Unit | B56: =IF('Final Calculation Sheet'!$E$6="","",'Final Calculation Sheet'!$E$6) | C56: =IF('Final Calculation Sheet'!$E$7="","",'Final Calculation Sheet'!$E$7) | O56: –
A57: Rate (₹) | B57: =IF('Final Calculation Sheet'!$C$6="","",'Final Calculation Sheet'!$C$6) | C57: =IF('Final Calculation Sheet'!$C$7="","",'Final Calculation Sheet'!$C$7) | O57: –
A58: ▸ FINANCIALS
A59: Mat. Value (₹) | B59: =IF('Final Calculation Sheet'!$H$6="","",'Final Calculation Sheet'!$H$6) | C59: =IF('Final Calculation Sheet'!$H$7="","",'Final Calculation Sheet'!$H$7) | O59: =SUM(B59:N59)
A60: GST @ 18% (₹) | B60: =IF('Final Calculation Sheet'!$I$6="","",'Final Calculation Sheet'!$I$6) | C60: =IF('Final Calculation Sheet'!$I$7="","",'Final Calculation Sheet'!$I$7) | O60: =SUM(B60:N60)
A61: Mat. Value + GST (₹) | B61: =IF('Final Calculation Sheet'!$J$6="","",'Final Calculation Sheet'!$J$6) | C61: =IF('Final Calculation Sheet'!$J$7="","",'Final Calculation Sheet'!$J$7) | O61: =SUM(B61:N61)
A62: TCS @ 2% (₹) | B62: =IF('Final Calculation Sheet'!$K$6="","",'Final Calculation Sheet'!$K$6) | C62: =IF('Final Calculation Sheet'!$K$7="","",'Final Calculation Sheet'!$K$7) | O62: =SUM(B62:N62)
A63: TDS u/s 194(O) (₹) | B63: =IF('Final Calculation Sheet'!$L$6="","",'Final Calculation Sheet'!$L$6) | C63: =IF('Final Calculation Sheet'!$L$7="","",'Final Calculation Sheet'!$L$7) | O63: =SUM(B63:N63)
A64: Service Charge gross (₹) | B64: =IF('Final Calculation Sheet'!$M$6="","",'Final Calculation Sheet'!$M$6) | C64: =IF('Final Calculation Sheet'!$M$7="","",'Final Calculation Sheet'!$M$7) | O64: =SUM(B64:N64)
A65: TDS u/s 194(H) (₹) | B65: =IF('Final Calculation Sheet'!$N$6="","",'Final Calculation Sheet'!$N$6) | C65: =IF('Final Calculation Sheet'!$N$7="","",'Final Calculation Sheet'!$N$7) | O65: =SUM(B65:N65)
A66: Net Service Charge (₹) | B66: =IF('Final Calculation Sheet'!$O$6="","",'Final Calculation Sheet'!$O$6) | C66: =IF('Final Calculation Sheet'!$O$7="","",'Final Calculation Sheet'!$O$7) | O66: =SUM(B66:N66)
A67: Svc Charge to MSTC (₹) | B67: =IF('Final Calculation Sheet'!$P$6="","",'Final Calculation Sheet'!$P$6) | C67: =IF('Final Calculation Sheet'!$P$7="","",'Final Calculation Sheet'!$P$7) | O67: =SUM(B67:N67)
A68: GST TDS Rate | B68: =IF('Final Calculation Sheet'!$Q$6="","",'Final Calculation Sheet'!$Q$6) | C68: =IF('Final Calculation Sheet'!$Q$7="","",'Final Calculation Sheet'!$Q$7) | O68: –
A69: GST TDS (₹) | B69: =IF('Final Calculation Sheet'!$R$6="","",'Final Calculation Sheet'!$R$6) | C69: =IF('Final Calculation Sheet'!$R$7="","",'Final Calculation Sheet'!$R$7) | O69: =SUM(B69:N69)
A70: Total Receivables (₹) | B70: =IF('Final Calculation Sheet'!$S$6="","",'Final Calculation Sheet'!$S$6) | C70: =IF('Final Calculation Sheet'!$S$7="","",'Final Calculation Sheet'!$S$7) | O70: =SUM(B70:N70)
A71: ▸ SECURITY DEPOSIT
A72: SD Expected (₹) | B72: =IF('Final Calculation Sheet'!$T$6="","",'Final Calculation Sheet'!$T$6) | C72: =IF('Final Calculation Sheet'!$T$7="","",'Final Calculation Sheet'!$T$7) | O72: =SUM(B72:N72)
A73: SD Received (₹) | B73: =IF('Final Calculation Sheet'!$U$6="","",'Final Calculation Sheet'!$U$6) | C73: =IF('Final Calculation Sheet'!$U$7="","",'Final Calculation Sheet'!$U$7) | O73: =SUM(B73:N73)
A74: SD Receipt Date | B74: =IF('Final Calculation Sheet'!$V$6="","",'Final Calculation Sheet'!$V$6) | C74: =IF('Final Calculation Sheet'!$V$7="","",'Final Calculation Sheet'!$V$7) | O74: –
A75: ▸ FINAL PAYMENT
A76: FP Expected (₹) | B76: =IF('Final Calculation Sheet'!$W$6="","",'Final Calculation Sheet'!$W$6) | C76: =IF('Final Calculation Sheet'!$W$7="","",'Final Calculation Sheet'!$W$7) | O76: =SUM(B76:N76)
A77: FP Received (₹) | B77: =IF('Final Calculation Sheet'!$X$6="","",'Final Calculation Sheet'!$X$6) | C77: =IF('Final Calculation Sheet'!$X$7="","",'Final Calculation Sheet'!$X$7) | O77: =SUM(B77:N77)
A78: FP Receipt Date | B78: =IF('Final Calculation Sheet'!$Y$6="","",'Final Calculation Sheet'!$Y$6) | C78: =IF('Final Calculation Sheet'!$Y$7="","",'Final Calculation Sheet'!$Y$7) | O78: –
A79: ▸ LPP
A80: LPP Expected (₹) | B80: =IF('Final Calculation Sheet'!$Z$6="","",'Final Calculation Sheet'!$Z$6) | C80: =IF('Final Calculation Sheet'!$Z$7="","",'Final Calculation Sheet'!$Z$7) | O80: =SUM(B80:N80)
A81: LPP Received (₹) | B81: =IF('Final Calculation Sheet'!$AA$6="","",'Final Calculation Sheet'!$AA$6) | C81: =IF('Final Calculation Sheet'!$AA$7="","",'Final Calculation Sheet'!$AA$7) | O81: =SUM(B81:N81)
A82: LPP Receipt Date | B82: =IF('Final Calculation Sheet'!$AB$6="","",'Final Calculation Sheet'!$AB$6) | C82: =IF('Final Calculation Sheet'!$AB$7="","",'Final Calculation Sheet'!$AB$7) | O82: –
A83: ▸ SUMMARY
A84: Total Received (₹) | B84: =IF('Final Calculation Sheet'!$AC$6="","",'Final Calculation Sheet'!$AC$6) | C84: =IF('Final Calculation Sheet'!$AC$7="","",'Final Calculation Sheet'!$AC$7) | O84: =SUM(B84:N84)
A85: Outstanding (₹) | B85: =IF('Final Calculation Sheet'!$AD$6="","",'Final Calculation Sheet'!$AD$6) | C85: =IF('Final Calculation Sheet'!$AD$7="","",'Final Calculation Sheet'!$AD$7) | O85: =SUM(B85:N85)
A86: Payment Status | B86: =IF('Final Calculation Sheet'!$AD$6="","",IF('Final Calculation Sheet'!$AD$6<=0,"SETTLED","OUTSTANDING")) | C86: =IF('Final Calculation Sheet'!$AD$7="","",IF('Final Calculation Sheet'!$AD$7<=0,"SETTLED","OUTSTANDING")) | O86: –
A87: ▸ DOCUMENT
A88: Invoice No. | B88: =IF('Final Calculation Sheet'!$AE$6="","",'Final Calculation Sheet'!$AE$6) | C88: =IF('Final Calculation Sheet'!$AE$7="","",'Final Calculation Sheet'!$AE$7) | O88: –
A89: SAP Document | B89: =IF('Final Calculation Sheet'!$AF$6="","",'Final Calculation Sheet'!$AF$6) | C89: =IF('Final Calculation Sheet'!$AF$7="","",'Final Calculation Sheet'!$AF$7) | O89: –
A90: Doc./Invoice Date | B90: =IF('Final Calculation Sheet'!$AG$6="","",'Final Calculation Sheet'!$AG$6) | C90: =IF('Final Calculation Sheet'!$AG$7="","",'Final Calculation Sheet'!$AG$7) | O90: –
A92: ="▼ HIND TRADERS • "&COUNTIF('Final Calculation Sheet'!$G$4:$G$1000,"HIND TRADERS")&" LOT(S) • MAT. VALUE ₹"&TEXT(SUMIF('Final Calculation Sheet'!$G$4:$G$1000,"HIND TRADERS",'Final Calculation Sheet'!$H$4:$H$1000),"#,##0")&" • RECEIVED ₹"&TEXT(SUMIF('Final Calculation Sheet'!$G$4:$G$1000,"HIND TRADERS",'Final Calculation Sheet'!$AC$4:$AC$1000),"#,##0")&" • OUTSTANDING ₹"&TEXT(SUMIF('Final Calculation Sheet'!$G$4:$G$1000,"HIND TRADERS",'Final Calculation Sheet'!$AD$4:$AD$1000),"#,##0")
A93: Lot No. → | B93: =IF('Final Calculation Sheet'!$F$15="","",'Final Calculation Sheet'!$F$15) | O93: TOTAL
A94: ▸ LOT INFORMATION
A95: Lot No. | B95: =IF('Final Calculation Sheet'!$F$15="","",'Final Calculation Sheet'!$F$15) | O95: –
A96: Lot Name | B96: =IF('Final Calculation Sheet'!$B$15="","",'Final Calculation Sheet'!$B$15) | O96: –
A97: Bid Sheet / Auction | B97: =IF('Final Calculation Sheet'!$D$15="","",'Final Calculation Sheet'!$D$15) | O97: –
A98: Quantity | B98: =IF('Final Calculation Sheet'!$A$15="","",'Final Calculation Sheet'!$A$15) | O98: =SUM(B98:N98)
A99: Unit | B99: =IF('Final Calculation Sheet'!$E$15="","",'Final Calculation Sheet'!$E$15) | O99: –
A100: Rate (₹) | B100: =IF('Final Calculation Sheet'!$C$15="","",'Final Calculation Sheet'!$C$15) | O100: –
A101: ▸ FINANCIALS
A102: Mat. Value (₹) | B102: =IF('Final Calculation Sheet'!$H$15="","",'Final Calculation Sheet'!$H$15) | O102: =SUM(B102:N102)
A103: GST @ 18% (₹) | B103: =IF('Final Calculation Sheet'!$I$15="","",'Final Calculation Sheet'!$I$15) | O103: =SUM(B103:N103)
...

Sheet Collapsible - Lots Down
A1: MSTC LIMITED • BUYER × LOT COLLAPSIBLE VIEW (lots ↓ rows | fields → columns)
A2: HOW TO USE ▶ the − / + buttons in the left margin fold a buyer: its lots hide and the banner plus the ∑ totals row stay on screen • the − above a column category (LOT INFO, FINANCIALS …) folds those columns away, keeping the category's first column • every figure is a live link to 'Final Calculation Sheet' • for filtering use 'Ledger Filter - Lots Down' or 'Ledger Filter - Lots Across'
A3: LOT INFORMATION | G3: FINANCIALS | S3: SECURITY DEPOSIT | V3: FINAL PAYMENT | Y3: LPP | AB3: SUMMARY | AE3: DOCUMENT
A4: Lot No. | B4: Lot Name | C4: Bid Sheet / Auction | D4: Quantity | E4: Unit | F4: Rate (₹) | G4: Mat. Value (₹) | H4: GST @ 18% (₹) | I4: Mat. Value + GST (₹) | J4: TCS @ 2% (₹) | K4: TDS u/s 194(O) (₹) | L4: Service Charge gross (₹) | M4: TDS u/s 194(H) (₹) | N4: Net Service Charge (₹) | O4: Svc Charge to MSTC (₹) | P4: GST TDS Rate | Q4: GST TDS (₹) | R4: Total Receivables (₹) | S4: SD Expected (₹) | T4: SD Received (₹) | U4: SD Receipt Date | V4: FP Expected (₹) | W4: FP Received (₹) | X4: FP Receipt Date | Y4: LPP Expected (₹) | Z4: LPP Received (₹) | AA4: LPP Receipt Date | AB4: Total Received (₹) | AC4: Outstanding (₹) | AD4: Payment Status | AE4: Invoice No. | AF4: SAP Document | AG4: Doc./Invoice Date
A5: ="▼ AL HAMD TRADE CORPORATION • "&COUNTIF('Final Calculation Sheet'!$G$4:$G$1000,"AL HAMD TRADE CORPORATION")&" LOT(S) • MAT. VALUE ₹"&TEXT(SUMIF('Final Calculation Sheet'!$G$4:$G$1000,"AL HAMD TRADE CORPORATION",'Final Calculation Sheet'!$H$4:$H$1000),"#,##0")&" • RECEIVED ₹"&TEXT(SUMIF('Final Calculation Sheet'!$G$4:$G$1000,"AL HAMD TRADE CORPORATION",'Final Calculation Sheet'!$AC$4:$AC$1000),"#,##0")&" • OUTSTANDING ₹"&TEXT(SUMIF('Final Calculation Sheet'!$G$4:$G$1000,"AL HAMD TRADE CORPORATION",'Final Calculation Sheet'!$AD$4:$AD$1000),"#,##0")
A6: =IF('Final Calculation Sheet'!$F$4="","",'Final Calculation Sheet'!$F$4) | B6: =IF('Final Calculation Sheet'!$B$4="","",'Final Calculation Sheet'!$B$4) | C6: =IF('Final Calculation Sheet'!$D$4="","",'Final Calculation Sheet'!$D$4) | D6: =IF('Final Calculation Sheet'!$A$4="","",'Final Calculation Sheet'!$A$4) | E6: =IF('Final Calculation Sheet'!$E$4="","",'Final Calculation Sheet'!$E$4) | F6: =IF('Final Calculation Sheet'!$C$4="","",'Final Calculation Sheet'!$C$4) | G6: =IF('Final Calculation Sheet'!$H$4="","",'Final Calculation Sheet'!$H$4) | H6: =IF('Final Calculation Sheet'!$I$4="","",'Final Calculation Sheet'!$I$4) | I6: =IF('Final Calculation Sheet'!$J$4="","",'Final Calculation Sheet'!$J$4) | J6: =IF('Final Calculation Sheet'!$K$4="","",'Final Calculation Sheet'!$K$4) | K6: =IF('Final Calculation Sheet'!$L$4="","",'Final Calculation Sheet'!$L$4) | L6: =IF('Final Calculation Sheet'!$M$4="","",'Final Calculation Sheet'!$M$4) | M6: =IF('Final Calculation Sheet'!$N$4="","",'Final Calculation Sheet'!$N$4) | N6: =IF('Final Calculation Sheet'!$O$4="","",'Final Calculation Sheet'!$O$4) | O6: =IF('Final Calculation Sheet'!$P$4="","",'Final Calculation Sheet'!$P$4) | P6: =IF('Final Calculation Sheet'!$Q$4="","",'Final Calculation Sheet'!$Q$4) | Q6: =IF('Final Calculation Sheet'!$R$4="","",'Final Calculation Sheet'!$R$4) | R6: =IF('Final Calculation Sheet'!$S$4="","",'Final Calculation Sheet'!$S$4) | S6: =IF('Final Calculation Sheet'!$T$4="","",'Final Calculation Sheet'!$T$4) | T6: =IF('Final Calculation Sheet'!$U$4="","",'Final Calculation Sheet'!$U$4) | U6: =IF('Final Calculation Sheet'!$V$4="","",'Final Calculation Sheet'!$V$4) | V6: =IF('Final Calculation Sheet'!$W$4="","",'Final Calculation Sheet'!$W$4) | W6: =IF('Final Calculation Sheet'!$X$4="","",'Final Calculation Sheet'!$X$4) | X6: =IF('Final Calculation Sheet'!$Y$4="","",'Final Calculation Sheet'!$Y$4) | Y6: =IF('Final Calculation Sheet'!$Z$4="","",'Final Calculation Sheet'!$Z$4) | Z6: =IF('Final Calculation Sheet'!$AA$4="","",'Final Calculation Sheet'!$AA$4) | AA6: =IF('Final Calculation Sheet'!$AB$4="","",'Final Calculation Sheet'!$AB$4) | AB6: =IF('Final Calculation Sheet'!$AC$4="","",'Final Calculation Sheet'!$AC$4) | AC6: =IF('Final Calculation Sheet'!$AD$4="","",'Final Calculation Sheet'!$AD$4) | AD6: =IF('Final Calculation Sheet'!$AD$4="","",IF('Final Calculation Sheet'!$AD$4<=0,"SETTLED","OUTSTANDING")) | AE6: =IF('Final Calculation Sheet'!$AE$4="","",'Final Calculation Sheet'!$AE$4) | AF6: =IF('Final Calculation Sheet'!$AF$4="","",'Final Calculation Sheet'!$AF$4) | AG6: =IF('Final Calculation Sheet'!$AG$4="","",'Final Calculation Sheet'!$AG$4)
A7: ∑ AL HAMD TRADE CORPORATION — TOTALS | B7: – | C7: – | D7: =SUM(D6:D6) | E7: – | F7: – | G7: =SUM(G6:G6) | H7: =SUM(H6:H6) | I7: =SUM(I6:I6) | J7: =SUM(J6:J6) | K7: =SUM(K6:K6) | L7: =SUM(L6:L6) | M7: =SUM(M6:M6) | N7: =SUM(N6:N6) | O7: =SUM(O6:O6) | P7: – | Q7: =SUM(Q6:Q6) | R7: =SUM(R6:R6) | S7: =SUM(S6:S6) | T7: =SUM(T6:T6) | U7: – | V7: =SUM(V6:V6) | W7: =SUM(W6:W6) | X7: – | Y7: =SUM(Y6:Y6) | Z7: =SUM(Z6:Z6) | AA7: – | AB7: =SUM(AB6:AB6) | AC7: =SUM(AC6:AC6) | AD7: – | AE7: – | AF7: – | AG7: –
A9: ="▼ F R KHANS ENTERPRISES • "&COUNTIF('Final Calculation Sheet'!$G$4:$G$1000,"F R KHANS ENTERPRISES")&" LOT(S) • MAT. VALUE ₹"&TEXT(SUMIF('Final Calculation Sheet'!$G$4:$G$1000,"F R KHANS ENTERPRISES",'Final Calculation Sheet'!$H$4:$H$1000),"#,##0")&" • RECEIVED ₹"&TEXT(SUMIF('Final Calculation Sheet'!$G$4:$G$1000,"F R KHANS ENTERPRISES",'Final Calculation Sheet'!$AC$4:$AC$1000),"#,##0")&" • OUTSTANDING ₹"&TEXT(SUMIF('Final Calculation Sheet'!$G$4:$G$1000,"F R KHANS ENTERPRISES",'Final Calculation Sheet'!$AD$4:$AD$1000),"#,##0")
A10: =IF('Final Calculation Sheet'!$F$6="","",'Final Calculation Sheet'!$F$6) | B10: =IF('Final Calculation Sheet'!$B$6="","",'Final Calculation Sheet'!$B$6) | C10: =IF('Final Calculation Sheet'!$D$6="","",'Final Calculation Sheet'!$D$6) | D10: =IF('Final Calculation Sheet'!$A$6="","",'Final Calculation Sheet'!$A$6) | E10: =IF('Final Calculation Sheet'!$E$6="","",'Final Calculation Sheet'!$E$6) | F10: =IF('Final Calculation Sheet'!$C$6="","",'Final Calculation Sheet'!$C$6) | G10: =IF('Final Calculation Sheet'!$H$6="","",'Final Calculation Sheet'!$H$6) | H10: =IF('Final Calculation Sheet'!$I$6="","",'Final Calculation Sheet'!$I$6) | I10: =IF('Final Calculation Sheet'!$J$6="","",'Final Calculation Sheet'!$J$6) | J10: =IF('Final Calculation Sheet'!$K$6="","",'Final Calculation Sheet'!$K$6) | K10: =IF('Final Calculation Sheet'!$L$6="","",'Final Calculation Sheet'!$L$6) | L10: =IF('Final Calculation Sheet'!$M$6="","",'Final Calculation Sheet'!$M$6) | M10: =IF('Final Calculation Sheet'!$N$6="","",'Final Calculation Sheet'!$N$6) | N10: =IF('Final Calculation Sheet'!$O$6="","",'Final Calculation Sheet'!$O$6) | O10: =IF('Final Calculation Sheet'!$P$6="","",'Final Calculation Sheet'!$P$6) | P10: =IF('Final Calculation Sheet'!$Q$6="","",'Final Calculation Sheet'!$Q$6) | Q10: =IF('Final Calculation Sheet'!$R$6="","",'Final Calculation Sheet'!$R$6) | R10: =IF('Final Calculation Sheet'!$S$6="","",'Final Calculation Sheet'!$S$6) | S10: =IF('Final Calculation Sheet'!$T$6="","",'Final Calculation Sheet'!$T$6) | T10: =IF('Final Calculation Sheet'!$U$6="","",'Final Calculation Sheet'!$U$6) | U10: =IF('Final Calculation Sheet'!$V$6="","",'Final Calculation Sheet'!$V$6) | V10: =IF('Final Calculation Sheet'!$W$6="","",'Final Calculation Sheet'!$W$6) | W10: =IF('Final Calculation Sheet'!$X$6="","",'Final Calculation Sheet'!$X$6) | X10: =IF('Final Calculation Sheet'!$Y$6="","",'Final Calculation Sheet'!$Y$6) | Y10: =IF('Final Calculation Sheet'!$Z$6="","",'Final Calculation Sheet'!$Z$6) | Z10: =IF('Final Calculation Sheet'!$AA$6="","",'Final Calculation Sheet'!$AA$6) | AA10: =IF('Final Calculation Sheet'!$AB$6="","",'Final Calculation Sheet'!$AB$6) | AB10: =IF('Final Calculation Sheet'!$AC$6="","",'Final Calculation Sheet'!$AC$6) | AC10: =IF('Final Calculation Sheet'!$AD$6="","",'Final Calculation Sheet'!$AD$6) | AD10: =IF('Final Calculation Sheet'!$AD$6="","",IF('Final Calculation Sheet'!$AD$6<=0,"SETTLED","OUTSTANDING")) | AE10: =IF('Final Calculation Sheet'!$AE$6="","",'Final Calculation Sheet'!$AE$6) | AF10: =IF('Final Calculation Sheet'!$AF$6="","",'Final Calculation Sheet'!$AF$6) | AG10: =IF('Final Calculation Sheet'!$AG$6="","",'Final Calculation Sheet'!$AG$6)
A11: =IF('Final Calculation Sheet'!$F$7="","",'Final Calculation Sheet'!$F$7) | B11: =IF('Final Calculation Sheet'!$B$7="","",'Final Calculation Sheet'!$B$7) | C11: =IF('Final Calculation Sheet'!$D$7="","",'Final Calculation Sheet'!$D$7) | D11: =IF('Final Calculation Sheet'!$A$7="","",'Final Calculation Sheet'!$A$7) | E11: =IF('Final Calculation Sheet'!$E$7="","",'Final Calculation Sheet'!$E$7) | F11: =IF('Final Calculation Sheet'!$C$7="","",'Final Calculation Sheet'!$C$7) | G11: =IF('Final Calculation Sheet'!$H$7="","",'Final Calculation Sheet'!$H$7) | H11: =IF('Final Calculation Sheet'!$I$7="","",'Final Calculation Sheet'!$I$7) | I11: =IF('Final Calculation Sheet'!$J$7="","",'Final Calculation Sheet'!$J$7) | J11: =IF('Final Calculation Sheet'!$K$7="","",'Final Calculation Sheet'!$K$7) | K11: =IF('Final Calculation Sheet'!$L$7="","",'Final Calculation Sheet'!$L$7) | L11: =IF('Final Calculation Sheet'!$M$7="","",'Final Calculation Sheet'!$M$7) | M11: =IF('Final Calculation Sheet'!$N$7="","",'Final Calculation Sheet'!$N$7) | N11: =IF('Final Calculation Sheet'!$O$7="","",'Final Calculation Sheet'!$O$7) | O11: =IF('Final Calculation Sheet'!$P$7="","",'Final Calculation Sheet'!$P$7) | P11: =IF('Final Calculation Sheet'!$Q$7="","",'Final Calculation Sheet'!$Q$7) | Q11: =IF('Final Calculation Sheet'!$R$7="","",'Final Calculation Sheet'!$R$7) | R11: =IF('Final Calculation Sheet'!$S$7="","",'Final Calculation Sheet'!$S$7) | S11: =IF('Final Calculation Sheet'!$T$7="","",'Final Calculation Sheet'!$T$7) | T11: =IF('Final Calculation Sheet'!$U$7="","",'Final Calculation Sheet'!$U$7) | U11: =IF('Final Calculation Sheet'!$V$7="","",'Final Calculation Sheet'!$V$7) | V11: =IF('Final Calculation Sheet'!$W$7="","",'Final Calculation Sheet'!$W$7) | W11: =IF('Final Calculation Sheet'!$X$7="","",'Final Calculation Sheet'!$X$7) | X11: =IF('Final Calculation Sheet'!$Y$7="","",'Final Calculation Sheet'!$Y$7) | Y11: =IF('Final Calculation Sheet'!$Z$7="","",'Final Calculation Sheet'!$Z$7) | Z11: =IF('Final Calculation Sheet'!$AA$7="","",'Final Calculation Sheet'!$AA$7) | AA11: =IF('Final Calculation Sheet'!$AB$7="","",'Final Calculation Sheet'!$AB$7) | AB11: =IF('Final Calculation Sheet'!$AC$7="","",'Final Calculation Sheet'!$AC$7) | AC11: =IF('Final Calculation Sheet'!$AD$7="","",'Final Calculation Sheet'!$AD$7) | AD11: =IF('Final Calculation Sheet'!$AD$7="","",IF('Final Calculation Sheet'!$AD$7<=0,"SETTLED","OUTSTANDING")) | AE11: =IF('Final Calculation Sheet'!$AE$7="","",'Final Calculation Sheet'!$AE$7) | AF11: =IF('Final Calculation Sheet'!$AF$7="","",'Final Calculation Sheet'!$AF$7) | AG11: =IF('Final Calculation Sheet'!$AG$7="","",'Final Calculation Sheet'!$AG$7)
A12: ∑ F R KHANS ENTERPRISES — TOTALS | B12: – | C12: – | D12: =SUM(D10:D11) | E12: – | F12: – | G12: =SUM(G10:G11) | H12: =SUM(H10:H11) | I12: =SUM(I10:I11) | J12: =SUM(J10:J11) | K12: =SUM(K10:K11) | L12: =SUM(L10:L11) | M12: =SUM(M10:M11) | N12: =SUM(N10:N11) | O12: =SUM(O10:O11) | P12: – | Q12: =SUM(Q10:Q11) | R12: =SUM(R10:R11) | S12: =SUM(S10:S11) | T12: =SUM(T10:T11) | U12: – | V12: =SUM(V10:V11) | W12: =SUM(W10:W11) | X12: – | Y12: =SUM(Y10:Y11) | Z12: =SUM(Z10:Z11) | AA12: – | AB12: =SUM(AB10:AB11) | AC12: =SUM(AC10:AC11) | AD12: – | AE12: – | AF12: – | AG12: –
A14: ="▼ HIND TRADERS • "&COUNTIF('Final Calculation Sheet'!$G$4:$G$1000,"HIND TRADERS")&" LOT(S) • MAT. VALUE ₹"&TEXT(SUMIF('Final Calculation Sheet'!$G$4:$G$1000,"HIND TRADERS",'Final Calculation Sheet'!$H$4:$H$1000),"#,##0")&" • RECEIVED ₹"&TEXT(SUMIF('Final Calculation Sheet'!$G$4:$G$1000,"HIND TRADERS",'Final Calculation Sheet'!$AC$4:$AC$1000),"#,##0")&" • OUTSTANDING ₹"&TEXT(SUMIF('Final Calculation Sheet'!$G$4:$G$1000,"HIND TRADERS",'Final Calculation Sheet'!$AD$4:$AD$1000),"#,##0")
A15: =IF('Final Calculation Sheet'!$F$15="","",'Final Calculation Sheet'!$F$15) | B15: =IF('Final Calculation Sheet'!$B$15="","",'Final Calculation Sheet'!$B$15) | C15: =IF('Final Calculation Sheet'!$D$15="","",'Final Calculation Sheet'!$D$15) | D15: =IF('Final Calculation Sheet'!$A$15="","",'Final Calculation Sheet'!$A$15) | E15: =IF('Final Calculation Sheet'!$E$15="","",'Final Calculation Sheet'!$E$15) | F15: =IF('Final Calculation Sheet'!$C$15="","",'Final Calculation Sheet'!$C$15) | G15: =IF('Final Calculation Sheet'!$H$15="","",'Final Calculation Sheet'!$H$15) | H15: =IF('Final Calculation Sheet'!$I$15="","",'Final Calculation Sheet'!$I$15) | I15: =IF('Final Calculation Sheet'!$J$15="","",'Final Calculation Sheet'!$J$15) | J15: =IF('Final Calculation Sheet'!$K$15="","",'Final Calculation Sheet'!$K$15) | K15: =IF('Final Calculation Sheet'!$L$15="","",'Final Calculation Sheet'!$L$15) | L15: =IF('Final Calculation Sheet'!$M$15="","",'Final Calculation Sheet'!$M$15) | M15: =IF('Final Calculation Sheet'!$N$15="","",'Final Calculation Sheet'!$N$15) | N15: =IF('Final Calculation Sheet'!$O$15="","",'Final Calculation Sheet'!$O$15) | O15: =IF('Final Calculation Sheet'!$P$15="","",'Final Calculation Sheet'!$P$15) | P15: =IF('Final Calculation Sheet'!$Q$15="","",'Final Calculation Sheet'!$Q$15) | Q15: =IF('Final Calculation Sheet'!$R$15="","",'Final Calculation Sheet'!$R$15) | R15: =IF('Final Calculation Sheet'!$S$15="","",'Final Calculation Sheet'!$S$15) | S15: =IF('Final Calculation Sheet'!$T$15="","",'Final Calculation Sheet'!$T$15) | T15: =IF('Final Calculation Sheet'!$U$15="","",'Final Calculation Sheet'!$U$15) | U15: =IF('Final Calculation Sheet'!$V$15="","",'Final Calculation Sheet'!$V$15) | V15: =IF('Final Calculation Sheet'!$W$15="","",'Final Calculation Sheet'!$W$15) | W15: =IF('Final Calculation Sheet'!$X$15="","",'Final Calculation Sheet'!$X$15) | X15: =IF('Final Calculation Sheet'!$Y$15="","",'Final Calculation Sheet'!$Y$15) | Y15: =IF('Final Calculation Sheet'!$Z$15="","",'Final Calculation Sheet'!$Z$15) | Z15: =IF('Final Calculation Sheet'!$AA$15="","",'Final Calculation Sheet'!$AA$15) | AA15: =IF('Final Calculation Sheet'!$AB$15="","",'Final Calculation Sheet'!$AB$15) | AB15: =IF('Final Calculation Sheet'!$AC$15="","",'Final Calculation Sheet'!$AC$15) | AC15: =IF('Final Calculation Sheet'!$AD$15="","",'Final Calculation Sheet'!$AD$15) | AD15: =IF('Final Calculation Sheet'!$AD$15="","",IF('Final Calculation Sheet'!$AD$15<=0,"SETTLED","OUTSTANDING")) | AE15: =IF('Final Calculation Sheet'!$AE$15="","",'Final Calculation Sheet'!$AE$15) | AF15: =IF('Final Calculation Sheet'!$AF$15="","",'Final Calculation Sheet'!$AF$15) | AG15: =IF('Final Calculation Sheet'!$AG$15="","",'Final Calculation Sheet'!$AG$15)
A16: ∑ HIND TRADERS — TOTALS | B16: – | C16: – | D16: =SUM(D15:D15) | E16: – | F16: – | G16: =SUM(G15:G15) | H16: =SUM(H15:H15) | I16: =SUM(I15:I15) | J16: =SUM(J15:J15) | K16: =SUM(K15:K15) | L16: =SUM(L15:L15) | M16: =SUM(M15:M15) | N16: =SUM(N15:N15) | O16: =SUM(O15:O15) | P16: – | Q16: =SUM(Q15:Q15) | R16: =SUM(R15:R15) | S16: =SUM(S15:S15) | T16: =SUM(T15:T15) | U16: – | V16: =SUM(V15:V15) | W16: =SUM(W15:W15) | X16: – | Y16: =SUM(Y15:Y15) | Z16: =SUM(Z15:Z15) | AA16: – | AB16: =SUM(AB15:AB15) | AC16: =SUM(AC15:AC15) | AD16: – | AE16: – | AF16: – | AG16: –
A18: ="▼ KASHYAP TRADING CO • "&COUNTIF('Final Calculation Sheet'!$G$4:$G$1000,"KASHYAP TRADING CO")&" LOT(S) • MAT. VALUE ₹"&TEXT(SUMIF('Final Calculation Sheet'!$G$4:$G$1000,"KASHYAP TRADING CO",'Final Calculation Sheet'!$H$4:$H$1000),"#,##0")&" • RECEIVED ₹"&TEXT(SUMIF('Final Calculation Sheet'!$G$4:$G$1000,"KASHYAP TRADING CO",'Final Calculation Sheet'!$AC$4:$AC$1000),"#,##0")&" • OUTSTANDING ₹"&TEXT(SUMIF('Final Calculation Sheet'!$G$4:$G$1000,"KASHYAP TRADING CO",'Final Calculation Sheet'!$AD$4:$AD$1000),"#,##0")
A19: =IF('Final Calculation Sheet'!$F$38="","",'Final Calculation Sheet'!$F$38) | B19: =IF('Final Calculation Sheet'!$B$38="","",'Final Calculation Sheet'!$B$38) | C19: =IF('Final Calculation Sheet'!$D$38="","",'Final Calculation Sheet'!$D$38) | D19: =IF('Final Calculation Sheet'!$A$38="","",'Final Calculation Sheet'!$A$38) | E19: =IF('Final Calculation Sheet'!$E$38="","",'Final Calculation Sheet'!$E$38) | F19: =IF('Final Calculation Sheet'!$C$38="","",'Final Calculation Sheet'!$C$38) | G19: =IF('Final Calculation Sheet'!$H$38="","",'Final Calculation Sheet'!$H$38) | H19: =IF('Final Calculation Sheet'!$I$38="","",'Final Calculation Sheet'!$I$38) | I19: =IF('Final Calculation Sheet'!$J$38="","",'Final Calculation Sheet'!$J$38) | J19: =IF('Final Calculation Sheet'!$K$38="","",'Final Calculation Sheet'!$K$38) | K19: =IF('Final Calculation Sheet'!$L$38="","",'Final Calculation Sheet'!$L$38) | L19: =IF('Final Calculation Sheet'!$M$38="","",'Final Calculation Sheet'!$M$38) | M19: =IF('Final Calculation Sheet'!$N$38="","",'Final Calculation Sheet'!$N$38) | N19: =IF('Final Calculation Sheet'!$O$38="","",'Final Calculation Sheet'!$O$38) | O19: =IF('Final Calculation Sheet'!$P$38="","",'Final Calculation Sheet'!$P$38) | P19: =IF('Final Calculation Sheet'!$Q$38="","",'Final Calculation Sheet'!$Q$38) | Q19: =IF('Final Calculation Sheet'!$R$38="","",'Final Calculation Sheet'!$R$38) | R19: =IF('Final Calculation Sheet'!$S$38="","",'Final Calculation Sheet'!$S$38) | S19: =IF('Final Calculation Sheet'!$T$38="","",'Final Calculation Sheet'!$T$38) | T19: =IF('Final Calculation Sheet'!$U$38="","",'Final Calculation Sheet'!$U$38) | U19: =IF('Final Calculation Sheet'!$V$38="","",'Final Calculation Sheet'!$V$38) | V19: =IF('Final Calculation Sheet'!$W$38="","",'Final Calculation Sheet'!$W$38) | W19: =IF('Final Calculation Sheet'!$X$38="","",'Final Calculation Sheet'!$X$38) | X19: =IF('Final Calculation Sheet'!$Y$38="","",'Final Calculation Sheet'!$Y$38) | Y19: =IF('Final Calculation Sheet'!$Z$38="","",'Final Calculation Sheet'!$Z$38) | Z19: =IF('Final Calculation Sheet'!$AA$38="","",'Final Calculation Sheet'!$AA$38) | AA19: =IF('Final Calculation Sheet'!$AB$38="","",'Final Calculation Sheet'!$AB$38) | AB19: =IF('Final Calculation Sheet'!$AC$38="","",'Final Calculation Sheet'!$AC$38) | AC19: =IF('Final Calculation Sheet'!$AD$38="","",'Final Calculation Sheet'!$AD$38) | AD19: =IF('Final Calculation Sheet'!$AD$38="","",IF('Final Calculation Sheet'!$AD$38<=0,"SETTLED","OUTSTANDING")) | AE19: =IF('Final Calculation Sheet'!$AE$38="","",'Final Calculation Sheet'!$AE$38) | AF19: =IF('Final Calculation Sheet'!$AF$38="","",'Final Calculation Sheet'!$AF$38) | AG19: =IF('Final Calculation Sheet'!$AG$38="","",'Final Calculation Sheet'!$AG$38)
A20: ∑ KASHYAP TRADING CO — TOTALS | B20: – | C20: – | D20: =SUM(D19:D19) | E20: – | F20: – | G20: =SUM(G19:G19) | H20: =SUM(H19:H19) | I20: =SUM(I19:I19) | J20: =SUM(J19:J19) | K20: =SUM(K19:K19) | L20: =SUM(L19:L19) | M20: =SUM(M19:M19) | N20: =SUM(N19:N19) | O20: =SUM(O19:O19) | P20: – | Q20: =SUM(Q19:Q19) | R20: =SUM(R19:R19) | S20: =SUM(S19:S19) | T20: =SUM(T19:T19) | U20: – | V20: =SUM(V19:V19) | W20: =SUM(W19:W19) | X20: – | Y20: =SUM(Y19:Y19) | Z20: =SUM(Z19:Z19) | AA20: – | AB20: =SUM(AB19:AB19) | AC20: =SUM(AC19:AC19) | AD20: – | AE20: – | AF20: – | AG20: –
A22: ="▼ M I SCRAP TRADERS • "&COUNTIF('Final Calculation Sheet'!$G$4:$G$1000,"M I SCRAP TRADERS")&" LOT(S) • MAT. VALUE ₹"&TEXT(SUMIF('Final Calculation Sheet'!$G$4:$G$1000,"M I SCRAP TRADERS",'Final Calculation Sheet'!$H$4:$H$1000),"#,##0")&" • RECEIVED ₹"&TEXT(SUMIF('Final Calculation Sheet'!$G$4:$G$1000,"M I SCRAP TRADERS",'Final Calculation Sheet'!$AC$4:$AC$1000),"#,##0")&" • OUTSTANDING ₹"&TEXT(SUMIF('Final Calculation Sheet'!$G$4:$G$1000,"M I SCRAP TRADERS",'Final Calculation Sheet'!$AD$4:$AD$1000),"#,##0")
A23: =IF('Final Calculation Sheet'!$F$27="","",'Final Calculation Sheet'!$F$27) | B23: =IF('Final Calculation Sheet'!$B$27="","",'Final Calculation Sheet'!$B$27) | C23: =IF('Final Calculation Sheet'!$D$27="","",'Final Calculation Sheet'!$D$27) | D23: =IF('Final Calculation Sheet'!$A$27="","",'Final Calculation Sheet'!$A$27) | E23: =IF('Final Calculation Sheet'!$E$27="","",'Final Calculation Sheet'!$E$27) | F23: =IF('Final Calculation Sheet'!$C$27="","",'Final Calculation Sheet'!$C$27) | G23: =IF('Final Calculation Sheet'!$H$27="","",'Final Calculation Sheet'!$H$27) | H23: =IF('Final Calculation Sheet'!$I$27="","",'Final Calculation Sheet'!$I$27) | I23: =IF('Final Calculation Sheet'!$J$27="","",'Final Calculation Sheet'!$J$27) | J23: =IF('Final Calculation Sheet'!$K$27="","",'Final Calculation Sheet'!$K$27) | K23: =IF('Final Calculation Sheet'!$L$27="","",'Final Calculation Sheet'!$L$27) | L23: =IF('Final Calculation Sheet'!$M$27="","",'Final Calculation Sheet'!$M$27) | M23: =IF('Final Calculation Sheet'!$N$27="","",'Final Calculation Sheet'!$N$27) | N23: =IF('Final Calculation Sheet'!$O$27="","",'Final Calculation Sheet'!$O$27) | O23: =IF('Final Calculation Sheet'!$P$27="","",'Final Calculation Sheet'!$P$27) | P23: =IF('Final Calculation Sheet'!$Q$27="","",'Final Calculation Sheet'!$Q$27) | Q23: =IF('Final Calculation Sheet'!$R$27="","",'Final Calculation Sheet'!$R$27) | R23: =IF('Final Calculation Sheet'!$S$27="","",'Final Calculation Sheet'!$S$27) | S23: =IF('Final Calculation Sheet'!$T$27="","",'Final Calculation Sheet'!$T$27) | T23: =IF('Final Calculation Sheet'!$U$27="","",'Final Calculation Sheet'!$U$27) | U23: =IF('Final Calculation Sheet'!$V$27="","",'Final Calculation Sheet'!$V$27) | V23: =IF('Final Calculation Sheet'!$W$27="","",'Final Calculation Sheet'!$W$27) | W23: =IF('Final Calculation Sheet'!$X$27="","",'Final Calculation Sheet'!$X$27) | X23: =IF('Final Calculation Sheet'!$Y$27="","",'Final Calculation Sheet'!$Y$27) | Y23: =IF('Final Calculation Sheet'!$Z$27="","",'Final Calculation Sheet'!$Z$27) | Z23: =IF('Final Calculation Sheet'!$AA$27="","",'Final Calculation Sheet'!$AA$27) | AA23: =IF('Final Calculation Sheet'!$AB$27="","",'Final Calculation Sheet'!$AB$27) | AB23: =IF('Final Calculation Sheet'!$AC$27="","",'Final Calculation Sheet'!$AC$27) | AC23: =IF('Final Calculation Sheet'!$AD$27="","",'Final Calculation Sheet'!$AD$27) | AD23: =IF('Final Calculation Sheet'!$AD$27="","",IF('Final Calculation Sheet'!$AD$27<=0,"SETTLED","OUTSTANDING")) | AE23: =IF('Final Calculation Sheet'!$AE$27="","",'Final Calculation Sheet'!$AE$27) | AF23: =IF('Final Calculation Sheet'!$AF$27="","",'Final Calculation Sheet'!$AF$27) | AG23: =IF('Final Calculation Sheet'!$AG$27="","",'Final Calculation Sheet'!$AG$27)
A24: ∑ M I SCRAP TRADERS — TOTALS | B24: – | C24: – | D24: =SUM(D23:D23) | E24: – | F24: – | G24: =SUM(G23:G23) | H24: =SUM(H23:H23) | I24: =SUM(I23:I23) | J24: =SUM(J23:J23) | K24: =SUM(K23:K23) | L24: =SUM(L23:L23) | M24: =SUM(M23:M23) | N24: =SUM(N23:N23) | O24: =SUM(O23:O23) | P24: – | Q24: =SUM(Q23:Q23) | R24: =SUM(R23:R23) | S24: =SUM(S23:S23) | T24: =SUM(T23:T23) | U24: – | V24: =SUM(V23:V23) | W24: =SUM(W23:W23) | X24: – | Y24: =SUM(Y23:Y23) | Z24: =SUM(Z23:Z23) | AA24: – | AB24: =SUM(AB23:AB23) | AC24: =SUM(AC23:AC23) | AD24: – | AE24: – | AF24: – | AG24: –
A26: ="▼ NATIONAL ENTERPRISES • "&COUNTIF('Final Calculation Sheet'!$G$4:$G$1000,"NATIONAL ENTERPRISES")&" LOT(S) • MAT. VALUE ₹"&TEXT(SUMIF('Final Calculation Sheet'!$G$4:$G$1000,"NATIONAL ENTERPRISES",'Final Calculation Sheet'!$H$4:$H$1000),"#,##0")&" • RECEIVED ₹"&TEXT(SUMIF('Final Calculation Sheet'!$G$4:$G$1000,"NATIONAL ENTERPRISES",'Final Calculation Sheet'!$AC$4:$AC$1000),"#,##0")&" • OUTSTANDING ₹"&TEXT(SUMIF('Final Calculation Sheet'!$G$4:$G$1000,"NATIONAL ENTERPRISES",'Final Calculation Sheet'!$AD$4:$AD$1000),"#,##0")
A27: =IF('Final Calculation Sheet'!$F$5="","",'Final Calculation Sheet'!$F$5) | B27: =IF('Final Calculation Sheet'!$B$5="","",'Final Calculation Sheet'!$B$5) | C27: =IF('Final Calculation Sheet'!$D$5="","",'Final Calculation Sheet'!$D$5) | D27: =IF('Final Calculation Sheet'!$A$5="","",'Final Calculation Sheet'!$A$5) | E27: =IF('Final Calculation Sheet'!$E$5="","",'Final Calculation Sheet'!$E$5) | F27: =IF('Final Calculation Sheet'!$C$5="","",'Final Calculation Sheet'!$C$5) | G27: =IF('Final Calculation Sheet'!$H$5="","",'Final Calculation Sheet'!$H$5) | H27: =IF('Final Calculation Sheet'!$I$5="","",'Final Calculation Sheet'!$I$5) | I27: =IF('Final Calculation Sheet'!$J$5="","",'Final Calculation Sheet'!$J$5) | J27: =IF('Final Calculation Sheet'!$K$5="","",'Final Calculation Sheet'!$K$5) | K27: =IF('Final Calculation Sheet'!$L$5="","",'Final Calculation Sheet'!$L$5) | L27: =IF('Final Calculation Sheet'!$M$5="","",'Final Calculation Sheet'!$M$5) | M27: =IF('Final Calculation Sheet'!$N$5="","",'Final Calculation Sheet'!$N$5) | N27: =IF('Final Calculation Sheet'!$O$5="","",'Final Calculation Sheet'!$O$5) | O27: =IF('Final Calculation Sheet'!$P$5="","",'Final Calculation Sheet'!$P$5) | P27: =IF('Final Calculation Sheet'!$Q$5="","",'Final Calculation Sheet'!$Q$5) | Q27: =IF('Final Calculation Sheet'!$R$5="","",'Final Calculation Sheet'!$R$5) | R27: =IF('Final Calculation Sheet'!$S$5="","",'Final Calculation Sheet'!$S$5) | S27: =IF('Final Calculation Sheet'!$T$5="","",'Final Calculation Sheet'!$T$5) | T27: =IF('Final Calculation Sheet'!$U$5="","",'Final Calculation Sheet'!$U$5) | U27: =IF('Final Calculation Sheet'!$V$5="","",'Final Calculation Sheet'!$V$5) | V27: =IF('Final Calculation Sheet'!$W$5="","",'Final Calculation Sheet'!$W$5) | W27: =IF('Final Calculation Sheet'!$X$5="","",'Final Calculation Sheet'!$X$5) | X27: =IF('Final Calculation Sheet'!$Y$5="","",'Final Calculation Sheet'!$Y$5) | Y27: =IF('Final Calculation Sheet'!$Z$5="","",'Final Calculation Sheet'!$Z$5) | Z27: =IF('Final Calculation Sheet'!$AA$5="","",'Final Calculation Sheet'!$AA$5) | AA27: =IF('Final Calculation Sheet'!$AB$5="","",'Final Calculation Sheet'!$AB$5) | AB27: =IF('Final Calculation Sheet'!$AC$5="","",'Final Calculation Sheet'!$AC$5) | AC27: =IF('Final Calculation Sheet'!$AD$5="","",'Final Calculation Sheet'!$AD$5) | AD27: =IF('Final Calculation Sheet'!$AD$5="","",IF('Final Calculation Sheet'!$AD$5<=0,"SETTLED","OUTSTANDING")) | AE27: =IF('Final Calculation Sheet'!$AE$5="","",'Final Calculation Sheet'!$AE$5) | AF27: =IF('Final Calculation Sheet'!$AF$5="","",'Final Calculation Sheet'!$AF$5) | AG27: =IF('Final Calculation Sheet'!$AG$5="","",'Final Calculation Sheet'!$AG$5)
A28: =IF('Final Calculation Sheet'!$F$10="","",'Final Calculation Sheet'!$F$10) | B28: =IF('Final Calculation Sheet'!$B$10="","",'Final Calculation Sheet'!$B$10) | C28: =IF('Final Calculation Sheet'!$D$10="","",'Final Calculation Sheet'!$D$10) | D28: =IF('Final Calculation Sheet'!$A$10="","",'Final Calculation Sheet'!$A$10) | E28: =IF('Final Calculation Sheet'!$E$10="","",'Final Calculation Sheet'!$E$10) | F28: =IF('Final Calculation Sheet'!$C$10="","",'Final Calculation Sheet'!$C$10) | G28: =IF('Final Calculation Sheet'!$H$10="","",'Final Calculation Sheet'!$H$10) | H28: =IF('Final Calculation Sheet'!$I$10="","",'Final Calculation Sheet'!$I$10) | I28: =IF('Final Calculation Sheet'!$J$10="","",'Final Calculation Sheet'!$J$10) | J28: =IF('Final Calculation Sheet'!$K$10="","",'Final Calculation Sheet'!$K$10) | K28: =IF('Final Calculation Sheet'!$L$10="","",'Final Calculation Sheet'!$L$10) | L28: =IF('Final Calculation Sheet'!$M$10="","",'Final Calculation Sheet'!$M$10) | M28: =IF('Final Calculation Sheet'!$N$10="","",'Final Calculation Sheet'!$N$10) | N28: =IF('Final Calculation Sheet'!$O$10="","",'Final Calculation Sheet'!$O$10) | O28: =IF('Final Calculation Sheet'!$P$10="","",'Final Calculation Sheet'!$P$10) | P28: =IF('Final Calculation Sheet'!$Q$10="","",'Final Calculation Sheet'!$Q$10) | Q28: =IF('Final Calculation Sheet'!$R$10="","",'Final Calculation Sheet'!$R$10) | R28: =IF('Final Calculation Sheet'!$S$10="","",'Final Calculation Sheet'!$S$10) | S28: =IF('Final Calculation Sheet'!$T$10="","",'Final Calculation Sheet'!$T$10) | T28: =IF('Final Calculation Sheet'!$U$10="","",'Final Calculation Sheet'!$U$10) | U28: =IF('Final Calculation Sheet'!$V$10="","",'Final Calculation Sheet'!$V$10) | V28: =IF('Final Calculation Sheet'!$W$10="","",'Final Calculation Sheet'!$W$10) | W28: =IF('Final Calculation Sheet'!$X$10="","",'Final Calculation Sheet'!$X$10) | X28: =IF('Final Calculation Sheet'!$Y$10="","",'Final Calculation Sheet'!$Y$10) | Y28: =IF('Final Calculation Sheet'!$Z$10="","",'Final Calculation Sheet'!$Z$10) | Z28: =IF('Final Calculation Sheet'!$AA$10="","",'Final Calculation Sheet'!$AA$10) | AA28: =IF('Final Calculation Sheet'!$AB$10="","",'Final Calculation Sheet'!$AB$10) | AB28: =IF('Final Calculation Sheet'!$AC$10="","",'Final Calculation Sheet'!$AC$10) | AC28: =IF('Final Calculation Sheet'!$AD$10="","",'Final Calculation Sheet'!$AD$10) | AD28: =IF('Final Calculation Sheet'!$AD$10="","",IF('Final Calculation Sheet'!$AD$10<=0,"SETTLED","OUTSTANDING")) | AE28: =IF('Final Calculation Sheet'!$AE$10="","",'Final Calculation Sheet'!$AE$10) | AF28: =IF('Final Calculation Sheet'!$AF$10="","",'Final Calculation Sheet'!$AF$10) | AG28: =IF('Final Calculation Sheet'!$AG$10="","",'Final Calculation Sheet'!$AG$10)
A29: =IF('Final Calculation Sheet'!$F$11="","",'Final Calculation Sheet'!$F$11) | B29: =IF('Final Calculation Sheet'!$B$11="","",'Final Calculation Sheet'!$B$11) | C29: =IF('Final Calculation Sheet'!$D$11="","",'Final Calculation Sheet'!$D$11) | D29: =IF('Final Calculation Sheet'!$A$11="","",'Final Calculation Sheet'!$A$11) | E29: =IF('Final Calculation Sheet'!$E$11="","",'Final Calculation Sheet'!$E$11) | F29: =IF('Final Calculation Sheet'!$C$11="","",'Final Calculation Sheet'!$C$11) | G29: =IF('Final Calculation Sheet'!$H$11="","",'Final Calculation Sheet'!$H$11) | H29: =IF('Final Calculation Sheet'!$I$11="","",'Final Calculation Sheet'!$I$11) | I29: =IF('Final Calculation Sheet'!$J$11="","",'Final Calculation Sheet'!$J$11) | J29: =IF('Final Calculation Sheet'!$K$11="","",'Final Calculation Sheet'!$K$11) | K29: =IF('Final Calculation Sheet'!$L$11="","",'Final Calculation Sheet'!$L$11) | L29: =IF('Final Calculation Sheet'!$M$11="","",'Final Calculation Sheet'!$M$11) | M29: =IF('Final Calculation Sheet'!$N$11="","",'Final Calculation Sheet'!$N$11) | N29: =IF('Final Calculation Sheet'!$O$11="","",'Final Calculation Sheet'!$O$11) | O29: =IF('Final Calculation Sheet'!$P$11="","",'Final Calculation Sheet'!$P$11) | P29: =IF('Final Calculation Sheet'!$Q$11="","",'Final Calculation Sheet'!$Q$11) | Q29: =IF('Final Calculation Sheet'!$R$11="","",'Final Calculation Sheet'!$R$11) | R29: =IF('Final Calculation Sheet'!$S$11="","",'Final Calculation Sheet'!$S$11) | S29: =IF('Final Calculation Sheet'!$T$11="","",'Final Calculation Sheet'!$T$11) | T29: =IF('Final Calculation Sheet'!$U$11="","",'Final Calculation Sheet'!$U$11) | U29: =IF('Final Calculation Sheet'!$V$11="","",'Final Calculation Sheet'!$V$11) | V29: =IF('Final Calculation Sheet'!$W$11="","",'Final Calculation Sheet'!$W$11) | W29: =IF('Final Calculation Sheet'!$X$11="","",'Final Calculation Sheet'!$X$11) | X29: =IF('Final Calculation Sheet'!$Y$11="","",'Final Calculation Sheet'!$Y$11) | Y29: =IF('Final Calculation Sheet'!$Z$11="","",'Final Calculation Sheet'!$Z$11) | Z29: =IF('Final Calculation Sheet'!$AA$11="","",'Final Calculation Sheet'!$AA$11) | AA29: =IF('Final Calculation Sheet'!$AB$11="","",'Final Calculation Sheet'!$AB$11) | AB29: =IF('Final Calculation Sheet'!$AC$11="","",'Final Calculation Sheet'!$AC$11) | AC29: =IF('Final Calculation Sheet'!$AD$11="","",'Final Calculation Sheet'!$AD$11) | AD29: =IF('Final Calculation Sheet'!$AD$11="","",IF('Final Calculation Sheet'!$AD$11<=0,"SETTLED","OUTSTANDING")) | AE29: =IF('Final Calculation Sheet'!$AE$11="","",'Final Calculation Sheet'!$AE$11) | AF29: =IF('Final Calculation Sheet'!$AF$11="","",'Final Calculation Sheet'!$AF$11) | AG29: =IF('Final Calculation Sheet'!$AG$11="","",'Final Calculation Sheet'!$AG$11)
A30: =IF('Final Calculation Sheet'!$F$12="","",'Final Calculation Sheet'!$F$12) | B30: =IF('Final Calculation Sheet'!$B$12="","",'Final Calculation Sheet'!$B$12) | C30: =IF('Final Calculation Sheet'!$D$12="","",'Final Calculation Sheet'!$D$12) | D30: =IF('Final Calculation Sheet'!$A$12="","",'Final Calculation Sheet'!$A$12) | E30: =IF('Final Calculation Sheet'!$E$12="","",'Final Calculation Sheet'!$E$12) | F30: =IF('Final Calculation Sheet'!$C$12="","",'Final Calculation Sheet'!$C$12) | G30: =IF('Final Calculation Sheet'!$H$12="","",'Final Calculation Sheet'!$H$12) | H30: =IF('Final Calculation Sheet'!$I$12="","",'Final Calculation Sheet'!$I$12) | I30: =IF('Final Calculation Sheet'!$J$12="","",'Final Calculation Sheet'!$J$12) | J30: =IF('Final Calculation Sheet'!$K$12="","",'Final Calculation Sheet'!$K$12) | K30: =IF('Final Calculation Sheet'!$L$12="","",'Final Calculation Sheet'!$L$12) | L30: =IF('Final Calculation Sheet'!$M$12="","",'Final Calculation Sheet'!$M$12) | M30: =IF('Final Calculation Sheet'!$N$12="","",'Final Calculation Sheet'!$N$12) | N30: =IF('Final Calculation Sheet'!$O$12="","",'Final Calculation Sheet'!$O$12) | O30: =IF('Final Calculation Sheet'!$P$12="","",'Final Calculation Sheet'!$P$12) | P30: =IF('Final Calculation Sheet'!$Q$12="","",'Final Calculation Sheet'!$Q$12) | Q30: =IF('Final Calculation Sheet'!$R$12="","",'Final Calculation Sheet'!$R$12) | R30: =IF('Final Calculation Sheet'!$S$12="","",'Final Calculation Sheet'!$S$12) | S30: =IF('Final Calculation Sheet'!$T$12="","",'Final Calculation Sheet'!$T$12) | T30: =IF('Final Calculation Sheet'!$U$12="","",'Final Calculation Sheet'!$U$12) | U30: =IF('Final Calculation Sheet'!$V$12="","",'Final Calculation Sheet'!$V$12) | V30: =IF('Final Calculation Sheet'!$W$12="","",'Final Calculation Sheet'!$W$12) | W30: =IF('Final Calculation Sheet'!$X$12="","",'Final Calculation Sheet'!$X$12) | X30: =IF('Final Calculation Sheet'!$Y$12="","",'Final Calculation Sheet'!$Y$12) | Y30: =IF('Final Calculation Sheet'!$Z$12="","",'Final Calculation Sheet'!$Z$12) | Z30: =IF('Final Calculation Sheet'!$AA$12="","",'Final Calculation Sheet'!$AA$12) | AA30: =IF('Final Calculation Sheet'!$AB$12="","",'Final Calculation Sheet'!$AB$12) | AB30: =IF('Final Calculation Sheet'!$AC$12="","",'Final Calculation Sheet'!$AC$12) | AC30: =IF('Final Calculation Sheet'!$AD$12="","",'Final Calculation Sheet'!$AD$12) | AD30: =IF('Final Calculation Sheet'!$AD$12="","",IF('Final Calculation Sheet'!$AD$12<=0,"SETTLED","OUTSTANDING")) | AE30: =IF('Final Calculation Sheet'!$AE$12="","",'Final Calculation Sheet'!$AE$12) | AF30: =IF('Final Calculation Sheet'!$AF$12="","",'Final Calculation Sheet'!$AF$12) | AG30: =IF('Final Calculation Sheet'!$AG$12="","",'Final Calculation Sheet'!$AG$12)
A31: =IF('Final Calculation Sheet'!$F$18="","",'Final Calculation Sheet'!$F$18) | B31: =IF('Final Calculation Sheet'!$B$18="","",'Final Calculation Sheet'!$B$18) | C31: =IF('Final Calculation Sheet'!$D$18="","",'Final Calculation Sheet'!$D$18) | D31: =IF('Final Calculation Sheet'!$A$18="","",'Final Calculation Sheet'!$A$18) | E31: =IF('Final Calculation Sheet'!$E$18="","",'Final Calculation Sheet'!$E$18) | F31: =IF('Final Calculation Sheet'!$C$18="","",'Final Calculation Sheet'!$C$18) | G31: =IF('Final Calculation Sheet'!$H$18="","",'Final Calculation Sheet'!$H$18) | H31: =IF('Final Calculation Sheet'!$I$18="","",'Final Calculation Sheet'!$I$18) | I31: =IF('Final Calculation Sheet'!$J$18="","",'Final Calculation Sheet'!$J$18) | J31: =IF('Final Calculation Sheet'!$K$18="","",'Final Calculation Sheet'!$K$18) | K31: =IF('Final Calculation Sheet'!$L$18="","",'Final Calculation Sheet'!$L$18) | L31: =IF('Final Calculation Sheet'!$M$18="","",'Final Calculation Sheet'!$M$18) | M31: =IF('Final Calculation Sheet'!$N$18="","",'Final Calculation Sheet'!$N$18) | N31: =IF('Final Calculation Sheet'!$O$18="","",'Final Calculation Sheet'!$O$18) | O31: =IF('Final Calculation Sheet'!$P$18="","",'Final Calculation Sheet'!$P$18) | P31: =IF('Final Calculation Sheet'!$Q$18="","",'Final Calculation Sheet'!$Q$18) | Q31: =IF('Final Calculation Sheet'!$R$18="","",'Final Calculation Sheet'!$R$18) | R31: =IF('Final Calculation Sheet'!$S$18="","",'Final Calculation Sheet'!$S$18) | S31: =IF('Final Calculation Sheet'!$T$18="","",'Final Calculation Sheet'!$T$18) | T31: =IF('Final Calculation Sheet'!$U$18="","",'Final Calculation Sheet'!$U$18) | U31: =IF('Final Calculation Sheet'!$V$18="","",'Final Calculation Sheet'!$V$18) | V31: =IF('Final Calculation Sheet'!$W$18="","",'Final Calculation Sheet'!$W$18) | W31: =IF('Final Calculation Sheet'!$X$18="","",'Final Calculation Sheet'!$X$18) | X31: =IF('Final Calculation Sheet'!$Y$18="","",'Final Calculation Sheet'!$Y$18) | Y31: =IF('Final Calculation Sheet'!$Z$18="","",'Final Calculation Sheet'!$Z$18) | Z31: =IF('Final Calculation Sheet'!$AA$18="","",'Final Calculation Sheet'!$AA$18) | AA31: =IF('Final Calculation Sheet'!$AB$18="","",'Final Calculation Sheet'!$AB$18) | AB31: =IF('Final Calculation Sheet'!$AC$18="","",'Final Calculation Sheet'!$AC$18) | AC31: =IF('Final Calculation Sheet'!$AD$18="","",'Final Calculation Sheet'!$AD$18) | AD31: =IF('Final Calculation Sheet'!$AD$18="","",IF('Final Calculation Sheet'!$AD$18<=0,"SETTLED","OUTSTANDING")) | AE31: =IF('Final Calculation Sheet'!$AE$18="","",'Final Calculation Sheet'!$AE$18) | AF31: =IF('Final Calculation Sheet'!$AF$18="","",'Final Calculation Sheet'!$AF$18) | AG31: =IF('Final Calculation Sheet'!$AG$18="","",'Final Calculation Sheet'!$AG$18)
A32: =IF('Final Calculation Sheet'!$F$19="","",'Final Calculation Sheet'!$F$19) | B32: =IF('Final Calculation Sheet'!$B$19="","",'Final Calculation Sheet'!$B$19) | C32: =IF('Final Calculation Sheet'!$D$19="","",'Final Calculation Sheet'!$D$19) | D32: =IF('Final Calculation Sheet'!$A$19="","",'Final Calculation Sheet'!$A$19) | E32: =IF('Final Calculation Sheet'!$E$19="","",'Final Calculation Sheet'!$E$19) | F32: =IF('Final Calculation Sheet'!$C$19="","",'Final Calculation Sheet'!$C$19) | G32: =IF('Final Calculation Sheet'!$H$19="","",'Final Calculation Sheet'!$H$19) | H32: =IF('Final Calculation Sheet'!$I$19="","",'Final Calculation Sheet'!$I$19) | I32: =IF('Final Calculation Sheet'!$J$19="","",'Final Calculation Sheet'!$J$19) | J32: =IF('Final Calculation Sheet'!$K$19="","",'Final Calculation Sheet'!$K$19) | K32: =IF('Final Calculation Sheet'!$L$19="","",'Final Calculation Sheet'!$L$19) | L32: =IF('Final Calculation Sheet'!$M$19="","",'Final Calculation Sheet'!$M$19) | M32: =IF('Final Calculation Sheet'!$N$19="","",'Final Calculation Sheet'!$N$19) | N32: =IF('Final Calculation Sheet'!$O$19="","",'Final Calculation Sheet'!$O$19) | O32: =IF('Final Calculation Sheet'!$P$19="","",'Final Calculation Sheet'!$P$19) | P32: =IF('Final Calculation Sheet'!$Q$19="","",'Final Calculation Sheet'!$Q$19) | Q32: =IF('Final Calculation Sheet'!$R$19="","",'Final Calculation Sheet'!$R$19) | R32: =IF('Final Calculation Sheet'!$S$19="","",'Final Calculation Sheet'!$S$19) | S32: =IF('Final Calculation Sheet'!$T$19="","",'Final Calculation Sheet'!$T$19) | T32: =IF('Final Calculation Sheet'!$U$19="","",'Final Calculation Sheet'!$U$19) | U32: =IF('Final Calculation Sheet'!$V$19="","",'Final Calculation Sheet'!$V$19) | V32: =IF('Final Calculation Sheet'!$W$19="","",'Final Calculation Sheet'!$W$19) | W32: =IF('Final Calculation Sheet'!$X$19="","",'Final Calculation Sheet'!$X$19) | X32: =IF('Final Calculation Sheet'!$Y$19="","",'Final Calculation Sheet'!$Y$19) | Y32: =IF('Final Calculation Sheet'!$Z$19="","",'Final Calculation Sheet'!$Z$19) | Z32: =IF('Final Calculation Sheet'!$AA$19="","",'Final Calculation Sheet'!$AA$19) | AA32: =IF('Final Calculation Sheet'!$AB$19="","",'Final Calculation Sheet'!$AB$19) | AB32: =IF('Final Calculation Sheet'!$AC$19="","",'Final Calculation Sheet'!$AC$19) | AC32: =IF('Final Calculation Sheet'!$AD$19="","",'Final Calculation Sheet'!$AD$19) | AD32: =IF('Final Calculation Sheet'!$AD$19="","",IF('Final Calculation Sheet'!$AD$19<=0,"SETTLED","OUTSTANDING")) | AE32: =IF('Final Calculation Sheet'!$AE$19="","",'Final Calculation Sheet'!$AE$19) | AF32: =IF('Final Calculation Sheet'!$AF$19="","",'Final Calculation Sheet'!$AF$19) | AG32: =IF('Final Calculation Sheet'!$AG$19="","",'Final Calculation Sheet'!$AG$19)
A33: =IF('Final Calculation Sheet'!$F$22="","",'Final Calculation Sheet'!$F$22) | B33: =IF('Final Calculation Sheet'!$B$22="","",'Final Calculation Sheet'!$B$22) | C33: =IF('Final Calculation Sheet'!$D$22="","",'Final Calculation Sheet'!$D$22) | D33: =IF('Final Calculation Sheet'!$A$22="","",'Final Calculation Sheet'!$A$22) | E33: =IF('Final Calculation Sheet'!$E$22="","",'Final Calculation Sheet'!$E$22) | F33: =IF('Final Calculation Sheet'!$C$22="","",'Final Calculation Sheet'!$C$22) | G33: =IF('Final Calculation Sheet'!$H$22="","",'Final Calculation Sheet'!$H$22) | H33: =IF('Final Calculation Sheet'!$I$22="","",'Final Calculation Sheet'!$I$22) | I33: =IF('Final Calculation Sheet'!$J$22="","",'Final Calculation Sheet'!$J$22) | J33: =IF('Final Calculation Sheet'!$K$22="","",'Final Calculation Sheet'!$K$22) | K33: =IF('Final Calculation Sheet'!$L$22="","",'Final Calculation Sheet'!$L$22) | L33: =IF('Final Calculation Sheet'!$M$22="","",'Final Calculation Sheet'!$M$22) | M33: =IF('Final Calculation Sheet'!$N$22="","",'Final Calculation Sheet'!$N$22) | N33: =IF('Final Calculation Sheet'!$O$22="","",'Final Calculation Sheet'!$O$22) | O33: =IF('Final Calculation Sheet'!$P$22="","",'Final Calculation Sheet'!$P$22) | P33: =IF('Final Calculation Sheet'!$Q$22="","",'Final Calculation Sheet'!$Q$22) | Q33: =IF('Final Calculation Sheet'!$R$22="","",'Final Calculation Sheet'!$R$22) | R33: =IF('Final Calculation Sheet'!$S$22="","",'Final Calculation Sheet'!$S$22) | S33: =IF('Final Calculation Sheet'!$T$22="","",'Final Calculation Sheet'!$T$22) | T33: =IF('Final Calculation Sheet'!$U$22="","",'Final Calculation Sheet'!$U$22) | U33: =IF('Final Calculation Sheet'!$V$22="","",'Final Calculation Sheet'!$V$22) | V33: =IF('Final Calculation Sheet'!$W$22="","",'Final Calculation Sheet'!$W$22) | W33: =IF('Final Calculation Sheet'!$X$22="","",'Final Calculation Sheet'!$X$22) | X33: =IF('Final Calculation Sheet'!$Y$22="","",'Final Calculation Sheet'!$Y$22) | Y33: =IF('Final Calculation Sheet'!$Z$22="","",'Final Calculation Sheet'!$Z$22) | Z33: =IF('Final Calculation Sheet'!$AA$22="","",'Final Calculation Sheet'!$AA$22) | AA33: =IF('Final Calculation Sheet'!$AB$22="","",'Final Calculation Sheet'!$AB$22) | AB33: =IF('Final Calculation Sheet'!$AC$22="","",'Final Calculation Sheet'!$AC$22) | AC33: =IF('Final Calculation Sheet'!$AD$22="","",'Final Calculation Sheet'!$AD$22) | AD33: =IF('Final Calculation Sheet'!$AD$22="","",IF('Final Calculation Sheet'!$AD$22<=0,"SETTLED","OUTSTANDING")) | AE33: =IF('Final Calculation Sheet'!$AE$22="","",'Final Calculation Sheet'!$AE$22) | AF33: =IF('Final Calculation Sheet'!$AF$22="","",'Final Calculation Sheet'!$AF$22) | AG33: =IF('Final Calculation Sheet'!$AG$22="","",'Final Calculation Sheet'!$AG$22)
A34: =IF('Final Calculation Sheet'!$F$24="","",'Final Calculation Sheet'!$F$24) | B34: =IF('Final Calculation Sheet'!$B$24="","",'Final Calculation Sheet'!$B$24) | C34: =IF('Final Calculation Sheet'!$D$24="","",'Final Calculation Sheet'!$D$24) | D34: =IF('Final Calculation Sheet'!$A$24="","",'Final Calculation Sheet'!$A$24) | E34: =IF('Final Calculation Sheet'!$E$24="","",'Final Calculation Sheet'!$E$24) | F34: =IF('Final Calculation Sheet'!$C$24="","",'Final Calculation Sheet'!$C$24) | G34: =IF('Final Calculation Sheet'!$H$24="","",'Final Calculation Sheet'!$H$24) | H34: =IF('Final Calculation Sheet'!$I$24="","",'Final Calculation Sheet'!$I$24) | I34: =IF('Final Calculation Sheet'!$J$24="","",'Final Calculation Sheet'!$J$24) | J34: =IF('Final Calculation Sheet'!$K$24="","",'Final Calculation Sheet'!$K$24) | K34: =IF('Final Calculation Sheet'!$L$24="","",'Final Calculation Sheet'!$L$24) | L34: =IF('Final Calculation Sheet'!$M$24="","",'Final Calculation Sheet'!$M$24) | M34: =IF('Final Calculation Sheet'!$N$24="","",'Final Calculation Sheet'!$N$24) | N34: =IF('Final Calculation Sheet'!$O$24="","",'Final Calculation Sheet'!$O$24) | O34: =IF('Final Calculation Sheet'!$P$24="","",'Final Calculation Sheet'!$P$24) | P34: =IF('Final Calculation Sheet'!$Q$24="","",'Final Calculation Sheet'!$Q$24) | Q34: =IF('Final Calculation Sheet'!$R$24="","",'Final Calculation Sheet'!$R$24) | R34: =IF('Final Calculation Sheet'!$S$24="","",'Final Calculation Sheet'!$S$24) | S34: =IF('Final Calculation Sheet'!$T$24="","",'Final Calculation Sheet'!$T$24) | T34: =IF('Final Calculation Sheet'!$U$24="","",'Final Calculation Sheet'!$U$24) | U34: =IF('Final Calculation Sheet'!$V$24="","",'Final Calculation Sheet'!$V$24) | V34: =IF('Final Calculation Sheet'!$W$24="","",'Final Calculation Sheet'!$W$24) | W34: =IF('Final Calculation Sheet'!$X$24="","",'Final Calculation Sheet'!$X$24) | X34: =IF('Final Calculation Sheet'!$Y$24="","",'Final Calculation Sheet'!$Y$24) | Y34: =IF('Final Calculation Sheet'!$Z$24="","",'Final Calculation Sheet'!$Z$24) | Z34: =IF('Final Calculation Sheet'!$AA$24="","",'Final Calculation Sheet'!$AA$24) | AA34: =IF('Final Calculation Sheet'!$AB$24="","",'Final Calculation Sheet'!$AB$24) | AB34: =IF('Final Calculation Sheet'!$AC$24="","",'Final Calculation Sheet'!$AC$24) | AC34: =IF('Final Calculation Sheet'!$AD$24="","",'Final Calculation Sheet'!$AD$24) | AD34: =IF('Final Calculation Sheet'!$AD$24="","",IF('Final Calculation Sheet'!$AD$24<=0,"SETTLED","OUTSTANDING")) | AE34: =IF('Final Calculation Sheet'!$AE$24="","",'Final Calculation Sheet'!$AE$24) | AF34: =IF('Final Calculation Sheet'!$AF$24="","",'Final Calculation Sheet'!$AF$24) | AG34: =IF('Final Calculation Sheet'!$AG$24="","",'Final Calculation Sheet'!$AG$24)
A35: =IF('Final Calculation Sheet'!$F$26="","",'Final Calculation Sheet'!$F$26) | B35: =IF('Final Calculation Sheet'!$B$26="","",'Final Calculation Sheet'!$B$26) | C35: =IF('Final Calculation Sheet'!$D$26="","",'Final Calculation Sheet'!$D$26) | D35: =IF('Final Calculation Sheet'!$A$26="","",'Final Calculation Sheet'!$A$26) | E35: =IF('Final Calculation Sheet'!$E$26="","",'Final Calculation Sheet'!$E$26) | F35: =IF('Final Calculation Sheet'!$C$26="","",'Final Calculation Sheet'!$C$26) | G35: =IF('Final Calculation Sheet'!$H$26="","",'Final Calculation Sheet'!$H$26) | H35: =IF('Final Calculation Sheet'!$I$26="","",'Final Calculation Sheet'!$I$26) | I35: =IF('Final Calculation Sheet'!$J$26="","",'Final Calculation Sheet'!$J$26) | J35: =IF('Final Calculation Sheet'!$K$26="","",'Final Calculation Sheet'!$K$26) | K35: =IF('Final Calculation Sheet'!$L$26="","",'Final Calculation Sheet'!$L$26) | L35: =IF('Final Calculation Sheet'!$M$26="","",'Final Calculation Sheet'!$M$26) | M35: =IF('Final Calculation Sheet'!$N$26="","",'Final Calculation Sheet'!$N$26) | N35: =IF('Final Calculation Sheet'!$O$26="","",'Final Calculation Sheet'!$O$26) | O35: =IF('Final Calculation Sheet'!$P$26="","",'Final Calculation Sheet'!$P$26) | P35: =IF('Final Calculation Sheet'!$Q$26="","",'Final Calculation Sheet'!$Q$26) | Q35: =IF('Final Calculation Sheet'!$R$26="","",'Final Calculation Sheet'!$R$26) | R35: =IF('Final Calculation Sheet'!$S$26="","",'Final Calculation Sheet'!$S$26) | S35: =IF('Final Calculation Sheet'!$T$26="","",'Final Calculation Sheet'!$T$26) | T35: =IF('Final Calculation Sheet'!$U$26="","",'Final Calculation Sheet'!$U$26) | U35: =IF('Final Calculation Sheet'!$V$26="","",'Final Calculation Sheet'!$V$26) | V35: =IF('Final Calculation Sheet'!$W$26="","",'Final Calculation Sheet'!$W$26) | W35: =IF('Final Calculation Sheet'!$X$26="","",'Final Calculation Sheet'!$X$26) | X35: =IF('Final Calculation Sheet'!$Y$26="","",'Final Calculation Sheet'!$Y$26) | Y35: =IF('Final Calculation Sheet'!$Z$26="","",'Final Calculation Sheet'!$Z$26) | Z35: =IF('Final Calculation Sheet'!$AA$26="","",'Final Calculation Sheet'!$AA$26) | AA35: =IF('Final Calculation Sheet'!$AB$26="","",'Final Calculation Sheet'!$AB$26) | AB35: =IF('Final Calculation Sheet'!$AC$26="","",'Final Calculation Sheet'!$AC$26) | AC35: =IF('Final Calculation Sheet'!$AD$26="","",'Final Calculation Sheet'!$AD$26) | AD35: =IF('Final Calculation Sheet'!$AD$26="","",IF('Final Calculation Sheet'!$AD$26<=0,"SETTLED","OUTSTANDING")) | AE35: =IF('Final Calculation Sheet'!$AE$26="","",'Final Calculation Sheet'!$AE$26) | AF35: =IF('Final Calculation Sheet'!$AF$26="","",'Final Calculation Sheet'!$AF$26) | AG35: =IF('Final Calculation Sheet'!$AG$26="","",'Final Calculation Sheet'!$AG$26)
A36: =IF('Final Calculation Sheet'!$F$30="","",'Final Calculation Sheet'!$F$30) | B36: =IF('Final Calculation Sheet'!$B$30="","",'Final Calculation Sheet'!$B$30) | C36: =IF('Final Calculation Sheet'!$D$30="","",'Final Calculation Sheet'!$D$30) | D36: =IF('Final Calculation Sheet'!$A$30="","",'Final Calculation Sheet'!$A$30) | E36: =IF('Final Calculation Sheet'!$E$30="","",'Final Calculation Sheet'!$E$30) | F36: =IF('Final Calculation Sheet'!$C$30="","",'Final Calculation Sheet'!$C$30) | G36: =IF('Final Calculation Sheet'!$H$30="","",'Final Calculation Sheet'!$H$30) | H36: =IF('Final Calculation Sheet'!$I$30="","",'Final Calculation Sheet'!$I$30) | I36: =IF('Final Calculation Sheet'!$J$30="","",'Final Calculation Sheet'!$J$30) | J36: =IF('Final Calculation Sheet'!$K$30="","",'Final Calculation Sheet'!$K$30) | K36: =IF('Final Calculation Sheet'!$L$30="","",'Final Calculation Sheet'!$L$30) | L36: =IF('Final Calculation Sheet'!$M$30="","",'Final Calculation Sheet'!$M$30) | M36: =IF('Final Calculation Sheet'!$N$30="","",'Final Calculation Sheet'!$N$30) | N36: =IF('Final Calculation Sheet'!$O$30="","",'Final Calculation Sheet'!$O$30) | O36: =IF('Final Calculation Sheet'!$P$30="","",'Final Calculation Sheet'!$P$30) | P36: =IF('Final Calculation Sheet'!$Q$30="","",'Final Calculation Sheet'!$Q$30) | Q36: =IF('Final Calculation Sheet'!$R$30="","",'Final Calculation Sheet'!$R$30) | R36: =IF('Final Calculation Sheet'!$S$30="","",'Final Calculation Sheet'!$S$30) | S36: =IF('Final Calculation Sheet'!$T$30="","",'Final Calculation Sheet'!$T$30) | T36: =IF('Final Calculation Sheet'!$U$30="","",'Final Calculation Sheet'!$U$30) | U36: =IF('Final Calculation Sheet'!$V$30="","",'Final Calculation Sheet'!$V$30) | V36: =IF('Final Calculation Sheet'!$W$30="","",'Final Calculation Sheet'!$W$30) | W36: =IF('Final Calculation Sheet'!$X$30="","",'Final Calculation Sheet'!$X$30) | X36: =IF('Final Calculation Sheet'!$Y$30="","",'Final Calculation Sheet'!$Y$30) | Y36: =IF('Final Calculation Sheet'!$Z$30="","",'Final Calculation Sheet'!$Z$30) | Z36: =IF('Final Calculation Sheet'!$AA$30="","",'Final Calculation Sheet'!$AA$30) | AA36: =IF('Final Calculation Sheet'!$AB$30="","",'Final Calculation Sheet'!$AB$30) | AB36: =IF('Final Calculation Sheet'!$AC$30="","",'Final Calculation Sheet'!$AC$30) | AC36: =IF('Final Calculation Sheet'!$AD$30="","",'Final Calculation Sheet'!$AD$30) | AD36: =IF('Final Calculation Sheet'!$AD$30="","",IF('Final Calculation Sheet'!$AD$30<=0,"SETTLED","OUTSTANDING")) | AE36: =IF('Final Calculation Sheet'!$AE$30="","",'Final Calculation Sheet'!$AE$30) | AF36: =IF('Final Calculation Sheet'!$AF$30="","",'Final Calculation Sheet'!$AF$30) | AG36: =IF('Final Calculation Sheet'!$AG$30="","",'Final Calculation Sheet'!$AG$30)
A37: =IF('Final Calculation Sheet'!$F$32="","",'Final Calculation Sheet'!$F$32) | B37: =IF('Final Calculation Sheet'!$B$32="","",'Final Calculation Sheet'!$B$32) | C37: =IF('Final Calculation Sheet'!$D$32="","",'Final Calculation Sheet'!$D$32) | D37: =IF('Final Calculation Sheet'!$A$32="","",'Final Calculation Sheet'!$A$32) | E37: =IF('Final Calculation Sheet'!$E$32="","",'Final Calculation Sheet'!$E$32) | F37: =IF('Final Calculation Sheet'!$C$32="","",'Final Calculation Sheet'!$C$32) | G37: =IF('Final Calculation Sheet'!$H$32="","",'Final Calculation Sheet'!$H$32) | H37: =IF('Final Calculation Sheet'!$I$32="","",'Final Calculation Sheet'!$I$32) | I37: =IF('Final Calculation Sheet'!$J$32="","",'Final Calculation Sheet'!$J$32) | J37: =IF('Final Calculation Sheet'!$K$32="","",'Final Calculation Sheet'!$K$32) | K37: =IF('Final Calculation Sheet'!$L$32="","",'Final Calculation Sheet'!$L$32) | L37: =IF('Final Calculation Sheet'!$M$32="","",'Final Calculation Sheet'!$M$32) | M37: =IF('Final Calculation Sheet'!$N$32="","",'Final Calculation Sheet'!$N$32) | N37: =IF('Final Calculation Sheet'!$O$32="","",'Final Calculation Sheet'!$O$32) | O37: =IF('Final Calculation Sheet'!$P$32="","",'Final Calculation Sheet'!$P$32) | P37: =IF('Final Calculation Sheet'!$Q$32="","",'Final Calculation Sheet'!$Q$32) | Q37: =IF('Final Calculation Sheet'!$R$32="","",'Final Calculation Sheet'!$R$32) | R37: =IF('Final Calculation Sheet'!$S$32="","",'Final Calculation Sheet'!$S$32) | S37: =IF('Final Calculation Sheet'!$T$32="","",'Final Calculation Sheet'!$T$32) | T37: =IF('Final Calculation Sheet'!$U$32="","",'Final Calculation Sheet'!$U$32) | U37: =IF('Final Calculation Sheet'!$V$32="","",'Final Calculation Sheet'!$V$32) | V37: =IF('Final Calculation Sheet'!$W$32="","",'Final Calculation Sheet'!$W$32) | W37: =IF('Final Calculation Sheet'!$X$32="","",'Final Calculation Sheet'!$X$32) | X37: =IF('Final Calculation Sheet'!$Y$32="","",'Final Calculation Sheet'!$Y$32) | Y37: =IF('Final Calculation Sheet'!$Z$32="","",'Final Calculation Sheet'!$Z$32) | Z37: =IF('Final Calculation Sheet'!$AA$32="","",'Final Calculation Sheet'!$AA$32) | AA37: =IF('Final Calculation Sheet'!$AB$32="","",'Final Calculation Sheet'!$AB$32) | AB37: =IF('Final Calculation Sheet'!$AC$32="","",'Final Calculation Sheet'!$AC$32) | AC37: =IF('Final Calculation Sheet'!$AD$32="","",'Final Calculation Sheet'!$AD$32) | AD37: =IF('Final Calculation Sheet'!$AD$32="","",IF('Final Calculation Sheet'!$AD$32<=0,"SETTLED","OUTSTANDING")) | AE37: =IF('Final Calculation Sheet'!$AE$32="","",'Final Calculation Sheet'!$AE$32) | AF37: =IF('Final Calculation Sheet'!$AF$32="","",'Final Calculation Sheet'!$AF$32) | AG37: =IF('Final Calculation Sheet'!$AG$32="","",'Final Calculation Sheet'!$AG$32)
A38: =IF('Final Calculation Sheet'!$F$33="","",'Final Calculation Sheet'!$F$33) | B38: =IF('Final Calculation Sheet'!$B$33="","",'Final Calculation Sheet'!$B$33) | C38: =IF('Final Calculation Sheet'!$D$33="","",'Final Calculation Sheet'!$D$33) | D38: =IF('Final Calculation Sheet'!$A$33="","",'Final Calculation Sheet'!$A$33) | E38: =IF('Final Calculation Sheet'!$E$33="","",'Final Calculation Sheet'!$E$33) | F38: =IF('Final Calculation Sheet'!$C$33="","",'Final Calculation Sheet'!$C$33) | G38: =IF('Final Calculation Sheet'!$H$33="","",'Final Calculation Sheet'!$H$33) | H38: =IF('Final Calculation Sheet'!$I$33="","",'Final Calculation Sheet'!$I$33) | I38: =IF('Final Calculation Sheet'!$J$33="","",'Final Calculation Sheet'!$J$33) | J38: =IF('Final Calculation Sheet'!$K$33="","",'Final Calculation Sheet'!$K$33) | K38: =IF('Final Calculation Sheet'!$L$33="","",'Final Calculation Sheet'!$L$33) | L38: =IF('Final Calculation Sheet'!$M$33="","",'Final Calculation Sheet'!$M$33) | M38: =IF('Final Calculation Sheet'!$N$33="","",'Final Calculation Sheet'!$N$33) | N38: =IF('Final Calculation Sheet'!$O$33="","",'Final Calculation Sheet'!$O$33) | O38: =IF('Final Calculation Sheet'!$P$33="","",'Final Calculation Sheet'!$P$33) | P38: =IF('Final Calculation Sheet'!$Q$33="","",'Final Calculation Sheet'!$Q$33) | Q38: =IF('Final Calculation Sheet'!$R$33="","",'Final Calculation Sheet'!$R$33) | R38: =IF('Final Calculation Sheet'!$S$33="","",'Final Calculation Sheet'!$S$33) | S38: =IF('Final Calculation Sheet'!$T$33="","",'Final Calculation Sheet'!$T$33) | T38: =IF('Final Calculation Sheet'!$U$33="","",'Final Calculation Sheet'!$U$33) | U38: =IF('Final Calculation Sheet'!$V$33="","",'Final Calculation Sheet'!$V$33) | V38: =IF('Final Calculation Sheet'!$W$33="","",'Final Calculation Sheet'!$W$33) | W38: =IF('Final Calculation Sheet'!$X$33="","",'Final Calculation Sheet'!$X$33) | X38: =IF('Final Calculation Sheet'!$Y$33="","",'Final Calculation Sheet'!$Y$33) | Y38: =IF('Final Calculation Sheet'!$Z$33="","",'Final Calculation Sheet'!$Z$33) | Z38: =IF('Final Calculation Sheet'!$AA$33="","",'Final Calculation Sheet'!$AA$33) | AA38: =IF('Final Calculation Sheet'!$AB$33="","",'Final Calculation Sheet'!$AB$33) | AB38: =IF('Final Calculation Sheet'!$AC$33="","",'Final Calculation Sheet'!$AC$33) | AC38: =IF('Final Calculation Sheet'!$AD$33="","",'Final Calculation Sheet'!$AD$33) | AD38: =IF('Final Calculation Sheet'!$AD$33="","",IF('Final Calculation Sheet'!$AD$33<=0,"SETTLED","OUTSTANDING")) | AE38: =IF('Final Calculation Sheet'!$AE$33="","",'Final Calculation Sheet'!$AE$33) | AF38: =IF('Final Calculation Sheet'!$AF$33="","",'Final Calculation Sheet'!$AF$33) | AG38: =IF('Final Calculation Sheet'!$AG$33="","",'Final Calculation Sheet'!$AG$33)
A39: =IF('Final Calculation Sheet'!$F$37="","",'Final Calculation Sheet'!$F$37) | B39: =IF('Final Calculation Sheet'!$B$37="","",'Final Calculation Sheet'!$B$37) | C39: =IF('Final Calculation Sheet'!$D$37="","",'Final Calculation Sheet'!$D$37) | D39: =IF('Final Calculation Sheet'!$A$37="","",'Final Calculation Sheet'!$A$37) | E39: =IF('Final Calculation Sheet'!$E$37="","",'Final Calculation Sheet'!$E$37) | F39: =IF('Final Calculation Sheet'!$C$37="","",'Final Calculation Sheet'!$C$37) | G39: =IF('Final Calculation Sheet'!$H$37="","",'Final Calculation Sheet'!$H$37) | H39: =IF('Final Calculation Sheet'!$I$37="","",'Final Calculation Sheet'!$I$37) | I39: =IF('Final Calculation Sheet'!$J$37="","",'Final Calculation Sheet'!$J$37) | J39: =IF('Final Calculation Sheet'!$K$37="","",'Final Calculation Sheet'!$K$37) | K39: =IF('Final Calculation Sheet'!$L$37="","",'Final Calculation Sheet'!$L$37) | L39: =IF('Final Calculation Sheet'!$M$37="","",'Final Calculation Sheet'!$M$37) | M39: =IF('Final Calculation Sheet'!$N$37="","",'Final Calculation Sheet'!$N$37) | N39: =IF('Final Calculation Sheet'!$O$37="","",'Final Calculation Sheet'!$O$37) | O39: =IF('Final Calculation Sheet'!$P$37="","",'Final Calculation Sheet'!$P$37) | P39: =IF('Final Calculation Sheet'!$Q$37="","",'Final Calculation Sheet'!$Q$37) | Q39: =IF('Final Calculation Sheet'!$R$37="","",'Final Calculation Sheet'!$R$37) | R39: =IF('Final Calculation Sheet'!$S$37="","",'Final Calculation Sheet'!$S$37) | S39: =IF('Final Calculation Sheet'!$T$37="","",'Final Calculation Sheet'!$T$37) | T39: =IF('Final Calculation Sheet'!$U$37="","",'Final Calculation Sheet'!$U$37) | U39: =IF('Final Calculation Sheet'!$V$37="","",'Final Calculation Sheet'!$V$37) | V39: =IF('Final Calculation Sheet'!$W$37="","",'Final Calculation Sheet'!$W$37) | W39: =IF('Final Calculation Sheet'!$X$37="","",'Final Calculation Sheet'!$X$37) | X39: =IF('Final Calculation Sheet'!$Y$37="","",'Final Calculation Sheet'!$Y$37) | Y39: =IF('Final Calculation Sheet'!$Z$37="","",'Final Calculation Sheet'!$Z$37) | Z39: =IF('Final Calculation Sheet'!$AA$37="","",'Final Calculation Sheet'!$AA$37) | AA39: =IF('Final Calculation Sheet'!$AB$37="","",'Final Calculation Sheet'!$AB$37) | AB39: =IF('Final Calculation Sheet'!$AC$37="","",'Final Calculation Sheet'!$AC$37) | AC39: =IF('Final Calculation Sheet'!$AD$37="","",'Final Calculation Sheet'!$AD$37) | AD39: =IF('Final Calculation Sheet'!$AD$37="","",IF('Final Calculation Sheet'!$AD$37<=0,"SETTLED","OUTSTANDING")) | AE39: =IF('Final Calculation Sheet'!$AE$37="","",'Final Calculation Sheet'!$AE$37) | AF39: =IF('Final Calculation Sheet'!$AF$37="","",'Final Calculation Sheet'!$AF$37) | AG39: =IF('Final Calculation Sheet'!$AG$37="","",'Final Calculation Sheet'!$AG$37)
A40: ∑ NATIONAL ENTERPRISES — TOTALS | B40: – | C40: – | D40: =SUM(D27:D39) | E40: – | F40: – | G40: =SUM(G27:G39) | H40: =SUM(H27:H39) | I40: =SUM(I27:I39) | J40: =SUM(J27:J39) | K40: =SUM(K27:K39) | L40: =SUM(L27:L39) | M40: =SUM(M27:M39) | N40: =SUM(N27:N39) | O40: =SUM(O27:O39) | P40: – | Q40: =SUM(Q27:Q39) | R40: =SUM(R27:R39) | S40: =SUM(S27:S39) | T40: =SUM(T27:T39) | U40: – | V40: =SUM(V27:V39) | W40: =SUM(W27:W39) | X40: – | Y40: =SUM(Y27:Y39) | Z40: =SUM(Z27:Z39) | AA40: – | AB40: =SUM(AB27:AB39) | AC40: =SUM(AC27:AC39) | AD40: – | AE40: – | AF40: – | AG40: –
A42: ="▼ NATIONAL SCRAP AND BUILDING MATERIAL SUPPLIER • "&COUNTIF('Final Calculation Sheet'!$G$4:$G$1000,"NATIONAL SCRAP AND BUILDING MATERIAL SUPPLIER")&" LOT(S) • MAT. VALUE ₹"&TEXT(SUMIF('Final Calculation Sheet'!$G$4:$G$1000,"NATIONAL SCRAP AND BUILDING MATERIAL SUPPLIER",'Final Calculation Sheet'!$H$4:$H$1000),"#,##0")&" • RECEIVED ₹"&TEXT(SUMIF('Final Calculation Sheet'!$G$4:$G$1000,"NATIONAL SCRAP AND BUILDING MATERIAL SUPPLIER",'Final Calculation Sheet'!$AC$4:$AC$1000),"#,##0")&" • OUTSTANDING ₹"&TEXT(SUMIF('Final Calculation Sheet'!$G$4:$G$1000,"NATIONAL SCRAP AND BUILDING MATERIAL SUPPLIER",'Final Calculation Sheet'!$AD$4:$AD$1000),"#,##0")
A43: =IF('Final Calculation Sheet'!$F$21="","",'Final Calculation Sheet'!$F$21) | B43: =IF('Final Calculation Sheet'!$B$21="","",'Final Calculation Sheet'!$B$21) | C43: =IF('Final Calculation Sheet'!$D$21="","",'Final Calculation Sheet'!$D$21) | D43: =IF('Final Calculation Sheet'!$A$21="","",'Final Calculation Sheet'!$A$21) | E43: =IF('Final Calculation Sheet'!$E$21="","",'Final Calculation Sheet'!$E$21) | F43: =IF('Final Calculation Sheet'!$C$21="","",'Final Calculation Sheet'!$C$21) | G43: =IF('Final Calculation Sheet'!$H$21="","",'Final Calculation Sheet'!$H$21) | H43: =IF('Final Calculation Sheet'!$I$21="","",'Final Calculation Sheet'!$I$21) | I43: =IF('Final Calculation Sheet'!$J$21="","",'Final Calculation Sheet'!$J$21) | J43: =IF('Final Calculation Sheet'!$K$21="","",'Final Calculation Sheet'!$K$21) | K43: =IF('Final Calculation Sheet'!$L$21="","",'Final Calculation Sheet'!$L$21) | L43: =IF('Final Calculation Sheet'!$M$21="","",'Final Calculation Sheet'!$M$21) | M43: =IF('Final Calculation Sheet'!$N$21="","",'Final Calculation Sheet'!$N$21) | N43: =IF('Final Calculation Sheet'!$O$21="","",'Final Calculation Sheet'!$O$21) | O43: =IF('Final Calculation Sheet'!$P$21="","",'Final Calculation Sheet'!$P$21) | P43: =IF('Final Calculation Sheet'!$Q$21="","",'Final Calculation Sheet'!$Q$21) | Q43: =IF('Final Calculation Sheet'!$R$21="","",'Final Calculation Sheet'!$R$21) | R43: =IF('Final Calculation Sheet'!$S$21="","",'Final Calculation Sheet'!$S$21) | S43: =IF('Final Calculation Sheet'!$T$21="","",'Final Calculation Sheet'!$T$21) | T43: =IF('Final Calculation Sheet'!$U$21="","",'Final Calculation Sheet'!$U$21) | U43: =IF('Final Calculation Sheet'!$V$21="","",'Final Calculation Sheet'!$V$21) | V43: =IF('Final Calculation Sheet'!$W$21="","",'Final Calculation Sheet'!$W$21) | W43: =IF('Final Calculation Sheet'!$X$21="","",'Final Calculation Sheet'!$X$21) | X43: =IF('Final Calculation Sheet'!$Y$21="","",'Final Calculation Sheet'!$Y$21) | Y43: =IF('Final Calculation Sheet'!$Z$21="","",'Final Calculation Sheet'!$Z$21) | Z43: =IF('Final Calculation Sheet'!$AA$21="","",'Final Calculation Sheet'!$AA$21) | AA43: =IF('Final Calculation Sheet'!$AB$21="","",'Final Calculation Sheet'!$AB$21) | AB43: =IF('Final Calculation Sheet'!$AC$21="","",'Final Calculation Sheet'!$AC$21) | AC43: =IF('Final Calculation Sheet'!$AD$21="","",'Final Calculation Sheet'!$AD$21) | AD43: =IF('Final Calculation Sheet'!$AD$21="","",IF('Final Calculation Sheet'!$AD$21<=0,"SETTLED","OUTSTANDING")) | AE43: =IF('Final Calculation Sheet'!$AE$21="","",'Final Calculation Sheet'!$AE$21) | AF43: =IF('Final Calculation Sheet'!$AF$21="","",'Final Calculation Sheet'!$AF$21) | AG43: =IF('Final Calculation Sheet'!$AG$21="","",'Final Calculation Sheet'!$AG$21)
A44: ∑ NATIONAL SCRAP AND BUILDING MATERIAL SUPPLIER — TOTALS | B44: – | C44: – | D44: =SUM(D43:D43) | E44: – | F44: – | G44: =SUM(G43:G43) | H44: =SUM(H43:H43) | I44: =SUM(I43:I43) | J44: =SUM(J43:J43) | K44: =SUM(K43:K43) | L44: =SUM(L43:L43) | M44: =SUM(M43:M43) | N44: =SUM(N43:N43) | O44: =SUM(O43:O43) | P44: – | Q44: =SUM(Q43:Q43) | R44: =SUM(R43:R43) | S44: =SUM(S43:S43) | T44: =SUM(T43:T43) | U44: – | V44: =SUM(V43:V43) | W44: =SUM(W43:W43) | X44: – | Y44: =SUM(Y43:Y43) | Z44: =SUM(Z43:Z43) | AA44: – | AB44: =SUM(AB43:AB43) | AC44: =SUM(AC43:AC43) | AD44: – | AE44: – | AF44: – | AG44: –
A46: ="▼ OMKAR STEELS • "&COUNTIF('Final Calculation Sheet'!$G$4:$G$1000,"OMKAR STEELS")&" LOT(S) • MAT. VALUE ₹"&TEXT(SUMIF('Final Calculation Sheet'!$G$4:$G$1000,"OMKAR STEELS",'Final Calculation Sheet'!$H$4:$H$1000),"#,##0")&" • RECEIVED ₹"&TEXT(SUMIF('Final Calculation Sheet'!$G$4:$G$1000,"OMKAR STEELS",'Final Calculation Sheet'!$AC$4:$AC$1000),"#,##0")&" • OUTSTANDING ₹"&TEXT(SUMIF('Final Calculation Sheet'!$G$4:$G$1000,"OMKAR STEELS",'Final Calculation Sheet'!$AD$4:$AD$1000),"#,##0")
A47: =IF('Final Calculation Sheet'!$F$8="","",'Final Calculation Sheet'!$F$8) | B47: =IF('Final Calculation Sheet'!$B$8="","",'Final Calculation Sheet'!$B$8) | C47: =IF('Final Calculation Sheet'!$D$8="","",'Final Calculation Sheet'!$D$8) | D47: =IF('Final Calculation Sheet'!$A$8="","",'Final Calculation Sheet'!$A$8) | E47: =IF('Final Calculation Sheet'!$E$8="","",'Final Calculation Sheet'!$E$8) | F47: =IF('Final Calculation Sheet'!$C$8="","",'Final Calculation Sheet'!$C$8) | G47: =IF('Final Calculation Sheet'!$H$8="","",'Final Calculation Sheet'!$H$8) | H47: =IF('Final Calculation Sheet'!$I$8="","",'Final Calculation Sheet'!$I$8) | I47: =IF('Final Calculation Sheet'!$J$8="","",'Final Calculation Sheet'!$J$8) | J47: =IF('Final Calculation Sheet'!$K$8="","",'Final Calculation Sheet'!$K$8) | K47: =IF('Final Calculation Sheet'!$L$8="","",'Final Calculation Sheet'!$L$8) | L47: =IF('Final Calculation Sheet'!$M$8="","",'Final Calculation Sheet'!$M$8) | M47: =IF('Final Calculation Sheet'!$N$8="","",'Final Calculation Sheet'!$N$8) | N47: =IF('Final Calculation Sheet'!$O$8="","",'Final Calculation Sheet'!$O$8) | O47: =IF('Final Calculation Sheet'!$P$8="","",'Final Calculation Sheet'!$P$8) | P47: =IF('Final Calculation Sheet'!$Q$8="","",'Final Calculation Sheet'!$Q$8) | Q47: =IF('Final Calculation Sheet'!$R$8="","",'Final Calculation Sheet'!$R$8) | R47: =IF('Final Calculation Sheet'!$S$8="","",'Final Calculation Sheet'!$S$8) | S47: =IF('Final Calculation Sheet'!$T$8="","",'Final Calculation Sheet'!$T$8) | T47: =IF('Final Calculation Sheet'!$U$8="","",'Final Calculation Sheet'!$U$8) | U47: =IF('Final Calculation Sheet'!$V$8="","",'Final Calculation Sheet'!$V$8) | V47: =IF('Final Calculation Sheet'!$W$8="","",'Final Calculation Sheet'!$W$8) | W47: =IF('Final Calculation Sheet'!$X$8="","",'Final Calculation Sheet'!$X$8) | X47: =IF('Final Calculation Sheet'!$Y$8="","",'Final Calculation Sheet'!$Y$8) | Y47: =IF('Final Calculation Sheet'!$Z$8="","",'Final Calculation Sheet'!$Z$8) | Z47: =IF('Final Calculation Sheet'!$AA$8="","",'Final Calculation Sheet'!$AA$8) | AA47: =IF('Final Calculation Sheet'!$AB$8="","",'Final Calculation Sheet'!$AB$8) | AB47: =IF('Final Calculation Sheet'!$AC$8="","",'Final Calculation Sheet'!$AC$8) | AC47: =IF('Final Calculation Sheet'!$AD$8="","",'Final Calculation Sheet'!$AD$8) | AD47: =IF('Final Calculation Sheet'!$AD$8="","",IF('Final Calculation Sheet'!$AD$8<=0,"SETTLED","OUTSTANDING")) | AE47: =IF('Final Calculation Sheet'!$AE$8="","",'Final Calculation Sheet'!$AE$8) | AF47: =IF('Final Calculation Sheet'!$AF$8="","",'Final Calculation Sheet'!$AF$8) | AG47: =IF('Final Calculation Sheet'!$AG$8="","",'Final Calculation Sheet'!$AG$8)
A48: =IF('Final Calculation Sheet'!$F$20="","",'Final Calculation Sheet'!$F$20) | B48: =IF('Final Calculation Sheet'!$B$20="","",'Final Calculation Sheet'!$B$20) | C48: =IF('Final Calculation Sheet'!$D$20="","",'Final Calculation Sheet'!$D$20) | D48: =IF('Final Calculation Sheet'!$A$20="","",'Final Calculation Sheet'!$A$20) | E48: =IF('Final Calculation Sheet'!$E$20="","",'Final Calculation Sheet'!$E$20) | F48: =IF('Final Calculation Sheet'!$C$20="","",'Final Calculation Sheet'!$C$20) | G48: =IF('Final Calculation Sheet'!$H$20="","",'Final Calculation Sheet'!$H$20) | H48: =IF('Final Calculation Sheet'!$I$20="","",'Final Calculation Sheet'!$I$20) | I48: =IF('Final Calculation Sheet'!$J$20="","",'Final Calculation Sheet'!$J$20) | J48: =IF('Final Calculation Sheet'!$K$20="","",'Final Calculation Sheet'!$K$20) | K48: =IF('Final Calculation Sheet'!$L$20="","",'Final Calculation Sheet'!$L$20) | L48: =IF('Final Calculation Sheet'!$M$20="","",'Final Calculation Sheet'!$M$20) | M48: =IF('Final Calculation Sheet'!$N$20="","",'Final Calculation Sheet'!$N$20) | N48: =IF('Final Calculation Sheet'!$O$20="","",'Final Calculation Sheet'!$O$20) | O48: =IF('Final Calculation Sheet'!$P$20="","",'Final Calculation Sheet'!$P$20) | P48: =IF('Final Calculation Sheet'!$Q$20="","",'Final Calculation Sheet'!$Q$20) | Q48: =IF('Final Calculation Sheet'!$R$20="","",'Final Calculation Sheet'!$R$20) | R48: =IF('Final Calculation Sheet'!$S$20="","",'Final Calculation Sheet'!$S$20) | S48: =IF('Final Calculation Sheet'!$T$20="","",'Final Calculation Sheet'!$T$20) | T48: =IF('Final Calculation Sheet'!$U$20="","",'Final Calculation Sheet'!$U$20) | U48: =IF('Final Calculation Sheet'!$V$20="","",'Final Calculation Sheet'!$V$20) | V48: =IF('Final Calculation Sheet'!$W$20="","",'Final Calculation Sheet'!$W$20) | W48: =IF('Final Calculation Sheet'!$X$20="","",'Final Calculation Sheet'!$X$20) | X48: =IF('Final Calculation Sheet'!$Y$20="","",'Final Calculation Sheet'!$Y$20) | Y48: =IF('Final Calculation Sheet'!$Z$20="","",'Final Calculation Sheet'!$Z$20) | Z48: =IF('Final Calculation Sheet'!$AA$20="","",'Final Calculation Sheet'!$AA$20) | AA48: =IF('Final Calculation Sheet'!$AB$20="","",'Final Calculation Sheet'!$AB$20) | AB48: =IF('Final Calculation Sheet'!$AC$20="","",'Final Calculation Sheet'!$AC$20) | AC48: =IF('Final Calculation Sheet'!$AD$20="","",'Final Calculation Sheet'!$AD$20) | AD48: =IF('Final Calculation Sheet'!$AD$20="","",IF('Final Calculation Sheet'!$AD$20<=0,"SETTLED","OUTSTANDING")) | AE48: =IF('Final Calculation Sheet'!$AE$20="","",'Final Calculation Sheet'!$AE$20) | AF48: =IF('Final Calculation Sheet'!$AF$20="","",'Final Calculation Sheet'!$AF$20) | AG48: =IF('Final Calculation Sheet'!$AG$20="","",'Final Calculation Sheet'!$AG$20)
A49: ∑ OMKAR STEELS — TOTALS | B49: – | C49: – | D49: =SUM(D47:D48) | E49: – | F49: – | G49: =SUM(G47:G48) | H49: =SUM(H47:H48) | I49: =SUM(I47:I48) | J49: =SUM(J47:J48) | K49: =SUM(K47:K48) | L49: =SUM(L47:L48) | M49: =SUM(M47:M48) | N49: =SUM(N47:N48) | O49: =SUM(O47:O48) | P49: – | Q49: =SUM(Q47:Q48) | R49: =SUM(R47:R48) | S49: =SUM(S47:S48) | T49: =SUM(T47:T48) | U49: – | V49: =SUM(V47:V48) | W49: =SUM(W47:W48) | X49: – | Y49: =SUM(Y47:Y48) | Z49: =SUM(Z47:Z48) | AA49: – | AB49: =SUM(AB47:AB48) | AC49: =SUM(AC47:AC48) | AD49: – | AE49: – | AF49: – | AG49: –
A51: ="▼ S M ENTERPRISES • "&COUNTIF('Final Calculation Sheet'!$G$4:$G$1000,"S M ENTERPRISES")&" LOT(S) • MAT. VALUE ₹"&TEXT(SUMIF('Final Calculation Sheet'!$G$4:$G$1000,"S M ENTERPRISES",'Final Calculation Sheet'!$H$4:$H$1000),"#,##0")&" • RECEIVED ₹"&TEXT(SUMIF('Final Calculation Sheet'!$G$4:$G$1000,"S M ENTERPRISES",'Final Calculation Sheet'!$AC$4:$AC$1000),"#,##0")&" • OUTSTANDING ₹"&TEXT(SUMIF('Final Calculation Sheet'!$G$4:$G$1000,"S M ENTERPRISES",'Final Calculation Sheet'!$AD$4:$AD$1000),"#,##0")
A52: =IF('Final Calculation Sheet'!$F$39="","",'Final Calculation Sheet'!$F$39) | B52: =IF('Final Calculation Sheet'!$B$39="","",'Final Calculation Sheet'!$B$39) | C52: =IF('Final Calculation Sheet'!$D$39="","",'Final Calculation Sheet'!$D$39) | D52: =IF('Final Calculation Sheet'!$A$39="","",'Final Calculation Sheet'!$A$39) | E52: =IF('Final Calculation Sheet'!$E$39="","",'Final Calculation Sheet'!$E$39) | F52: =IF('Final Calculation Sheet'!$C$39="","",'Final Calculation Sheet'!$C$39) | G52: =IF('Final Calculation Sheet'!$H$39="","",'Final Calculation Sheet'!$H$39) | H52: =IF('Final Calculation Sheet'!$I$39="","",'Final Calculation Sheet'!$I$39) | I52: =IF('Final Calculation Sheet'!$J$39="","",'Final Calculation Sheet'!$J$39) | J52: =IF('Final Calculation Sheet'!$K$39="","",'Final Calculation Sheet'!$K$39) | K52: =IF('Final Calculation Sheet'!$L$39="","",'Final Calculation Sheet'!$L$39) | L52: =IF('Final Calculation Sheet'!$M$39="","",'Final Calculation Sheet'!$M$39) | M52: =IF('Final Calculation Sheet'!$N$39="","",'Final Calculation Sheet'!$N$39) | N52: =IF('Final Calculation Sheet'!$O$39="","",'Final Calculation Sheet'!$O$39) | O52: =IF('Final Calculation Sheet'!$P$39="","",'Final Calculation Sheet'!$P$39) | P52: =IF('Final Calculation Sheet'!$Q$39="","",'Final Calculation Sheet'!$Q$39) | Q52: =IF('Final Calculation Sheet'!$R$39="","",'Final Calculation Sheet'!$R$39) | R52: =IF('Final Calculation Sheet'!$S$39="","",'Final Calculation Sheet'!$S$39) | S52: =IF('Final Calculation Sheet'!$T$39="","",'Final Calculation Sheet'!$T$39) | T52: =IF('Final Calculation Sheet'!$U$39="","",'Final Calculation Sheet'!$U$39) | U52: =IF('Final Calculation Sheet'!$V$39="","",'Final Calculation Sheet'!$V$39) | V52: =IF('Final Calculation Sheet'!$W$39="","",'Final Calculation Sheet'!$W$39) | W52: =IF('Final Calculation Sheet'!$X$39="","",'Final Calculation Sheet'!$X$39) | X52: =IF('Final Calculation Sheet'!$Y$39="","",'Final Calculation Sheet'!$Y$39) | Y52: =IF('Final Calculation Sheet'!$Z$39="","",'Final Calculation Sheet'!$Z$39) | Z52: =IF('Final Calculation Sheet'!$AA$39="","",'Final Calculation Sheet'!$AA$39) | AA52: =IF('Final Calculation Sheet'!$AB$39="","",'Final Calculation Sheet'!$AB$39) | AB52: =IF('Final Calculation Sheet'!$AC$39="","",'Final Calculation Sheet'!$AC$39) | AC52: =IF('Final Calculation Sheet'!$AD$39="","",'Final Calculation Sheet'!$AD$39) | AD52: =IF('Final Calculation Sheet'!$AD$39="","",IF('Final Calculation Sheet'!$AD$39<=0,"SETTLED","OUTSTANDING")) | AE52: =IF('Final Calculation Sheet'!$AE$39="","",'Final Calculation Sheet'!$AE$39) | AF52: =IF('Final Calculation Sheet'!$AF$39="","",'Final Calculation Sheet'!$AF$39) | AG52: =IF('Final Calculation Sheet'!$AG$39="","",'Final Calculation Sheet'!$AG$39)
A53: =IF('Final Calculation Sheet'!$F$40="","",'Final Calculation Sheet'!$F$40) | B53: =IF('Final Calculation Sheet'!$B$40="","",'Final Calculation Sheet'!$B$40) | C53: =IF('Final Calculation Sheet'!$D$40="","",'Final Calculation Sheet'!$D$40) | D53: =IF('Final Calculation Sheet'!$A$40="","",'Final Calculation Sheet'!$A$40) | E53: =IF('Final Calculation Sheet'!$E$40="","",'Final Calculation Sheet'!$E$40) | F53: =IF('Final Calculation Sheet'!$C$40="","",'Final Calculation Sheet'!$C$40) | G53: =IF('Final Calculation Sheet'!$H$40="","",'Final Calculation Sheet'!$H$40) | H53: =IF('Final Calculation Sheet'!$I$40="","",'Final Calculation Sheet'!$I$40) | I53: =IF('Final Calculation Sheet'!$J$40="","",'Final Calculation Sheet'!$J$40) | J53: =IF('Final Calculation Sheet'!$K$40="","",'Final Calculation Sheet'!$K$40) | K53: =IF('Final Calculation Sheet'!$L$40="","",'Final Calculation Sheet'!$L$40) | L53: =IF('Final Calculation Sheet'!$M$40="","",'Final Calculation Sheet'!$M$40) | M53: =IF('Final Calculation Sheet'!$N$40="","",'Final Calculation Sheet'!$N$40) | N53: =IF('Final Calculation Sheet'!$O$40="","",'Final Calculation Sheet'!$O$40) | O53: =IF('Final Calculation Sheet'!$P$40="","",'Final Calculation Sheet'!$P$40) | P53: =IF('Final Calculation Sheet'!$Q$40="","",'Final Calculation Sheet'!$Q$40) | Q53: =IF('Final Calculation Sheet'!$R$40="","",'Final Calculation Sheet'!$R$40) | R53: =IF('Final Calculation Sheet'!$S$40="","",'Final Calculation Sheet'!$S$40) | S53: =IF('Final Calculation Sheet'!$T$40="","",'Final Calculation Sheet'!$T$40) | T53: =IF('Final Calculation Sheet'!$U$40="","",'Final Calculation Sheet'!$U$40) | U53: =IF('Final Calculation Sheet'!$V$40="","",'Final Calculation Sheet'!$V$40) | V53: =IF('Final Calculation Sheet'!$W$40="","",'Final Calculation Sheet'!$W$40) | W53: =IF('Final Calculation Sheet'!$X$40="","",'Final Calculation Sheet'!$X$40) | X53: =IF('Final Calculation Sheet'!$Y$40="","",'Final Calculation Sheet'!$Y$40) | Y53: =IF('Final Calculation Sheet'!$Z$40="","",'Final Calculation Sheet'!$Z$40) | Z53: =IF('Final Calculation Sheet'!$AA$40="","",'Final Calculation Sheet'!$AA$40) | AA53: =IF('Final Calculation Sheet'!$AB$40="","",'Final Calculation Sheet'!$AB$40) | AB53: =IF('Final Calculation Sheet'!$AC$40="","",'Final Calculation Sheet'!$AC$40) | AC53: =IF('Final Calculation Sheet'!$AD$40="","",'Final Calculation Sheet'!$AD$40) | AD53: =IF('Final Calculation Sheet'!$AD$40="","",IF('Final Calculation Sheet'!$AD$40<=0,"SETTLED","OUTSTANDING")) | AE53: =IF('Final Calculation Sheet'!$AE$40="","",'Final Calculation Sheet'!$AE$40) | AF53: =IF('Final Calculation Sheet'!$AF$40="","",'Final Calculation Sheet'!$AF$40) | AG53: =IF('Final Calculation Sheet'!$AG$40="","",'Final Calculation Sheet'!$AG$40)
A54: ∑ S M ENTERPRISES — TOTALS | B54: – | C54: – | D54: =SUM(D52:D53) | E54: – | F54: – | G54: =SUM(G52:G53) | H54: =SUM(H52:H53) | I54: =SUM(I52:I53) | J54: =SUM(J52:J53) | K54: =SUM(K52:K53) | L54: =SUM(L52:L53) | M54: =SUM(M52:M53) | N54: =SUM(N52:N53) | O54: =SUM(O52:O53) | P54: – | Q54: =SUM(Q52:Q53) | R54: =SUM(R52:R53) | S54: =SUM(S52:S53) | T54: =SUM(T52:T53) | U54: – | V54: =SUM(V52:V53) | W54: =SUM(W52:W53) | X54: – | Y54: =SUM(Y52:Y53) | Z54: =SUM(Z52:Z53) | AA54: – | AB54: =SUM(AB52:AB53) | AC54: =SUM(AC52:AC53) | AD54: – | AE54: – | AF54: – | AG54: –
A56: ="▼ SAHARA ENTERPRISES • "&COUNTIF('Final Calculation Sheet'!$G$4:$G$1000,"SAHARA ENTERPRISES")&" LOT(S) • MAT. VALUE ₹"&TEXT(SUMIF('Final Calculation Sheet'!$G$4:$G$1000,"SAHARA ENTERPRISES",'Final Calculation Sheet'!$H$4:$H$1000),"#,##0")&" • RECEIVED ₹"&TEXT(SUMIF('Final Calculation Sheet'!$G$4:$G$1000,"SAHARA ENTERPRISES",'Final Calculation Sheet'!$AC$4:$AC$1000),"#,##0")&" • OUTSTANDING ₹"&TEXT(SUMIF('Final Calculation Sheet'!$G$4:$G$1000,"SAHARA ENTERPRISES",'Final Calculation Sheet'!$AD$4:$AD$1000),"#,##0")
A57: =IF('Final Calculation Sheet'!$F$31="","",'Final Calculation Sheet'!$F$31) | B57: =IF('Final Calculation Sheet'!$B$31="","",'Final Calculation Sheet'!$B$31) | C57: =IF('Final Calculation Sheet'!$D$31="","",'Final Calculation Sheet'!$D$31) | D57: =IF('Final Calculation Sheet'!$A$31="","",'Final Calculation Sheet'!$A$31) | E57: =IF('Final Calculation Sheet'!$E$31="","",'Final Calculation Sheet'!$E$31) | F57: =IF('Final Calculation Sheet'!$C$31="","",'Final Calculation Sheet'!$C$31) | G57: =IF('Final Calculation Sheet'!$H$31="","",'Final Calculation Sheet'!$H$31) | H57: =IF('Final Calculation Sheet'!$I$31="","",'Final Calculation Sheet'!$I$31) | I57: =IF('Final Calculation Sheet'!$J$31="","",'Final Calculation Sheet'!$J$31) | J57: =IF('Final Calculation Sheet'!$K$31="","",'Final Calculation Sheet'!$K$31) | K57: =IF('Final Calculation Sheet'!$L$31="","",'Final Calculation Sheet'!$L$31) | L57: =IF('Final Calculation Sheet'!$M$31="","",'Final Calculation Sheet'!$M$31) | M57: =IF('Final Calculation Sheet'!$N$31="","",'Final Calculation Sheet'!$N$31) | N57: =IF('Final Calculation Sheet'!$O$31="","",'Final Calculation Sheet'!$O$31) | O57: =IF('Final Calculation Sheet'!$P$31="","",'Final Calculation Sheet'!$P$31) | P57: =IF('Final Calculation Sheet'!$Q$31="","",'Final Calculation Sheet'!$Q$31) | Q57: =IF('Final Calculation Sheet'!$R$31="","",'Final Calculation Sheet'!$R$31) | R57: =IF('Final Calculation Sheet'!$S$31="","",'Final Calculation Sheet'!$S$31) | S57: =IF('Final Calculation Sheet'!$T$31="","",'Final Calculation Sheet'!$T$31) | T57: =IF('Final Calculation Sheet'!$U$31="","",'Final Calculation Sheet'!$U$31) | U57: =IF('Final Calculation Sheet'!$V$31="","",'Final Calculation Sheet'!$V$31) | V57: =IF('Final Calculation Sheet'!$W$31="","",'Final Calculation Sheet'!$W$31) | W57: =IF('Final Calculation Sheet'!$X$31="","",'Final Calculation Sheet'!$X$31) | X57: =IF('Final Calculation Sheet'!$Y$31="","",'Final Calculation Sheet'!$Y$31) | Y57: =IF('Final Calculation Sheet'!$Z$31="","",'Final Calculation Sheet'!$Z$31) | Z57: =IF('Final Calculation Sheet'!$AA$31="","",'Final Calculation Sheet'!$AA$31) | AA57: =IF('Final Calculation Sheet'!$AB$31="","",'Final Calculation Sheet'!$AB$31) | AB57: =IF('Final Calculation Sheet'!$AC$31="","",'Final Calculation Sheet'!$AC$31) | AC57: =IF('Final Calculation Sheet'!$AD$31="","",'Final Calculation Sheet'!$AD$31) | AD57: =IF('Final Calculation Sheet'!$AD$31="","",IF('Final Calculation Sheet'!$AD$31<=0,"SETTLED","OUTSTANDING")) | AE57: =IF('Final Calculation Sheet'!$AE$31="","",'Final Calculation Sheet'!$AE$31) | AF57: =IF('Final Calculation Sheet'!$AF$31="","",'Final Calculation Sheet'!$AF$31) | AG57: =IF('Final Calculation Sheet'!$AG$31="","",'Final Calculation Sheet'!$AG$31)
A58: ∑ SAHARA ENTERPRISES — TOTALS | B58: – | C58: – | D58: =SUM(D57:D57) | E58: – | F58: – | G58: =SUM(G57:G57) | H58: =SUM(H57:H57) | I58: =SUM(I57:I57) | J58: =SUM(J57:J57) | K58: =SUM(K57:K57) | L58: =SUM(L57:L57) | M58: =SUM(M57:M57) | N58: =SUM(N57:N57) | O58: =SUM(O57:O57) | P58: – | Q58: =SUM(Q57:Q57) | R58: =SUM(R57:R57) | S58: =SUM(S57:S57) | T58: =SUM(T57:T57) | U58: – | V58: =SUM(V57:V57) | W58: =SUM(W57:W57) | X58: – | Y58: =SUM(Y57:Y57) | Z58: =SUM(Z57:Z57) | AA58: – | AB58: =SUM(AB57:AB57) | AC58: =SUM(AC57:AC57) | AD58: – | AE58: – | AF58: – | AG58: –
A60: ="▼ SHAR JAHAN TRADERS • "&COUNTIF('Final Calculation Sheet'!$G$4:$G$1000,"SHAR JAHAN TRADERS")&" LOT(S) • MAT. VALUE ₹"&TEXT(SUMIF('Final Calculation Sheet'!$G$4:$G$1000,"SHAR JAHAN TRADERS",'Final Calculation Sheet'!$H$4:$H$1000),"#,##0")&" • RECEIVED ₹"&TEXT(SUMIF('Final Calculation Sheet'!$G$4:$G$1000,"SHAR JAHAN TRADERS",'Final Calculation Sheet'!$AC$4:$AC$1000),"#,##0")&" • OUTSTANDING ₹"&TEXT(SUMIF('Final Calculation Sheet'!$G$4:$G$1000,"SHAR JAHAN TRADERS",'Final Calculation Sheet'!$AD$4:$AD$1000),"#,##0")
A61: =IF('Final Calculation Sheet'!$F$9="","",'Final Calculation Sheet'!$F$9) | B61: =IF('Final Calculation Sheet'!$B$9="","",'Final Calculation Sheet'!$B$9) | C61: =IF('Final Calculation Sheet'!$D$9="","",'Final Calculation Sheet'!$D$9) | D61: =IF('Final Calculation Sheet'!$A$9="","",'Final Calculation Sheet'!$A$9) | E61: =IF('Final Calculation Sheet'!$E$9="","",'Final Calculation Sheet'!$E$9) | F61: =IF('Final Calculation Sheet'!$C$9="","",'Final Calculation Sheet'!$C$9) | G61: =IF('Final Calculation Sheet'!$H$9="","",'Final Calculation Sheet'!$H$9) | H61: =IF('Final Calculation Sheet'!$I$9="","",'Final Calculation Sheet'!$I$9) | I61: =IF('Final Calculation Sheet'!$J$9="","",'Final Calculation Sheet'!$J$9) | J61: =IF('Final Calculation Sheet'!$K$9="","",'Final Calculation Sheet'!$K$9) | K61: =IF('Final Calculation Sheet'!$L$9="","",'Final Calculation Sheet'!$L$9) | L61: =IF('Final Calculation Sheet'!$M$9="","",'Final Calculation Sheet'!$M$9) | M61: =IF('Final Calculation Sheet'!$N$9="","",'Final Calculation Sheet'!$N$9) | N61: =IF('Final Calculation Sheet'!$O$9="","",'Final Calculation Sheet'!$O$9) | O61: =IF('Final Calculation Sheet'!$P$9="","",'Final Calculation Sheet'!$P$9) | P61: =IF('Final Calculation Sheet'!$Q$9="","",'Final Calculation Sheet'!$Q$9) | Q61: =IF('Final Calculation Sheet'!$R$9="","",'Final Calculation Sheet'!$R$9) | R61: =IF('Final Calculation Sheet'!$S$9="","",'Final Calculation Sheet'!$S$9) | S61: =IF('Final Calculation Sheet'!$T$9="","",'Final Calculation Sheet'!$T$9) | T61: =IF('Final Calculation Sheet'!$U$9="","",'Final Calculation Sheet'!$U$9) | U61: =IF('Final Calculation Sheet'!$V$9="","",'Final Calculation Sheet'!$V$9) | V61: =IF('Final Calculation Sheet'!$W$9="","",'Final Calculation Sheet'!$W$9) | W61: =IF('Final Calculation Sheet'!$X$9="","",'Final Calculation Sheet'!$X$9) | X61: =IF('Final Calculation Sheet'!$Y$9="","",'Final Calculation Sheet'!$Y$9) | Y61: =IF('Final Calculation Sheet'!$Z$9="","",'Final Calculation Sheet'!$Z$9) | Z61: =IF('Final Calculation Sheet'!$AA$9="","",'Final Calculation Sheet'!$AA$9) | AA61: =IF('Final Calculation Sheet'!$AB$9="","",'Final Calculation Sheet'!$AB$9) | AB61: =IF('Final Calculation Sheet'!$AC$9="","",'Final Calculation Sheet'!$AC$9) | AC61: =IF('Final Calculation Sheet'!$AD$9="","",'Final Calculation Sheet'!$AD$9) | AD61: =IF('Final Calculation Sheet'!$AD$9="","",IF('Final Calculation Sheet'!$AD$9<=0,"SETTLED","OUTSTANDING")) | AE61: =IF('Final Calculation Sheet'!$AE$9="","",'Final Calculation Sheet'!$AE$9) | AF61: =IF('Final Calculation Sheet'!$AF$9="","",'Final Calculation Sheet'!$AF$9) | AG61: =IF('Final Calculation Sheet'!$AG$9="","",'Final Calculation Sheet'!$AG$9)
A62: =IF('Final Calculation Sheet'!$F$14="","",'Final Calculation Sheet'!$F$14) | B62: =IF('Final Calculation Sheet'!$B$14="","",'Final Calculation Sheet'!$B$14) | C62: =IF('Final Calculation Sheet'!$D$14="","",'Final Calculation Sheet'!$D$14) | D62: =IF('Final Calculation Sheet'!$A$14="","",'Final Calculation Sheet'!$A$14) | E62: =IF('Final Calculation Sheet'!$E$14="","",'Final Calculation Sheet'!$E$14) | F62: =IF('Final Calculation Sheet'!$C$14="","",'Final Calculation Sheet'!$C$14) | G62: =IF('Final Calculation Sheet'!$H$14="","",'Final Calculation Sheet'!$H$14) | H62: =IF('Final Calculation Sheet'!$I$14="","",'Final Calculation Sheet'!$I$14) | I62: =IF('Final Calculation Sheet'!$J$14="","",'Final Calculation Sheet'!$J$14) | J62: =IF('Final Calculation Sheet'!$K$14="","",'Final Calculation Sheet'!$K$14) | K62: =IF('Final Calculation Sheet'!$L$14="","",'Final Calculation Sheet'!$L$14) | L62: =IF('Final Calculation Sheet'!$M$14="","",'Final Calculation Sheet'!$M$14) | M62: =IF('Final Calculation Sheet'!$N$14="","",'Final Calculation Sheet'!$N$14) | N62: =IF('Final Calculation Sheet'!$O$14="","",'Final Calculation Sheet'!$O$14) | O62: =IF('Final Calculation Sheet'!$P$14="","",'Final Calculation Sheet'!$P$14) | P62: =IF('Final Calculation Sheet'!$Q$14="","",'Final Calculation Sheet'!$Q$14) | Q62: =IF('Final Calculation Sheet'!$R$14="","",'Final Calculation Sheet'!$R$14) | R62: =IF('Final Calculation Sheet'!$S$14="","",'Final Calculation Sheet'!$S$14) | S62: =IF('Final Calculation Sheet'!$T$14="","",'Final Calculation Sheet'!$T$14) | T62: =IF('Final Calculation Sheet'!$U$14="","",'Final Calculation Sheet'!$U$14) | U62: =IF('Final Calculation Sheet'!$V$14="","",'Final Calculation Sheet'!$V$14) | V62: =IF('Final Calculation Sheet'!$W$14="","",'Final Calculation Sheet'!$W$14) | W62: =IF('Final Calculation Sheet'!$X$14="","",'Final Calculation Sheet'!$X$14) | X62: =IF('Final Calculation Sheet'!$Y$14="","",'Final Calculation Sheet'!$Y$14) | Y62: =IF('Final Calculation Sheet'!$Z$14="","",'Final Calculation Sheet'!$Z$14) | Z62: =IF('Final Calculation Sheet'!$AA$14="","",'Final Calculation Sheet'!$AA$14) | AA62: =IF('Final Calculation Sheet'!$AB$14="","",'Final Calculation Sheet'!$AB$14) | AB62: =IF('Final Calculation Sheet'!$AC$14="","",'Final Calculation Sheet'!$AC$14) | AC62: =IF('Final Calculation Sheet'!$AD$14="","",'Final Calculation Sheet'!$AD$14) | AD62: =IF('Final Calculation Sheet'!$AD$14="","",IF('Final Calculation Sheet'!$AD$14<=0,"SETTLED","OUTSTANDING")) | AE62: =IF('Final Calculation Sheet'!$AE$14="","",'Final Calculation Sheet'!$AE$14) | AF62: =IF('Final Calculation Sheet'!$AF$14="","",'Final Calculation Sheet'!$AF$14) | AG62: =IF('Final Calculation Sheet'!$AG$14="","",'Final Calculation Sheet'!$AG$14)
A63: ∑ SHAR JAHAN TRADERS — TOTALS | B63: – | C63: – | D63: =SUM(D61:D62) | E63: – | F63: – | G63: =SUM(G61:G62) | H63: =SUM(H61:H62) | I63: =SUM(I61:I62) | J63: =SUM(J61:J62) | K63: =SUM(K61:K62) | L63: =SUM(L61:L62) | M63: =SUM(M61:M62) | N63: =SUM(N61:N62) | O63: =SUM(O61:O62) | P63: – | Q63: =SUM(Q61:Q62) | R63: =SUM(R61:R62) | S63: =SUM(S61:S62) | T63: =SUM(T61:T62) | U63: – | V63: =SUM(V61:V62) | W63: =SUM(W61:W62) | X63: – | Y63: =SUM(Y61:Y62) | Z63: =SUM(Z61:Z62) | AA63: – | AB63: =SUM(AB61:AB62) | AC63: =SUM(AC61:AC62) | AD63: – | AE63: – | AF63: – | AG63: –
A65: ="▼ STERLING ENTERPRISES • "&COUNTIF('Final Calculation Sheet'!$G$4:$G$1000,"STERLING ENTERPRISES")&" LOT(S) • MAT. VALUE ₹"&TEXT(SUMIF('Final Calculation Sheet'!$G$4:$G$1000,"STERLING ENTERPRISES",'Final Calculation Sheet'!$H$4:$H$1000),"#,##0")&" • RECEIVED ₹"&TEXT(SUMIF('Final Calculation Sheet'!$G$4:$G$1000,"STERLING ENTERPRISES",'Final Calculation Sheet'!$AC$4:$AC$1000),"#,##0")&" • OUTSTANDING ₹"&TEXT(SUMIF('Final Calculation Sheet'!$G$4:$G$1000,"STERLING ENTERPRISES",'Final Calculation Sheet'!$AD$4:$AD$1000),"#,##0")
A66: =IF('Final Calculation Sheet'!$F$13="","",'Final Calculation Sheet'!$F$13) | B66: =IF('Final Calculation Sheet'!$B$13="","",'Final Calculation Sheet'!$B$13) | C66: =IF('Final Calculation Sheet'!$D$13="","",'Final Calculation Sheet'!$D$13) | D66: =IF('Final Calculation Sheet'!$A$13="","",'Final Calculation Sheet'!$A$13) | E66: =IF('Final Calculation Sheet'!$E$13="","",'Final Calculation Sheet'!$E$13) | F66: =IF('Final Calculation Sheet'!$C$13="","",'Final Calculation Sheet'!$C$13) | G66: =IF('Final Calculation Sheet'!$H$13="","",'Final Calculation Sheet'!$H$13) | H66: =IF('Final Calculation Sheet'!$I$13="","",'Final Calculation Sheet'!$I$13) | I66: =IF('Final Calculation Sheet'!$J$13="","",'Final Calculation Sheet'!$J$13) | J66: =IF('Final Calculation Sheet'!$K$13="","",'Final Calculation Sheet'!$K$13) | K66: =IF('Final Calculation Sheet'!$L$13="","",'Final Calculation Sheet'!$L$13) | L66: =IF('Final Calculation Sheet'!$M$13="","",'Final Calculation Sheet'!$M$13) | M66: =IF('Final Calculation Sheet'!$N$13="","",'Final Calculation Sheet'!$N$13) | N66: =IF('Final Calculation Sheet'!$O$13="","",'Final Calculation Sheet'!$O$13) | O66: =IF('Final Calculation Sheet'!$P$13="","",'Final Calculation Sheet'!$P$13) | P66: =IF('Final Calculation Sheet'!$Q$13="","",'Final Calculation Sheet'!$Q$13) | Q66: =IF('Final Calculation Sheet'!$R$13="","",'Final Calculation Sheet'!$R$13) | R66: =IF('Final Calculation Sheet'!$S$13="","",'Final Calculation Sheet'!$S$13) | S66: =IF('Final Calculation Sheet'!$T$13="","",'Final Calculation Sheet'!$T$13) | T66: =IF('Final Calculation Sheet'!$U$13="","",'Final Calculation Sheet'!$U$13) | U66: =IF('Final Calculation Sheet'!$V$13="","",'Final Calculation Sheet'!$V$13) | V66: =IF('Final Calculation Sheet'!$W$13="","",'Final Calculation Sheet'!$W$13) | W66: =IF('Final Calculation Sheet'!$X$13="","",'Final Calculation Sheet'!$X$13) | X66: =IF('Final Calculation Sheet'!$Y$13="","",'Final Calculation Sheet'!$Y$13) | Y66: =IF('Final Calculation Sheet'!$Z$13="","",'Final Calculation Sheet'!$Z$13) | Z66: =IF('Final Calculation Sheet'!$AA$13="","",'Final Calculation Sheet'!$AA$13) | AA66: =IF('Final Calculation Sheet'!$AB$13="","",'Final Calculation Sheet'!$AB$13) | AB66: =IF('Final Calculation Sheet'!$AC$13="","",'Final Calculation Sheet'!$AC$13) | AC66: =IF('Final Calculation Sheet'!$AD$13="","",'Final Calculation Sheet'!$AD$13) | AD66: =IF('Final Calculation Sheet'!$AD$13="","",IF('Final Calculation Sheet'!$AD$13<=0,"SETTLED","OUTSTANDING")) | AE66: =IF('Final Calculation Sheet'!$AE$13="","",'Final Calculation Sheet'!$AE$13) | AF66: =IF('Final Calculation Sheet'!$AF$13="","",'Final Calculation Sheet'!$AF$13) | AG66: =IF('Final Calculation Sheet'!$AG$13="","",'Final Calculation Sheet'!$AG$13)
A67: =IF('Final Calculation Sheet'!$F$16="","",'Final Calculation Sheet'!$F$16) | B67: =IF('Final Calculation Sheet'!$B$16="","",'Final Calculation Sheet'!$B$16) | C67: =IF('Final Calculation Sheet'!$D$16="","",'Final Calculation Sheet'!$D$16) | D67: =IF('Final Calculation Sheet'!$A$16="","",'Final Calculation Sheet'!$A$16) | E67: =IF('Final Calculation Sheet'!$E$16="","",'Final Calculation Sheet'!$E$16) | F67: =IF('Final Calculation Sheet'!$C$16="","",'Final Calculation Sheet'!$C$16) | G67: =IF('Final Calculation Sheet'!$H$16="","",'Final Calculation Sheet'!$H$16) | H67: =IF('Final Calculation Sheet'!$I$16="","",'Final Calculation Sheet'!$I$16) | I67: =IF('Final Calculation Sheet'!$J$16="","",'Final Calculation Sheet'!$J$16) | J67: =IF('Final Calculation Sheet'!$K$16="","",'Final Calculation Sheet'!$K$16) | K67: =IF('Final Calculation Sheet'!$L$16="","",'Final Calculation Sheet'!$L$16) | L67: =IF('Final Calculation Sheet'!$M$16="","",'Final Calculation Sheet'!$M$16) | M67: =IF('Final Calculation Sheet'!$N$16="","",'Final Calculation Sheet'!$N$16) | N67: =IF('Final Calculation Sheet'!$O$16="","",'Final Calculation Sheet'!$O$16) | O67: =IF('Final Calculation Sheet'!$P$16="","",'Final Calculation Sheet'!$P$16) | P67: =IF('Final Calculation Sheet'!$Q$16="","",'Final Calculation Sheet'!$Q$16) | Q67: =IF('Final Calculation Sheet'!$R$16="","",'Final Calculation Sheet'!$R$16) | R67: =IF('Final Calculation Sheet'!$S$16="","",'Final Calculation Sheet'!$S$16) | S67: =IF('Final Calculation Sheet'!$T$16="","",'Final Calculation Sheet'!$T$16) | T67: =IF('Final Calculation Sheet'!$U$16="","",'Final Calculation Sheet'!$U$16) | U67: =IF('Final Calculation Sheet'!$V$16="","",'Final Calculation Sheet'!$V$16) | V67: =IF('Final Calculation Sheet'!$W$16="","",'Final Calculation Sheet'!$W$16) | W67: =IF('Final Calculation Sheet'!$X$16="","",'Final Calculation Sheet'!$X$16) | X67: =IF('Final Calculation Sheet'!$Y$16="","",'Final Calculation Sheet'!$Y$16) | Y67: =IF('Final Calculation Sheet'!$Z$16="","",'Final Calculation Sheet'!$Z$16) | Z67: =IF('Final Calculation Sheet'!$AA$16="","",'Final Calculation Sheet'!$AA$16) | AA67: =IF('Final Calculation Sheet'!$AB$16="","",'Final Calculation Sheet'!$AB$16) | AB67: =IF('Final Calculation Sheet'!$AC$16="","",'Final Calculation Sheet'!$AC$16) | AC67: =IF('Final Calculation Sheet'!$AD$16="","",'Final Calculation Sheet'!$AD$16) | AD67: =IF('Final Calculation Sheet'!$AD$16="","",IF('Final Calculation Sheet'!$AD$16<=0,"SETTLED","OUTSTANDING")) | AE67: =IF('Final Calculation Sheet'!$AE$16="","",'Final Calculation Sheet'!$AE$16) | AF67: =IF('Final Calculation Sheet'!$AF$16="","",'Final Calculation Sheet'!$AF$16) | AG67: =IF('Final Calculation Sheet'!$AG$16="","",'Final Calculation Sheet'!$AG$16)
A68: =IF('Final Calculation Sheet'!$F$17="","",'Final Calculation Sheet'!$F$17) | B68: =IF('Final Calculation Sheet'!$B$17="","",'Final Calculation Sheet'!$B$17) | C68: =IF('Final Calculation Sheet'!$D$17="","",'Final Calculation Sheet'!$D$17) | D68: =IF('Final Calculation Sheet'!$A$17="","",'Final Calculation Sheet'!$A$17) | E68: =IF('Final Calculation Sheet'!$E$17="","",'Final Calculation Sheet'!$E$17) | F68: =IF('Final Calculation Sheet'!$C$17="","",'Final Calculation Sheet'!$C$17) | G68: =IF('Final Calculation Sheet'!$H$17="","",'Final Calculation Sheet'!$H$17) | H68: =IF('Final Calculation Sheet'!$I$17="","",'Final Calculation Sheet'!$I$17) | I68: =IF('Final Calculation Sheet'!$J$17="","",'Final Calculation Sheet'!$J$17) | J68: =IF('Final Calculation Sheet'!$K$17="","",'Final Calculation Sheet'!$K$17) | K68: =IF('Final Calculation Sheet'!$L$17="","",'Final Calculation Sheet'!$L$17) | L68: =IF('Final Calculation Sheet'!$M$17="","",'Final Calculation Sheet'!$M$17) | M68: =IF('Final Calculation Sheet'!$N$17="","",'Final Calculation Sheet'!$N$17) | N68: =IF('Final Calculation Sheet'!$O$17="","",'Final Calculation Sheet'!$O$17) | O68: =IF('Final Calculation Sheet'!$P$17="","",'Final Calculation Sheet'!$P$17) | P68: =IF('Final Calculation Sheet'!$Q$17="","",'Final Calculation Sheet'!$Q$17) | Q68: =IF('Final Calculation Sheet'!$R$17="","",'Final Calculation Sheet'!$R$17) | R68: =IF('Final Calculation Sheet'!$S$17="","",'Final Calculation Sheet'!$S$17) | S68: =IF('Final Calculation Sheet'!$T$17="","",'Final Calculation Sheet'!$T$17) | T68: =IF('Final Calculation Sheet'!$U$17="","",'Final Calculation Sheet'!$U$17) | U68: =IF('Final Calculation Sheet'!$V$17="","",'Final Calculation Sheet'!$V$17) | V68: =IF('Final Calculation Sheet'!$W$17="","",'Final Calculation Sheet'!$W$17) | W68: =IF('Final Calculation Sheet'!$X$17="","",'Final Calculation Sheet'!$X$17) | X68: =IF('Final Calculation Sheet'!$Y$17="","",'Final Calculation Sheet'!$Y$17) | Y68: =IF('Final Calculation Sheet'!$Z$17="","",'Final Calculation Sheet'!$Z$17) | Z68: =IF('Final Calculation Sheet'!$AA$17="","",'Final Calculation Sheet'!$AA$17) | AA68: =IF('Final Calculation Sheet'!$AB$17="","",'Final Calculation Sheet'!$AB$17) | AB68: =IF('Final Calculation Sheet'!$AC$17="","",'Final Calculation Sheet'!$AC$17) | AC68: =IF('Final Calculation Sheet'!$AD$17="","",'Final Calculation Sheet'!$AD$17) | AD68: =IF('Final Calculation Sheet'!$AD$17="","",IF('Final Calculation Sheet'!$AD$17<=0,"SETTLED","OUTSTANDING")) | AE68: =IF('Final Calculation Sheet'!$AE$17="","",'Final Calculation Sheet'!$AE$17) | AF68: =IF('Final Calculation Sheet'!$AF$17="","",'Final Calculation Sheet'!$AF$17) | AG68: =IF('Final Calculation Sheet'!$AG$17="","",'Final Calculation Sheet'!$AG$17)
A69: =IF('Final Calculation Sheet'!$F$23="","",'Final Calculation Sheet'!$F$23) | B69: =IF('Final Calculation Sheet'!$B$23="","",'Final Calculation Sheet'!$B$23) | C69: =IF('Final Calculation Sheet'!$D$23="","",'Final Calculation Sheet'!$D$23) | D69: =IF('Final Calculation Sheet'!$A$23="","",'Final Calculation Sheet'!$A$23) | E69: =IF('Final Calculation Sheet'!$E$23="","",'Final Calculation Sheet'!$E$23) | F69: =IF('Final Calculation Sheet'!$C$23="","",'Final Calculation Sheet'!$C$23) | G69: =IF('Final Calculation Sheet'!$H$23="","",'Final Calculation Sheet'!$H$23) | H69: =IF('Final Calculation Sheet'!$I$23="","",'Final Calculation Sheet'!$I$23) | I69: =IF('Final Calculation Sheet'!$J$23="","",'Final Calculation Sheet'!$J$23) | J69: =IF('Final Calculation Sheet'!$K$23="","",'Final Calculation Sheet'!$K$23) | K69: =IF('Final Calculation Sheet'!$L$23="","",'Final Calculation Sheet'!$L$23) | L69: =IF('Final Calculation Sheet'!$M$23="","",'Final Calculation Sheet'!$M$23) | M69: =IF('Final Calculation Sheet'!$N$23="","",'Final Calculation Sheet'!$N$23) | N69: =IF('Final Calculation Sheet'!$O$23="","",'Final Calculation Sheet'!$O$23) | O69: =IF('Final Calculation Sheet'!$P$23="","",'Final Calculation Sheet'!$P$23) | P69: =IF('Final Calculation Sheet'!$Q$23="","",'Final Calculation Sheet'!$Q$23) | Q69: =IF('Final Calculation Sheet'!$R$23="","",'Final Calculation Sheet'!$R$23) | R69: =IF('Final Calculation Sheet'!$S$23="","",'Final Calculation Sheet'!$S$23) | S69: =IF('Final Calculation Sheet'!$T$23="","",'Final Calculation Sheet'!$T$23) | T69: =IF('Final Calculation Sheet'!$U$23="","",'Final Calculation Sheet'!$U$23) | U69: =IF('Final Calculation Sheet'!$V$23="","",'Final Calculation Sheet'!$V$23) | V69: =IF('Final Calculation Sheet'!$W$23="","",'Final Calculation Sheet'!$W$23) | W69: =IF('Final Calculation Sheet'!$X$23="","",'Final Calculation Sheet'!$X$23) | X69: =IF('Final Calculation Sheet'!$Y$23="","",'Final Calculation Sheet'!$Y$23) | Y69: =IF('Final Calculation Sheet'!$Z$23="","",'Final Calculation Sheet'!$Z$23) | Z69: =IF('Final Calculation Sheet'!$AA$23="","",'Final Calculation Sheet'!$AA$23) | AA69: =IF('Final Calculation Sheet'!$AB$23="","",'Final Calculation Sheet'!$AB$23) | AB69: =IF('Final Calculation Sheet'!$AC$23="","",'Final Calculation Sheet'!$AC$23) | AC69: =IF('Final Calculation Sheet'!$AD$23="","",'Final Calculation Sheet'!$AD$23) | AD69: =IF('Final Calculation Sheet'!$AD$23="","",IF('Final Calculation Sheet'!$AD$23<=0,"SETTLED","OUTSTANDING")) | AE69: =IF('Final Calculation Sheet'!$AE$23="","",'Final Calculation Sheet'!$AE$23) | AF69: =IF('Final Calculation Sheet'!$AF$23="","",'Final Calculation Sheet'!$AF$23) | AG69: =IF('Final Calculation Sheet'!$AG$23="","",'Final Calculation Sheet'!$AG$23)
A70: =IF('Final Calculation Sheet'!$F$29="","",'Final Calculation Sheet'!$F$29) | B70: =IF('Final Calculation Sheet'!$B$29="","",'Final Calculation Sheet'!$B$29) | C70: =IF('Final Calculation Sheet'!$D$29="","",'Final Calculation Sheet'!$D$29) | D70: =IF('Final Calculation Sheet'!$A$29="","",'Final Calculation Sheet'!$A$29) | E70: =IF('Final Calculation Sheet'!$E$29="","",'Final Calculation Sheet'!$E$29) | F70: =IF('Final Calculation Sheet'!$C$29="","",'Final Calculation Sheet'!$C$29) | G70: =IF('Final Calculation Sheet'!$H$29="","",'Final Calculation Sheet'!$H$29) | H70: =IF('Final Calculation Sheet'!$I$29="","",'Final Calculation Sheet'!$I$29) | I70: =IF('Final Calculation Sheet'!$J$29="","",'Final Calculation Sheet'!$J$29) | J70: =IF('Final Calculation Sheet'!$K$29="","",'Final Calculation Sheet'!$K$29) | K70: =IF('Final Calculation Sheet'!$L$29="","",'Final Calculation Sheet'!$L$29) | L70: =IF('Final Calculation Sheet'!$M$29="","",'Final Calculation Sheet'!$M$29) | M70: =IF('Final Calculation Sheet'!$N$29="","",'Final Calculation Sheet'!$N$29) | N70: =IF('Final Calculation Sheet'!$O$29="","",'Final Calculation Sheet'!$O$29) | O70: =IF('Final Calculation Sheet'!$P$29="","",'Final Calculation Sheet'!$P$29) | P70: =IF('Final Calculation Sheet'!$Q$29="","",'Final Calculation Sheet'!$Q$29) | Q70: =IF('Final Calculation Sheet'!$R$29="","",'Final Calculation Sheet'!$R$29) | R70: =IF('Final Calculation Sheet'!$S$29="","",'Final Calculation Sheet'!$S$29) | S70: =IF('Final Calculation Sheet'!$T$29="","",'Final Calculation Sheet'!$T$29) | T70: =IF('Final Calculation Sheet'!$U$29="","",'Final Calculation Sheet'!$U$29) | U70: =IF('Final Calculation Sheet'!$V$29="","",'Final Calculation Sheet'!$V$29) | V70: =IF('Final Calculation Sheet'!$W$29="","",'Final Calculation Sheet'!$W$29) | W70: =IF('Final Calculation Sheet'!$X$29="","",'Final Calculation Sheet'!$X$29) | X70: =IF('Final Calculation Sheet'!$Y$29="","",'Final Calculation Sheet'!$Y$29) | Y70: =IF('Final Calculation Sheet'!$Z$29="","",'Final Calculation Sheet'!$Z$29) | Z70: =IF('Final Calculation Sheet'!$AA$29="","",'Final Calculation Sheet'!$AA$29) | AA70: =IF('Final Calculation Sheet'!$AB$29="","",'Final Calculation Sheet'!$AB$29) | AB70: =IF('Final Calculation Sheet'!$AC$29="","",'Final Calculation Sheet'!$AC$29) | AC70: =IF('Final Calculation Sheet'!$AD$29="","",'Final Calculation Sheet'!$AD$29) | AD70: =IF('Final Calculation Sheet'!$AD$29="","",IF('Final Calculation Sheet'!$AD$29<=0,"SETTLED","OUTSTANDING")) | AE70: =IF('Final Calculation Sheet'!$AE$29="","",'Final Calculation Sheet'!$AE$29) | AF70: =IF('Final Calculation Sheet'!$AF$29="","",'Final Calculation Sheet'!$AF$29) | AG70: =IF('Final Calculation Sheet'!$AG$29="","",'Final Calculation Sheet'!$AG$29)
A71: =IF('Final Calculation Sheet'!$F$34="","",'Final Calculation Sheet'!$F$34) | B71: =IF('Final Calculation Sheet'!$B$34="","",'Final Calculation Sheet'!$B$34) | C71: =IF('Final Calculation Sheet'!$D$34="","",'Final Calculation Sheet'!$D$34) | D71: =IF('Final Calculation Sheet'!$A$34="","",'Final Calculation Sheet'!$A$34) | E71: =IF('Final Calculation Sheet'!$E$34="","",'Final Calculation Sheet'!$E$34) | F71: =IF('Final Calculation Sheet'!$C$34="","",'Final Calculation Sheet'!$C$34) | G71: =IF('Final Calculation Sheet'!$H$34="","",'Final Calculation Sheet'!$H$34) | H71: =IF('Final Calculation Sheet'!$I$34="","",'Final Calculation Sheet'!$I$34) | I71: =IF('Final Calculation Sheet'!$J$34="","",'Final Calculation Sheet'!$J$34) | J71: =IF('Final Calculation Sheet'!$K$34="","",'Final Calculation Sheet'!$K$34) | K71: =IF('Final Calculation Sheet'!$L$34="","",'Final Calculation Sheet'!$L$34) | L71: =IF('Final Calculation Sheet'!$M$34="","",'Final Calculation Sheet'!$M$34) | M71: =IF('Final Calculation Sheet'!$N$34="","",'Final Calculation Sheet'!$N$34) | N71: =IF('Final Calculation Sheet'!$O$34="","",'Final Calculation Sheet'!$O$34) | O71: =IF('Final Calculation Sheet'!$P$34="","",'Final Calculation Sheet'!$P$34) | P71: =IF('Final Calculation Sheet'!$Q$34="","",'Final Calculation Sheet'!$Q$34) | Q71: =IF('Final Calculation Sheet'!$R$34="","",'Final Calculation Sheet'!$R$34) | R71: =IF('Final Calculation Sheet'!$S$34="","",'Final Calculation Sheet'!$S$34) | S71: =IF('Final Calculation Sheet'!$T$34="","",'Final Calculation Sheet'!$T$34) | T71: =IF('Final Calculation Sheet'!$U$34="","",'Final Calculation Sheet'!$U$34) | U71: =IF('Final Calculation Sheet'!$V$34="","",'Final Calculation Sheet'!$V$34) | V71: =IF('Final Calculation Sheet'!$W$34="","",'Final Calculation Sheet'!$W$34) | W71: =IF('Final Calculation Sheet'!$X$34="","",'Final Calculation Sheet'!$X$34) | X71: =IF('Final Calculation Sheet'!$Y$34="","",'Final Calculation Sheet'!$Y$34) | Y71: =IF('Final Calculation Sheet'!$Z$34="","",'Final Calculation Sheet'!$Z$34) | Z71: =IF('Final Calculation Sheet'!$AA$34="","",'Final Calculation Sheet'!$AA$34) | AA71: =IF('Final Calculation Sheet'!$AB$34="","",'Final Calculation Sheet'!$AB$34) | AB71: =IF('Final Calculation Sheet'!$AC$34="","",'Final Calculation Sheet'!$AC$34) | AC71: =IF('Final Calculation Sheet'!$AD$34="","",'Final Calculation Sheet'!$AD$34) | AD71: =IF('Final Calculation Sheet'!$AD$34="","",IF('Final Calculation Sheet'!$AD$34<=0,"SETTLED","OUTSTANDING")) | AE71: =IF('Final Calculation Sheet'!$AE$34="","",'Final Calculation Sheet'!$AE$34) | AF71: =IF('Final Calculation Sheet'!$AF$34="","",'Final Calculation Sheet'!$AF$34) | AG71: =IF('Final Calculation Sheet'!$AG$34="","",'Final Calculation Sheet'!$AG$34)
A72: =IF('Final Calculation Sheet'!$F$36="","",'Final Calculation Sheet'!$F$36) | B72: =IF('Final Calculation Sheet'!$B$36="","",'Final Calculation Sheet'!$B$36) | C72: =IF('Final Calculation Sheet'!$D$36="","",'Final Calculation Sheet'!$D$36) | D72: =IF('Final Calculation Sheet'!$A$36="","",'Final Calculation Sheet'!$A$36) | E72: =IF('Final Calculation Sheet'!$E$36="","",'Final Calculation Sheet'!$E$36) | F72: =IF('Final Calculation Sheet'!$C$36="","",'Final Calculation Sheet'!$C$36) | G72: =IF('Final Calculation Sheet'!$H$36="","",'Final Calculation Sheet'!$H$36) | H72: =IF('Final Calculation Sheet'!$I$36="","",'Final Calculation Sheet'!$I$36) | I72: =IF('Final Calculation Sheet'!$J$36="","",'Final Calculation Sheet'!$J$36) | J72: =IF('Final Calculation Sheet'!$K$36="","",'Final Calculation Sheet'!$K$36) | K72: =IF('Final Calculation Sheet'!$L$36="","",'Final Calculation Sheet'!$L$36) | L72: =IF('Final Calculation Sheet'!$M$36="","",'Final Calculation Sheet'!$M$36) | M72: =IF('Final Calculation Sheet'!$N$36="","",'Final Calculation Sheet'!$N$36) | N72: =IF('Final Calculation Sheet'!$O$36="","",'Final Calculation Sheet'!$O$36) | O72: =IF('Final Calculation Sheet'!$P$36="","",'Final Calculation Sheet'!$P$36) | P72: =IF('Final Calculation Sheet'!$Q$36="","",'Final Calculation Sheet'!$Q$36) | Q72: =IF('Final Calculation Sheet'!$R$36="","",'Final Calculation Sheet'!$R$36) | R72: =IF('Final Calculation Sheet'!$S$36="","",'Final Calculation Sheet'!$S$36) | S72: =IF('Final Calculation Sheet'!$T$36="","",'Final Calculation Sheet'!$T$36) | T72: =IF('Final Calculation Sheet'!$U$36="","",'Final Calculation Sheet'!$U$36) | U72: =IF('Final Calculation Sheet'!$V$36="","",'Final Calculation Sheet'!$V$36) | V72: =IF('Final Calculation Sheet'!$W$36="","",'Final Calculation Sheet'!$W$36) | W72: =IF('Final Calculation Sheet'!$X$36="","",'Final Calculation Sheet'!$X$36) | X72: =IF('Final Calculation Sheet'!$Y$36="","",'Final Calculation Sheet'!$Y$36) | Y72: =IF('Final Calculation Sheet'!$Z$36="","",'Final Calculation Sheet'!$Z$36) | Z72: =IF('Final Calculation Sheet'!$AA$36="","",'Final Calculation Sheet'!$AA$36) | AA72: =IF('Final Calculation Sheet'!$AB$36="","",'Final Calculation Sheet'!$AB$36) | AB72: =IF('Final Calculation Sheet'!$AC$36="","",'Final Calculation Sheet'!$AC$36) | AC72: =IF('Final Calculation Sheet'!$AD$36="","",'Final Calculation Sheet'!$AD$36) | AD72: =IF('Final Calculation Sheet'!$AD$36="","",IF('Final Calculation Sheet'!$AD$36<=0,"SETTLED","OUTSTANDING")) | AE72: =IF('Final Calculation Sheet'!$AE$36="","",'Final Calculation Sheet'!$AE$36) | AF72: =IF('Final Calculation Sheet'!$AF$36="","",'Final Calculation Sheet'!$AF$36) | AG72: =IF('Final Calculation Sheet'!$AG$36="","",'Final Calculation Sheet'!$AG$36)
A73: ∑ STERLING ENTERPRISES — TOTALS | B73: – | C73: – | D73: =SUM(D66:D72) | E73: – | F73: – | G73: =SUM(G66:G72) | H73: =SUM(H66:H72) | I73: =SUM(I66:I72) | J73: =SUM(J66:J72) | K73: =SUM(K66:K72) | L73: =SUM(L66:L72) | M73: =SUM(M66:M72) | N73: =SUM(N66:N72) | O73: =SUM(O66:O72) | P73: – | Q73: =SUM(Q66:Q72) | R73: =SUM(R66:R72) | S73: =SUM(S66:S72) | T73: =SUM(T66:T72) | U73: – | V73: =SUM(V66:V72) | W73: =SUM(W66:W72) | X73: – | Y73: =SUM(Y66:Y72) | Z73: =SUM(Z66:Z72) | AA73: – | AB73: =SUM(AB66:AB72) | AC73: =SUM(AC66:AC72) | AD73: – | AE73: – | AF73: – | AG73: –
A75: ="▼ WATAN SCRAP TRADERS • "&COUNTIF('Final Calculation Sheet'!$G$4:$G$1000,"WATAN SCRAP TRADERS")&" LOT(S) • MAT. VALUE ₹"&TEXT(SUMIF('Final Calculation Sheet'!$G$4:$G$1000,"WATAN SCRAP TRADERS",'Final Calculation Sheet'!$H$4:$H$1000),"#,##0")&" • RECEIVED ₹"&TEXT(SUMIF('Final Calculation Sheet'!$G$4:$G$1000,"WATAN SCRAP TRADERS",'Final Calculation Sheet'!$AC$4:$AC$1000),"#,##0")&" • OUTSTANDING ₹"&TEXT(SUMIF('Final Calculation Sheet'!$G$4:$G$1000,"WATAN SCRAP TRADERS",'Final Calculation Sheet'!$AD$4:$AD$1000),"#,##0")
A76: =IF('Final Calculation Sheet'!$F$25="","",'Final Calculation Sheet'!$F$25) | B76: =IF('Final Calculation Sheet'!$B$25="","",'Final Calculation Sheet'!$B$25) | C76: =IF('Final Calculation Sheet'!$D$25="","",'Final Calculation Sheet'!$D$25) | D76: =IF('Final Calculation Sheet'!$A$25="","",'Final Calculation Sheet'!$A$25) | E76: =IF('Final Calculation Sheet'!$E$25="","",'Final Calculation Sheet'!$E$25) | F76: =IF('Final Calculation Sheet'!$C$25="","",'Final Calculation Sheet'!$C$25) | G76: =IF('Final Calculation Sheet'!$H$25="","",'Final Calculation Sheet'!$H$25) | H76: =IF('Final Calculation Sheet'!$I$25="","",'Final Calculation Sheet'!$I$25) | I76: =IF('Final Calculation Sheet'!$J$25="","",'Final Calculation Sheet'!$J$25) | J76: =IF('Final Calculation Sheet'!$K$25="","",'Final Calculation Sheet'!$K$25) | K76: =IF('Final Calculation Sheet'!$L$25="","",'Final Calculation Sheet'!$L$25) | L76: =IF('Final Calculation Sheet'!$M$25="","",'Final Calculation Sheet'!$M$25) | M76: =IF('Final Calculation Sheet'!$N$25="","",'Final Calculation Sheet'!$N$25) | N76: =IF('Final Calculation Sheet'!$O$25="","",'Final Calculation Sheet'!$O$25) | O76: =IF('Final Calculation Sheet'!$P$25="","",'Final Calculation Sheet'!$P$25) | P76: =IF('Final Calculation Sheet'!$Q$25="","",'Final Calculation Sheet'!$Q$25) | Q76: =IF('Final Calculation Sheet'!$R$25="","",'Final Calculation Sheet'!$R$25) | R76: =IF('Final Calculation Sheet'!$S$25="","",'Final Calculation Sheet'!$S$25) | S76: =IF('Final Calculation Sheet'!$T$25="","",'Final Calculation Sheet'!$T$25) | T76: =IF('Final Calculation Sheet'!$U$25="","",'Final Calculation Sheet'!$U$25) | U76: =IF('Final Calculation Sheet'!$V$25="","",'Final Calculation Sheet'!$V$25) | V76: =IF('Final Calculation Sheet'!$W$25="","",'Final Calculation Sheet'!$W$25) | W76: =IF('Final Calculation Sheet'!$X$25="","",'Final Calculation Sheet'!$X$25) | X76: =IF('Final Calculation Sheet'!$Y$25="","",'Final Calculation Sheet'!$Y$25) | Y76: =IF('Final Calculation Sheet'!$Z$25="","",'Final Calculation Sheet'!$Z$25) | Z76: =IF('Final Calculation Sheet'!$AA$25="","",'Final Calculation Sheet'!$AA$25) | AA76: =IF('Final Calculation Sheet'!$AB$25="","",'Final Calculation Sheet'!$AB$25) | AB76: =IF('Final Calculation Sheet'!$AC$25="","",'Final Calculation Sheet'!$AC$25) | AC76: =IF('Final Calculation Sheet'!$AD$25="","",'Final Calculation Sheet'!$AD$25) | AD76: =IF('Final Calculation Sheet'!$AD$25="","",IF('Final Calculation Sheet'!$AD$25<=0,"SETTLED","OUTSTANDING")) | AE76: =IF('Final Calculation Sheet'!$AE$25="","",'Final Calculation Sheet'!$AE$25) | AF76: =IF('Final Calculation Sheet'!$AF$25="","",'Final Calculation Sheet'!$AF$25) | AG76: =IF('Final Calculation Sheet'!$AG$25="","",'Final Calculation Sheet'!$AG$25)
A77: =IF('Final Calculation Sheet'!$F$28="","",'Final Calculation Sheet'!$F$28) | B77: =IF('Final Calculation Sheet'!$B$28="","",'Final Calculation Sheet'!$B$28) | C77: =IF('Final Calculation Sheet'!$D$28="","",'Final Calculation Sheet'!$D$28) | D77: =IF('Final Calculation Sheet'!$A$28="","",'Final Calculation Sheet'!$A$28) | E77: =IF('Final Calculation Sheet'!$E$28="","",'Final Calculation Sheet'!$E$28) | F77: =IF('Final Calculation Sheet'!$C$28="","",'Final Calculation Sheet'!$C$28) | G77: =IF('Final Calculation Sheet'!$H$28="","",'Final Calculation Sheet'!$H$28) | H77: =IF('Final Calculation Sheet'!$I$28="","",'Final Calculation Sheet'!$I$28) | I77: =IF('Final Calculation Sheet'!$J$28="","",'Final Calculation Sheet'!$J$28) | J77: =IF('Final Calculation Sheet'!$K$28="","",'Final Calculation Sheet'!$K$28) | K77: =IF('Final Calculation Sheet'!$L$28="","",'Final Calculation Sheet'!$L$28) | L77: =IF('Final Calculation Sheet'!$M$28="","",'Final Calculation Sheet'!$M$28) | M77: =IF('Final Calculation Sheet'!$N$28="","",'Final Calculation Sheet'!$N$28) | N77: =IF('Final Calculation Sheet'!$O$28="","",'Final Calculation Sheet'!$O$28) | O77: =IF('Final Calculation Sheet'!$P$28="","",'Final Calculation Sheet'!$P$28) | P77: =IF('Final Calculation Sheet'!$Q$28="","",'Final Calculation Sheet'!$Q$28) | Q77: =IF('Final Calculation Sheet'!$R$28="","",'Final Calculation Sheet'!$R$28) | R77: =IF('Final Calculation Sheet'!$S$28="","",'Final Calculation Sheet'!$S$28) | S77: =IF('Final Calculation Sheet'!$T$28="","",'Final Calculation Sheet'!$T$28) | T77: =IF('Final Calculation Sheet'!$U$28="","",'Final Calculation Sheet'!$U$28) | U77: =IF('Final Calculation Sheet'!$V$28="","",'Final Calculation Sheet'!$V$28) | V77: =IF('Final Calculation Sheet'!$W$28="","",'Final Calculation Sheet'!$W$28) | W77: =IF('Final Calculation Sheet'!$X$28="","",'Final Calculation Sheet'!$X$28) | X77: =IF('Final Calculation Sheet'!$Y$28="","",'Final Calculation Sheet'!$Y$28) | Y77: =IF('Final Calculation Sheet'!$Z$28="","",'Final Calculation Sheet'!$Z$28) | Z77: =IF('Final Calculation Sheet'!$AA$28="","",'Final Calculation Sheet'!$AA$28) | AA77: =IF('Final Calculation Sheet'!$AB$28="","",'Final Calculation Sheet'!$AB$28) | AB77: =IF('Final Calculation Sheet'!$AC$28="","",'Final Calculation Sheet'!$AC$28) | AC77: =IF('Final Calculation Sheet'!$AD$28="","",'Final Calculation Sheet'!$AD$28) | AD77: =IF('Final Calculation Sheet'!$AD$28="","",IF('Final Calculation Sheet'!$AD$28<=0,"SETTLED","OUTSTANDING")) | AE77: =IF('Final Calculation Sheet'!$AE$28="","",'Final Calculation Sheet'!$AE$28) | AF77: =IF('Final Calculation Sheet'!$AF$28="","",'Final Calculation Sheet'!$AF$28) | AG77: =IF('Final Calculation Sheet'!$AG$28="","",'Final Calculation Sheet'!$AG$28)
A78: =IF('Final Calculation Sheet'!$F$35="","",'Final Calculation Sheet'!$F$35) | B78: =IF('Final Calculation Sheet'!$B$35="","",'Final Calculation Sheet'!$B$35) | C78: =IF('Final Calculation Sheet'!$D$35="","",'Final Calculation Sheet'!$D$35) | D78: =IF('Final Calculation Sheet'!$A$35="","",'Final Calculation Sheet'!$A$35) | E78: =IF('Final Calculation Sheet'!$E$35="","",'Final Calculation Sheet'!$E$35) | F78: =IF('Final Calculation Sheet'!$C$35="","",'Final Calculation Sheet'!$C$35) | G78: =IF('Final Calculation Sheet'!$H$35="","",'Final Calculation Sheet'!$H$35) | H78: =IF('Final Calculation Sheet'!$I$35="","",'Final Calculation Sheet'!$I$35) | I78: =IF('Final Calculation Sheet'!$J$35="","",'Final Calculation Sheet'!$J$35) | J78: =IF('Final Calculation Sheet'!$K$35="","",'Final Calculation Sheet'!$K$35) | K78: =IF('Final Calculation Sheet'!$L$35="","",'Final Calculation Sheet'!$L$35) | L78: =IF('Final Calculation Sheet'!$M$35="","",'Final Calculation Sheet'!$M$35) | M78: =IF('Final Calculation Sheet'!$N$35="","",'Final Calculation Sheet'!$N$35) | N78: =IF('Final Calculation Sheet'!$O$35="","",'Final Calculation Sheet'!$O$35) | O78: =IF('Final Calculation Sheet'!$P$35="","",'Final Calculation Sheet'!$P$35) | P78: =IF('Final Calculation Sheet'!$Q$35="","",'Final Calculation Sheet'!$Q$35) | Q78: =IF('Final Calculation Sheet'!$R$35="","",'Final Calculation Sheet'!$R$35) | R78: =IF('Final Calculation Sheet'!$S$35="","",'Final Calculation Sheet'!$S$35) | S78: =IF('Final Calculation Sheet'!$T$35="","",'Final Calculation Sheet'!$T$35) | T78: =IF('Final Calculation Sheet'!$U$35="","",'Final Calculation Sheet'!$U$35) | U78: =IF('Final Calculation Sheet'!$V$35="","",'Final Calculation Sheet'!$V$35) | V78: =IF('Final Calculation Sheet'!$W$35="","",'Final Calculation Sheet'!$W$35) | W78: =IF('Final Calculation Sheet'!$X$35="","",'Final Calculation Sheet'!$X$35) | X78: =IF('Final Calculation Sheet'!$Y$35="","",'Final Calculation Sheet'!$Y$35) | Y78: =IF('Final Calculation Sheet'!$Z$35="","",'Final Calculation Sheet'!$Z$35) | Z78: =IF('Final Calculation Sheet'!$AA$35="","",'Final Calculation Sheet'!$AA$35) | AA78: =IF('Final Calculation Sheet'!$AB$35="","",'Final Calculation Sheet'!$AB$35) | AB78: =IF('Final Calculation Sheet'!$AC$35="","",'Final Calculation Sheet'!$AC$35) | AC78: =IF('Final Calculation Sheet'!$AD$35="","",'Final Calculation Sheet'!$AD$35) | AD78: =IF('Final Calculation Sheet'!$AD$35="","",IF('Final Calculation Sheet'!$AD$35<=0,"SETTLED","OUTSTANDING")) | AE78: =IF('Final Calculation Sheet'!$AE$35="","",'Final Calculation Sheet'!$AE$35) | AF78: =IF('Final Calculation Sheet'!$AF$35="","",'Final Calculation Sheet'!$AF$35) | AG78: =IF('Final Calculation Sheet'!$AG$35="","",'Final Calculation Sheet'!$AG$35)
A79: ∑ WATAN SCRAP TRADERS — TOTALS | B79: – | C79: – | D79: =SUM(D76:D78) | E79: – | F79: – | G79: =SUM(G76:G78) | H79: =SUM(H76:H78) | I79: =SUM(I76:I78) | J79: =SUM(J76:J78) | K79: =SUM(K76:K78) | L79: =SUM(L76:L78) | M79: =SUM(M76:M78) | N79: =SUM(N76:N78) | O79: =SUM(O76:O78) | P79: – | Q79: =SUM(Q76:Q78) | R79: =SUM(R76:R78) | S79: =SUM(S76:S78) | T79: =SUM(T76:T78) | U79: – | V79: =SUM(V76:V78) | W79: =SUM(W76:W78) | X79: – | Y79: =SUM(Y76:Y78) | Z79: =SUM(Z76:Z78) | AA79: – | AB79: =SUM(AB76:AB78) | AC79: =SUM(AC76:AC78) | AD79: – | AE79: – | AF79: – | AG79: –

Sheet Ledger Filter - Lots Down
A1: MSTC LIMITED • BUYER & LOT LEDGER (filter + fold) (lots ↓ rows | fields → columns)
A2: HOW TO USE ▶ filter with the ▼ arrows in row 5 (buyer, lot no., bid sheet, unit, payment status …) • fold a buyer with the − button in the left margin — its coloured summary row stays on screen • fold a column category (FINANCIALS, SECURITY DEPOSIT …) with the − above its first column; that key column stays on screen • the KPI band in row 3 and the GRAND TOTAL row always follow the filter
A3: LOTS VISIBLE ▸ | C3: =SUBTOTAL(103,$B$7:$B$55) | E3: MAT. VALUE ₹ ▸ | G3: =SUBTOTAL(109,$H$7:$H$55) | I3: RECEIVABLES ₹ ▸ | K3: =SUBTOTAL(109,$S$7:$S$55) | M3: SD RECEIVED ₹ ▸ | O3: =SUBTOTAL(109,$U$7:$U$55) | Q3: FP RECEIVED ₹ ▸ | S3: =SUBTOTAL(109,$X$7:$X$55) | U3: TOTAL RECEIVED ₹ ▸ | W3: =SUBTOTAL(109,$AC$7:$AC$55) | Y3: OUTSTANDING ₹ ▸ | AA3: =SUBTOTAL(109,$AD$7:$AD$55)
A4: IDENTITY | C4: LOT INFO | H4: FINANCIALS | T4: SECURITY DEPOSIT | W4: FINAL PAYMENT | Z4: LPP | AC4: SUMMARY | AF4: DOCUMENT | AI4: TRACE
A5: Buyer | B5: Lot No. | C5: Lot Name | D5: Bid Sheet / Auction | E5: Quantity | F5: Unit | G5: Rate (₹) | H5: Mat. Value (₹) | I5: GST @ 18% (₹) | J5: Mat. Value + GST (₹) | K5: TCS @ 2% (₹) | L5: TDS u/s 194(O) (₹) | M5: Service Charge gross (₹) | N5: TDS u/s 194(H) (₹) | O5: Net Service Charge (₹) | P5: Svc Charge to MSTC (₹) | Q5: GST TDS Rate | R5: GST TDS (₹) | S5: Total Receivables (₹) | T5: SD Expected (₹) | U5: SD Received (₹) | V5: SD Receipt Date | W5: FP Expected (₹) | X5: FP Received (₹) | Y5: FP Receipt Date | Z5: LPP Expected (₹) | AA5: LPP Received (₹) | AB5: LPP Receipt Date | AC5: Total Received (₹) | AD5: Outstanding (₹) | AE5: Payment Status | AF5: Invoice No. | AG5: SAP Document | AH5: Doc./Invoice Date | AI5: Src Row
A6: ▼ AL HAMD TRADE CORPORATION | C6: 1 lot — click − to fold this buyer | E6: =SUBTOTAL(109,E7:E7) | H6: =SUBTOTAL(109,H7:H7) | I6: =SUBTOTAL(109,I7:I7) | J6: =SUBTOTAL(109,J7:J7) | K6: =SUBTOTAL(109,K7:K7) | L6: =SUBTOTAL(109,L7:L7) | M6: =SUBTOTAL(109,M7:M7) | N6: =SUBTOTAL(109,N7:N7) | O6: =SUBTOTAL(109,O7:O7) | P6: =SUBTOTAL(109,P7:P7) | R6: =SUBTOTAL(109,R7:R7) | S6: =SUBTOTAL(109,S7:S7) | T6: =SUBTOTAL(109,T7:T7) | U6: =SUBTOTAL(109,U7:U7) | W6: =SUBTOTAL(109,W7:W7) | X6: =SUBTOTAL(109,X7:X7) | Z6: =SUBTOTAL(109,Z7:Z7) | AA6: =SUBTOTAL(109,AA7:AA7) | AC6: =SUBTOTAL(109,AC7:AC7) | AD6: =SUBTOTAL(109,AD7:AD7)
A7: =IF('Final Calculation Sheet'!$G$4="","",'Final Calculation Sheet'!$G$4) | B7: =IF('Final Calculation Sheet'!$F$4="","",'Final Calculation Sheet'!$F$4) | C7: =IF('Final Calculation Sheet'!$B$4="","",'Final Calculation Sheet'!$B$4) | D7: =IF('Final Calculation Sheet'!$D$4="","",'Final Calculation Sheet'!$D$4) | E7: =IF('Final Calculation Sheet'!$A$4="","",'Final Calculation Sheet'!$A$4) | F7: =IF('Final Calculation Sheet'!$E$4="","",'Final Calculation Sheet'!$E$4) | G7: =IF('Final Calculation Sheet'!$C$4="","",'Final Calculation Sheet'!$C$4) | H7: =IF('Final Calculation Sheet'!$H$4="","",'Final Calculation Sheet'!$H$4) | I7: =IF('Final Calculation Sheet'!$I$4="","",'Final Calculation Sheet'!$I$4) | J7: =IF('Final Calculation Sheet'!$J$4="","",'Final Calculation Sheet'!$J$4) | K7: =IF('Final Calculation Sheet'!$K$4="","",'Final Calculation Sheet'!$K$4) | L7: =IF('Final Calculation Sheet'!$L$4="","",'Final Calculation Sheet'!$L$4) | M7: =IF('Final Calculation Sheet'!$M$4="","",'Final Calculation Sheet'!$M$4) | N7: =IF('Final Calculation Sheet'!$N$4="","",'Final Calculation Sheet'!$N$4) | O7: =IF('Final Calculation Sheet'!$O$4="","",'Final Calculation Sheet'!$O$4) | P7: =IF('Final Calculation Sheet'!$P$4="","",'Final Calculation Sheet'!$P$4) | Q7: =IF('Final Calculation Sheet'!$Q$4="","",'Final Calculation Sheet'!$Q$4) | R7: =IF('Final Calculation Sheet'!$R$4="","",'Final Calculation Sheet'!$R$4) | S7: =IF('Final Calculation Sheet'!$S$4="","",'Final Calculation Sheet'!$S$4) | T7: =IF('Final Calculation Sheet'!$T$4="","",'Final Calculation Sheet'!$T$4) | U7: =IF('Final Calculation Sheet'!$U$4="","",'Final Calculation Sheet'!$U$4) | V7: =IF('Final Calculation Sheet'!$V$4="","",'Final Calculation Sheet'!$V$4) | W7: =IF('Final Calculation Sheet'!$W$4="","",'Final Calculation Sheet'!$W$4) | X7: =IF('Final Calculation Sheet'!$X$4="","",'Final Calculation Sheet'!$X$4) | Y7: =IF('Final Calculation Sheet'!$Y$4="","",'Final Calculation Sheet'!$Y$4) | Z7: =IF('Final Calculation Sheet'!$Z$4="","",'Final Calculation Sheet'!$Z$4) | AA7: =IF('Final Calculation Sheet'!$AA$4="","",'Final Calculation Sheet'!$AA$4) | AB7: =IF('Final Calculation Sheet'!$AB$4="","",'Final Calculation Sheet'!$AB$4) | AC7: =IF('Final Calculation Sheet'!$AC$4="","",'Final Calculation Sheet'!$AC$4) | AD7: =IF('Final Calculation Sheet'!$AD$4="","",'Final Calculation Sheet'!$AD$4) | AE7: =IF('Final Calculation Sheet'!$AD$4="","",IF('Final Calculation Sheet'!$AD$4<=0,"SETTLED","OUTSTANDING")) | AF7: =IF('Final Calculation Sheet'!$AE$4="","",'Final Calculation Sheet'!$AE$4) | AG7: =IF('Final Calculation Sheet'!$AF$4="","",'Final Calculation Sheet'!$AF$4) | AH7: =IF('Final Calculation Sheet'!$AG$4="","",'Final Calculation Sheet'!$AG$4) | AI7: 4
A8: ▼ F R KHANS ENTERPRISES | C8: 2 lots — click − to fold this buyer | E8: =SUBTOTAL(109,E9:E10) | H8: =SUBTOTAL(109,H9:H10) | I8: =SUBTOTAL(109,I9:I10) | J8: =SUBTOTAL(109,J9:J10) | K8: =SUBTOTAL(109,K9:K10) | L8: =SUBTOTAL(109,L9:L10) | M8: =SUBTOTAL(109,M9:M10) | N8: =SUBTOTAL(109,N9:N10) | O8: =SUBTOTAL(109,O9:O10) | P8: =SUBTOTAL(109,P9:P10) | R8: =SUBTOTAL(109,R9:R10) | S8: =SUBTOTAL(109,S9:S10) | T8: =SUBTOTAL(109,T9:T10) | U8: =SUBTOTAL(109,U9:U10) | W8: =SUBTOTAL(109,W9:W10) | X8: =SUBTOTAL(109,X9:X10) | Z8: =SUBTOTAL(109,Z9:Z10) | AA8: =SUBTOTAL(109,AA9:AA10) | AC8: =SUBTOTAL(109,AC9:AC10) | AD8: =SUBTOTAL(109,AD9:AD10)
A9: =IF('Final Calculation Sheet'!$G$6="","",'Final Calculation Sheet'!$G$6) | B9: =IF('Final Calculation Sheet'!$F$6="","",'Final Calculation Sheet'!$F$6) | C9: =IF('Final Calculation Sheet'!$B$6="","",'Final Calculation Sheet'!$B$6) | D9: =IF('Final Calculation Sheet'!$D$6="","",'Final Calculation Sheet'!$D$6) | E9: =IF('Final Calculation Sheet'!$A$6="","",'Final Calculation Sheet'!$A$6) | F9: =IF('Final Calculation Sheet'!$E$6="","",'Final Calculation Sheet'!$E$6) | G9: =IF('Final Calculation Sheet'!$C$6="","",'Final Calculation Sheet'!$C$6) | H9: =IF('Final Calculation Sheet'!$H$6="","",'Final Calculation Sheet'!$H$6) | I9: =IF('Final Calculation Sheet'!$I$6="","",'Final Calculation Sheet'!$I$6) | J9: =IF('Final Calculation Sheet'!$J$6="","",'Final Calculation Sheet'!$J$6) | K9: =IF('Final Calculation Sheet'!$K$6="","",'Final Calculation Sheet'!$K$6) | L9: =IF('Final Calculation Sheet'!$L$6="","",'Final Calculation Sheet'!$L$6) | M9: =IF('Final Calculation Sheet'!$M$6="","",'Final Calculation Sheet'!$M$6) | N9: =IF('Final Calculation Sheet'!$N$6="","",'Final Calculation Sheet'!$N$6) | O9: =IF('Final Calculation Sheet'!$O$6="","",'Final Calculation Sheet'!$O$6) | P9: =IF('Final Calculation Sheet'!$P$6="","",'Final Calculation Sheet'!$P$6) | Q9: =IF('Final Calculation Sheet'!$Q$6="","",'Final Calculation Sheet'!$Q$6) | R9: =IF('Final Calculation Sheet'!$R$6="","",'Final Calculation Sheet'!$R$6) | S9: =IF('Final Calculation Sheet'!$S$6="","",'Final Calculation Sheet'!$S$6) | T9: =IF('Final Calculation Sheet'!$T$6="","",'Final Calculation Sheet'!$T$6) | U9: =IF('Final Calculation Sheet'!$U$6="","",'Final Calculation Sheet'!$U$6) | V9: =IF('Final Calculation Sheet'!$V$6="","",'Final Calculation Sheet'!$V$6) | W9: =IF('Final Calculation Sheet'!$W$6="","",'Final Calculation Sheet'!$W$6) | X9: =IF('Final Calculation Sheet'!$X$6="","",'Final Calculation Sheet'!$X$6) | Y9: =IF('Final Calculation Sheet'!$Y$6="","",'Final Calculation Sheet'!$Y$6) | Z9: =IF('Final Calculation Sheet'!$Z$6="","",'Final Calculation Sheet'!$Z$6) | AA9: =IF('Final Calculation Sheet'!$AA$6="","",'Final Calculation Sheet'!$AA$6) | AB9: =IF('Final Calculation Sheet'!$AB$6="","",'Final Calculation Sheet'!$AB$6) | AC9: =IF('Final Calculation Sheet'!$AC$6="","",'Final Calculation Sheet'!$AC$6) | AD9: =IF('Final Calculation Sheet'!$AD$6="","",'Final Calculation Sheet'!$AD$6) | AE9: =IF('Final Calculation Sheet'!$AD$6="","",IF('Final Calculation Sheet'!$AD$6<=0,"SETTLED","OUTSTANDING")) | AF9: =IF('Final Calculation Sheet'!$AE$6="","",'Final Calculation Sheet'!$AE$6) | AG9: =IF('Final Calculation Sheet'!$AF$6="","",'Final Calculation Sheet'!$AF$6) | AH9: =IF('Final Calculation Sheet'!$AG$6="","",'Final Calculation Sheet'!$AG$6) | AI9: 6
A10: =IF('Final Calculation Sheet'!$G$7="","",'Final Calculation Sheet'!$G$7) | B10: =IF('Final Calculation Sheet'!$F$7="","",'Final Calculation Sheet'!$F$7) | C10: =IF('Final Calculation Sheet'!$B$7="","",'Final Calculation Sheet'!$B$7) | D10: =IF('Final Calculation Sheet'!$D$7="","",'Final Calculation Sheet'!$D$7) | E10: =IF('Final Calculation Sheet'!$A$7="","",'Final Calculation Sheet'!$A$7) | F10: =IF('Final Calculation Sheet'!$E$7="","",'Final Calculation Sheet'!$E$7) | G10: =IF('Final Calculation Sheet'!$C$7="","",'Final Calculation Sheet'!$C$7) | H10: =IF('Final Calculation Sheet'!$H$7="","",'Final Calculation Sheet'!$H$7) | I10: =IF('Final Calculation Sheet'!$I$7="","",'Final Calculation Sheet'!$I$7) | J10: =IF('Final Calculation Sheet'!$J$7="","",'Final Calculation Sheet'!$J$7) | K10: =IF('Final Calculation Sheet'!$K$7="","",'Final Calculation Sheet'!$K$7) | L10: =IF('Final Calculation Sheet'!$L$7="","",'Final Calculation Sheet'!$L$7) | M10: =IF('Final Calculation Sheet'!$M$7="","",'Final Calculation Sheet'!$M$7) | N10: =IF('Final Calculation Sheet'!$N$7="","",'Final Calculation Sheet'!$N$7) | O10: =IF('Final Calculation Sheet'!$O$7="","",'Final Calculation Sheet'!$O$7) | P10: =IF('Final Calculation Sheet'!$P$7="","",'Final Calculation Sheet'!$P$7) | Q10: =IF('Final Calculation Sheet'!$Q$7="","",'Final Calculation Sheet'!$Q$7) | R10: =IF('Final Calculation Sheet'!$R$7="","",'Final Calculation Sheet'!$R$7) | S10: =IF('Final Calculation Sheet'!$S$7="","",'Final Calculation Sheet'!$S$7) | T10: =IF('Final Calculation Sheet'!$T$7="","",'Final Calculation Sheet'!$T$7) | U10: =IF('Final Calculation Sheet'!$U$7="","",'Final Calculation Sheet'!$U$7) | V10: =IF('Final Calculation Sheet'!$V$7="","",'Final Calculation Sheet'!$V$7) | W10: =IF('Final Calculation Sheet'!$W$7="","",'Final Calculation Sheet'!$W$7) | X10: =IF('Final Calculation Sheet'!$X$7="","",'Final Calculation Sheet'!$X$7) | Y10: =IF('Final Calculation Sheet'!$Y$7="","",'Final Calculation Sheet'!$Y$7) | Z10: =IF('Final Calculation Sheet'!$Z$7="","",'Final Calculation Sheet'!$Z$7) | AA10: =IF('Final Calculation Sheet'!$AA$7="","",'Final Calculation Sheet'!$AA$7) | AB10: =IF('Final Calculation Sheet'!$AB$7="","",'Final Calculation Sheet'!$AB$7) | AC10: =IF('Final Calculation Sheet'!$AC$7="","",'Final Calculation Sheet'!$AC$7) | AD10: =IF('Final Calculation Sheet'!$AD$7="","",'Final Calculation Sheet'!$AD$7) | AE10: =IF('Final Calculation Sheet'!$AD$7="","",IF('Final Calculation Sheet'!$AD$7<=0,"SETTLED","OUTSTANDING")) | AF10: =IF('Final Calculation Sheet'!$AE$7="","",'Final Calculation Sheet'!$AE$7) | AG10: =IF('Final Calculation Sheet'!$AF$7="","",'Final Calculation Sheet'!$AF$7) | AH10: =IF('Final Calculation Sheet'!$AG$7="","",'Final Calculation Sheet'!$AG$7) | AI10: 7
A11: ▼ HIND TRADERS | C11: 1 lot — click − to fold this buyer | E11: =SUBTOTAL(109,E12:E12) | H11: =SUBTOTAL(109,H12:H12) | I11: =SUBTOTAL(109,I12:I12) | J11: =SUBTOTAL(109,J12:J12) | K11: =SUBTOTAL(109,K12:K12) | L11: =SUBTOTAL(109,L12:L12) | M11: =SUBTOTAL(109,M12:M12) | N11: =SUBTOTAL(109,N12:N12) | O11: =SUBTOTAL(109,O12:O12) | P11: =SUBTOTAL(109,P12:P12) | R11: =SUBTOTAL(109,R12:R12) | S11: =SUBTOTAL(109,S12:S12) | T11: =SUBTOTAL(109,T12:T12) | U11: =SUBTOTAL(109,U12:U12) | W11: =SUBTOTAL(109,W12:W12) | X11: =SUBTOTAL(109,X12:X12) | Z11: =SUBTOTAL(109,Z12:Z12) | AA11: =SUBTOTAL(109,AA12:AA12) | AC11: =SUBTOTAL(109,AC12:AC12) | AD11: =SUBTOTAL(109,AD12:AD12)
A12: =IF('Final Calculation Sheet'!$G$15="","",'Final Calculation Sheet'!$G$15) | B12: =IF('Final Calculation Sheet'!$F$15="","",'Final Calculation Sheet'!$F$15) | C12: =IF('Final Calculation Sheet'!$B$15="","",'Final Calculation Sheet'!$B$15) | D12: =IF('Final Calculation Sheet'!$D$15="","",'Final Calculation Sheet'!$D$15) | E12: =IF('Final Calculation Sheet'!$A$15="","",'Final Calculation Sheet'!$A$15) | F12: =IF('Final Calculation Sheet'!$E$15="","",'Final Calculation Sheet'!$E$15) | G12: =IF('Final Calculation Sheet'!$C$15="","",'Final Calculation Sheet'!$C$15) | H12: =IF('Final Calculation Sheet'!$H$15="","",'Final Calculation Sheet'!$H$15) | I12: =IF('Final Calculation Sheet'!$I$15="","",'Final Calculation Sheet'!$I$15) | J12: =IF('Final Calculation Sheet'!$J$15="","",'Final Calculation Sheet'!$J$15) | K12: =IF('Final Calculation Sheet'!$K$15="","",'Final Calculation Sheet'!$K$15) | L12: =IF('Final Calculation Sheet'!$L$15="","",'Final Calculation Sheet'!$L$15) | M12: =IF('Final Calculation Sheet'!$M$15="","",'Final Calculation Sheet'!$M$15) | N12: =IF('Final Calculation Sheet'!$N$15="","",'Final Calculation Sheet'!$N$15) | O12: =IF('Final Calculation Sheet'!$O$15="","",'Final Calculation Sheet'!$O$15) | P12: =IF('Final Calculation Sheet'!$P$15="","",'Final Calculation Sheet'!$P$15) | Q12: =IF('Final Calculation Sheet'!$Q$15="","",'Final Calculation Sheet'!$Q$15) | R12: =IF('Final Calculation Sheet'!$R$15="","",'Final Calculation Sheet'!$R$15) | S12: =IF('Final Calculation Sheet'!$S$15="","",'Final Calculation Sheet'!$S$15) | T12: =IF('Final Calculation Sheet'!$T$15="","",'Final Calculation Sheet'!$T$15) | U12: =IF('Final Calculation Sheet'!$U$15="","",'Final Calculation Sheet'!$U$15) | V12: =IF('Final Calculation Sheet'!$V$15="","",'Final Calculation Sheet'!$V$15) | W12: =IF('Final Calculation Sheet'!$W$15="","",'Final Calculation Sheet'!$W$15) | X12: =IF('Final Calculation Sheet'!$X$15="","",'Final Calculation Sheet'!$X$15) | Y12: =IF('Final Calculation Sheet'!$Y$15="","",'Final Calculation Sheet'!$Y$15) | Z12: =IF('Final Calculation Sheet'!$Z$15="","",'Final Calculation Sheet'!$Z$15) | AA12: =IF('Final Calculation Sheet'!$AA$15="","",'Final Calculation Sheet'!$AA$15) | AB12: =IF('Final Calculation Sheet'!$AB$15="","",'Final Calculation Sheet'!$AB$15) | AC12: =IF('Final Calculation Sheet'!$AC$15="","",'Final Calculation Sheet'!$AC$15) | AD12: =IF('Final Calculation Sheet'!$AD$15="","",'Final Calculation Sheet'!$AD$15) | AE12: =IF('Final Calculation Sheet'!$AD$15="","",IF('Final Calculation Sheet'!$AD$15<=0,"SETTLED","OUTSTANDING")) | AF12: =IF('Final Calculation Sheet'!$AE$15="","",'Final Calculation Sheet'!$AE$15) | AG12: =IF('Final Calculation Sheet'!$AF$15="","",'Final Calculation Sheet'!$AF$15) | AH12: =IF('Final Calculation Sheet'!$AG$15="","",'Final Calculation Sheet'!$AG$15) | AI12: 15
A13: ▼ KASHYAP TRADING CO | C13: 1 lot — click − to fold this buyer | E13: =SUBTOTAL(109,E14:E14) | H13: =SUBTOTAL(109,H14:H14) | I13: =SUBTOTAL(109,I14:I14) | J13: =SUBTOTAL(109,J14:J14) | K13: =SUBTOTAL(109,K14:K14) | L13: =SUBTOTAL(109,L14:L14) | M13: =SUBTOTAL(109,M14:M14) | N13: =SUBTOTAL(109,N14:N14) | O13: =SUBTOTAL(109,O14:O14) | P13: =SUBTOTAL(109,P14:P14) | R13: =SUBTOTAL(109,R14:R14) | S13: =SUBTOTAL(109,S14:S14) | T13: =SUBTOTAL(109,T14:T14) | U13: =SUBTOTAL(109,U14:U14) | W13: =SUBTOTAL(109,W14:W14) | X13: =SUBTOTAL(109,X14:X14) | Z13: =SUBTOTAL(109,Z14:Z14) | AA13: =SUBTOTAL(109,AA14:AA14) | AC13: =SUBTOTAL(109,AC14:AC14) | AD13: =SUBTOTAL(109,AD14:AD14)
A14: =IF('Final Calculation Sheet'!$G$38="","",'Final Calculation Sheet'!$G$38) | B14: =IF('Final Calculation Sheet'!$F$38="","",'Final Calculation Sheet'!$F$38) | C14: =IF('Final Calculation Sheet'!$B$38="","",'Final Calculation Sheet'!$B$38) | D14: =IF('Final Calculation Sheet'!$D$38="","",'Final Calculation Sheet'!$D$38) | E14: =IF('Final Calculation Sheet'!$A$38="","",'Final Calculation Sheet'!$A$38) | F14: =IF('Final Calculation Sheet'!$E$38="","",'Final Calculation Sheet'!$E$38) | G14: =IF('Final Calculation Sheet'!$C$38="","",'Final Calculation Sheet'!$C$38) | H14: =IF('Final Calculation Sheet'!$H$38="","",'Final Calculation Sheet'!$H$38) | I14: =IF('Final Calculation Sheet'!$I$38="","",'Final Calculation Sheet'!$I$38) | J14: =IF('Final Calculation Sheet'!$J$38="","",'Final Calculation Sheet'!$J$38) | K14: =IF('Final Calculation Sheet'!$K$38="","",'Final Calculation Sheet'!$K$38) | L14: =IF('Final Calculation Sheet'!$L$38="","",'Final Calculation Sheet'!$L$38) | M14: =IF('Final Calculation Sheet'!$M$38="","",'Final Calculation Sheet'!$M$38) | N14: =IF('Final Calculation Sheet'!$N$38="","",'Final Calculation Sheet'!$N$38) | O14: =IF('Final Calculation Sheet'!$O$38="","",'Final Calculation Sheet'!$O$38) | P14: =IF('Final Calculation Sheet'!$P$38="","",'Final Calculation Sheet'!$P$38) | Q14: =IF('Final Calculation Sheet'!$Q$38="","",'Final Calculation Sheet'!$Q$38) | R14: =IF('Final Calculation Sheet'!$R$38="","",'Final Calculation Sheet'!$R$38) | S14: =IF('Final Calculation Sheet'!$S$38="","",'Final Calculation Sheet'!$S$38) | T14: =IF('Final Calculation Sheet'!$T$38="","",'Final Calculation Sheet'!$T$38) | U14: =IF('Final Calculation Sheet'!$U$38="","",'Final Calculation Sheet'!$U$38) | V14: =IF('Final Calculation Sheet'!$V$38="","",'Final Calculation Sheet'!$V$38) | W14: =IF('Final Calculation Sheet'!$W$38="","",'Final Calculation Sheet'!$W$38) | X14: =IF('Final Calculation Sheet'!$X$38="","",'Final Calculation Sheet'!$X$38) | Y14: =IF('Final Calculation Sheet'!$Y$38="","",'Final Calculation Sheet'!$Y$38) | Z14: =IF('Final Calculation Sheet'!$Z$38="","",'Final Calculation Sheet'!$Z$38) | AA14: =IF('Final Calculation Sheet'!$AA$38="","",'Final Calculation Sheet'!$AA$38) | AB14: =IF('Final Calculation Sheet'!$AB$38="","",'Final Calculation Sheet'!$AB$38) | AC14: =IF('Final Calculation Sheet'!$AC$38="","",'Final Calculation Sheet'!$AC$38) | AD14: =IF('Final Calculation Sheet'!$AD$38="","",'Final Calculation Sheet'!$AD$38) | AE14: =IF('Final Calculation Sheet'!$AD$38="","",IF('Final Calculation Sheet'!$AD$38<=0,"SETTLED","OUTSTANDING")) | AF14: =IF('Final Calculation Sheet'!$AE$38="","",'Final Calculation Sheet'!$AE$38) | AG14: =IF('Final Calculation Sheet'!$AF$38="","",'Final Calculation Sheet'!$AF$38) | AH14: =IF('Final Calculation Sheet'!$AG$38="","",'Final Calculation Sheet'!$AG$38) | AI14: 38
A15: ▼ M I SCRAP TRADERS | C15: 1 lot — click − to fold this buyer | E15: =SUBTOTAL(109,E16:E16) | H15: =SUBTOTAL(109,H16:H16) | I15: =SUBTOTAL(109,I16:I16) | J15: =SUBTOTAL(109,J16:J16) | K15: =SUBTOTAL(109,K16:K16) | L15: =SUBTOTAL(109,L16:L16) | M15: =SUBTOTAL(109,M16:M16) | N15: =SUBTOTAL(109,N16:N16) | O15: =SUBTOTAL(109,O16:O16) | P15: =SUBTOTAL(109,P16:P16) | R15: =SUBTOTAL(109,R16:R16) | S15: =SUBTOTAL(109,S16:S16) | T15: =SUBTOTAL(109,T16:T16) | U15: =SUBTOTAL(109,U16:U16) | W15: =SUBTOTAL(109,W16:W16) | X15: =SUBTOTAL(109,X16:X16) | Z15: =SUBTOTAL(109,Z16:Z16) | AA15: =SUBTOTAL(109,AA16:AA16) | AC15: =SUBTOTAL(109,AC16:AC16) | AD15: =SUBTOTAL(109,AD16:AD16)
A16: =IF('Final Calculation Sheet'!$G$27="","",'Final Calculation Sheet'!$G$27) | B16: =IF('Final Calculation Sheet'!$F$27="","",'Final Calculation Sheet'!$F$27) | C16: =IF('Final Calculation Sheet'!$B$27="","",'Final Calculation Sheet'!$B$27) | D16: =IF('Final Calculation Sheet'!$D$27="","",'Final Calculation Sheet'!$D$27) | E16: =IF('Final Calculation Sheet'!$A$27="","",'Final Calculation Sheet'!$A$27) | F16: =IF('Final Calculation Sheet'!$E$27="","",'Final Calculation Sheet'!$E$27) | G16: =IF('Final Calculation Sheet'!$C$27="","",'Final Calculation Sheet'!$C$27) | H16: =IF('Final Calculation Sheet'!$H$27="","",'Final Calculation Sheet'!$H$27) | I16: =IF('Final Calculation Sheet'!$I$27="","",'Final Calculation Sheet'!$I$27) | J16: =IF('Final Calculation Sheet'!$J$27="","",'Final Calculation Sheet'!$J$27) | K16: =IF('Final Calculation Sheet'!$K$27="","",'Final Calculation Sheet'!$K$27) | L16: =IF('Final Calculation Sheet'!$L$27="","",'Final Calculation Sheet'!$L$27) | M16: =IF('Final Calculation Sheet'!$M$27="","",'Final Calculation Sheet'!$M$27) | N16: =IF('Final Calculation Sheet'!$N$27="","",'Final Calculation Sheet'!$N$27) | O16: =IF('Final Calculation Sheet'!$O$27="","",'Final Calculation Sheet'!$O$27) | P16: =IF('Final Calculation Sheet'!$P$27="","",'Final Calculation Sheet'!$P$27) | Q16: =IF('Final Calculation Sheet'!$Q$27="","",'Final Calculation Sheet'!$Q$27) | R16: =IF('Final Calculation Sheet'!$R$27="","",'Final Calculation Sheet'!$R$27) | S16: =IF('Final Calculation Sheet'!$S$27="","",'Final Calculation Sheet'!$S$27) | T16: =IF('Final Calculation Sheet'!$T$27="","",'Final Calculation Sheet'!$T$27) | U16: =IF('Final Calculation Sheet'!$U$27="","",'Final Calculation Sheet'!$U$27) | V16: =IF('Final Calculation Sheet'!$V$27="","",'Final Calculation Sheet'!$V$27) | W16: =IF('Final Calculation Sheet'!$W$27="","",'Final Calculation Sheet'!$W$27) | X16: =IF('Final Calculation Sheet'!$X$27="","",'Final Calculation Sheet'!$X$27) | Y16: =IF('Final Calculation Sheet'!$Y$27="","",'Final Calculation Sheet'!$Y$27) | Z16: =IF('Final Calculation Sheet'!$Z$27="","",'Final Calculation Sheet'!$Z$27) | AA16: =IF('Final Calculation Sheet'!$AA$27="","",'Final Calculation Sheet'!$AA$27) | AB16: =IF('Final Calculation Sheet'!$AB$27="","",'Final Calculation Sheet'!$AB$27) | AC16: =IF('Final Calculation Sheet'!$AC$27="","",'Final Calculation Sheet'!$AC$27) | AD16: =IF('Final Calculation Sheet'!$AD$27="","",'Final Calculation Sheet'!$AD$27) | AE16: =IF('Final Calculation Sheet'!$AD$27="","",IF('Final Calculation Sheet'!$AD$27<=0,"SETTLED","OUTSTANDING")) | AF16: =IF('Final Calculation Sheet'!$AE$27="","",'Final Calculation Sheet'!$AE$27) | AG16: =IF('Final Calculation Sheet'!$AF$27="","",'Final Calculation Sheet'!$AF$27) | AH16: =IF('Final Calculation Sheet'!$AG$27="","",'Final Calculation Sheet'!$AG$27) | AI16: 27
A17: ▼ NATIONAL ENTERPRISES | C17: 13 lots — click − to fold this buyer | E17: =SUBTOTAL(109,E18:E30) | H17: =SUBTOTAL(109,H18:H30) | I17: =SUBTOTAL(109,I18:I30) | J17: =SUBTOTAL(109,J18:J30) | K17: =SUBTOTAL(109,K18:K30) | L17: =SUBTOTAL(109,L18:L30) | M17: =SUBTOTAL(109,M18:M30) | N17: =SUBTOTAL(109,N18:N30) | O17: =SUBTOTAL(109,O18:O30) | P17: =SUBTOTAL(109,P18:P30) | R17: =SUBTOTAL(109,R18:R30) | S17: =SUBTOTAL(109,S18:S30) | T17: =SUBTOTAL(109,T18:T30) | U17: =SUBTOTAL(109,U18:U30) | W17: =SUBTOTAL(109,W18:W30) | X17: =SUBTOTAL(109,X18:X30) | Z17: =SUBTOTAL(109,Z18:Z30) | AA17: =SUBTOTAL(109,AA18:AA30) | AC17: =SUBTOTAL(109,AC18:AC30) | AD17: =SUBTOTAL(109,AD18:AD30)
A18: =IF('Final Calculation Sheet'!$G$5="","",'Final Calculation Sheet'!$G$5) | B18: =IF('Final Calculation Sheet'!$F$5="","",'Final Calculation Sheet'!$F$5) | C18: =IF('Final Calculation Sheet'!$B$5="","",'Final Calculation Sheet'!$B$5) | D18: =IF('Final Calculation Sheet'!$D$5="","",'Final Calculation Sheet'!$D$5) | E18: =IF('Final Calculation Sheet'!$A$5="","",'Final Calculation Sheet'!$A$5) | F18: =IF('Final Calculation Sheet'!$E$5="","",'Final Calculation Sheet'!$E$5) | G18: =IF('Final Calculation Sheet'!$C$5="","",'Final Calculation Sheet'!$C$5) | H18: =IF('Final Calculation Sheet'!$H$5="","",'Final Calculation Sheet'!$H$5) | I18: =IF('Final Calculation Sheet'!$I$5="","",'Final Calculation Sheet'!$I$5) | J18: =IF('Final Calculation Sheet'!$J$5="","",'Final Calculation Sheet'!$J$5) | K18: =IF('Final Calculation Sheet'!$K$5="","",'Final Calculation Sheet'!$K$5) | L18: =IF('Final Calculation Sheet'!$L$5="","",'Final Calculation Sheet'!$L$5) | M18: =IF('Final Calculation Sheet'!$M$5="","",'Final Calculation Sheet'!$M$5) | N18: =IF('Final Calculation Sheet'!$N$5="","",'Final Calculation Sheet'!$N$5) | O18: =IF('Final Calculation Sheet'!$O$5="","",'Final Calculation Sheet'!$O$5) | P18: =IF('Final Calculation Sheet'!$P$5="","",'Final Calculation Sheet'!$P$5) | Q18: =IF('Final Calculation Sheet'!$Q$5="","",'Final Calculation Sheet'!$Q$5) | R18: =IF('Final Calculation Sheet'!$R$5="","",'Final Calculation Sheet'!$R$5) | S18: =IF('Final Calculation Sheet'!$S$5="","",'Final Calculation Sheet'!$S$5) | T18: =IF('Final Calculation Sheet'!$T$5="","",'Final Calculation Sheet'!$T$5) | U18: =IF('Final Calculation Sheet'!$U$5="","",'Final Calculation Sheet'!$U$5) | V18: =IF('Final Calculation Sheet'!$V$5="","",'Final Calculation Sheet'!$V$5) | W18: =IF('Final Calculation Sheet'!$W$5="","",'Final Calculation Sheet'!$W$5) | X18: =IF('Final Calculation Sheet'!$X$5="","",'Final Calculation Sheet'!$X$5) | Y18: =IF('Final Calculation Sheet'!$Y$5="","",'Final Calculation Sheet'!$Y$5) | Z18: =IF('Final Calculation Sheet'!$Z$5="","",'Final Calculation Sheet'!$Z$5) | AA18: =IF('Final Calculation Sheet'!$AA$5="","",'Final Calculation Sheet'!$AA$5) | AB18: =IF('Final Calculation Sheet'!$AB$5="","",'Final Calculation Sheet'!$AB$5) | AC18: =IF('Final Calculation Sheet'!$AC$5="","",'Final Calculation Sheet'!$AC$5) | AD18: =IF('Final Calculation Sheet'!$AD$5="","",'Final Calculation Sheet'!$AD$5) | AE18: =IF('Final Calculation Sheet'!$AD$5="","",IF('Final Calculation Sheet'!$AD$5<=0,"SETTLED","OUTSTANDING")) | AF18: =IF('Final Calculation Sheet'!$AE$5="","",'Final Calculation Sheet'!$AE$5) | AG18: =IF('Final Calculation Sheet'!$AF$5="","",'Final Calculation Sheet'!$AF$5) | AH18: =IF('Final Calculation Sheet'!$AG$5="","",'Final Calculation Sheet'!$AG$5) | AI18: 5
A19: =IF('Final Calculation Sheet'!$G$10="","",'Final Calculation Sheet'!$G$10) | B19: =IF('Final Calculation Sheet'!$F$10="","",'Final Calculation Sheet'!$F$10) | C19: =IF('Final Calculation Sheet'!$B$10="","",'Final Calculation Sheet'!$B$10) | D19: =IF('Final Calculation Sheet'!$D$10="","",'Final Calculation Sheet'!$D$10) | E19: =IF('Final Calculation Sheet'!$A$10="","",'Final Calculation Sheet'!$A$10) | F19: =IF('Final Calculation Sheet'!$E$10="","",'Final Calculation Sheet'!$E$10) | G19: =IF('Final Calculation Sheet'!$C$10="","",'Final Calculation Sheet'!$C$10) | H19: =IF('Final Calculation Sheet'!$H$10="","",'Final Calculation Sheet'!$H$10) | I19: =IF('Final Calculation Sheet'!$I$10="","",'Final Calculation Sheet'!$I$10) | J19: =IF('Final Calculation Sheet'!$J$10="","",'Final Calculation Sheet'!$J$10) | K19: =IF('Final Calculation Sheet'!$K$10="","",'Final Calculation Sheet'!$K$10) | L19: =IF('Final Calculation Sheet'!$L$10="","",'Final Calculation Sheet'!$L$10) | M19: =IF('Final Calculation Sheet'!$M$10="","",'Final Calculation Sheet'!$M$10) | N19: =IF('Final Calculation Sheet'!$N$10="","",'Final Calculation Sheet'!$N$10) | O19: =IF('Final Calculation Sheet'!$O$10="","",'Final Calculation Sheet'!$O$10) | P19: =IF('Final Calculation Sheet'!$P$10="","",'Final Calculation Sheet'!$P$10) | Q19: =IF('Final Calculation Sheet'!$Q$10="","",'Final Calculation Sheet'!$Q$10) | R19: =IF('Final Calculation Sheet'!$R$10="","",'Final Calculation Sheet'!$R$10) | S19: =IF('Final Calculation Sheet'!$S$10="","",'Final Calculation Sheet'!$S$10) | T19: =IF('Final Calculation Sheet'!$T$10="","",'Final Calculation Sheet'!$T$10) | U19: =IF('Final Calculation Sheet'!$U$10="","",'Final Calculation Sheet'!$U$10) | V19: =IF('Final Calculation Sheet'!$V$10="","",'Final Calculation Sheet'!$V$10) | W19: =IF('Final Calculation Sheet'!$W$10="","",'Final Calculation Sheet'!$W$10) | X19: =IF('Final Calculation Sheet'!$X$10="","",'Final Calculation Sheet'!$X$10) | Y19: =IF('Final Calculation Sheet'!$Y$10="","",'Final Calculation Sheet'!$Y$10) | Z19: =IF('Final Calculation Sheet'!$Z$10="","",'Final Calculation Sheet'!$Z$10) | AA19: =IF('Final Calculation Sheet'!$AA$10="","",'Final Calculation Sheet'!$AA$10) | AB19: =IF('Final Calculation Sheet'!$AB$10="","",'Final Calculation Sheet'!$AB$10) | AC19: =IF('Final Calculation Sheet'!$AC$10="","",'Final Calculation Sheet'!$AC$10) | AD19: =IF('Final Calculation Sheet'!$AD$10="","",'Final Calculation Sheet'!$AD$10) | AE19: =IF('Final Calculation Sheet'!$AD$10="","",IF('Final Calculation Sheet'!$AD$10<=0,"SETTLED","OUTSTANDING")) | AF19: =IF('Final Calculation Sheet'!$AE$10="","",'Final Calculation Sheet'!$AE$10) | AG19: =IF('Final Calculation Sheet'!$AF$10="","",'Final Calculation Sheet'!$AF$10) | AH19: =IF('Final Calculation Sheet'!$AG$10="","",'Final Calculation Sheet'!$AG$10) | AI19: 10
A20: =IF('Final Calculation Sheet'!$G$11="","",'Final Calculation Sheet'!$G$11) | B20: =IF('Final Calculation Sheet'!$F$11="","",'Final Calculation Sheet'!$F$11) | C20: =IF('Final Calculation Sheet'!$B$11="","",'Final Calculation Sheet'!$B$11) | D20: =IF('Final Calculation Sheet'!$D$11="","",'Final Calculation Sheet'!$D$11) | E20: =IF('Final Calculation Sheet'!$A$11="","",'Final Calculation Sheet'!$A$11) | F20: =IF('Final Calculation Sheet'!$E$11="","",'Final Calculation Sheet'!$E$11) | G20: =IF('Final Calculation Sheet'!$C$11="","",'Final Calculation Sheet'!$C$11) | H20: =IF('Final Calculation Sheet'!$H$11="","",'Final Calculation Sheet'!$H$11) | I20: =IF('Final Calculation Sheet'!$I$11="","",'Final Calculation Sheet'!$I$11) | J20: =IF('Final Calculation Sheet'!$J$11="","",'Final Calculation Sheet'!$J$11) | K20: =IF('Final Calculation Sheet'!$K$11="","",'Final Calculation Sheet'!$K$11) | L20: =IF('Final Calculation Sheet'!$L$11="","",'Final Calculation Sheet'!$L$11) | M20: =IF('Final Calculation Sheet'!$M$11="","",'Final Calculation Sheet'!$M$11) | N20: =IF('Final Calculation Sheet'!$N$11="","",'Final Calculation Sheet'!$N$11) | O20: =IF('Final Calculation Sheet'!$O$11="","",'Final Calculation Sheet'!$O$11) | P20: =IF('Final Calculation Sheet'!$P$11="","",'Final Calculation Sheet'!$P$11) | Q20: =IF('Final Calculation Sheet'!$Q$11="","",'Final Calculation Sheet'!$Q$11) | R20: =IF('Final Calculation Sheet'!$R$11="","",'Final Calculation Sheet'!$R$11) | S20: =IF('Final Calculation Sheet'!$S$11="","",'Final Calculation Sheet'!$S$11) | T20: =IF('Final Calculation Sheet'!$T$11="","",'Final Calculation Sheet'!$T$11) | U20: =IF('Final Calculation Sheet'!$U$11="","",'Final Calculation Sheet'!$U$11) | V20: =IF('Final Calculation Sheet'!$V$11="","",'Final Calculation Sheet'!$V$11) | W20: =IF('Final Calculation Sheet'!$W$11="","",'Final Calculation Sheet'!$W$11) | X20: =IF('Final Calculation Sheet'!$X$11="","",'Final Calculation Sheet'!$X$11) | Y20: =IF('Final Calculation Sheet'!$Y$11="","",'Final Calculation Sheet'!$Y$11) | Z20: =IF('Final Calculation Sheet'!$Z$11="","",'Final Calculation Sheet'!$Z$11) | AA20: =IF('Final Calculation Sheet'!$AA$11="","",'Final Calculation Sheet'!$AA$11) | AB20: =IF('Final Calculation Sheet'!$AB$11="","",'Final Calculation Sheet'!$AB$11) | AC20: =IF('Final Calculation Sheet'!$AC$11="","",'Final Calculation Sheet'!$AC$11) | AD20: =IF('Final Calculation Sheet'!$AD$11="","",'Final Calculation Sheet'!$AD$11) | AE20: =IF('Final Calculation Sheet'!$AD$11="","",IF('Final Calculation Sheet'!$AD$11<=0,"SETTLED","OUTSTANDING")) | AF20: =IF('Final Calculation Sheet'!$AE$11="","",'Final Calculation Sheet'!$AE$11) | AG20: =IF('Final Calculation Sheet'!$AF$11="","",'Final Calculation Sheet'!$AF$11) | AH20: =IF('Final Calculation Sheet'!$AG$11="","",'Final Calculation Sheet'!$AG$11) | AI20: 11
A21: =IF('Final Calculation Sheet'!$G$12="","",'Final Calculation Sheet'!$G$12) | B21: =IF('Final Calculation Sheet'!$F$12="","",'Final Calculation Sheet'!$F$12) | C21: =IF('Final Calculation Sheet'!$B$12="","",'Final Calculation Sheet'!$B$12) | D21: =IF('Final Calculation Sheet'!$D$12="","",'Final Calculation Sheet'!$D$12) | E21: =IF('Final Calculation Sheet'!$A$12="","",'Final Calculation Sheet'!$A$12) | F21: =IF('Final Calculation Sheet'!$E$12="","",'Final Calculation Sheet'!$E$12) | G21: =IF('Final Calculation Sheet'!$C$12="","",'Final Calculation Sheet'!$C$12) | H21: =IF('Final Calculation Sheet'!$H$12="","",'Final Calculation Sheet'!$H$12) | I21: =IF('Final Calculation Sheet'!$I$12="","",'Final Calculation Sheet'!$I$12) | J21: =IF('Final Calculation Sheet'!$J$12="","",'Final Calculation Sheet'!$J$12) | K21: =IF('Final Calculation Sheet'!$K$12="","",'Final Calculation Sheet'!$K$12) | L21: =IF('Final Calculation Sheet'!$L$12="","",'Final Calculation Sheet'!$L$12) | M21: =IF('Final Calculation Sheet'!$M$12="","",'Final Calculation Sheet'!$M$12) | N21: =IF('Final Calculation Sheet'!$N$12="","",'Final Calculation Sheet'!$N$12) | O21: =IF('Final Calculation Sheet'!$O$12="","",'Final Calculation Sheet'!$O$12) | P21: =IF('Final Calculation Sheet'!$P$12="","",'Final Calculation Sheet'!$P$12) | Q21: =IF('Final Calculation Sheet'!$Q$12="","",'Final Calculation Sheet'!$Q$12) | R21: =IF('Final Calculation Sheet'!$R$12="","",'Final Calculation Sheet'!$R$12) | S21: =IF('Final Calculation Sheet'!$S$12="","",'Final Calculation Sheet'!$S$12) | T21: =IF('Final Calculation Sheet'!$T$12="","",'Final Calculation Sheet'!$T$12) | U21: =IF('Final Calculation Sheet'!$U$12="","",'Final Calculation Sheet'!$U$12) | V21: =IF('Final Calculation Sheet'!$V$12="","",'Final Calculation Sheet'!$V$12) | W21: =IF('Final Calculation Sheet'!$W$12="","",'Final Calculation Sheet'!$W$12) | X21: =IF('Final Calculation Sheet'!$X$12="","",'Final Calculation Sheet'!$X$12) | Y21: =IF('Final Calculation Sheet'!$Y$12="","",'Final Calculation Sheet'!$Y$12) | Z21: =IF('Final Calculation Sheet'!$Z$12="","",'Final Calculation Sheet'!$Z$12) | AA21: =IF('Final Calculation Sheet'!$AA$12="","",'Final Calculation Sheet'!$AA$12) | AB21: =IF('Final Calculation Sheet'!$AB$12="","",'Final Calculation Sheet'!$AB$12) | AC21: =IF('Final Calculation Sheet'!$AC$12="","",'Final Calculation Sheet'!$AC$12) | AD21: =IF('Final Calculation Sheet'!$AD$12="","",'Final Calculation Sheet'!$AD$12) | AE21: =IF('Final Calculation Sheet'!$AD$12="","",IF('Final Calculation Sheet'!$AD$12<=0,"SETTLED","OUTSTANDING")) | AF21: =IF('Final Calculation Sheet'!$AE$12="","",'Final Calculation Sheet'!$AE$12) | AG21: =IF('Final Calculation Sheet'!$AF$12="","",'Final Calculation Sheet'!$AF$12) | AH21: =IF('Final Calculation Sheet'!$AG$12="","",'Final Calculation Sheet'!$AG$12) | AI21: 12
