Workbook

Sheet Buyer Pivot
A1: MSTC LIMITED — Buyer-wise Lot Details
A2: ▶ Select Buyer: | B2: AL HAMD TRADE CORPORATION | C2: ← Click cell to pick buyer from dropdown
A3: Buyer Name: | B3: =B2 -> AL HAMD TRADE CORPORATION
A4: Field | B4: Lot 1 | C4: Lot 2 | D4: Lot 3 | E4: Lot 4 | F4: Lot 5 | G4: Lot 6 | H4: Lot 7 | I4: Lot 8 | J4: Lot 9 | K4: Lot 10 | L4: Lot 11 | M4: Lot 12 | N4: Lot 13
A5: LOT INFORMATION
A6: Lot No. | B6: =IFERROR(INDIRECT("'Final Calculation Sheet'!$F"&INDEX('Buyer Lookup'!$A:$AZ,MATCH($B$2,'Buyer Lookup'!$A:$A,0),2)),"") -> 1763 | C6: =IFERROR(INDIRECT("'Final Calculation Sheet'!$F"&INDEX('Buyer Lookup'!$A:$AZ,MATCH($B$2,'Buyer Lookup'!$A:$A,0),3)),"") -> 0 | D6: =IFERROR(INDIRECT("'Final Calculation Sheet'!$F"&INDEX('Buyer Lookup'!$A:$AZ,MATCH($B$2,'Buyer Lookup'!$A:$A,0),4)),"") | E6: =IFERROR(INDIRECT("'Final Calculation Sheet'!$F"&INDEX('Buyer Lookup'!$A:$AZ,MATCH($B$2,'Buyer Lookup'!$A:$A,0),5)),"") | F6: =IFERROR(INDIRECT("'Final Calculation Sheet'!$F"&INDEX('Buyer Lookup'!$A:$AZ,MATCH($B$2,'Buyer Lookup'!$A:$A,0),6)),"") | G6: =IFERROR(INDIRECT("'Final Calculation Sheet'!$F"&INDEX('Buyer Lookup'!$A:$AZ,MATCH($B$2,'Buyer Lookup'!$A:$A,0),7)),"") | H6: =IFERROR(INDIRECT("'Final Calculation Sheet'!$F"&INDEX('Buyer Lookup'!$A:$AZ,MATCH($B$2,'Buyer Lookup'!$A:$A,0),8)),"") | I6: =IFERROR(INDIRECT("'Final Calculation Sheet'!$F"&INDEX('Buyer Lookup'!$A:$AZ,MATCH($B$2,'Buyer Lookup'!$A:$A,0),9)),"") | J6: =IFERROR(INDIRECT("'Final Calculation Sheet'!$F"&INDEX('Buyer Lookup'!$A:$AZ,MATCH($B$2,'Buyer Lookup'!$A:$A,0),10)),"") | K6: =IFERROR(INDIRECT("'Final Calculation Sheet'!$F"&INDEX('Buyer Lookup'!$A:$AZ,MATCH($B$2,'Buyer Lookup'!$A:$A,0),11)),"") | L6: =IFERROR(INDIRECT("'Final Calculation Sheet'!$F"&INDEX('Buyer Lookup'!$A:$AZ,MATCH($B$2,'Buyer Lookup'!$A:$A,0),12)),"") | M6: =IFERROR(INDIRECT("'Final Calculation Sheet'!$F"&INDEX('Buyer Lookup'!$A:$AZ,MATCH($B$2,'Buyer Lookup'!$A:$A,0),13)),"") | N6: =IFERROR(INDIRECT("'Final Calculation Sheet'!$F"&INDEX('Buyer Lookup'!$A:$AZ,MATCH($B$2,'Buyer Lookup'!$A:$A,0),14)),"")
A7: Lot Name | B7: =IFERROR(INDIRECT("'Final Calculation Sheet'!$B"&INDEX('Buyer Lookup'!$A:$AZ,MATCH($B$2,'Buyer Lookup'!$A:$A,0),2)),"") -> SCRAP COPPER OF T/F WINDING (Oil impregnated paper insulated T/F winding) | C7: =IFERROR(INDIRECT("'Final Calculation Sheet'!$B"&INDEX('Buyer Lookup'!$A:$AZ,MATCH($B$2,'Buyer Lookup'!$A:$A,0),3)),"") -> 0 | D7: =IFERROR(INDIRECT("'Final Calculation Sheet'!$B"&INDEX('Buyer Lookup'!$A:$AZ,MATCH($B$2,'Buyer Lookup'!$A:$A,0),4)),"") | E7: =IFERROR(INDIRECT("'Final Calculation Sheet'!$B"&INDEX('Buyer Lookup'!$A:$AZ,MATCH($B$2,'Buyer Lookup'!$A:$A,0),5)),"") | F7: =IFERROR(INDIRECT("'Final Calculation Sheet'!$B"&INDEX('Buyer Lookup'!$A:$AZ,MATCH($B$2,'Buyer Lookup'!$A:$A,0),6)),"") | G7: =IFERROR(INDIRECT("'Final Calculation Sheet'!$B"&INDEX('Buyer Lookup'!$A:$AZ,MATCH($B$2,'Buyer Lookup'!$A:$A,0),7)),"") | H7: =IFERROR(INDIRECT("'Final Calculation Sheet'!$B"&INDEX('Buyer Lookup'!$A:$AZ,MATCH($B$2,'Buyer Lookup'!$A:$A,0),8)),"") | I7: =IFERROR(INDIRECT("'Final Calculation Sheet'!$B"&INDEX('Buyer Lookup'!$A:$AZ,MATCH($B$2,'Buyer Lookup'!$A:$A,0),9)),"") | J7: =IFERROR(INDIRECT("'Final Calculation Sheet'!$B"&INDEX('Buyer Lookup'!$A:$AZ,MATCH($B$2,'Buyer Lookup'!$A:$A,0),10)),"") | K7: =IFERROR(INDIRECT("'Final Calculation Sheet'!$B"&INDEX('Buyer Lookup'!$A:$AZ,MATCH($B$2,'Buyer Lookup'!$A:$A,0),11)),"") | L7: =IFERROR(INDIRECT("'Final Calculation Sheet'!$B"&INDEX('Buyer Lookup'!$A:$AZ,MATCH($B$2,'Buyer Lookup'!$A:$A,0),12)),"") | M7: =IFERROR(INDIRECT("'Final Calculation Sheet'!$B"&INDEX('Buyer Lookup'!$A:$AZ,MATCH($B$2,'Buyer Lookup'!$A:$A,0),13)),"") | N7: =IFERROR(INDIRECT("'Final Calculation Sheet'!$B"&INDEX('Buyer Lookup'!$A:$AZ,MATCH($B$2,'Buyer Lookup'!$A:$A,0),14)),"")
A8: Bid Sheet | B8: =IFERROR(INDIRECT("'Final Calculation Sheet'!$D"&INDEX('Buyer Lookup'!$A:$AZ,MATCH($B$2,'Buyer Lookup'!$A:$A,0),2)),"") -> 21980 | C8: =IFERROR(INDIRECT("'Final Calculation Sheet'!$D"&INDEX('Buyer Lookup'!$A:$AZ,MATCH($B$2,'Buyer Lookup'!$A:$A,0),3)),"") -> 0 | D8: =IFERROR(INDIRECT("'Final Calculation Sheet'!$D"&INDEX('Buyer Lookup'!$A:$AZ,MATCH($B$2,'Buyer Lookup'!$A:$A,0),4)),"") | E8: =IFERROR(INDIRECT("'Final Calculation Sheet'!$D"&INDEX('Buyer Lookup'!$A:$AZ,MATCH($B$2,'Buyer Lookup'!$A:$A,0),5)),"") | F8: =IFERROR(INDIRECT("'Final Calculation Sheet'!$D"&INDEX('Buyer Lookup'!$A:$AZ,MATCH($B$2,'Buyer Lookup'!$A:$A,0),6)),"") | G8: =IFERROR(INDIRECT("'Final Calculation Sheet'!$D"&INDEX('Buyer Lookup'!$A:$AZ,MATCH($B$2,'Buyer Lookup'!$A:$A,0),7)),"") | H8: =IFERROR(INDIRECT("'Final Calculation Sheet'!$D"&INDEX('Buyer Lookup'!$A:$AZ,MATCH($B$2,'Buyer Lookup'!$A:$A,0),8)),"") | I8: =IFERROR(INDIRECT("'Final Calculation Sheet'!$D"&INDEX('Buyer Lookup'!$A:$AZ,MATCH($B$2,'Buyer Lookup'!$A:$A,0),9)),"") | J8: =IFERROR(INDIRECT("'Final Calculation Sheet'!$D"&INDEX('Buyer Lookup'!$A:$AZ,MATCH($B$2,'Buyer Lookup'!$A:$A,0),10)),"") | K8: =IFERROR(INDIRECT("'Final Calculation Sheet'!$D"&INDEX('Buyer Lookup'!$A:$AZ,MATCH($B$2,'Buyer Lookup'!$A:$A,0),11)),"") | L8: =IFERROR(INDIRECT("'Final Calculation Sheet'!$D"&INDEX('Buyer Lookup'!$A:$AZ,MATCH($B$2,'Buyer Lookup'!$A:$A,0),12)),"") | M8: =IFERROR(INDIRECT("'Final Calculation Sheet'!$D"&INDEX('Buyer Lookup'!$A:$AZ,MATCH($B$2,'Buyer Lookup'!$A:$A,0),13)),"") | N8: =IFERROR(INDIRECT("'Final Calculation Sheet'!$D"&INDEX('Buyer Lookup'!$A:$AZ,MATCH($B$2,'Buyer Lookup'!$A:$A,0),14)),"")
A9: Quantity | B9: =IFERROR(INDIRECT("'Final Calculation Sheet'!$A"&INDEX('Buyer Lookup'!$A:$AZ,MATCH($B$2,'Buyer Lookup'!$A:$A,0),2)),"") -> 669 | C9: =IFERROR(INDIRECT("'Final Calculation Sheet'!$A"&INDEX('Buyer Lookup'!$A:$AZ,MATCH($B$2,'Buyer Lookup'!$A:$A,0),3)),"") -> 0 | D9: =IFERROR(INDIRECT("'Final Calculation Sheet'!$A"&INDEX('Buyer Lookup'!$A:$AZ,MATCH($B$2,'Buyer Lookup'!$A:$A,0),4)),"") | E9: =IFERROR(INDIRECT("'Final Calculation Sheet'!$A"&INDEX('Buyer Lookup'!$A:$AZ,MATCH($B$2,'Buyer Lookup'!$A:$A,0),5)),"") | F9: =IFERROR(INDIRECT("'Final Calculation Sheet'!$A"&INDEX('Buyer Lookup'!$A:$AZ,MATCH($B$2,'Buyer Lookup'!$A:$A,0),6)),"") | G9: =IFERROR(INDIRECT("'Final Calculation Sheet'!$A"&INDEX('Buyer Lookup'!$A:$AZ,MATCH($B$2,'Buyer Lookup'!$A:$A,0),7)),"") | H9: =IFERROR(INDIRECT("'Final Calculation Sheet'!$A"&INDEX('Buyer Lookup'!$A:$AZ,MATCH($B$2,'Buyer Lookup'!$A:$A,0),8)),"") | I9: =IFERROR(INDIRECT("'Final Calculation Sheet'!$A"&INDEX('Buyer Lookup'!$A:$AZ,MATCH($B$2,'Buyer Lookup'!$A:$A,0),9)),"") | J9: =IFERROR(INDIRECT("'Final Calculation Sheet'!$A"&INDEX('Buyer Lookup'!$A:$AZ,MATCH($B$2,'Buyer Lookup'!$A:$A,0),10)),"") | K9: =IFERROR(INDIRECT("'Final Calculation Sheet'!$A"&INDEX('Buyer Lookup'!$A:$AZ,MATCH($B$2,'Buyer Lookup'!$A:$A,0),11)),"") | L9: =IFERROR(INDIRECT("'Final Calculation Sheet'!$A"&INDEX('Buyer Lookup'!$A:$AZ,MATCH($B$2,'Buyer Lookup'!$A:$A,0),12)),"") | M9: =IFERROR(INDIRECT("'Final Calculation Sheet'!$A"&INDEX('Buyer Lookup'!$A:$AZ,MATCH($B$2,'Buyer Lookup'!$A:$A,0),13)),"") | N9: =IFERROR(INDIRECT("'Final Calculation Sheet'!$A"&INDEX('Buyer Lookup'!$A:$AZ,MATCH($B$2,'Buyer Lookup'!$A:$A,0),14)),"")
A10: Unit | B10: =IFERROR(INDIRECT("'Final Calculation Sheet'!$E"&INDEX('Buyer Lookup'!$A:$AZ,MATCH($B$2,'Buyer Lookup'!$A:$A,0),2)),"") -> KG | C10: =IFERROR(INDIRECT("'Final Calculation Sheet'!$E"&INDEX('Buyer Lookup'!$A:$AZ,MATCH($B$2,'Buyer Lookup'!$A:$A,0),3)),"") -> 0 | D10: =IFERROR(INDIRECT("'Final Calculation Sheet'!$E"&INDEX('Buyer Lookup'!$A:$AZ,MATCH($B$2,'Buyer Lookup'!$A:$A,0),4)),"") | E10: =IFERROR(INDIRECT("'Final Calculation Sheet'!$E"&INDEX('Buyer Lookup'!$A:$AZ,MATCH($B$2,'Buyer Lookup'!$A:$A,0),5)),"") | F10: =IFERROR(INDIRECT("'Final Calculation Sheet'!$E"&INDEX('Buyer Lookup'!$A:$AZ,MATCH($B$2,'Buyer Lookup'!$A:$A,0),6)),"") | G10: =IFERROR(INDIRECT("'Final Calculation Sheet'!$E"&INDEX('Buyer Lookup'!$A:$AZ,MATCH($B$2,'Buyer Lookup'!$A:$A,0),7)),"") | H10: =IFERROR(INDIRECT("'Final Calculation Sheet'!$E"&INDEX('Buyer Lookup'!$A:$AZ,MATCH($B$2,'Buyer Lookup'!$A:$A,0),8)),"") | I10: =IFERROR(INDIRECT("'Final Calculation Sheet'!$E"&INDEX('Buyer Lookup'!$A:$AZ,MATCH($B$2,'Buyer Lookup'!$A:$A,0),9)),"") | J10: =IFERROR(INDIRECT("'Final Calculation Sheet'!$E"&INDEX('Buyer Lookup'!$A:$AZ,MATCH($B$2,'Buyer Lookup'!$A:$A,0),10)),"") | K10: =IFERROR(INDIRECT("'Final Calculation Sheet'!$E"&INDEX('Buyer Lookup'!$A:$AZ,MATCH($B$2,'Buyer Lookup'!$A:$A,0),11)),"") | L10: =IFERROR(INDIRECT("'Final Calculation Sheet'!$E"&INDEX('Buyer Lookup'!$A:$AZ,MATCH($B$2,'Buyer Lookup'!$A:$A,0),12)),"") | M10: =IFERROR(INDIRECT("'Final Calculation Sheet'!$E"&INDEX('Buyer Lookup'!$A:$AZ,MATCH($B$2,'Buyer Lookup'!$A:$A,0),13)),"") | N10: =IFERROR(INDIRECT("'Final Calculation Sheet'!$E"&INDEX('Buyer Lookup'!$A:$AZ,MATCH($B$2,'Buyer Lookup'!$A:$A,0),14)),"")
A11: Rate (₹) | B11: =IFERROR(INDIRECT("'Final Calculation Sheet'!$C"&INDEX('Buyer Lookup'!$A:$AZ,MATCH($B$2,'Buyer Lookup'!$A:$A,0),2)),"") -> 1181 | C11: =IFERROR(INDIRECT("'Final Calculation Sheet'!$C"&INDEX('Buyer Lookup'!$A:$AZ,MATCH($B$2,'Buyer Lookup'!$A:$A,0),3)),"") -> 0 | D11: =IFERROR(INDIRECT("'Final Calculation Sheet'!$C"&INDEX('Buyer Lookup'!$A:$AZ,MATCH($B$2,'Buyer Lookup'!$A:$A,0),4)),"") | E11: =IFERROR(INDIRECT("'Final Calculation Sheet'!$C"&INDEX('Buyer Lookup'!$A:$AZ,MATCH($B$2,'Buyer Lookup'!$A:$A,0),5)),"") | F11: =IFERROR(INDIRECT("'Final Calculation Sheet'!$C"&INDEX('Buyer Lookup'!$A:$AZ,MATCH($B$2,'Buyer Lookup'!$A:$A,0),6)),"") | G11: =IFERROR(INDIRECT("'Final Calculation Sheet'!$C"&INDEX('Buyer Lookup'!$A:$AZ,MATCH($B$2,'Buyer Lookup'!$A:$A,0),7)),"") | H11: =IFERROR(INDIRECT("'Final Calculation Sheet'!$C"&INDEX('Buyer Lookup'!$A:$AZ,MATCH($B$2,'Buyer Lookup'!$A:$A,0),8)),"") | I11: =IFERROR(INDIRECT("'Final Calculation Sheet'!$C"&INDEX('Buyer Lookup'!$A:$AZ,MATCH($B$2,'Buyer Lookup'!$A:$A,0),9)),"") | J11: =IFERROR(INDIRECT("'Final Calculation Sheet'!$C"&INDEX('Buyer Lookup'!$A:$AZ,MATCH($B$2,'Buyer Lookup'!$A:$A,0),10)),"") | K11: =IFERROR(INDIRECT("'Final Calculation Sheet'!$C"&INDEX('Buyer Lookup'!$A:$AZ,MATCH($B$2,'Buyer Lookup'!$A:$A,0),11)),"") | L11: =IFERROR(INDIRECT("'Final Calculation Sheet'!$C"&INDEX('Buyer Lookup'!$A:$AZ,MATCH($B$2,'Buyer Lookup'!$A:$A,0),12)),"") | M11: =IFERROR(INDIRECT("'Final Calculation Sheet'!$C"&INDEX('Buyer Lookup'!$A:$AZ,MATCH($B$2,'Buyer Lookup'!$A:$A,0),13)),"") | N11: =IFERROR(INDIRECT("'Final Calculation Sheet'!$C"&INDEX('Buyer Lookup'!$A:$AZ,MATCH($B$2,'Buyer Lookup'!$A:$A,0),14)),"")
A13: FINANCIALS
A14: Mat. Value (₹) | B14: =IFERROR(INDIRECT("'Final Calculation Sheet'!$H"&INDEX('Buyer Lookup'!$A:$AZ,MATCH($B$2,'Buyer Lookup'!$A:$A,0),2)),"") -> 790089 | C14: =IFERROR(INDIRECT("'Final Calculation Sheet'!$H"&INDEX('Buyer Lookup'!$A:$AZ,MATCH($B$2,'Buyer Lookup'!$A:$A,0),3)),"") -> 0 | D14: =IFERROR(INDIRECT("'Final Calculation Sheet'!$H"&INDEX('Buyer Lookup'!$A:$AZ,MATCH($B$2,'Buyer Lookup'!$A:$A,0),4)),"") | E14: =IFERROR(INDIRECT("'Final Calculation Sheet'!$H"&INDEX('Buyer Lookup'!$A:$AZ,MATCH($B$2,'Buyer Lookup'!$A:$A,0),5)),"") | F14: =IFERROR(INDIRECT("'Final Calculation Sheet'!$H"&INDEX('Buyer Lookup'!$A:$AZ,MATCH($B$2,'Buyer Lookup'!$A:$A,0),6)),"") | G14: =IFERROR(INDIRECT("'Final Calculation Sheet'!$H"&INDEX('Buyer Lookup'!$A:$AZ,MATCH($B$2,'Buyer Lookup'!$A:$A,0),7)),"") | H14: =IFERROR(INDIRECT("'Final Calculation Sheet'!$H"&INDEX('Buyer Lookup'!$A:$AZ,MATCH($B$2,'Buyer Lookup'!$A:$A,0),8)),"") | I14: =IFERROR(INDIRECT("'Final Calculation Sheet'!$H"&INDEX('Buyer Lookup'!$A:$AZ,MATCH($B$2,'Buyer Lookup'!$A:$A,0),9)),"") | J14: =IFERROR(INDIRECT("'Final Calculation Sheet'!$H"&INDEX('Buyer Lookup'!$A:$AZ,MATCH($B$2,'Buyer Lookup'!$A:$A,0),10)),"") | K14: =IFERROR(INDIRECT("'Final Calculation Sheet'!$H"&INDEX('Buyer Lookup'!$A:$AZ,MATCH($B$2,'Buyer Lookup'!$A:$A,0),11)),"") | L14: =IFERROR(INDIRECT("'Final Calculation Sheet'!$H"&INDEX('Buyer Lookup'!$A:$AZ,MATCH($B$2,'Buyer Lookup'!$A:$A,0),12)),"") | M14: =IFERROR(INDIRECT("'Final Calculation Sheet'!$H"&INDEX('Buyer Lookup'!$A:$AZ,MATCH($B$2,'Buyer Lookup'!$A:$A,0),13)),"") | N14: =IFERROR(INDIRECT("'Final Calculation Sheet'!$H"&INDEX('Buyer Lookup'!$A:$AZ,MATCH($B$2,'Buyer Lookup'!$A:$A,0),14)),"")
A15: GST (₹) | B15: =IFERROR(INDIRECT("'Final Calculation Sheet'!$I"&INDEX('Buyer Lookup'!$A:$AZ,MATCH($B$2,'Buyer Lookup'!$A:$A,0),2)),"") -> 142216 | C15: =IFERROR(INDIRECT("'Final Calculation Sheet'!$I"&INDEX('Buyer Lookup'!$A:$AZ,MATCH($B$2,'Buyer Lookup'!$A:$A,0),3)),"") -> 0 | D15: =IFERROR(INDIRECT("'Final Calculation Sheet'!$I"&INDEX('Buyer Lookup'!$A:$AZ,MATCH($B$2,'Buyer Lookup'!$A:$A,0),4)),"") | E15: =IFERROR(INDIRECT("'Final Calculation Sheet'!$I"&INDEX('Buyer Lookup'!$A:$AZ,MATCH($B$2,'Buyer Lookup'!$A:$A,0),5)),"") | F15: =IFERROR(INDIRECT("'Final Calculation Sheet'!$I"&INDEX('Buyer Lookup'!$A:$AZ,MATCH($B$2,'Buyer Lookup'!$A:$A,0),6)),"") | G15: =IFERROR(INDIRECT("'Final Calculation Sheet'!$I"&INDEX('Buyer Lookup'!$A:$AZ,MATCH($B$2,'Buyer Lookup'!$A:$A,0),7)),"") | H15: =IFERROR(INDIRECT("'Final Calculation Sheet'!$I"&INDEX('Buyer Lookup'!$A:$AZ,MATCH($B$2,'Buyer Lookup'!$A:$A,0),8)),"") | I15: =IFERROR(INDIRECT("'Final Calculation Sheet'!$I"&INDEX('Buyer Lookup'!$A:$AZ,MATCH($B$2,'Buyer Lookup'!$A:$A,0),9)),"") | J15: =IFERROR(INDIRECT("'Final Calculation Sheet'!$I"&INDEX('Buyer Lookup'!$A:$AZ,MATCH($B$2,'Buyer Lookup'!$A:$A,0),10)),"") | K15: =IFERROR(INDIRECT("'Final Calculation Sheet'!$I"&INDEX('Buyer Lookup'!$A:$AZ,MATCH($B$2,'Buyer Lookup'!$A:$A,0),11)),"") | L15: =IFERROR(INDIRECT("'Final Calculation Sheet'!$I"&INDEX('Buyer Lookup'!$A:$AZ,MATCH($B$2,'Buyer Lookup'!$A:$A,0),12)),"") | M15: =IFERROR(INDIRECT("'Final Calculation Sheet'!$I"&INDEX('Buyer Lookup'!$A:$AZ,MATCH($B$2,'Buyer Lookup'!$A:$A,0),13)),"") | N15: =IFERROR(INDIRECT("'Final Calculation Sheet'!$I"&INDEX('Buyer Lookup'!$A:$AZ,MATCH($B$2,'Buyer Lookup'!$A:$A,0),14)),"")
A16: Mat. Value + GST (₹) | B16: =IFERROR(INDIRECT("'Final Calculation Sheet'!$J"&INDEX('Buyer Lookup'!$A:$AZ,MATCH($B$2,'Buyer Lookup'!$A:$A,0),2)),"") -> 932305 | C16: =IFERROR(INDIRECT("'Final Calculation Sheet'!$J"&INDEX('Buyer Lookup'!$A:$AZ,MATCH($B$2,'Buyer Lookup'!$A:$A,0),3)),"") -> 0 | D16: =IFERROR(INDIRECT("'Final Calculation Sheet'!$J"&INDEX('Buyer Lookup'!$A:$AZ,MATCH($B$2,'Buyer Lookup'!$A:$A,0),4)),"") | E16: =IFERROR(INDIRECT("'Final Calculation Sheet'!$J"&INDEX('Buyer Lookup'!$A:$AZ,MATCH($B$2,'Buyer Lookup'!$A:$A,0),5)),"") | F16: =IFERROR(INDIRECT("'Final Calculation Sheet'!$J"&INDEX('Buyer Lookup'!$A:$AZ,MATCH($B$2,'Buyer Lookup'!$A:$A,0),6)),"") | G16: =IFERROR(INDIRECT("'Final Calculation Sheet'!$J"&INDEX('Buyer Lookup'!$A:$AZ,MATCH($B$2,'Buyer Lookup'!$A:$A,0),7)),"") | H16: =IFERROR(INDIRECT("'Final Calculation Sheet'!$J"&INDEX('Buyer Lookup'!$A:$AZ,MATCH($B$2,'Buyer Lookup'!$A:$A,0),8)),"") | I16: =IFERROR(INDIRECT("'Final Calculation Sheet'!$J"&INDEX('Buyer Lookup'!$A:$AZ,MATCH($B$2,'Buyer Lookup'!$A:$A,0),9)),"") | J16: =IFERROR(INDIRECT("'Final Calculation Sheet'!$J"&INDEX('Buyer Lookup'!$A:$AZ,MATCH($B$2,'Buyer Lookup'!$A:$A,0),10)),"") | K16: =IFERROR(INDIRECT("'Final Calculation Sheet'!$J"&INDEX('Buyer Lookup'!$A:$AZ,MATCH($B$2,'Buyer Lookup'!$A:$A,0),11)),"") | L16: =IFERROR(INDIRECT("'Final Calculation Sheet'!$J"&INDEX('Buyer Lookup'!$A:$AZ,MATCH($B$2,'Buyer Lookup'!$A:$A,0),12)),"") | M16: =IFERROR(INDIRECT("'Final Calculation Sheet'!$J"&INDEX('Buyer Lookup'!$A:$AZ,MATCH($B$2,'Buyer Lookup'!$A:$A,0),13)),"") | N16: =IFERROR(INDIRECT("'Final Calculation Sheet'!$J"&INDEX('Buyer Lookup'!$A:$AZ,MATCH($B$2,'Buyer Lookup'!$A:$A,0),14)),"")
A17: TCS (₹) | B17: =IFERROR(INDIRECT("'Final Calculation Sheet'!$K"&INDEX('Buyer Lookup'!$A:$AZ,MATCH($B$2,'Buyer Lookup'!$A:$A,0),2)),"") -> 18646 | C17: =IFERROR(INDIRECT("'Final Calculation Sheet'!$K"&INDEX('Buyer Lookup'!$A:$AZ,MATCH($B$2,'Buyer Lookup'!$A:$A,0),3)),"") -> 0 | D17: =IFERROR(INDIRECT("'Final Calculation Sheet'!$K"&INDEX('Buyer Lookup'!$A:$AZ,MATCH($B$2,'Buyer Lookup'!$A:$A,0),4)),"") | E17: =IFERROR(INDIRECT("'Final Calculation Sheet'!$K"&INDEX('Buyer Lookup'!$A:$AZ,MATCH($B$2,'Buyer Lookup'!$A:$A,0),5)),"") | F17: =IFERROR(INDIRECT("'Final Calculation Sheet'!$K"&INDEX('Buyer Lookup'!$A:$AZ,MATCH($B$2,'Buyer Lookup'!$A:$A,0),6)),"") | G17: =IFERROR(INDIRECT("'Final Calculation Sheet'!$K"&INDEX('Buyer Lookup'!$A:$AZ,MATCH($B$2,'Buyer Lookup'!$A:$A,0),7)),"") | H17: =IFERROR(INDIRECT("'Final Calculation Sheet'!$K"&INDEX('Buyer Lookup'!$A:$AZ,MATCH($B$2,'Buyer Lookup'!$A:$A,0),8)),"") | I17: =IFERROR(INDIRECT("'Final Calculation Sheet'!$K"&INDEX('Buyer Lookup'!$A:$AZ,MATCH($B$2,'Buyer Lookup'!$A:$A,0),9)),"") | J17: =IFERROR(INDIRECT("'Final Calculation Sheet'!$K"&INDEX('Buyer Lookup'!$A:$AZ,MATCH($B$2,'Buyer Lookup'!$A:$A,0),10)),"") | K17: =IFERROR(INDIRECT("'Final Calculation Sheet'!$K"&INDEX('Buyer Lookup'!$A:$AZ,MATCH($B$2,'Buyer Lookup'!$A:$A,0),11)),"") | L17: =IFERROR(INDIRECT("'Final Calculation Sheet'!$K"&INDEX('Buyer Lookup'!$A:$AZ,MATCH($B$2,'Buyer Lookup'!$A:$A,0),12)),"") | M17: =IFERROR(INDIRECT("'Final Calculation Sheet'!$K"&INDEX('Buyer Lookup'!$A:$AZ,MATCH($B$2,'Buyer Lookup'!$A:$A,0),13)),"") | N17: =IFERROR(INDIRECT("'Final Calculation Sheet'!$K"&INDEX('Buyer Lookup'!$A:$AZ,MATCH($B$2,'Buyer Lookup'!$A:$A,0),14)),"")
A18: TDS u/s 194(O) (₹) | B18: =IFERROR(INDIRECT("'Final Calculation Sheet'!$L"&INDEX('Buyer Lookup'!$A:$AZ,MATCH($B$2,'Buyer Lookup'!$A:$A,0),2)),"") -> 790.089 | C18: =IFERROR(INDIRECT("'Final Calculation Sheet'!$L"&INDEX('Buyer Lookup'!$A:$AZ,MATCH($B$2,'Buyer Lookup'!$A:$A,0),3)),"") -> 0 | D18: =IFERROR(INDIRECT("'Final Calculation Sheet'!$L"&INDEX('Buyer Lookup'!$A:$AZ,MATCH($B$2,'Buyer Lookup'!$A:$A,0),4)),"") | E18: =IFERROR(INDIRECT("'Final Calculation Sheet'!$L"&INDEX('Buyer Lookup'!$A:$AZ,MATCH($B$2,'Buyer Lookup'!$A:$A,0),5)),"") | F18: =IFERROR(INDIRECT("'Final Calculation Sheet'!$L"&INDEX('Buyer Lookup'!$A:$AZ,MATCH($B$2,'Buyer Lookup'!$A:$A,0),6)),"") | G18: =IFERROR(INDIRECT("'Final Calculation Sheet'!$L"&INDEX('Buyer Lookup'!$A:$AZ,MATCH($B$2,'Buyer Lookup'!$A:$A,0),7)),"") | H18: =IFERROR(INDIRECT("'Final Calculation Sheet'!$L"&INDEX('Buyer Lookup'!$A:$AZ,MATCH($B$2,'Buyer Lookup'!$A:$A,0),8)),"") | I18: =IFERROR(INDIRECT("'Final Calculation Sheet'!$L"&INDEX('Buyer Lookup'!$A:$AZ,MATCH($B$2,'Buyer Lookup'!$A:$A,0),9)),"") | J18: =IFERROR(INDIRECT("'Final Calculation Sheet'!$L"&INDEX('Buyer Lookup'!$A:$AZ,MATCH($B$2,'Buyer Lookup'!$A:$A,0),10)),"") | K18: =IFERROR(INDIRECT("'Final Calculation Sheet'!$L"&INDEX('Buyer Lookup'!$A:$AZ,MATCH($B$2,'Buyer Lookup'!$A:$A,0),11)),"") | L18: =IFERROR(INDIRECT("'Final Calculation Sheet'!$L"&INDEX('Buyer Lookup'!$A:$AZ,MATCH($B$2,'Buyer Lookup'!$A:$A,0),12)),"") | M18: =IFERROR(INDIRECT("'Final Calculation Sheet'!$L"&INDEX('Buyer Lookup'!$A:$AZ,MATCH($B$2,'Buyer Lookup'!$A:$A,0),13)),"") | N18: =IFERROR(INDIRECT("'Final Calculation Sheet'!$L"&INDEX('Buyer Lookup'!$A:$AZ,MATCH($B$2,'Buyer Lookup'!$A:$A,0),14)),"")
A19: Service Charge (₹) | B19: =IFERROR(INDIRECT("'Final Calculation Sheet'!$M"&INDEX('Buyer Lookup'!$A:$AZ,MATCH($B$2,'Buyer Lookup'!$A:$A,0),2)),"") -> 20976.863 | C19: =IFERROR(INDIRECT("'Final Calculation Sheet'!$M"&INDEX('Buyer Lookup'!$A:$AZ,MATCH($B$2,'Buyer Lookup'!$A:$A,0),3)),"") -> 0 | D19: =IFERROR(INDIRECT("'Final Calculation Sheet'!$M"&INDEX('Buyer Lookup'!$A:$AZ,MATCH($B$2,'Buyer Lookup'!$A:$A,0),4)),"") | E19: =IFERROR(INDIRECT("'Final Calculation Sheet'!$M"&INDEX('Buyer Lookup'!$A:$AZ,MATCH($B$2,'Buyer Lookup'!$A:$A,0),5)),"") | F19: =IFERROR(INDIRECT("'Final Calculation Sheet'!$M"&INDEX('Buyer Lookup'!$A:$AZ,MATCH($B$2,'Buyer Lookup'!$A:$A,0),6)),"") | G19: =IFERROR(INDIRECT("'Final Calculation Sheet'!$M"&INDEX('Buyer Lookup'!$A:$AZ,MATCH($B$2,'Buyer Lookup'!$A:$A,0),7)),"") | H19: =IFERROR(INDIRECT("'Final Calculation Sheet'!$M"&INDEX('Buyer Lookup'!$A:$AZ,MATCH($B$2,'Buyer Lookup'!$A:$A,0),8)),"") | I19: =IFERROR(INDIRECT("'Final Calculation Sheet'!$M"&INDEX('Buyer Lookup'!$A:$AZ,MATCH($B$2,'Buyer Lookup'!$A:$A,0),9)),"") | J19: =IFERROR(INDIRECT("'Final Calculation Sheet'!$M"&INDEX('Buyer Lookup'!$A:$AZ,MATCH($B$2,'Buyer Lookup'!$A:$A,0),10)),"") | K19: =IFERROR(INDIRECT("'Final Calculation Sheet'!$M"&INDEX('Buyer Lookup'!$A:$AZ,MATCH($B$2,'Buyer Lookup'!$A:$A,0),11)),"") | L19: =IFERROR(INDIRECT("'Final Calculation Sheet'!$M"&INDEX('Buyer Lookup'!$A:$AZ,MATCH($B$2,'Buyer Lookup'!$A:$A,0),12)),"") | M19: =IFERROR(INDIRECT("'Final Calculation Sheet'!$M"&INDEX('Buyer Lookup'!$A:$AZ,MATCH($B$2,'Buyer Lookup'!$A:$A,0),13)),"") | N19: =IFERROR(INDIRECT("'Final Calculation Sheet'!$M"&INDEX('Buyer Lookup'!$A:$AZ,MATCH($B$2,'Buyer Lookup'!$A:$A,0),14)),"")
A20: TDS u/s 194(H) (₹) | B20: =IFERROR(INDIRECT("'Final Calculation Sheet'!$N"&INDEX('Buyer Lookup'!$A:$AZ,MATCH($B$2,'Buyer Lookup'!$A:$A,0),2)),"") -> 355.54005 | C20: =IFERROR(INDIRECT("'Final Calculation Sheet'!$N"&INDEX('Buyer Lookup'!$A:$AZ,MATCH($B$2,'Buyer Lookup'!$A:$A,0),3)),"") -> 0 | D20: =IFERROR(INDIRECT("'Final Calculation Sheet'!$N"&INDEX('Buyer Lookup'!$A:$AZ,MATCH($B$2,'Buyer Lookup'!$A:$A,0),4)),"") | E20: =IFERROR(INDIRECT("'Final Calculation Sheet'!$N"&INDEX('Buyer Lookup'!$A:$AZ,MATCH($B$2,'Buyer Lookup'!$A:$A,0),5)),"") | F20: =IFERROR(INDIRECT("'Final Calculation Sheet'!$N"&INDEX('Buyer Lookup'!$A:$AZ,MATCH($B$2,'Buyer Lookup'!$A:$A,0),6)),"") | G20: =IFERROR(INDIRECT("'Final Calculation Sheet'!$N"&INDEX('Buyer Lookup'!$A:$AZ,MATCH($B$2,'Buyer Lookup'!$A:$A,0),7)),"") | H20: =IFERROR(INDIRECT("'Final Calculation Sheet'!$N"&INDEX('Buyer Lookup'!$A:$AZ,MATCH($B$2,'Buyer Lookup'!$A:$A,0),8)),"") | I20: =IFERROR(INDIRECT("'Final Calculation Sheet'!$N"&INDEX('Buyer Lookup'!$A:$AZ,MATCH($B$2,'Buyer Lookup'!$A:$A,0),9)),"") | J20: =IFERROR(INDIRECT("'Final Calculation Sheet'!$N"&INDEX('Buyer Lookup'!$A:$AZ,MATCH($B$2,'Buyer Lookup'!$A:$A,0),10)),"") | K20: =IFERROR(INDIRECT("'Final Calculation Sheet'!$N"&INDEX('Buyer Lookup'!$A:$AZ,MATCH($B$2,'Buyer Lookup'!$A:$A,0),11)),"") | L20: =IFERROR(INDIRECT("'Final Calculation Sheet'!$N"&INDEX('Buyer Lookup'!$A:$AZ,MATCH($B$2,'Buyer Lookup'!$A:$A,0),12)),"") | M20: =IFERROR(INDIRECT("'Final Calculation Sheet'!$N"&INDEX('Buyer Lookup'!$A:$AZ,MATCH($B$2,'Buyer Lookup'!$A:$A,0),13)),"") | N20: =IFERROR(INDIRECT("'Final Calculation Sheet'!$N"&INDEX('Buyer Lookup'!$A:$AZ,MATCH($B$2,'Buyer Lookup'!$A:$A,0),14)),"")
A21: Net Svc Charge (₹) | B21: =IFERROR(INDIRECT("'Final Calculation Sheet'!$O"&INDEX('Buyer Lookup'!$A:$AZ,MATCH($B$2,'Buyer Lookup'!$A:$A,0),2)),"") -> 20621.323 | C21: =IFERROR(INDIRECT("'Final Calculation Sheet'!$O"&INDEX('Buyer Lookup'!$A:$AZ,MATCH($B$2,'Buyer Lookup'!$A:$A,0),3)),"") -> 0 | D21: =IFERROR(INDIRECT("'Final Calculation Sheet'!$O"&INDEX('Buyer Lookup'!$A:$AZ,MATCH($B$2,'Buyer Lookup'!$A:$A,0),4)),"") | E21: =IFERROR(INDIRECT("'Final Calculation Sheet'!$O"&INDEX('Buyer Lookup'!$A:$AZ,MATCH($B$2,'Buyer Lookup'!$A:$A,0),5)),"") | F21: =IFERROR(INDIRECT("'Final Calculation Sheet'!$O"&INDEX('Buyer Lookup'!$A:$AZ,MATCH($B$2,'Buyer Lookup'!$A:$A,0),6)),"") | G21: =IFERROR(INDIRECT("'Final Calculation Sheet'!$O"&INDEX('Buyer Lookup'!$A:$AZ,MATCH($B$2,'Buyer Lookup'!$A:$A,0),7)),"") | H21: =IFERROR(INDIRECT("'Final Calculation Sheet'!$O"&INDEX('Buyer Lookup'!$A:$AZ,MATCH($B$2,'Buyer Lookup'!$A:$A,0),8)),"") | I21: =IFERROR(INDIRECT("'Final Calculation Sheet'!$O"&INDEX('Buyer Lookup'!$A:$AZ,MATCH($B$2,'Buyer Lookup'!$A:$A,0),9)),"") | J21: =IFERROR(INDIRECT("'Final Calculation Sheet'!$O"&INDEX('Buyer Lookup'!$A:$AZ,MATCH($B$2,'Buyer Lookup'!$A:$A,0),10)),"") | K21: =IFERROR(INDIRECT("'Final Calculation Sheet'!$O"&INDEX('Buyer Lookup'!$A:$AZ,MATCH($B$2,'Buyer Lookup'!$A:$A,0),11)),"") | L21: =IFERROR(INDIRECT("'Final Calculation Sheet'!$O"&INDEX('Buyer Lookup'!$A:$AZ,MATCH($B$2,'Buyer Lookup'!$A:$A,0),12)),"") | M21: =IFERROR(INDIRECT("'Final Calculation Sheet'!$O"&INDEX('Buyer Lookup'!$A:$AZ,MATCH($B$2,'Buyer Lookup'!$A:$A,0),13)),"") | N21: =IFERROR(INDIRECT("'Final Calculation Sheet'!$O"&INDEX('Buyer Lookup'!$A:$AZ,MATCH($B$2,'Buyer Lookup'!$A:$A,0),14)),"")
A22: Svc Charge to MSTC (₹) | B22: =IFERROR(INDIRECT("'Final Calculation Sheet'!$P"&INDEX('Buyer Lookup'!$A:$AZ,MATCH($B$2,'Buyer Lookup'!$A:$A,0),2)),"") -> 21411 | C22: =IFERROR(INDIRECT("'Final Calculation Sheet'!$P"&INDEX('Buyer Lookup'!$A:$AZ,MATCH($B$2,'Buyer Lookup'!$A:$A,0),3)),"") -> 0 | D22: =IFERROR(INDIRECT("'Final Calculation Sheet'!$P"&INDEX('Buyer Lookup'!$A:$AZ,MATCH($B$2,'Buyer Lookup'!$A:$A,0),4)),"") | E22: =IFERROR(INDIRECT("'Final Calculation Sheet'!$P"&INDEX('Buyer Lookup'!$A:$AZ,MATCH($B$2,'Buyer Lookup'!$A:$A,0),5)),"") | F22: =IFERROR(INDIRECT("'Final Calculation Sheet'!$P"&INDEX('Buyer Lookup'!$A:$AZ,MATCH($B$2,'Buyer Lookup'!$A:$A,0),6)),"") | G22: =IFERROR(INDIRECT("'Final Calculation Sheet'!$P"&INDEX('Buyer Lookup'!$A:$AZ,MATCH($B$2,'Buyer Lookup'!$A:$A,0),7)),"") | H22: =IFERROR(INDIRECT("'Final Calculation Sheet'!$P"&INDEX('Buyer Lookup'!$A:$AZ,MATCH($B$2,'Buyer Lookup'!$A:$A,0),8)),"") | I22: =IFERROR(INDIRECT("'Final Calculation Sheet'!$P"&INDEX('Buyer Lookup'!$A:$AZ,MATCH($B$2,'Buyer Lookup'!$A:$A,0),9)),"") | J22: =IFERROR(INDIRECT("'Final Calculation Sheet'!$P"&INDEX('Buyer Lookup'!$A:$AZ,MATCH($B$2,'Buyer Lookup'!$A:$A,0),10)),"") | K22: =IFERROR(INDIRECT("'Final Calculation Sheet'!$P"&INDEX('Buyer Lookup'!$A:$AZ,MATCH($B$2,'Buyer Lookup'!$A:$A,0),11)),"") | L22: =IFERROR(INDIRECT("'Final Calculation Sheet'!$P"&INDEX('Buyer Lookup'!$A:$AZ,MATCH($B$2,'Buyer Lookup'!$A:$A,0),12)),"") | M22: =IFERROR(INDIRECT("'Final Calculation Sheet'!$P"&INDEX('Buyer Lookup'!$A:$AZ,MATCH($B$2,'Buyer Lookup'!$A:$A,0),13)),"") | N22: =IFERROR(INDIRECT("'Final Calculation Sheet'!$P"&INDEX('Buyer Lookup'!$A:$AZ,MATCH($B$2,'Buyer Lookup'!$A:$A,0),14)),"")
A23: GST TDS Rate | B23: =IFERROR(INDIRECT("'Final Calculation Sheet'!$Q"&INDEX('Buyer Lookup'!$A:$AZ,MATCH($B$2,'Buyer Lookup'!$A:$A,0),2)),"") -> 0.02 | C23: =IFERROR(INDIRECT("'Final Calculation Sheet'!$Q"&INDEX('Buyer Lookup'!$A:$AZ,MATCH($B$2,'Buyer Lookup'!$A:$A,0),3)),"") -> 0 | D23: =IFERROR(INDIRECT("'Final Calculation Sheet'!$Q"&INDEX('Buyer Lookup'!$A:$AZ,MATCH($B$2,'Buyer Lookup'!$A:$A,0),4)),"") | E23: =IFERROR(INDIRECT("'Final Calculation Sheet'!$Q"&INDEX('Buyer Lookup'!$A:$AZ,MATCH($B$2,'Buyer Lookup'!$A:$A,0),5)),"") | F23: =IFERROR(INDIRECT("'Final Calculation Sheet'!$Q"&INDEX('Buyer Lookup'!$A:$AZ,MATCH($B$2,'Buyer Lookup'!$A:$A,0),6)),"") | G23: =IFERROR(INDIRECT("'Final Calculation Sheet'!$Q"&INDEX('Buyer Lookup'!$A:$AZ,MATCH($B$2,'Buyer Lookup'!$A:$A,0),7)),"") | H23: =IFERROR(INDIRECT("'Final Calculation Sheet'!$Q"&INDEX('Buyer Lookup'!$A:$AZ,MATCH($B$2,'Buyer Lookup'!$A:$A,0),8)),"") | I23: =IFERROR(INDIRECT("'Final Calculation Sheet'!$Q"&INDEX('Buyer Lookup'!$A:$AZ,MATCH($B$2,'Buyer Lookup'!$A:$A,0),9)),"") | J23: =IFERROR(INDIRECT("'Final Calculation Sheet'!$Q"&INDEX('Buyer Lookup'!$A:$AZ,MATCH($B$2,'Buyer Lookup'!$A:$A,0),10)),"") | K23: =IFERROR(INDIRECT("'Final Calculation Sheet'!$Q"&INDEX('Buyer Lookup'!$A:$AZ,MATCH($B$2,'Buyer Lookup'!$A:$A,0),11)),"") | L23: =IFERROR(INDIRECT("'Final Calculation Sheet'!$Q"&INDEX('Buyer Lookup'!$A:$AZ,MATCH($B$2,'Buyer Lookup'!$A:$A,0),12)),"") | M23: =IFERROR(INDIRECT("'Final Calculation Sheet'!$Q"&INDEX('Buyer Lookup'!$A:$AZ,MATCH($B$2,'Buyer Lookup'!$A:$A,0),13)),"") | N23: =IFERROR(INDIRECT("'Final Calculation Sheet'!$Q"&INDEX('Buyer Lookup'!$A:$AZ,MATCH($B$2,'Buyer Lookup'!$A:$A,0),14)),"")
A24: GST TDS (₹) | B24: =IFERROR(INDIRECT("'Final Calculation Sheet'!$R"&INDEX('Buyer Lookup'!$A:$AZ,MATCH($B$2,'Buyer Lookup'!$A:$A,0),2)),"") -> 15802 | C24: =IFERROR(INDIRECT("'Final Calculation Sheet'!$R"&INDEX('Buyer Lookup'!$A:$AZ,MATCH($B$2,'Buyer Lookup'!$A:$A,0),3)),"") -> 0 | D24: =IFERROR(INDIRECT("'Final Calculation Sheet'!$R"&INDEX('Buyer Lookup'!$A:$AZ,MATCH($B$2,'Buyer Lookup'!$A:$A,0),4)),"") | E24: =IFERROR(INDIRECT("'Final Calculation Sheet'!$R"&INDEX('Buyer Lookup'!$A:$AZ,MATCH($B$2,'Buyer Lookup'!$A:$A,0),5)),"") | F24: =IFERROR(INDIRECT("'Final Calculation Sheet'!$R"&INDEX('Buyer Lookup'!$A:$AZ,MATCH($B$2,'Buyer Lookup'!$A:$A,0),6)),"") | G24: =IFERROR(INDIRECT("'Final Calculation Sheet'!$R"&INDEX('Buyer Lookup'!$A:$AZ,MATCH($B$2,'Buyer Lookup'!$A:$A,0),7)),"") | H24: =IFERROR(INDIRECT("'Final Calculation Sheet'!$R"&INDEX('Buyer Lookup'!$A:$AZ,MATCH($B$2,'Buyer Lookup'!$A:$A,0),8)),"") | I24: =IFERROR(INDIRECT("'Final Calculation Sheet'!$R"&INDEX('Buyer Lookup'!$A:$AZ,MATCH($B$2,'Buyer Lookup'!$A:$A,0),9)),"") | J24: =IFERROR(INDIRECT("'Final Calculation Sheet'!$R"&INDEX('Buyer Lookup'!$A:$AZ,MATCH($B$2,'Buyer Lookup'!$A:$A,0),10)),"") | K24: =IFERROR(INDIRECT("'Final Calculation Sheet'!$R"&INDEX('Buyer Lookup'!$A:$AZ,MATCH($B$2,'Buyer Lookup'!$A:$A,0),11)),"") | L24: =IFERROR(INDIRECT("'Final Calculation Sheet'!$R"&INDEX('Buyer Lookup'!$A:$AZ,MATCH($B$2,'Buyer Lookup'!$A:$A,0),12)),"") | M24: =IFERROR(INDIRECT("'Final Calculation Sheet'!$R"&INDEX('Buyer Lookup'!$A:$AZ,MATCH($B$2,'Buyer Lookup'!$A:$A,0),13)),"") | N24: =IFERROR(INDIRECT("'Final Calculation Sheet'!$R"&INDEX('Buyer Lookup'!$A:$AZ,MATCH($B$2,'Buyer Lookup'!$A:$A,0),14)),"")
A25: Total Receivables (₹) | B25: =IFERROR(INDIRECT("'Final Calculation Sheet'!$S"&INDEX('Buyer Lookup'!$A:$AZ,MATCH($B$2,'Buyer Lookup'!$A:$A,0),2)),"") -> 913738 | C25: =IFERROR(INDIRECT("'Final Calculation Sheet'!$S"&INDEX('Buyer Lookup'!$A:$AZ,MATCH($B$2,'Buyer Lookup'!$A:$A,0),3)),"") -> 0 | D25: =IFERROR(INDIRECT("'Final Calculation Sheet'!$S"&INDEX('Buyer Lookup'!$A:$AZ,MATCH($B$2,'Buyer Lookup'!$A:$A,0),4)),"") | E25: =IFERROR(INDIRECT("'Final Calculation Sheet'!$S"&INDEX('Buyer Lookup'!$A:$AZ,MATCH($B$2,'Buyer Lookup'!$A:$A,0),5)),"") | F25: =IFERROR(INDIRECT("'Final Calculation Sheet'!$S"&INDEX('Buyer Lookup'!$A:$AZ,MATCH($B$2,'Buyer Lookup'!$A:$A,0),6)),"") | G25: =IFERROR(INDIRECT("'Final Calculation Sheet'!$S"&INDEX('Buyer Lookup'!$A:$AZ,MATCH($B$2,'Buyer Lookup'!$A:$A,0),7)),"") | H25: =IFERROR(INDIRECT("'Final Calculation Sheet'!$S"&INDEX('Buyer Lookup'!$A:$AZ,MATCH($B$2,'Buyer Lookup'!$A:$A,0),8)),"") | I25: =IFERROR(INDIRECT("'Final Calculation Sheet'!$S"&INDEX('Buyer Lookup'!$A:$AZ,MATCH($B$2,'Buyer Lookup'!$A:$A,0),9)),"") | J25: =IFERROR(INDIRECT("'Final Calculation Sheet'!$S"&INDEX('Buyer Lookup'!$A:$AZ,MATCH($B$2,'Buyer Lookup'!$A:$A,0),10)),"") | K25: =IFERROR(INDIRECT("'Final Calculation Sheet'!$S"&INDEX('Buyer Lookup'!$A:$AZ,MATCH($B$2,'Buyer Lookup'!$A:$A,0),11)),"") | L25: =IFERROR(INDIRECT("'Final Calculation Sheet'!$S"&INDEX('Buyer Lookup'!$A:$AZ,MATCH($B$2,'Buyer Lookup'!$A:$A,0),12)),"") | M25: =IFERROR(INDIRECT("'Final Calculation Sheet'!$S"&INDEX('Buyer Lookup'!$A:$AZ,MATCH($B$2,'Buyer Lookup'!$A:$A,0),13)),"") | N25: =IFERROR(INDIRECT("'Final Calculation Sheet'!$S"&INDEX('Buyer Lookup'!$A:$AZ,MATCH($B$2,'Buyer Lookup'!$A:$A,0),14)),"")
A27: SECURITY DEPOSIT
A28: SD Expected (₹) | B28: =IFERROR(INDIRECT("'Final Calculation Sheet'!$T"&INDEX('Buyer Lookup'!$A:$AZ,MATCH($B$2,'Buyer Lookup'!$A:$A,0),2)),"") -> 197522 | C28: =IFERROR(INDIRECT("'Final Calculation Sheet'!$T"&INDEX('Buyer Lookup'!$A:$AZ,MATCH($B$2,'Buyer Lookup'!$A:$A,0),3)),"") -> 0 | D28: =IFERROR(INDIRECT("'Final Calculation Sheet'!$T"&INDEX('Buyer Lookup'!$A:$AZ,MATCH($B$2,'Buyer Lookup'!$A:$A,0),4)),"") | E28: =IFERROR(INDIRECT("'Final Calculation Sheet'!$T"&INDEX('Buyer Lookup'!$A:$AZ,MATCH($B$2,'Buyer Lookup'!$A:$A,0),5)),"") | F28: =IFERROR(INDIRECT("'Final Calculation Sheet'!$T"&INDEX('Buyer Lookup'!$A:$AZ,MATCH($B$2,'Buyer Lookup'!$A:$A,0),6)),"") | G28: =IFERROR(INDIRECT("'Final Calculation Sheet'!$T"&INDEX('Buyer Lookup'!$A:$AZ,MATCH($B$2,'Buyer Lookup'!$A:$A,0),7)),"") | H28: =IFERROR(INDIRECT("'Final Calculation Sheet'!$T"&INDEX('Buyer Lookup'!$A:$AZ,MATCH($B$2,'Buyer Lookup'!$A:$A,0),8)),"") | I28: =IFERROR(INDIRECT("'Final Calculation Sheet'!$T"&INDEX('Buyer Lookup'!$A:$AZ,MATCH($B$2,'Buyer Lookup'!$A:$A,0),9)),"") | J28: =IFERROR(INDIRECT("'Final Calculation Sheet'!$T"&INDEX('Buyer Lookup'!$A:$AZ,MATCH($B$2,'Buyer Lookup'!$A:$A,0),10)),"") | K28: =IFERROR(INDIRECT("'Final Calculation Sheet'!$T"&INDEX('Buyer Lookup'!$A:$AZ,MATCH($B$2,'Buyer Lookup'!$A:$A,0),11)),"") | L28: =IFERROR(INDIRECT("'Final Calculation Sheet'!$T"&INDEX('Buyer Lookup'!$A:$AZ,MATCH($B$2,'Buyer Lookup'!$A:$A,0),12)),"") | M28: =IFERROR(INDIRECT("'Final Calculation Sheet'!$T"&INDEX('Buyer Lookup'!$A:$AZ,MATCH($B$2,'Buyer Lookup'!$A:$A,0),13)),"") | N28: =IFERROR(INDIRECT("'Final Calculation Sheet'!$T"&INDEX('Buyer Lookup'!$A:$AZ,MATCH($B$2,'Buyer Lookup'!$A:$A,0),14)),"")
A29: SD Received (₹) | B29: =IFERROR(INDIRECT("'Final Calculation Sheet'!$U"&INDEX('Buyer Lookup'!$A:$AZ,MATCH($B$2,'Buyer Lookup'!$A:$A,0),2)),"") -> 197522 | C29: =IFERROR(INDIRECT("'Final Calculation Sheet'!$U"&INDEX('Buyer Lookup'!$A:$AZ,MATCH($B$2,'Buyer Lookup'!$A:$A,0),3)),"") -> 0 | D29: =IFERROR(INDIRECT("'Final Calculation Sheet'!$U"&INDEX('Buyer Lookup'!$A:$AZ,MATCH($B$2,'Buyer Lookup'!$A:$A,0),4)),"") | E29: =IFERROR(INDIRECT("'Final Calculation Sheet'!$U"&INDEX('Buyer Lookup'!$A:$AZ,MATCH($B$2,'Buyer Lookup'!$A:$A,0),5)),"") | F29: =IFERROR(INDIRECT("'Final Calculation Sheet'!$U"&INDEX('Buyer Lookup'!$A:$AZ,MATCH($B$2,'Buyer Lookup'!$A:$A,0),6)),"") | G29: =IFERROR(INDIRECT("'Final Calculation Sheet'!$U"&INDEX('Buyer Lookup'!$A:$AZ,MATCH($B$2,'Buyer Lookup'!$A:$A,0),7)),"") | H29: =IFERROR(INDIRECT("'Final Calculation Sheet'!$U"&INDEX('Buyer Lookup'!$A:$AZ,MATCH($B$2,'Buyer Lookup'!$A:$A,0),8)),"") | I29: =IFERROR(INDIRECT("'Final Calculation Sheet'!$U"&INDEX('Buyer Lookup'!$A:$AZ,MATCH($B$2,'Buyer Lookup'!$A:$A,0),9)),"") | J29: =IFERROR(INDIRECT("'Final Calculation Sheet'!$U"&INDEX('Buyer Lookup'!$A:$AZ,MATCH($B$2,'Buyer Lookup'!$A:$A,0),10)),"") | K29: =IFERROR(INDIRECT("'Final Calculation Sheet'!$U"&INDEX('Buyer Lookup'!$A:$AZ,MATCH($B$2,'Buyer Lookup'!$A:$A,0),11)),"") | L29: =IFERROR(INDIRECT("'Final Calculation Sheet'!$U"&INDEX('Buyer Lookup'!$A:$AZ,MATCH($B$2,'Buyer Lookup'!$A:$A,0),12)),"") | M29: =IFERROR(INDIRECT("'Final Calculation Sheet'!$U"&INDEX('Buyer Lookup'!$A:$AZ,MATCH($B$2,'Buyer Lookup'!$A:$A,0),13)),"") | N29: =IFERROR(INDIRECT("'Final Calculation Sheet'!$U"&INDEX('Buyer Lookup'!$A:$AZ,MATCH($B$2,'Buyer Lookup'!$A:$A,0),14)),"")
A30: SD Receipt Date | B30: =IFERROR(INDIRECT("'Final Calculation Sheet'!$V"&INDEX('Buyer Lookup'!$A:$AZ,MATCH($B$2,'Buyer Lookup'!$A:$A,0),2)),"") -> 24.08.2026 | C30: =IFERROR(INDIRECT("'Final Calculation Sheet'!$V"&INDEX('Buyer Lookup'!$A:$AZ,MATCH($B$2,'Buyer Lookup'!$A:$A,0),3)),"") -> 0 | D30: =IFERROR(INDIRECT("'Final Calculation Sheet'!$V"&INDEX('Buyer Lookup'!$A:$AZ,MATCH($B$2,'Buyer Lookup'!$A:$A,0),4)),"") | E30: =IFERROR(INDIRECT("'Final Calculation Sheet'!$V"&INDEX('Buyer Lookup'!$A:$AZ,MATCH($B$2,'Buyer Lookup'!$A:$A,0),5)),"") | F30: =IFERROR(INDIRECT("'Final Calculation Sheet'!$V"&INDEX('Buyer Lookup'!$A:$AZ,MATCH($B$2,'Buyer Lookup'!$A:$A,0),6)),"") | G30: =IFERROR(INDIRECT("'Final Calculation Sheet'!$V"&INDEX('Buyer Lookup'!$A:$AZ,MATCH($B$2,'Buyer Lookup'!$A:$A,0),7)),"") | H30: =IFERROR(INDIRECT("'Final Calculation Sheet'!$V"&INDEX('Buyer Lookup'!$A:$AZ,MATCH($B$2,'Buyer Lookup'!$A:$A,0),8)),"") | I30: =IFERROR(INDIRECT("'Final Calculation Sheet'!$V"&INDEX('Buyer Lookup'!$A:$AZ,MATCH($B$2,'Buyer Lookup'!$A:$A,0),9)),"") | J30: =IFERROR(INDIRECT("'Final Calculation Sheet'!$V"&INDEX('Buyer Lookup'!$A:$AZ,MATCH($B$2,'Buyer Lookup'!$A:$A,0),10)),"") | K30: =IFERROR(INDIRECT("'Final Calculation Sheet'!$V"&INDEX('Buyer Lookup'!$A:$AZ,MATCH($B$2,'Buyer Lookup'!$A:$A,0),11)),"") | L30: =IFERROR(INDIRECT("'Final Calculation Sheet'!$V"&INDEX('Buyer Lookup'!$A:$AZ,MATCH($B$2,'Buyer Lookup'!$A:$A,0),12)),"") | M30: =IFERROR(INDIRECT("'Final Calculation Sheet'!$V"&INDEX('Buyer Lookup'!$A:$AZ,MATCH($B$2,'Buyer Lookup'!$A:$A,0),13)),"") | N30: =IFERROR(INDIRECT("'Final Calculation Sheet'!$V"&INDEX('Buyer Lookup'!$A:$AZ,MATCH($B$2,'Buyer Lookup'!$A:$A,0),14)),"")
A32: FINAL PAYMENT
A33: FP Expected (₹) | B33: =IFERROR(INDIRECT("'Final Calculation Sheet'!$W"&INDEX('Buyer Lookup'!$A:$AZ,MATCH($B$2,'Buyer Lookup'!$A:$A,0),2)),"") -> 716215 | C33: =IFERROR(INDIRECT("'Final Calculation Sheet'!$W"&INDEX('Buyer Lookup'!$A:$AZ,MATCH($B$2,'Buyer Lookup'!$A:$A,0),3)),"") -> 0 | D33: =IFERROR(INDIRECT("'Final Calculation Sheet'!$W"&INDEX('Buyer Lookup'!$A:$AZ,MATCH($B$2,'Buyer Lookup'!$A:$A,0),4)),"") | E33: =IFERROR(INDIRECT("'Final Calculation Sheet'!$W"&INDEX('Buyer Lookup'!$A:$AZ,MATCH($B$2,'Buyer Lookup'!$A:$A,0),5)),"") | F33: =IFERROR(INDIRECT("'Final Calculation Sheet'!$W"&INDEX('Buyer Lookup'!$A:$AZ,MATCH($B$2,'Buyer Lookup'!$A:$A,0),6)),"") | G33: =IFERROR(INDIRECT("'Final Calculation Sheet'!$W"&INDEX('Buyer Lookup'!$A:$AZ,MATCH($B$2,'Buyer Lookup'!$A:$A,0),7)),"") | H33: =IFERROR(INDIRECT("'Final Calculation Sheet'!$W"&INDEX('Buyer Lookup'!$A:$AZ,MATCH($B$2,'Buyer Lookup'!$A:$A,0),8)),"") | I33: =IFERROR(INDIRECT("'Final Calculation Sheet'!$W"&INDEX('Buyer Lookup'!$A:$AZ,MATCH($B$2,'Buyer Lookup'!$A:$A,0),9)),"") | J33: =IFERROR(INDIRECT("'Final Calculation Sheet'!$W"&INDEX('Buyer Lookup'!$A:$AZ,MATCH($B$2,'Buyer Lookup'!$A:$A,0),10)),"") | K33: =IFERROR(INDIRECT("'Final Calculation Sheet'!$W"&INDEX('Buyer Lookup'!$A:$AZ,MATCH($B$2,'Buyer Lookup'!$A:$A,0),11)),"") | L33: =IFERROR(INDIRECT("'Final Calculation Sheet'!$W"&INDEX('Buyer Lookup'!$A:$AZ,MATCH($B$2,'Buyer Lookup'!$A:$A,0),12)),"") | M33: =IFERROR(INDIRECT("'Final Calculation Sheet'!$W"&INDEX('Buyer Lookup'!$A:$AZ,MATCH($B$2,'Buyer Lookup'!$A:$A,0),13)),"") | N33: =IFERROR(INDIRECT("'Final Calculation Sheet'!$W"&INDEX('Buyer Lookup'!$A:$AZ,MATCH($B$2,'Buyer Lookup'!$A:$A,0),14)),"")
A34: FP Received (₹) | B34: =IFERROR(INDIRECT("'Final Calculation Sheet'!$X"&INDEX('Buyer Lookup'!$A:$AZ,MATCH($B$2,'Buyer Lookup'!$A:$A,0),2)),"") -> 716216 | C34: =IFERROR(INDIRECT("'Final Calculation Sheet'!$X"&INDEX('Buyer Lookup'!$A:$AZ,MATCH($B$2,'Buyer Lookup'!$A:$A,0),3)),"") -> 0 | D34: =IFERROR(INDIRECT("'Final Calculation Sheet'!$X"&INDEX('Buyer Lookup'!$A:$AZ,MATCH($B$2,'Buyer Lookup'!$A:$A,0),4)),"") | E34: =IFERROR(INDIRECT("'Final Calculation Sheet'!$X"&INDEX('Buyer Lookup'!$A:$AZ,MATCH($B$2,'Buyer Lookup'!$A:$A,0),5)),"") | F34: =IFERROR(INDIRECT("'Final Calculation Sheet'!$X"&INDEX('Buyer Lookup'!$A:$AZ,MATCH($B$2,'Buyer Lookup'!$A:$A,0),6)),"") | G34: =IFERROR(INDIRECT("'Final Calculation Sheet'!$X"&INDEX('Buyer Lookup'!$A:$AZ,MATCH($B$2,'Buyer Lookup'!$A:$A,0),7)),"") | H34: =IFERROR(INDIRECT("'Final Calculation Sheet'!$X"&INDEX('Buyer Lookup'!$A:$AZ,MATCH($B$2,'Buyer Lookup'!$A:$A,0),8)),"") | I34: =IFERROR(INDIRECT("'Final Calculation Sheet'!$X"&INDEX('Buyer Lookup'!$A:$AZ,MATCH($B$2,'Buyer Lookup'!$A:$A,0),9)),"") | J34: =IFERROR(INDIRECT("'Final Calculation Sheet'!$X"&INDEX('Buyer Lookup'!$A:$AZ,MATCH($B$2,'Buyer Lookup'!$A:$A,0),10)),"") | K34: =IFERROR(INDIRECT("'Final Calculation Sheet'!$X"&INDEX('Buyer Lookup'!$A:$AZ,MATCH($B$2,'Buyer Lookup'!$A:$A,0),11)),"") | L34: =IFERROR(INDIRECT("'Final Calculation Sheet'!$X"&INDEX('Buyer Lookup'!$A:$AZ,MATCH($B$2,'Buyer Lookup'!$A:$A,0),12)),"") | M34: =IFERROR(INDIRECT("'Final Calculation Sheet'!$X"&INDEX('Buyer Lookup'!$A:$AZ,MATCH($B$2,'Buyer Lookup'!$A:$A,0),13)),"") | N34: =IFERROR(INDIRECT("'Final Calculation Sheet'!$X"&INDEX('Buyer Lookup'!$A:$AZ,MATCH($B$2,'Buyer Lookup'!$A:$A,0),14)),"")
A35: FP Receipt Date | B35: =IFERROR(INDIRECT("'Final Calculation Sheet'!$Y"&INDEX('Buyer Lookup'!$A:$AZ,MATCH($B$2,'Buyer Lookup'!$A:$A,0),2)),"") -> 18.08.2026 | C35: =IFERROR(INDIRECT("'Final Calculation Sheet'!$Y"&INDEX('Buyer Lookup'!$A:$AZ,MATCH($B$2,'Buyer Lookup'!$A:$A,0),3)),"") -> 0 | D35: =IFERROR(INDIRECT("'Final Calculation Sheet'!$Y"&INDEX('Buyer Lookup'!$A:$AZ,MATCH($B$2,'Buyer Lookup'!$A:$A,0),4)),"") | E35: =IFERROR(INDIRECT("'Final Calculation Sheet'!$Y"&INDEX('Buyer Lookup'!$A:$AZ,MATCH($B$2,'Buyer Lookup'!$A:$A,0),5)),"") | F35: =IFERROR(INDIRECT("'Final Calculation Sheet'!$Y"&INDEX('Buyer Lookup'!$A:$AZ,MATCH($B$2,'Buyer Lookup'!$A:$A,0),6)),"") | G35: =IFERROR(INDIRECT("'Final Calculation Sheet'!$Y"&INDEX('Buyer Lookup'!$A:$AZ,MATCH($B$2,'Buyer Lookup'!$A:$A,0),7)),"") | H35: =IFERROR(INDIRECT("'Final Calculation Sheet'!$Y"&INDEX('Buyer Lookup'!$A:$AZ,MATCH($B$2,'Buyer Lookup'!$A:$A,0),8)),"") | I35: =IFERROR(INDIRECT("'Final Calculation Sheet'!$Y"&INDEX('Buyer Lookup'!$A:$AZ,MATCH($B$2,'Buyer Lookup'!$A:$A,0),9)),"") | J35: =IFERROR(INDIRECT("'Final Calculation Sheet'!$Y"&INDEX('Buyer Lookup'!$A:$AZ,MATCH($B$2,'Buyer Lookup'!$A:$A,0),10)),"") | K35: =IFERROR(INDIRECT("'Final Calculation Sheet'!$Y"&INDEX('Buyer Lookup'!$A:$AZ,MATCH($B$2,'Buyer Lookup'!$A:$A,0),11)),"") | L35: =IFERROR(INDIRECT("'Final Calculation Sheet'!$Y"&INDEX('Buyer Lookup'!$A:$AZ,MATCH($B$2,'Buyer Lookup'!$A:$A,0),12)),"") | M35: =IFERROR(INDIRECT("'Final Calculation Sheet'!$Y"&INDEX('Buyer Lookup'!$A:$AZ,MATCH($B$2,'Buyer Lookup'!$A:$A,0),13)),"") | N35: =IFERROR(INDIRECT("'Final Calculation Sheet'!$Y"&INDEX('Buyer Lookup'!$A:$AZ,MATCH($B$2,'Buyer Lookup'!$A:$A,0),14)),"")
A37: LPP
A38: LPP Expected (₹) | B38: =IFERROR(INDIRECT("'Final Calculation Sheet'!$Z"&INDEX('Buyer Lookup'!$A:$AZ,MATCH($B$2,'Buyer Lookup'!$A:$A,0),2)),"") -> 0 | C38: =IFERROR(INDIRECT("'Final Calculation Sheet'!$Z"&INDEX('Buyer Lookup'!$A:$AZ,MATCH($B$2,'Buyer Lookup'!$A:$A,0),3)),"") -> 0 | D38: =IFERROR(INDIRECT("'Final Calculation Sheet'!$Z"&INDEX('Buyer Lookup'!$A:$AZ,MATCH($B$2,'Buyer Lookup'!$A:$A,0),4)),"") | E38: =IFERROR(INDIRECT("'Final Calculation Sheet'!$Z"&INDEX('Buyer Lookup'!$A:$AZ,MATCH($B$2,'Buyer Lookup'!$A:$A,0),5)),"") | F38: =IFERROR(INDIRECT("'Final Calculation Sheet'!$Z"&INDEX('Buyer Lookup'!$A:$AZ,MATCH($B$2,'Buyer Lookup'!$A:$A,0),6)),"") | G38: =IFERROR(INDIRECT("'Final Calculation Sheet'!$Z"&INDEX('Buyer Lookup'!$A:$AZ,MATCH($B$2,'Buyer Lookup'!$A:$A,0),7)),"") | H38: =IFERROR(INDIRECT("'Final Calculation Sheet'!$Z"&INDEX('Buyer Lookup'!$A:$AZ,MATCH($B$2,'Buyer Lookup'!$A:$A,0),8)),"") | I38: =IFERROR(INDIRECT("'Final Calculation Sheet'!$Z"&INDEX('Buyer Lookup'!$A:$AZ,MATCH($B$2,'Buyer Lookup'!$A:$A,0),9)),"") | J38: =IFERROR(INDIRECT("'Final Calculation Sheet'!$Z"&INDEX('Buyer Lookup'!$A:$AZ,MATCH($B$2,'Buyer Lookup'!$A:$A,0),10)),"") | K38: =IFERROR(INDIRECT("'Final Calculation Sheet'!$Z"&INDEX('Buyer Lookup'!$A:$AZ,MATCH($B$2,'Buyer Lookup'!$A:$A,0),11)),"") | L38: =IFERROR(INDIRECT("'Final Calculation Sheet'!$Z"&INDEX('Buyer Lookup'!$A:$AZ,MATCH($B$2,'Buyer Lookup'!$A:$A,0),12)),"") | M38: =IFERROR(INDIRECT("'Final Calculation Sheet'!$Z"&INDEX('Buyer Lookup'!$A:$AZ,MATCH($B$2,'Buyer Lookup'!$A:$A,0),13)),"") | N38: =IFERROR(INDIRECT("'Final Calculation Sheet'!$Z"&INDEX('Buyer Lookup'!$A:$AZ,MATCH($B$2,'Buyer Lookup'!$A:$A,0),14)),"")
A39: LPP Received (₹) | B39: =IFERROR(INDIRECT("'Final Calculation Sheet'!$AA"&INDEX('Buyer Lookup'!$A:$AZ,MATCH($B$2,'Buyer Lookup'!$A:$A,0),2)),"") -> 0 | C39: =IFERROR(INDIRECT("'Final Calculation Sheet'!$AA"&INDEX('Buyer Lookup'!$A:$AZ,MATCH($B$2,'Buyer Lookup'!$A:$A,0),3)),"") -> 0 | D39: =IFERROR(INDIRECT("'Final Calculation Sheet'!$AA"&INDEX('Buyer Lookup'!$A:$AZ,MATCH($B$2,'Buyer Lookup'!$A:$A,0),4)),"") | E39: =IFERROR(INDIRECT("'Final Calculation Sheet'!$AA"&INDEX('Buyer Lookup'!$A:$AZ,MATCH($B$2,'Buyer Lookup'!$A:$A,0),5)),"") | F39: =IFERROR(INDIRECT("'Final Calculation Sheet'!$AA"&INDEX('Buyer Lookup'!$A:$AZ,MATCH($B$2,'Buyer Lookup'!$A:$A,0),6)),"") | G39: =IFERROR(INDIRECT("'Final Calculation Sheet'!$AA"&INDEX('Buyer Lookup'!$A:$AZ,MATCH($B$2,'Buyer Lookup'!$A:$A,0),7)),"") | H39: =IFERROR(INDIRECT("'Final Calculation Sheet'!$AA"&INDEX('Buyer Lookup'!$A:$AZ,MATCH($B$2,'Buyer Lookup'!$A:$A,0),8)),"") | I39: =IFERROR(INDIRECT("'Final Calculation Sheet'!$AA"&INDEX('Buyer Lookup'!$A:$AZ,MATCH($B$2,'Buyer Lookup'!$A:$A,0),9)),"") | J39: =IFERROR(INDIRECT("'Final Calculation Sheet'!$AA"&INDEX('Buyer Lookup'!$A:$AZ,MATCH($B$2,'Buyer Lookup'!$A:$A,0),10)),"") | K39: =IFERROR(INDIRECT("'Final Calculation Sheet'!$AA"&INDEX('Buyer Lookup'!$A:$AZ,MATCH($B$2,'Buyer Lookup'!$A:$A,0),11)),"") | L39: =IFERROR(INDIRECT("'Final Calculation Sheet'!$AA"&INDEX('Buyer Lookup'!$A:$AZ,MATCH($B$2,'Buyer Lookup'!$A:$A,0),12)),"") | M39: =IFERROR(INDIRECT("'Final Calculation Sheet'!$AA"&INDEX('Buyer Lookup'!$A:$AZ,MATCH($B$2,'Buyer Lookup'!$A:$A,0),13)),"") | N39: =IFERROR(INDIRECT("'Final Calculation Sheet'!$AA"&INDEX('Buyer Lookup'!$A:$AZ,MATCH($B$2,'Buyer Lookup'!$A:$A,0),14)),"")
A40: LPP Receipt Date | B40: =IFERROR(INDIRECT("'Final Calculation Sheet'!$AB"&INDEX('Buyer Lookup'!$A:$AZ,MATCH($B$2,'Buyer Lookup'!$A:$A,0),2)),"") -> 0 | C40: =IFERROR(INDIRECT("'Final Calculation Sheet'!$AB"&INDEX('Buyer Lookup'!$A:$AZ,MATCH($B$2,'Buyer Lookup'!$A:$A,0),3)),"") -> 0 | D40: =IFERROR(INDIRECT("'Final Calculation Sheet'!$AB"&INDEX('Buyer Lookup'!$A:$AZ,MATCH($B$2,'Buyer Lookup'!$A:$A,0),4)),"") | E40: =IFERROR(INDIRECT("'Final Calculation Sheet'!$AB"&INDEX('Buyer Lookup'!$A:$AZ,MATCH($B$2,'Buyer Lookup'!$A:$A,0),5)),"") | F40: =IFERROR(INDIRECT("'Final Calculation Sheet'!$AB"&INDEX('Buyer Lookup'!$A:$AZ,MATCH($B$2,'Buyer Lookup'!$A:$A,0),6)),"") | G40: =IFERROR(INDIRECT("'Final Calculation Sheet'!$AB"&INDEX('Buyer Lookup'!$A:$AZ,MATCH($B$2,'Buyer Lookup'!$A:$A,0),7)),"") | H40: =IFERROR(INDIRECT("'Final Calculation Sheet'!$AB"&INDEX('Buyer Lookup'!$A:$AZ,MATCH($B$2,'Buyer Lookup'!$A:$A,0),8)),"") | I40: =IFERROR(INDIRECT("'Final Calculation Sheet'!$AB"&INDEX('Buyer Lookup'!$A:$AZ,MATCH($B$2,'Buyer Lookup'!$A:$A,0),9)),"") | J40: =IFERROR(INDIRECT("'Final Calculation Sheet'!$AB"&INDEX('Buyer Lookup'!$A:$AZ,MATCH($B$2,'Buyer Lookup'!$A:$A,0),10)),"") | K40: =IFERROR(INDIRECT("'Final Calculation Sheet'!$AB"&INDEX('Buyer Lookup'!$A:$AZ,MATCH($B$2,'Buyer Lookup'!$A:$A,0),11)),"") | L40: =IFERROR(INDIRECT("'Final Calculation Sheet'!$AB"&INDEX('Buyer Lookup'!$A:$AZ,MATCH($B$2,'Buyer Lookup'!$A:$A,0),12)),"") | M40: =IFERROR(INDIRECT("'Final Calculation Sheet'!$AB"&INDEX('Buyer Lookup'!$A:$AZ,MATCH($B$2,'Buyer Lookup'!$A:$A,0),13)),"") | N40: =IFERROR(INDIRECT("'Final Calculation Sheet'!$AB"&INDEX('Buyer Lookup'!$A:$AZ,MATCH($B$2,'Buyer Lookup'!$A:$A,0),14)),"")
A42: SUMMARY
A43: Total Received (₹) | B43: =IFERROR(INDIRECT("'Final Calculation Sheet'!$AC"&INDEX('Buyer Lookup'!$A:$AZ,MATCH($B$2,'Buyer Lookup'!$A:$A,0),2)),"") -> 0 | C43: =IFERROR(INDIRECT("'Final Calculation Sheet'!$AC"&INDEX('Buyer Lookup'!$A:$AZ,MATCH($B$2,'Buyer Lookup'!$A:$A,0),3)),"") -> 0 | D43: =IFERROR(INDIRECT("'Final Calculation Sheet'!$AC"&INDEX('Buyer Lookup'!$A:$AZ,MATCH($B$2,'Buyer Lookup'!$A:$A,0),4)),"") | E43: =IFERROR(INDIRECT("'Final Calculation Sheet'!$AC"&INDEX('Buyer Lookup'!$A:$AZ,MATCH($B$2,'Buyer Lookup'!$A:$A,0),5)),"") | F43: =IFERROR(INDIRECT("'Final Calculation Sheet'!$AC"&INDEX('Buyer Lookup'!$A:$AZ,MATCH($B$2,'Buyer Lookup'!$A:$A,0),6)),"") | G43: =IFERROR(INDIRECT("'Final Calculation Sheet'!$AC"&INDEX('Buyer Lookup'!$A:$AZ,MATCH($B$2,'Buyer Lookup'!$A:$A,0),7)),"") | H43: =IFERROR(INDIRECT("'Final Calculation Sheet'!$AC"&INDEX('Buyer Lookup'!$A:$AZ,MATCH($B$2,'Buyer Lookup'!$A:$A,0),8)),"") | I43: =IFERROR(INDIRECT("'Final Calculation Sheet'!$AC"&INDEX('Buyer Lookup'!$A:$AZ,MATCH($B$2,'Buyer Lookup'!$A:$A,0),9)),"") | J43: =IFERROR(INDIRECT("'Final Calculation Sheet'!$AC"&INDEX('Buyer Lookup'!$A:$AZ,MATCH($B$2,'Buyer Lookup'!$A:$A,0),10)),"") | K43: =IFERROR(INDIRECT("'Final Calculation Sheet'!$AC"&INDEX('Buyer Lookup'!$A:$AZ,MATCH($B$2,'Buyer Lookup'!$A:$A,0),11)),"") | L43: =IFERROR(INDIRECT("'Final Calculation Sheet'!$AC"&INDEX('Buyer Lookup'!$A:$AZ,MATCH($B$2,'Buyer Lookup'!$A:$A,0),12)),"") | M43: =IFERROR(INDIRECT("'Final Calculation Sheet'!$AC"&INDEX('Buyer Lookup'!$A:$AZ,MATCH($B$2,'Buyer Lookup'!$A:$A,0),13)),"") | N43: =IFERROR(INDIRECT("'Final Calculation Sheet'!$AC"&INDEX('Buyer Lookup'!$A:$AZ,MATCH($B$2,'Buyer Lookup'!$A:$A,0),14)),"")
A44: Outstanding (₹) | B44: =IFERROR(INDIRECT("'Final Calculation Sheet'!$AD"&INDEX('Buyer Lookup'!$A:$AZ,MATCH($B$2,'Buyer Lookup'!$A:$A,0),2)),"") -> 0 | C44: =IFERROR(INDIRECT("'Final Calculation Sheet'!$AD"&INDEX('Buyer Lookup'!$A:$AZ,MATCH($B$2,'Buyer Lookup'!$A:$A,0),3)),"") -> 0 | D44: =IFERROR(INDIRECT("'Final Calculation Sheet'!$AD"&INDEX('Buyer Lookup'!$A:$AZ,MATCH($B$2,'Buyer Lookup'!$A:$A,0),4)),"") | E44: =IFERROR(INDIRECT("'Final Calculation Sheet'!$AD"&INDEX('Buyer Lookup'!$A:$AZ,MATCH($B$2,'Buyer Lookup'!$A:$A,0),5)),"") | F44: =IFERROR(INDIRECT("'Final Calculation Sheet'!$AD"&INDEX('Buyer Lookup'!$A:$AZ,MATCH($B$2,'Buyer Lookup'!$A:$A,0),6)),"") | G44: =IFERROR(INDIRECT("'Final Calculation Sheet'!$AD"&INDEX('Buyer Lookup'!$A:$AZ,MATCH($B$2,'Buyer Lookup'!$A:$A,0),7)),"") | H44: =IFERROR(INDIRECT("'Final Calculation Sheet'!$AD"&INDEX('Buyer Lookup'!$A:$AZ,MATCH($B$2,'Buyer Lookup'!$A:$A,0),8)),"") | I44: =IFERROR(INDIRECT("'Final Calculation Sheet'!$AD"&INDEX('Buyer Lookup'!$A:$AZ,MATCH($B$2,'Buyer Lookup'!$A:$A,0),9)),"") | J44: =IFERROR(INDIRECT("'Final Calculation Sheet'!$AD"&INDEX('Buyer Lookup'!$A:$AZ,MATCH($B$2,'Buyer Lookup'!$A:$A,0),10)),"") | K44: =IFERROR(INDIRECT("'Final Calculation Sheet'!$AD"&INDEX('Buyer Lookup'!$A:$AZ,MATCH($B$2,'Buyer Lookup'!$A:$A,0),11)),"") | L44: =IFERROR(INDIRECT("'Final Calculation Sheet'!$AD"&INDEX('Buyer Lookup'!$A:$AZ,MATCH($B$2,'Buyer Lookup'!$A:$A,0),12)),"") | M44: =IFERROR(INDIRECT("'Final Calculation Sheet'!$AD"&INDEX('Buyer Lookup'!$A:$AZ,MATCH($B$2,'Buyer Lookup'!$A:$A,0),13)),"") | N44: =IFERROR(INDIRECT("'Final Calculation Sheet'!$AD"&INDEX('Buyer Lookup'!$A:$AZ,MATCH($B$2,'Buyer Lookup'!$A:$A,0),14)),"")
A46: DOCUMENT
A47: Invoice No. | B47: =IFERROR(INDIRECT("'Final Calculation Sheet'!$AE"&INDEX('Buyer Lookup'!$A:$AZ,MATCH($B$2,'Buyer Lookup'!$A:$A,0),2)),"") -> DR2640100029 | C47: =IFERROR(INDIRECT("'Final Calculation Sheet'!$AE"&INDEX('Buyer Lookup'!$A:$AZ,MATCH($B$2,'Buyer Lookup'!$A:$A,0),3)),"") -> 0 | D47: =IFERROR(INDIRECT("'Final Calculation Sheet'!$AE"&INDEX('Buyer Lookup'!$A:$AZ,MATCH($B$2,'Buyer Lookup'!$A:$A,0),4)),"") | E47: =IFERROR(INDIRECT("'Final Calculation Sheet'!$AE"&INDEX('Buyer Lookup'!$A:$AZ,MATCH($B$2,'Buyer Lookup'!$A:$A,0),5)),"") | F47: =IFERROR(INDIRECT("'Final Calculation Sheet'!$AE"&INDEX('Buyer Lookup'!$A:$AZ,MATCH($B$2,'Buyer Lookup'!$A:$A,0),6)),"") | G47: =IFERROR(INDIRECT("'Final Calculation Sheet'!$AE"&INDEX('Buyer Lookup'!$A:$AZ,MATCH($B$2,'Buyer Lookup'!$A:$A,0),7)),"") | H47: =IFERROR(INDIRECT("'Final Calculation Sheet'!$AE"&INDEX('Buyer Lookup'!$A:$AZ,MATCH($B$2,'Buyer Lookup'!$A:$A,0),8)),"") | I47: =IFERROR(INDIRECT("'Final Calculation Sheet'!$AE"&INDEX('Buyer Lookup'!$A:$AZ,MATCH($B$2,'Buyer Lookup'!$A:$A,0),9)),"") | J47: =IFERROR(INDIRECT("'Final Calculation Sheet'!$AE"&INDEX('Buyer Lookup'!$A:$AZ,MATCH($B$2,'Buyer Lookup'!$A:$A,0),10)),"") | K47: =IFERROR(INDIRECT("'Final Calculation Sheet'!$AE"&INDEX('Buyer Lookup'!$A:$AZ,MATCH($B$2,'Buyer Lookup'!$A:$A,0),11)),"") | L47: =IFERROR(INDIRECT("'Final Calculation Sheet'!$AE"&INDEX('Buyer Lookup'!$A:$AZ,MATCH($B$2,'Buyer Lookup'!$A:$A,0),12)),"") | M47: =IFERROR(INDIRECT("'Final Calculation Sheet'!$AE"&INDEX('Buyer Lookup'!$A:$AZ,MATCH($B$2,'Buyer Lookup'!$A:$A,0),13)),"") | N47: =IFERROR(INDIRECT("'Final Calculation Sheet'!$AE"&INDEX('Buyer Lookup'!$A:$AZ,MATCH($B$2,'Buyer Lookup'!$A:$A,0),14)),"")
A48: SAP Document | B48: =IFERROR(INDIRECT("'Final Calculation Sheet'!$AF"&INDEX('Buyer Lookup'!$A:$AZ,MATCH($B$2,'Buyer Lookup'!$A:$A,0),2)),"") -> 1800003271 | C48: =IFERROR(INDIRECT("'Final Calculation Sheet'!$AF"&INDEX('Buyer Lookup'!$A:$AZ,MATCH($B$2,'Buyer Lookup'!$A:$A,0),3)),"") -> 0 | D48: =IFERROR(INDIRECT("'Final Calculation Sheet'!$AF"&INDEX('Buyer Lookup'!$A:$AZ,MATCH($B$2,'Buyer Lookup'!$A:$A,0),4)),"") | E48: =IFERROR(INDIRECT("'Final Calculation Sheet'!$AF"&INDEX('Buyer Lookup'!$A:$AZ,MATCH($B$2,'Buyer Lookup'!$A:$A,0),5)),"") | F48: =IFERROR(INDIRECT("'Final Calculation Sheet'!$AF"&INDEX('Buyer Lookup'!$A:$AZ,MATCH($B$2,'Buyer Lookup'!$A:$A,0),6)),"") | G48: =IFERROR(INDIRECT("'Final Calculation Sheet'!$AF"&INDEX('Buyer Lookup'!$A:$AZ,MATCH($B$2,'Buyer Lookup'!$A:$A,0),7)),"") | H48: =IFERROR(INDIRECT("'Final Calculation Sheet'!$AF"&INDEX('Buyer Lookup'!$A:$AZ,MATCH($B$2,'Buyer Lookup'!$A:$A,0),8)),"") | I48: =IFERROR(INDIRECT("'Final Calculation Sheet'!$AF"&INDEX('Buyer Lookup'!$A:$AZ,MATCH($B$2,'Buyer Lookup'!$A:$A,0),9)),"") | J48: =IFERROR(INDIRECT("'Final Calculation Sheet'!$AF"&INDEX('Buyer Lookup'!$A:$AZ,MATCH($B$2,'Buyer Lookup'!$A:$A,0),10)),"") | K48: =IFERROR(INDIRECT("'Final Calculation Sheet'!$AF"&INDEX('Buyer Lookup'!$A:$AZ,MATCH($B$2,'Buyer Lookup'!$A:$A,0),11)),"") | L48: =IFERROR(INDIRECT("'Final Calculation Sheet'!$AF"&INDEX('Buyer Lookup'!$A:$AZ,MATCH($B$2,'Buyer Lookup'!$A:$A,0),12)),"") | M48: =IFERROR(INDIRECT("'Final Calculation Sheet'!$AF"&INDEX('Buyer Lookup'!$A:$AZ,MATCH($B$2,'Buyer Lookup'!$A:$A,0),13)),"") | N48: =IFERROR(INDIRECT("'Final Calculation Sheet'!$AF"&INDEX('Buyer Lookup'!$A:$AZ,MATCH($B$2,'Buyer Lookup'!$A:$A,0),14)),"")
A49: Doc./Invoice Date | B49: =IFERROR(INDIRECT("'Final Calculation Sheet'!$AG"&INDEX('Buyer Lookup'!$A:$AZ,MATCH($B$2,'Buyer Lookup'!$A:$A,0),2)),"") -> 24.08.2026 | C49: =IFERROR(INDIRECT("'Final Calculation Sheet'!$AG"&INDEX('Buyer Lookup'!$A:$AZ,MATCH($B$2,'Buyer Lookup'!$A:$A,0),3)),"") -> 0 | D49: =IFERROR(INDIRECT("'Final Calculation Sheet'!$AG"&INDEX('Buyer Lookup'!$A:$AZ,MATCH($B$2,'Buyer Lookup'!$A:$A,0),4)),"") | E49: =IFERROR(INDIRECT("'Final Calculation Sheet'!$AG"&INDEX('Buyer Lookup'!$A:$AZ,MATCH($B$2,'Buyer Lookup'!$A:$A,0),5)),"") | F49: =IFERROR(INDIRECT("'Final Calculation Sheet'!$AG"&INDEX('Buyer Lookup'!$A:$AZ,MATCH($B$2,'Buyer Lookup'!$A:$A,0),6)),"") | G49: =IFERROR(INDIRECT("'Final Calculation Sheet'!$AG"&INDEX('Buyer Lookup'!$A:$AZ,MATCH($B$2,'Buyer Lookup'!$A:$A,0),7)),"") | H49: =IFERROR(INDIRECT("'Final Calculation Sheet'!$AG"&INDEX('Buyer Lookup'!$A:$AZ,MATCH($B$2,'Buyer Lookup'!$A:$A,0),8)),"") | I49: =IFERROR(INDIRECT("'Final Calculation Sheet'!$AG"&INDEX('Buyer Lookup'!$A:$AZ,MATCH($B$2,'Buyer Lookup'!$A:$A,0),9)),"") | J49: =IFERROR(INDIRECT("'Final Calculation Sheet'!$AG"&INDEX('Buyer Lookup'!$A:$AZ,MATCH($B$2,'Buyer Lookup'!$A:$A,0),10)),"") | K49: =IFERROR(INDIRECT("'Final Calculation Sheet'!$AG"&INDEX('Buyer Lookup'!$A:$AZ,MATCH($B$2,'Buyer Lookup'!$A:$A,0),11)),"") | L49: =IFERROR(INDIRECT("'Final Calculation Sheet'!$AG"&INDEX('Buyer Lookup'!$A:$AZ,MATCH($B$2,'Buyer Lookup'!$A:$A,0),12)),"") | M49: =IFERROR(INDIRECT("'Final Calculation Sheet'!$AG"&INDEX('Buyer Lookup'!$A:$AZ,MATCH($B$2,'Buyer Lookup'!$A:$A,0),13)),"") | N49: =IFERROR(INDIRECT("'Final Calculation Sheet'!$AG"&INDEX('Buyer Lookup'!$A:$AZ,MATCH($B$2,'Buyer Lookup'!$A:$A,0),14)),"")
A51: BUYER TOTALS
A52: Total Lots | B52: =IFERROR(COUNTA(INDEX('Buyer Lookup'!$B:$AZ,MATCH($B$2,'Buyer Lookup'!$A:$A,0),0)),"0") -> 2 | C52: ← Total lots for selected buyer
A53: Total Mat. Value (₹) | B53: =IFERROR(INDIRECT("'Final Calculation Sheet'!$H"&INDEX('Buyer Lookup'!$A:$AZ,MATCH($B$2,'Buyer Lookup'!$A:$A,0),2)),0)+IFERROR(INDIRECT("'Final Calculation Sheet'!$H"&INDEX('Buyer Lookup'!$A:$AZ,MATCH($B$2,'Buyer Lookup'!$A:$A,0),3)),0)+IFERROR(INDIRECT("'Final Calculation Sheet'!$H"&INDEX('Buyer Lookup'!$A:$AZ,MATCH($B$2,'Buyer Lookup'!$A:$A,0),4)),0)+IFERROR(INDIRECT("'Final Calculation Sheet'!$H"&INDEX('Buyer Lookup'!$A:$AZ,MATCH($B$2,'Buyer Lookup'!$A:$A,0),5)),0)+IFERROR(INDIRECT("'Final Calculation Sheet'!$H"&INDEX('Buyer Lookup'!$A:$AZ,MATCH($B$2,'Buyer Lookup'!$A:$A,0),6)),0)+IFERROR(INDIRECT("'Final Calculation Sheet'!$H"&INDEX('Buyer Lookup'!$A:$AZ,MATCH($B$2,'Buyer Lookup'!$A:$A,0),7)),0)+IFERROR(INDIRECT("'Final Calculation Sheet'!$H"&INDEX('Buyer Lookup'!$A:$AZ,MATCH($B$2,'Buyer Lookup'!$A:$A,0),8)),0)+IFERROR(INDIRECT("'Final Calculation Sheet'!$H"&INDEX('Buyer Lookup'!$A:$AZ,MATCH($B$2,'Buyer Lookup'!$A:$A,0),9)),0)+IFERROR(INDIRECT("'Final Calculation Sheet'!$H"&INDEX('Buyer Lookup'!$A:$AZ,MATCH($B$2,'Buyer Lookup'!$A:$A,0),10)),0)+IFERROR(INDIRECT("'Final Calculation Sheet'!$H"&INDEX('Buyer Lookup'!$A:$AZ,MATCH($B$2,'Buyer Lookup'!$A:$A,0),11)),0)+IFERROR(INDIRECT("'Final Calculation Sheet'!$H"&INDEX('Buyer Lookup'!$A:$AZ,MATCH($B$2,'Buyer Lookup'!$A:$A,0),12)),0)+IFERROR(INDIRECT("'Final Calculation Sheet'!$H"&INDEX('Buyer Lookup'!$A:$AZ,MATCH($B$2,'Buyer Lookup'!$A:$A,0),13)),0)+IFERROR(INDIRECT("'Final Calculation Sheet'!$H"&INDEX('Buyer Lookup'!$A:$AZ,MATCH($B$2,'Buyer Lookup'!$A:$A,0),14)),0) -> 790089 | C53: ← Sum across all lots for selected buyer
A54: Total Mat.Value+GST (₹) | B54: =IFERROR(INDIRECT("'Final Calculation Sheet'!$J"&INDEX('Buyer Lookup'!$A:$AZ,MATCH($B$2,'Buyer Lookup'!$A:$A,0),2)),0)+IFERROR(INDIRECT("'Final Calculation Sheet'!$J"&INDEX('Buyer Lookup'!$A:$AZ,MATCH($B$2,'Buyer Lookup'!$A:$A,0),3)),0)+IFERROR(INDIRECT("'Final Calculation Sheet'!$J"&INDEX('Buyer Lookup'!$A:$AZ,MATCH($B$2,'Buyer Lookup'!$A:$A,0),4)),0)+IFERROR(INDIRECT("'Final Calculation Sheet'!$J"&INDEX('Buyer Lookup'!$A:$AZ,MATCH($B$2,'Buyer Lookup'!$A:$A,0),5)),0)+IFERROR(INDIRECT("'Final Calculation Sheet'!$J"&INDEX('Buyer Lookup'!$A:$AZ,MATCH($B$2,'Buyer Lookup'!$A:$A,0),6)),0)+IFERROR(INDIRECT("'Final Calculation Sheet'!$J"&INDEX('Buyer Lookup'!$A:$AZ,MATCH($B$2,'Buyer Lookup'!$A:$A,0),7)),0)+IFERROR(INDIRECT("'Final Calculation Sheet'!$J"&INDEX('Buyer Lookup'!$A:$AZ,MATCH($B$2,'Buyer Lookup'!$A:$A,0),8)),0)+IFERROR(INDIRECT("'Final Calculation Sheet'!$J"&INDEX('Buyer Lookup'!$A:$AZ,MATCH($B$2,'Buyer Lookup'!$A:$A,0),9)),0)+IFERROR(INDIRECT("'Final Calculation Sheet'!$J"&INDEX('Buyer Lookup'!$A:$AZ,MATCH($B$2,'Buyer Lookup'!$A:$A,0),10)),0)+IFERROR(INDIRECT("'Final Calculation Sheet'!$J"&INDEX('Buyer Lookup'!$A:$AZ,MATCH($B$2,'Buyer Lookup'!$A:$A,0),11)),0)+IFERROR(INDIRECT("'Final Calculation Sheet'!$J"&INDEX('Buyer Lookup'!$A:$AZ,MATCH($B$2,'Buyer Lookup'!$A:$A,0),12)),0)+IFERROR(INDIRECT("'Final Calculation Sheet'!$J"&INDEX('Buyer Lookup'!$A:$AZ,MATCH($B$2,'Buyer Lookup'!$A:$A,0),13)),0)+IFERROR(INDIRECT("'Final Calculation Sheet'!$J"&INDEX('Buyer Lookup'!$A:$AZ,MATCH($B$2,'Buyer Lookup'!$A:$A,0),14)),0) -> 932305 | C54: ← Sum across all lots for selected buyer
A55: Total TCS (₹) | B55: =IFERROR(INDIRECT("'Final Calculation Sheet'!$K"&INDEX('Buyer Lookup'!$A:$AZ,MATCH($B$2,'Buyer Lookup'!$A:$A,0),2)),0)+IFERROR(INDIRECT("'Final Calculation Sheet'!$K"&INDEX('Buyer Lookup'!$A:$AZ,MATCH($B$2,'Buyer Lookup'!$A:$A,0),3)),0)+IFERROR(INDIRECT("'Final Calculation Sheet'!$K"&INDEX('Buyer Lookup'!$A:$AZ,MATCH($B$2,'Buyer Lookup'!$A:$A,0),4)),0)+IFERROR(INDIRECT("'Final Calculation Sheet'!$K"&INDEX('Buyer Lookup'!$A:$AZ,MATCH($B$2,'Buyer Lookup'!$A:$A,0),5)),0)+IFERROR(INDIRECT("'Final Calculation Sheet'!$K"&INDEX('Buyer Lookup'!$A:$AZ,MATCH($B$2,'Buyer Lookup'!$A:$A,0),6)),0)+IFERROR(INDIRECT("'Final Calculation Sheet'!$K"&INDEX('Buyer Lookup'!$A:$AZ,MATCH($B$2,'Buyer Lookup'!$A:$A,0),7)),0)+IFERROR(INDIRECT("'Final Calculation Sheet'!$K"&INDEX('Buyer Lookup'!$A:$AZ,MATCH($B$2,'Buyer Lookup'!$A:$A,0),8)),0)+IFERROR(INDIRECT("'Final Calculation Sheet'!$K"&INDEX('Buyer Lookup'!$A:$AZ,MATCH($B$2,'Buyer Lookup'!$A:$A,0),9)),0)+IFERROR(INDIRECT("'Final Calculation Sheet'!$K"&INDEX('Buyer Lookup'!$A:$AZ,MATCH($B$2,'Buyer Lookup'!$A:$A,0),10)),0)+IFERROR(INDIRECT("'Final Calculation Sheet'!$K"&INDEX('Buyer Lookup'!$A:$AZ,MATCH($B$2,'Buyer Lookup'!$A:$A,0),11)),0)+IFERROR(INDIRECT("'Final Calculation Sheet'!$K"&INDEX('Buyer Lookup'!$A:$AZ,MATCH($B$2,'Buyer Lookup'!$A:$A,0),12)),0)+IFERROR(INDIRECT("'Final Calculation Sheet'!$K"&INDEX('Buyer Lookup'!$A:$AZ,MATCH($B$2,'Buyer Lookup'!$A:$A,0),13)),0)+IFERROR(INDIRECT("'Final Calculation Sheet'!$K"&INDEX('Buyer Lookup'!$A:$AZ,MATCH($B$2,'Buyer Lookup'!$A:$A,0),14)),0) -> 18646 | C55: ← Sum across all lots for selected buyer
A56: Total Receivables (₹) | B56: =IFERROR(INDIRECT("'Final Calculation Sheet'!$S"&INDEX('Buyer Lookup'!$A:$AZ,MATCH($B$2,'Buyer Lookup'!$A:$A,0),2)),0)+IFERROR(INDIRECT("'Final Calculation Sheet'!$S"&INDEX('Buyer Lookup'!$A:$AZ,MATCH($B$2,'Buyer Lookup'!$A:$A,0),3)),0)+IFERROR(INDIRECT("'Final Calculation Sheet'!$S"&INDEX('Buyer Lookup'!$A:$AZ,MATCH($B$2,'Buyer Lookup'!$A:$A,0),4)),0)+IFERROR(INDIRECT("'Final Calculation Sheet'!$S"&INDEX('Buyer Lookup'!$A:$AZ,MATCH($B$2,'Buyer Lookup'!$A:$A,0),5)),0)+IFERROR(INDIRECT("'Final Calculation Sheet'!$S"&INDEX('Buyer Lookup'!$A:$AZ,MATCH($B$2,'Buyer Lookup'!$A:$A,0),6)),0)+IFERROR(INDIRECT("'Final Calculation Sheet'!$S"&INDEX('Buyer Lookup'!$A:$AZ,MATCH($B$2,'Buyer Lookup'!$A:$A,0),7)),0)+IFERROR(INDIRECT("'Final Calculation Sheet'!$S"&INDEX('Buyer Lookup'!$A:$AZ,MATCH($B$2,'Buyer Lookup'!$A:$A,0),8)),0)+IFERROR(INDIRECT("'Final Calculation Sheet'!$S"&INDEX('Buyer Lookup'!$A:$AZ,MATCH($B$2,'Buyer Lookup'!$A:$A,0),9)),0)+IFERROR(INDIRECT("'Final Calculation Sheet'!$S"&INDEX('Buyer Lookup'!$A:$AZ,MATCH($B$2,'Buyer Lookup'!$A:$A,0),10)),0)+IFERROR(INDIRECT("'Final Calculation Sheet'!$S"&INDEX('Buyer Lookup'!$A:$AZ,MATCH($B$2,'Buyer Lookup'!$A:$A,0),11)),0)+IFERROR(INDIRECT("'Final Calculation Sheet'!$S"&INDEX('Buyer Lookup'!$A:$AZ,MATCH($B$2,'Buyer Lookup'!$A:$A,0),12)),0)+IFERROR(INDIRECT("'Final Calculation Sheet'!$S"&INDEX('Buyer Lookup'!$A:$AZ,MATCH($B$2,'Buyer Lookup'!$A:$A,0),13)),0)+IFERROR(INDIRECT("'Final Calculation Sheet'!$S"&INDEX('Buyer Lookup'!$A:$AZ,MATCH($B$2,'Buyer Lookup'!$A:$A,0),14)),0) -> 913738 | C56: ← Sum across all lots for selected buyer
A57: Total SD Expected (₹) | B57: =IFERROR(INDIRECT("'Final Calculation Sheet'!$T"&INDEX('Buyer Lookup'!$A:$AZ,MATCH($B$2,'Buyer Lookup'!$A:$A,0),2)),0)+IFERROR(INDIRECT("'Final Calculation Sheet'!$T"&INDEX('Buyer Lookup'!$A:$AZ,MATCH($B$2,'Buyer Lookup'!$A:$A,0),3)),0)+IFERROR(INDIRECT("'Final Calculation Sheet'!$T"&INDEX('Buyer Lookup'!$A:$AZ,MATCH($B$2,'Buyer Lookup'!$A:$A,0),4)),0)+IFERROR(INDIRECT("'Final Calculation Sheet'!$T"&INDEX('Buyer Lookup'!$A:$AZ,MATCH($B$2,'Buyer Lookup'!$A:$A,0),5)),0)+IFERROR(INDIRECT("'Final Calculation Sheet'!$T"&INDEX('Buyer Lookup'!$A:$AZ,MATCH($B$2,'Buyer Lookup'!$A:$A,0),6)),0)+IFERROR(INDIRECT("'Final Calculation Sheet'!$T"&INDEX('Buyer Lookup'!$A:$AZ,MATCH($B$2,'Buyer Lookup'!$A:$A,0),7)),0)+IFERROR(INDIRECT("'Final Calculation Sheet'!$T"&INDEX('Buyer Lookup'!$A:$AZ,MATCH($B$2,'Buyer Lookup'!$A:$A,0),8)),0)+IFERROR(INDIRECT("'Final Calculation Sheet'!$T"&INDEX('Buyer Lookup'!$A:$AZ,MATCH($B$2,'Buyer Lookup'!$A:$A,0),9)),0)+IFERROR(INDIRECT("'Final Calculation Sheet'!$T"&INDEX('Buyer Lookup'!$A:$AZ,MATCH($B$2,'Buyer Lookup'!$A:$A,0),10)),0)+IFERROR(INDIRECT("'Final Calculation Sheet'!$T"&INDEX('Buyer Lookup'!$A:$AZ,MATCH($B$2,'Buyer Lookup'!$A:$A,0),11)),0)+IFERROR(INDIRECT("'Final Calculation Sheet'!$T"&INDEX('Buyer Lookup'!$A:$AZ,MATCH($B$2,'Buyer Lookup'!$A:$A,0),12)),0)+IFERROR(INDIRECT("'Final Calculation Sheet'!$T"&INDEX('Buyer Lookup'!$A:$AZ,MATCH($B$2,'Buyer Lookup'!$A:$A,0),13)),0)+IFERROR(INDIRECT("'Final Calculation Sheet'!$T"&INDEX('Buyer Lookup'!$A:$AZ,MATCH($B$2,'Buyer Lookup'!$A:$A,0),14)),0) -> 197522 | C57: ← Sum across all lots for selected buyer
A58: Total SD Received (₹) | B58: =IFERROR(INDIRECT("'Final Calculation Sheet'!$U"&INDEX('Buyer Lookup'!$A:$AZ,MATCH($B$2,'Buyer Lookup'!$A:$A,0),2)),0)+IFERROR(INDIRECT("'Final Calculation Sheet'!$U"&INDEX('Buyer Lookup'!$A:$AZ,MATCH($B$2,'Buyer Lookup'!$A:$A,0),3)),0)+IFERROR(INDIRECT("'Final Calculation Sheet'!$U"&INDEX('Buyer Lookup'!$A:$AZ,MATCH($B$2,'Buyer Lookup'!$A:$A,0),4)),0)+IFERROR(INDIRECT("'Final Calculation Sheet'!$U"&INDEX('Buyer Lookup'!$A:$AZ,MATCH($B$2,'Buyer Lookup'!$A:$A,0),5)),0)+IFERROR(INDIRECT("'Final Calculation Sheet'!$U"&INDEX('Buyer Lookup'!$A:$AZ,MATCH($B$2,'Buyer Lookup'!$A:$A,0),6)),0)+IFERROR(INDIRECT("'Final Calculation Sheet'!$U"&INDEX('Buyer Lookup'!$A:$AZ,MATCH($B$2,'Buyer Lookup'!$A:$A,0),7)),0)+IFERROR(INDIRECT("'Final Calculation Sheet'!$U"&INDEX('Buyer Lookup'!$A:$AZ,MATCH($B$2,'Buyer Lookup'!$A:$A,0),8)),0)+IFERROR(INDIRECT("'Final Calculation Sheet'!$U"&INDEX('Buyer Lookup'!$A:$AZ,MATCH($B$2,'Buyer Lookup'!$A:$A,0),9)),0)+IFERROR(INDIRECT("'Final Calculation Sheet'!$U"&INDEX('Buyer Lookup'!$A:$AZ,MATCH($B$2,'Buyer Lookup'!$A:$A,0),10)),0)+IFERROR(INDIRECT("'Final Calculation Sheet'!$U"&INDEX('Buyer Lookup'!$A:$AZ,MATCH($B$2,'Buyer Lookup'!$A:$A,0),11)),0)+IFERROR(INDIRECT("'Final Calculation Sheet'!$U"&INDEX('Buyer Lookup'!$A:$AZ,MATCH($B$2,'Buyer Lookup'!$A:$A,0),12)),0)+IFERROR(INDIRECT("'Final Calculation Sheet'!$U"&INDEX('Buyer Lookup'!$A:$AZ,MATCH($B$2,'Buyer Lookup'!$A:$A,0),13)),0)+IFERROR(INDIRECT("'Final Calculation Sheet'!$U"&INDEX('Buyer Lookup'!$A:$AZ,MATCH($B$2,'Buyer Lookup'!$A:$A,0),14)),0) -> 197522 | C58: ← Sum across all lots for selected buyer
A59: Total FP Expected (₹) | B59: =IFERROR(INDIRECT("'Final Calculation Sheet'!$W"&INDEX('Buyer Lookup'!$A:$AZ,MATCH($B$2,'Buyer Lookup'!$A:$A,0),2)),0)+IFERROR(INDIRECT("'Final Calculation Sheet'!$W"&INDEX('Buyer Lookup'!$A:$AZ,MATCH($B$2,'Buyer Lookup'!$A:$A,0),3)),0)+IFERROR(INDIRECT("'Final Calculation Sheet'!$W"&INDEX('Buyer Lookup'!$A:$AZ,MATCH($B$2,'Buyer Lookup'!$A:$A,0),4)),0)+IFERROR(INDIRECT("'Final Calculation Sheet'!$W"&INDEX('Buyer Lookup'!$A:$AZ,MATCH($B$2,'Buyer Lookup'!$A:$A,0),5)),0)+IFERROR(INDIRECT("'Final Calculation Sheet'!$W"&INDEX('Buyer Lookup'!$A:$AZ,MATCH($B$2,'Buyer Lookup'!$A:$A,0),6)),0)+IFERROR(INDIRECT("'Final Calculation Sheet'!$W"&INDEX('Buyer Lookup'!$A:$AZ,MATCH($B$2,'Buyer Lookup'!$A:$A,0),7)),0)+IFERROR(INDIRECT("'Final Calculation Sheet'!$W"&INDEX('Buyer Lookup'!$A:$AZ,MATCH($B$2,'Buyer Lookup'!$A:$A,0),8)),0)+IFERROR(INDIRECT("'Final Calculation Sheet'!$W"&INDEX('Buyer Lookup'!$A:$AZ,MATCH($B$2,'Buyer Lookup'!$A:$A,0),9)),0)+IFERROR(INDIRECT("'Final Calculation Sheet'!$W"&INDEX('Buyer Lookup'!$A:$AZ,MATCH($B$2,'Buyer Lookup'!$A:$A,0),10)),0)+IFERROR(INDIRECT("'Final Calculation Sheet'!$W"&INDEX('Buyer Lookup'!$A:$AZ,MATCH($B$2,'Buyer Lookup'!$A:$A,0),11)),0)+IFERROR(INDIRECT("'Final Calculation Sheet'!$W"&INDEX('Buyer Lookup'!$A:$AZ,MATCH($B$2,'Buyer Lookup'!$A:$A,0),12)),0)+IFERROR(INDIRECT("'Final Calculation Sheet'!$W"&INDEX('Buyer Lookup'!$A:$AZ,MATCH($B$2,'Buyer Lookup'!$A:$A,0),13)),0)+IFERROR(INDIRECT("'Final Calculation Sheet'!$W"&INDEX('Buyer Lookup'!$A:$AZ,MATCH($B$2,'Buyer Lookup'!$A:$A,0),14)),0) -> 716215 | C59: ← Sum across all lots for selected buyer
A60: Total FP Received (₹) | B60: =IFERROR(INDIRECT("'Final Calculation Sheet'!$X"&INDEX('Buyer Lookup'!$A:$AZ,MATCH($B$2,'Buyer Lookup'!$A:$A,0),2)),0)+IFERROR(INDIRECT("'Final Calculation Sheet'!$X"&INDEX('Buyer Lookup'!$A:$AZ,MATCH($B$2,'Buyer Lookup'!$A:$A,0),3)),0)+IFERROR(INDIRECT("'Final Calculation Sheet'!$X"&INDEX('Buyer Lookup'!$A:$AZ,MATCH($B$2,'Buyer Lookup'!$A:$A,0),4)),0)+IFERROR(INDIRECT("'Final Calculation Sheet'!$X"&INDEX('Buyer Lookup'!$A:$AZ,MATCH($B$2,'Buyer Lookup'!$A:$A,0),5)),0)+IFERROR(INDIRECT("'Final Calculation Sheet'!$X"&INDEX('Buyer Lookup'!$A:$AZ,MATCH($B$2,'Buyer Lookup'!$A:$A,0),6)),0)+IFERROR(INDIRECT("'Final Calculation Sheet'!$X"&INDEX('Buyer Lookup'!$A:$AZ,MATCH($B$2,'Buyer Lookup'!$A:$A,0),7)),0)+IFERROR(INDIRECT("'Final Calculation Sheet'!$X"&INDEX('Buyer Lookup'!$A:$AZ,MATCH($B$2,'Buyer Lookup'!$A:$A,0),8)),0)+IFERROR(INDIRECT("'Final Calculation Sheet'!$X"&INDEX('Buyer Lookup'!$A:$AZ,MATCH($B$2,'Buyer Lookup'!$A:$A,0),9)),0)+IFERROR(INDIRECT("'Final Calculation Sheet'!$X"&INDEX('Buyer Lookup'!$A:$AZ,MATCH($B$2,'Buyer Lookup'!$A:$A,0),10)),0)+IFERROR(INDIRECT("'Final Calculation Sheet'!$X"&INDEX('Buyer Lookup'!$A:$AZ,MATCH($B$2,'Buyer Lookup'!$A:$A,0),11)),0)+IFERROR(INDIRECT("'Final Calculation Sheet'!$X"&INDEX('Buyer Lookup'!$A:$AZ,MATCH($B$2,'Buyer Lookup'!$A:$A,0),12)),0)+IFERROR(INDIRECT("'Final Calculation Sheet'!$X"&INDEX('Buyer Lookup'!$A:$AZ,MATCH($B$2,'Buyer Lookup'!$A:$A,0),13)),0)+IFERROR(INDIRECT("'Final Calculation Sheet'!$X"&INDEX('Buyer Lookup'!$A:$AZ,MATCH($B$2,'Buyer Lookup'!$A:$A,0),14)),0) -> 716216 | C60: ← Sum across all lots for selected buyer
A61: Total LPP Expected (₹) | B61: =IFERROR(INDIRECT("'Final Calculation Sheet'!$Z"&INDEX('Buyer Lookup'!$A:$AZ,MATCH($B$2,'Buyer Lookup'!$A:$A,0),2)),0)+IFERROR(INDIRECT("'Final Calculation Sheet'!$Z"&INDEX('Buyer Lookup'!$A:$AZ,MATCH($B$2,'Buyer Lookup'!$A:$A,0),3)),0)+IFERROR(INDIRECT("'Final Calculation Sheet'!$Z"&INDEX('Buyer Lookup'!$A:$AZ,MATCH($B$2,'Buyer Lookup'!$A:$A,0),4)),0)+IFERROR(INDIRECT("'Final Calculation Sheet'!$Z"&INDEX('Buyer Lookup'!$A:$AZ,MATCH($B$2,'Buyer Lookup'!$A:$A,0),5)),0)+IFERROR(INDIRECT("'Final Calculation Sheet'!$Z"&INDEX('Buyer Lookup'!$A:$AZ,MATCH($B$2,'Buyer Lookup'!$A:$A,0),6)),0)+IFERROR(INDIRECT("'Final Calculation Sheet'!$Z"&INDEX('Buyer Lookup'!$A:$AZ,MATCH($B$2,'Buyer Lookup'!$A:$A,0),7)),0)+IFERROR(INDIRECT("'Final Calculation Sheet'!$Z"&INDEX('Buyer Lookup'!$A:$AZ,MATCH($B$2,'Buyer Lookup'!$A:$A,0),8)),0)+IFERROR(INDIRECT("'Final Calculation Sheet'!$Z"&INDEX('Buyer Lookup'!$A:$AZ,MATCH($B$2,'Buyer Lookup'!$A:$A,0),9)),0)+IFERROR(INDIRECT("'Final Calculation Sheet'!$Z"&INDEX('Buyer Lookup'!$A:$AZ,MATCH($B$2,'Buyer Lookup'!$A:$A,0),10)),0)+IFERROR(INDIRECT("'Final Calculation Sheet'!$Z"&INDEX('Buyer Lookup'!$A:$AZ,MATCH($B$2,'Buyer Lookup'!$A:$A,0),11)),0)+IFERROR(INDIRECT("'Final Calculation Sheet'!$Z"&INDEX('Buyer Lookup'!$A:$AZ,MATCH($B$2,'Buyer Lookup'!$A:$A,0),12)),0)+IFERROR(INDIRECT("'Final Calculation Sheet'!$Z"&INDEX('Buyer Lookup'!$A:$AZ,MATCH($B$2,'Buyer Lookup'!$A:$A,0),13)),0)+IFERROR(INDIRECT("'Final Calculation Sheet'!$Z"&INDEX('Buyer Lookup'!$A:$AZ,MATCH($B$2,'Buyer Lookup'!$A:$A,0),14)),0) -> 0 | C61: ← Sum across all lots for selected buyer
A62: Total LPP Received (₹) | B62: =IFERROR(INDIRECT("'Final Calculation Sheet'!$AA"&INDEX('Buyer Lookup'!$A:$AZ,MATCH($B$2,'Buyer Lookup'!$A:$A,0),2)),0)+IFERROR(INDIRECT("'Final Calculation Sheet'!$AA"&INDEX('Buyer Lookup'!$A:$AZ,MATCH($B$2,'Buyer Lookup'!$A:$A,0),3)),0)+IFERROR(INDIRECT("'Final Calculation Sheet'!$AA"&INDEX('Buyer Lookup'!$A:$AZ,MATCH($B$2,'Buyer Lookup'!$A:$A,0),4)),0)+IFERROR(INDIRECT("'Final Calculation Sheet'!$AA"&INDEX('Buyer Lookup'!$A:$AZ,MATCH($B$2,'Buyer Lookup'!$A:$A,0),5)),0)+IFERROR(INDIRECT("'Final Calculation Sheet'!$AA"&INDEX('Buyer Lookup'!$A:$AZ,MATCH($B$2,'Buyer Lookup'!$A:$A,0),6)),0)+IFERROR(INDIRECT("'Final Calculation Sheet'!$AA"&INDEX('Buyer Lookup'!$A:$AZ,MATCH($B$2,'Buyer Lookup'!$A:$A,0),7)),0)+IFERROR(INDIRECT("'Final Calculation Sheet'!$AA"&INDEX('Buyer Lookup'!$A:$AZ,MATCH($B$2,'Buyer Lookup'!$A:$A,0),8)),0)+IFERROR(INDIRECT("'Final Calculation Sheet'!$AA"&INDEX('Buyer Lookup'!$A:$AZ,MATCH($B$2,'Buyer Lookup'!$A:$A,0),9)),0)+IFERROR(INDIRECT("'Final Calculation Sheet'!$AA"&INDEX('Buyer Lookup'!$A:$AZ,MATCH($B$2,'Buyer Lookup'!$A:$A,0),10)),0)+IFERROR(INDIRECT("'Final Calculation Sheet'!$AA"&INDEX('Buyer Lookup'!$A:$AZ,MATCH($B$2,'Buyer Lookup'!$A:$A,0),11)),0)+IFERROR(INDIRECT("'Final Calculation Sheet'!$AA"&INDEX('Buyer Lookup'!$A:$AZ,MATCH($B$2,'Buyer Lookup'!$A:$A,0),12)),0)+IFERROR(INDIRECT("'Final Calculation Sheet'!$AA"&INDEX('Buyer Lookup'!$A:$AZ,MATCH($B$2,'Buyer Lookup'!$A:$A,0),13)),0)+IFERROR(INDIRECT("'Final Calculation Sheet'!$AA"&INDEX('Buyer Lookup'!$A:$AZ,MATCH($B$2,'Buyer Lookup'!$A:$A,0),14)),0) -> 0 | C62: ← Sum across all lots for selected buyer
A63: Total Received (₹) | B63: =IFERROR(INDIRECT("'Final Calculation Sheet'!$AC"&INDEX('Buyer Lookup'!$A:$AZ,MATCH($B$2,'Buyer Lookup'!$A:$A,0),2)),0)+IFERROR(INDIRECT("'Final Calculation Sheet'!$AC"&INDEX('Buyer Lookup'!$A:$AZ,MATCH($B$2,'Buyer Lookup'!$A:$A,0),3)),0)+IFERROR(INDIRECT("'Final Calculation Sheet'!$AC"&INDEX('Buyer Lookup'!$A:$AZ,MATCH($B$2,'Buyer Lookup'!$A:$A,0),4)),0)+IFERROR(INDIRECT("'Final Calculation Sheet'!$AC"&INDEX('Buyer Lookup'!$A:$AZ,MATCH($B$2,'Buyer Lookup'!$A:$A,0),5)),0)+IFERROR(INDIRECT("'Final Calculation Sheet'!$AC"&INDEX('Buyer Lookup'!$A:$AZ,MATCH($B$2,'Buyer Lookup'!$A:$A,0),6)),0)+IFERROR(INDIRECT("'Final Calculation Sheet'!$AC"&INDEX('Buyer Lookup'!$A:$AZ,MATCH($B$2,'Buyer Lookup'!$A:$A,0),7)),0)+IFERROR(INDIRECT("'Final Calculation Sheet'!$AC"&INDEX('Buyer Lookup'!$A:$AZ,MATCH($B$2,'Buyer Lookup'!$A:$A,0),8)),0)+IFERROR(INDIRECT("'Final Calculation Sheet'!$AC"&INDEX('Buyer Lookup'!$A:$AZ,MATCH($B$2,'Buyer Lookup'!$A:$A,0),9)),0)+IFERROR(INDIRECT("'Final Calculation Sheet'!$AC"&INDEX('Buyer Lookup'!$A:$AZ,MATCH($B$2,'Buyer Lookup'!$A:$A,0),10)),0)+IFERROR(INDIRECT("'Final Calculation Sheet'!$AC"&INDEX('Buyer Lookup'!$A:$AZ,MATCH($B$2,'Buyer Lookup'!$A:$A,0),11)),0)+IFERROR(INDIRECT("'Final Calculation Sheet'!$AC"&INDEX('Buyer Lookup'!$A:$AZ,MATCH($B$2,'Buyer Lookup'!$A:$A,0),12)),0)+IFERROR(INDIRECT("'Final Calculation Sheet'!$AC"&INDEX('Buyer Lookup'!$A:$AZ,MATCH($B$2,'Buyer Lookup'!$A:$A,0),13)),0)+IFERROR(INDIRECT("'Final Calculation Sheet'!$AC"&INDEX('Buyer Lookup'!$A:$AZ,MATCH($B$2,'Buyer Lookup'!$A:$A,0),14)),0) -> 0 | C63: ← Sum across all lots for selected buyer
A64: Total Outstanding (₹) | B64: =IFERROR(INDIRECT("'Final Calculation Sheet'!$AD"&INDEX('Buyer Lookup'!$A:$AZ,MATCH($B$2,'Buyer Lookup'!$A:$A,0),2)),0)+IFERROR(INDIRECT("'Final Calculation Sheet'!$AD"&INDEX('Buyer Lookup'!$A:$AZ,MATCH($B$2,'Buyer Lookup'!$A:$A,0),3)),0)+IFERROR(INDIRECT("'Final Calculation Sheet'!$AD"&INDEX('Buyer Lookup'!$A:$AZ,MATCH($B$2,'Buyer Lookup'!$A:$A,0),4)),0)+IFERROR(INDIRECT("'Final Calculation Sheet'!$AD"&INDEX('Buyer Lookup'!$A:$AZ,MATCH($B$2,'Buyer Lookup'!$A:$A,0),5)),0)+IFERROR(INDIRECT("'Final Calculation Sheet'!$AD"&INDEX('Buyer Lookup'!$A:$AZ,MATCH($B$2,'Buyer Lookup'!$A:$A,0),6)),0)+IFERROR(INDIRECT("'Final Calculation Sheet'!$AD"&INDEX('Buyer Lookup'!$A:$AZ,MATCH($B$2,'Buyer Lookup'!$A:$A,0),7)),0)+IFERROR(INDIRECT("'Final Calculation Sheet'!$AD"&INDEX('Buyer Lookup'!$A:$AZ,MATCH($B$2,'Buyer Lookup'!$A:$A,0),8)),0)+IFERROR(INDIRECT("'Final Calculation Sheet'!$AD"&INDEX('Buyer Lookup'!$A:$AZ,MATCH($B$2,'Buyer Lookup'!$A:$A,0),9)),0)+IFERROR(INDIRECT("'Final Calculation Sheet'!$AD"&INDEX('Buyer Lookup'!$A:$AZ,MATCH($B$2,'Buyer Lookup'!$A:$A,0),10)),0)+IFERROR(INDIRECT("'Final Calculation Sheet'!$AD"&INDEX('Buyer Lookup'!$A:$AZ,MATCH($B$2,'Buyer Lookup'!$A:$A,0),11)),0)+IFERROR(INDIRECT("'Final Calculation Sheet'!$AD"&INDEX('Buyer Lookup'!$A:$AZ,MATCH($B$2,'Buyer Lookup'!$A:$A,0),12)),0)+IFERROR(INDIRECT("'Final Calculation Sheet'!$AD"&INDEX('Buyer Lookup'!$A:$AZ,MATCH($B$2,'Buyer Lookup'!$A:$A,0),13)),0)+IFERROR(INDIRECT("'Final Calculation Sheet'!$AD"&INDEX('Buyer Lookup'!$A:$AZ,MATCH($B$2,'Buyer Lookup'!$A:$A,0),14)),0) -> 0 | C64: ← Sum across all lots for selected buyer

Sheet Collapsible View
A1: MSTC LIMITED — Buyer-wise Collapsible Detail Sheet
A2: ► Use the row group controls on the LEFT MARGIN ( − / + buttons ) to collapse/expand each section within a buyer block
A3: Field / Buyer | B3: Lot 1 | C3: Lot 2 | D3: Lot 3 | E3: Lot 4 | F3: Lot 5 | G3: Lot 6 | H3: Lot 7 | I3: Lot 8 | J3: Lot 9 | K3: Lot 10 | L3: Lot 11 | M3: Lot 12 | N3: Lot 13 | O3: BUYER TOTAL
A4: AL HAMD TRADE CORPORATION (1 lot)
A5: Lot No. → | B5: 1763 | O5: Total
A6: ▸ LOT INFO
A7: Lot No. | B7: 1763
A8: Lot Name | B8: SCRAP COPPER OF T/F WINDING (Oil impregnated paper insulated T/F winding)
A9: Bid Sheet | B9: 21980
A10: Quantity | B10: 669
A11: Unit | B11: KG
A12: Rate (₹) | B12: 1181
A13: ▸ FINANCIALS
A14: Mat. Value (₹) | B14: 790089 | O14: =B14 -> 790089
A15: GST (₹) | B15: 142216 | O15: =B15 -> 142216
A16: Mat. Value + GST (₹) | B16: 932305 | O16: =B16 -> 932305
A17: TCS (₹) | B17: 18646 | O17: =B17 -> 18646
A18: TDS u/s 194(O) (₹) | B18: 790.089 | O18: =B18 -> 790.089
A19: Service Charge (₹) | B19: 20976.863 | O19: =B19 -> 20976.863
A20: TDS u/s 194(H) (₹) | B20: 355.54005 | O20: =B20 -> 355.54005
A21: Net Svc Charge (₹) | B21: 20621.323 | O21: =B21 -> 20621.323
A22: Svc Charge to MSTC (₹) | B22: 21411 | O22: =B22 -> 21411
A23: GST TDS Rate | B23: 0.02
A24: GST TDS (₹) | B24: 15802 | O24: =B24 -> 15802
A25: Total Receivables (₹) | B25: 913738 | O25: =B25 -> 913738
A26: ▸ SECURITY DEPOSIT
A27: SD Expected (₹) | B27: 197522 | O27: =B27 -> 197522
A28: SD Received (₹) | B28: 197522 | O28: =B28 -> 197522
A29: SD Receipt Date | B29: 24.08.2026
A30: ▸ FINAL PAYMENT
A31: FP Expected (₹) | B31: 716215 | O31: =B31 -> 716215
A32: FP Received (₹) | B32: 716216 | O32: =B32 -> 716216
A33: FP Receipt Date | B33: 18.08.2026
A34: ▸ LPP
A35: LPP Expected (₹) | B35: 0 | O35: =B35 -> 0
A36: LPP Received (₹) | O36: =B36 -> 0
A37: LPP Receipt Date
A38: ▸ SUMMARY
A39: Total Received (₹) | O39: =B39 -> 0
A40: Outstanding (₹) | B40: 0 | O40: =B40 -> 0
A41: ▸ DOCUMENT
A42: Invoice No. | B42: DR2640100029
A43: SAP Document | B43: 1800003271
A44: Doc./Invoice Date | B44: 24.08.2026
A45: ∑ AL HAMD TRADE CORPORATION — TOTALS | O45: 790089
A47: F R KHANS ENTERPRISES (2 lots)
A48: Lot No. → | B48: 1875 | C48: 1876 | O48: Total
A49: ▸ LOT INFO
A50: Lot No. | B50: 1875 | C50: 1876
A51: Lot Name | B51: Scrap of Copper of faulty AC compressor | C51: Scrap of MS (extracted from equip cage and empty Sf6 gas cylinder)
A52: Bid Sheet | B52: 21977 | C52: 21977
A53: Quantity | B53: 28 | C53: 3000
A54: Unit | B54: KG | C54: KG
A55: Rate (₹) | B55: 1456 | C55: 66
A56: ▸ FINANCIALS
A57: Mat. Value (₹) | B57: 40768 | C57: 198000 | O57: =B57+C57 -> 238768
A58: GST (₹) | B58: 7338 | C58: 35640 | O58: =B58+C58 -> 42978
A59: Mat. Value + GST (₹) | B59: 48106 | C59: 233640 | O59: =B59+C59 -> 281746
A60: TCS (₹) | B60: 962 | C60: 4673 | O60: =B60+C60 -> 5635
A61: TDS u/s 194(O) (₹) | B61: 40.768 | C61: 198 | O61: =B61+C61 -> 238.768
A62: Service Charge (₹) | B62: 1082.3904 | C62: 5256.9 | O62: =B62+C62 -> 6339.2904
A63: TDS u/s 194(H) (₹) | B63: 18.3456 | C63: 89.1 | O63: =B63+C63 -> 107.4456
A64: Net Svc Charge (₹) | B64: 1064.0448 | C64: 5167.8 | O64: =B64+C64 -> 6231.8448
A65: Svc Charge to MSTC (₹) | B65: 1105 | C65: 5366 | O65: =B65+C65 -> 6471
A66: GST TDS Rate | B66: 0 | C66: 0
A67: GST TDS (₹) | B67: 0 | C67: 0 | O67: =B67+C67 -> 0
A68: Total Receivables (₹) | B68: 47964 | C68: 232947 | O68: =B68+C68 -> 280911
A69: ▸ SECURITY DEPOSIT
A70: SD Expected (₹) | B70: 10192 | C70: 49500 | O70: =B70+C70 -> 59692
A71: SD Received (₹) | B71: 10192 | C71: 49500 | O71: =B71+C71 -> 59692
A72: SD Receipt Date | B72: 11.08.2026 | C72: 11.08.2026
A73: ▸ FINAL PAYMENT
A74: FP Expected (₹) | B74: 37772 | C74: 183447 | O74: =B74+C74 -> 221219
A75: FP Received (₹) | B75: 37772 | C75: 183446 | O75: =B75+C75 -> 221218
A76: FP Receipt Date | B76: 20.08.2026 | C76: 20.08.2026
A77: ▸ LPP
A78: LPP Expected (₹) | B78: 0 | C78: 0 | O78: =B78+C78 -> 0
A79: LPP Received (₹) | O79: =B79+C79 -> 0
A80: LPP Receipt Date
A81: ▸ SUMMARY
A82: Total Received (₹) | O82: =B82+C82 -> 0
A83: Outstanding (₹) | B83: 0 | C83: 1 | O83: =B83+C83 -> 1
A84: ▸ DOCUMENT
A85: Invoice No. | B85: DR2640100047 | C85: DR2640100048
A86: SAP Document | B86: 1800003346 | C86: 1800003347
A87: Doc./Invoice Date | B87: 27.08.2026 | C87: 27.08.2026
A88: ∑ F R KHANS ENTERPRISES — TOTALS | O88: 238768
A90: HIND TRADERS (1 lot)
A91: Lot No. → | B91: 2008 | O91: Total
A92: ▸ LOT INFO
A93: Lot No. | B93: 2008
A94: Lot Name | B94: Scrap of empty oil Druam
A95: Bid Sheet | B95: 21977
A96: Quantity | B96: 250
A97: Unit | B97: NO
A98: Rate (₹) | B98: 543
A99: ▸ FINANCIALS
A100: Mat. Value (₹) | B100: 135750 | O100: =B100 -> 135750
A101: GST (₹) | B101: 24435 | O101: =B101 -> 24435
A102: Mat. Value + GST (₹) | B102: 160185 | O102: =B102 -> 160185
...

Sheet Final Calculation Sheet
B1: MSTC LIMITED - COMBINED BID SHEET (Auctions 21977, 21978, 21979, 21980)
A2: Filter by Buyer ▼ | B2: (All Buyers) | F2: Filter by Lot No. ▼ | G2: (All Lots) | I2: ① Pick Buyer or Lot No. from dropdown ② Click the ▼ AutoFilter arrow in Row 3 to filter ③ Clear: select "(All Buyers)" / "(All Lots)"
A3: Quantity | B3: Lot Name | C3: Rate | D3: Bid Sheet | E3: Unit | F3: Lot No. | G3: Buyer | H3: Mat. Value | I3: GST | J3: Mat. Value + GST | K3: TCS | L3: TDS u/s 194(O) | M3: Service Charge to MSTC | N3: TDS u/s 194(H) | O3: Net Service Charge (post TDS 194H) | P3: Service charge to MSTC | Q3: GST TDS Rate | R3: GST TDS | S3: Total Receivables in Cash | T3: Security Deposit (Expected) | U3: Security Deposit (Received) | V3: Date of Receipt | W3: Final Payment (Expected) | X3: Final Payment (Received) | Y3: Date of Receipt | Z3: LPP Expected | AA3: LPP Received | AB3: Date of Recepit of LPP | AC3: Total Received | AD3: Outstanding | AE3: Invoice No. | AF3: SAP Document | AG3: Doc./Invoice Date
A4: 669 | B4: SCRAP COPPER OF T/F WINDING (Oil impregnated paper insulated T/F winding) | C4: 1181 | D4: 21980 | E4: KG | F4: 1763 | G4: AL HAMD TRADE CORPORATION | H4: 790089 | I4: 142216 | J4: 932305 | K4: 18646 | L4: 790.089 | M4: 20976.863 | N4: 355.54005 | O4: 20621.323 | P4: 21411 | Q4: 0.02 | R4: 15802 | S4: 913738 | T4: 197522 | U4: 197522 | V4: 24.08.2026 | W4: 716215 | X4: 716216 | Y4: 18.08.2026 | Z4: 0 | AD4: 0 | AE4: DR2640100029 | AF4: 1800003271 | AG4: 24.08.2026
A5: 270 | B5: Scrap of Empty oil drum | C5: 580 | D5: 21977 | E5: NO | F5: 1874 | G5: NATIONAL ENTERPRISES | H5: 156600 | I5: 28188 | J5: 184788 | K5: 3696 | L5: 156.6 | M5: 4157.73 | N5: 70.47 | O5: 4087.26 | P5: 4244 | Q5: 0 | R5: 0 | S5: 184240 | T5: 39150 | U5: 39150 | V5: 13.08.2026 | W5: 145090 | X5: 145090 | Y5: 24.08.2026 | Z5: 0 | AD5: 0 | AE5: DR2640100030 | AF5: 1800003302 | AG5: 27.08.2026
A6: 28 | B6: Scrap of Copper of faulty AC compressor | C6: 1456 | D6: 21977 | E6: KG | F6: 1875 | G6: F R KHANS ENTERPRISES | H6: 40768 | I6: 7338 | J6: 48106 | K6: 962 | L6: 40.768 | M6: 1082.3904 | N6: 18.3456 | O6: 1064.0448 | P6: 1105 | Q6: 0 | R6: 0 | S6: 47964 | T6: 10192 | U6: 10192 | V6: 11.08.2026 | W6: 37772 | X6: 37772 | Y6: 20.08.2026 | Z6: 0 | AD6: 0 | AE6: DR2640100047 | AF6: 1800003346 | AG6: 27.08.2026
A7: 3000 | B7: Scrap of MS (extracted from equip cage and empty Sf6 gas cylinder) | C7: 66 | D7: 21977 | E7: KG | F7: 1876 | G7: F R KHANS ENTERPRISES | H7: 198000 | I7: 35640 | J7: 233640 | K7: 4673 | L7: 198 | M7: 5256.9 | N7: 89.1 | O7: 5167.8 | P7: 5366 | Q7: 0 | R7: 0 | S7: 232947 | T7: 49500 | U7: 49500 | V7: 11.08.2026 | W7: 183447 | X7: 183446 | Y7: 20.08.2026 | Z7: 0 | AD7: 1 | AE7: DR2640100048 | AF7: 1800003347 | AG7: 27.08.2026
A8: 7253 | B8: SCRAP ACSR CONDUCTORS (Conductor Pieces) | C8: 227 | D8: 21980 | E8: KG | F8: 1923 | G8: OMKAR STEELS | H8: 1646431 | I8: 296358 | J8: 1942789 | K8: 38856 | L8: 1646.431 | M8: 43712.743 | N8: 740.89395 | O8: 42971.849 | P8: 44618 | Q8: 0.02 | R8: 32929 | S8: 1904097 | T8: 411608 | U8: 411608 | V8: 14.08.2026 | W8: 1492489 | X8: 1492490 | Y8: 24.08.2026 | Z8: 0 | AD8: -1 | AE8: DR2640100045 | AF8: 1800003315 | AG8: 27.08.2026
A9: 1 | B9: Scrap Power Transformer | C9: 2787314 | D9: 21977 | E9: NO | F9: 1976 | G9: SHAR JAHAN TRADERS | H9: 2787314 | I9: 501717 | J9: 3289031 | K9: 65781 | L9: 2787.314 | M9: 74003.187 | N9: 1254.2913 | O9: 72748.895 | P9: 75536 | Q9: 0 | R9: 0 | S9: 3279275 | T9: 696829 | U9: 696829 | V9: 13.08.2026 | W9: 2582446 | X9: 2582447.1 | Y9: 13.08.2026 | Z9: 0 | AD9: -1.0942916 | AE9: DR2640100023 | AF9: 1800003194 | AG9: 17.08.2026
A10: 4 | B10: Scrap of 132 KV CT | C10: 51511 | D10: 21977 | E10: NO | F10: 2002 | G10: NATIONAL ENTERPRISES | H10: 206044 | I10: 37088 | J10: 243132 | K10: 4863 | L10: 206.044 | M10: 5470.4682 | N10: 92.7198 | O10: 5377.7484 | P10: 5584 | Q10: 0 | R10: 0 | S10: 242411 | T10: 51511 | U10: 51511 | V10: 13.08.2026 | W10: 190900 | X10: 190900 | Y10: 24.08.2026 | Z10: 0 | AD10: 0 | AE10: DR2640100031 | AF10: 1800003303 | AG10: 27.08.2026
A11: 1 | B11: Scrap of 145 KV CB | C11: 65007 | D11: 21977 | E11: NO | F11: 2003 | G11: NATIONAL ENTERPRISES | H11: 65007 | I11: 11701 | J11: 76708 | K11: 1534 | L11: 65.007 | M11: 1725.9359 | N11: 29.25315 | O11: 1696.6827 | P11: 1762 | Q11: 0 | R11: 0 | S11: 76481 | T11: 16252 | U11: 16252 | V11: 13.08.2026 | W11: 60229 | X11: 60229 | Y11: 24.08.2026 | Z11: 0 | AD11: 0 | AE11: DR2640100032 | AF11: 1800003304 | AG11: 27.08.2026
A12: 1 | B12: Scrap of 220KV CT | C12: 70006 | D12: 21977 | E12: NO | F12: 2005 | G12: NATIONAL ENTERPRISES | H12: 70006 | I12: 12601 | J12: 82607 | K12: 1652 | L12: 70.006 | M12: 1858.6593 | N12: 31.5027 | O12: 1827.1566 | P12: 1897 | Q12: 0 | R12: 0 | S12: 82362 | T12: 17502 | U12: 17502 | V12: 13.08.2026 | W12: 64861 | X12: 64859 | Y12: 24.08.2026 | Z12: 0 | AD12: 1 | AE12: DR2640100033 | AF12: 1800003305 | AG12: 27.08.2026
A13: 25 | B13: Scrap of empty oil drums | C13: 700 | D13: 21977 | E13: NO | F13: 2006 | G13: STERLING ENTERPRISES | H13: 17500 | I13: 3150 | J13: 20650 | K13: 413 | L13: 17.5 | M13: 464.625 | N13: 7.875 | O13: 456.75 | P13: 474 | Q13: 0 | R13: 0 | S13: 20589 | T13: 4375 | U13: 4375 | V13: 11.08.2026 | W13: 16214 | X13: 16214 | Y13: 11.08.2026 | Z13: 0 | AD13: 0 | AE13: DR2640100018 | AF13: 1800003156 | AG13: 14.08.2026
A14: 1 | B14: SCRAP POWER TRANSFORMER | C14: 3857116 | D14: 21977 | E14: NO | F14: 2007 | G14: SHAR JAHAN TRADERS | H14: 3857116 | I14: 694281 | J14: 4551397 | K14: 91028 | L14: 3857.116 | M14: 102406.43 | N14: 1735.7022 | O14: 100670.73 | P14: 104528 | Q14: 0 | R14: 0 | S14: 4537897 | T14: 964279 | U14: 964279 | V14: 13.08.2026 | W14: 3573618 | X14: 3573618.9 | Y14: 13.08.2026 | Z14: 0 | AD14: -0.90570839 | AE14: DR2640100024 | AF14: 1800003196 | AG14: 17.08.2026
A15: 250 | B15: Scrap of empty oil Druam | C15: 543 | D15: 21977 | E15: NO | F15: 2008 | G15: HIND TRADERS | H15: 135750 | I15: 24435 | J15: 160185 | K15: 3204 | L15: 135.75 | M15: 3604.1625 | N15: 61.0875 | O15: 3543.075 | P15: 3679 | Q15: 0 | R15: 0 | S15: 159710 | T15: 33938 | U15: 33938 | V15: 14.08.2026 | W15: 125772 | X15: 125772 | Y15: 18.08.2026 | Z15: 0 | AD15: 0 | AE15: DR2640100026 | AF15: 1800003247 | AG15: 20.08.2026
... A26: 2 | B26: Scrap of 132 KV Wave Trap | C26: 14001 | D26: 21978 | E26: NO | F26: 2035 | G26: NATIONAL ENTERPRISES | H26: 28002 | I26: 5040 | J26: 33042 | K26: 661 | L26: 28.002 | M26: 743.4531 | N26: 12.6009 | O26: 730.8522 | P26: 759 | Q26: 0 | R26: 0 | S26: 32944 | T26: 7001 | U26: 7001 | V26: 13.08.2026 | W26: 25944 | X26: 25943 | Y26: 24.08.2026 | Z26: 0 | AD26: 0 | AE26: DR2640100037 | AF26: 1800003310 | AG26: 27.08.2026
A27: 8.2 | B27: Mix Scrap (Tower angles & 0.2 ACSR Condutor pieces) | C27: 67000 | D27: 21978 | E27: MT | F27: 2036 | G27: M I SCRAP TRADERS | H27: 549400 | I27: 98892 | J27: 648292 | K27: 12966 | L27: 549.4 | M27: 14586.57 | N27: 247.23 | O27: 14339.34 | P27: 14889 | Q27: 0.02 | R27: 10988 | S27: 635381 | T27: 137350 | U27: 137350 | V27: 14.08.2026 | W27: 498031 | Y27: 0 | Z27: 19448.76 | AD27: 498031
A28: 50 | B28: Scrap of empty oil Barrels | C28: 531 | D28: 21978 | E28: NO | F28: 2037 | G28: WATAN SCRAP TRADERS | H28: 26550 | I28: 4779 | J28: 31329 | K28: 627 | L28: 26.55 | M28: 704.9025 | N28: 11.9475 | O28: 692.955 | P28: 720 | Q28: 0 | R28: 0 | S28: 31236 | T28: 6638 | U28: 6638 | V28: 14.08.2026 | W28: 24599 | X28: 24598 | Y28: 21.08.2026 | Z28: 0 | AD28: 0 | AE28: DR2640100043 | AF28: 1800003318 | AG28: 27.08.2026
A29: 3 | B29: Scrap of 33 KV CT | C29: 90002 | D29: 21978 | E29: NO | F29: 2040 | G29: STERLING ENTERPRISES | H29: 270006 | I29: 48601 | J29: 318607 | K29: 6372 | L29: 270.006 | M29: 7168.6593 | N29: 121.5027 | O29: 7047.1566 | P29: 7317 | Q29: 0 | R29: 0 | S29: 317662 | T29: 67502 | U29: 67502 | V29: 11.08.2026 | W29: 250161 | Y29: 0 | Z29: 9558.2124 | AD29: 250160
A30: 5 | B30: Scrap of 132 KV CT | C30: 80000 | D30: 21979 | E30: NO | F30: 2043 | G30: NATIONAL ENTERPRISES | H30: 400000 | I30: 72000 | J30: 472000 | K30: 9440 | L30: 400 | M30: 10620 | N30: 180 | O30: 10440 | P30: 10840 | Q30: 0 | R30: 0 | S30: 470600 | T30: 100000 | U30: 100000 | V30: 13.08.2026 | W30: 370600 | X30: 370600 | Y30: 24.08.2026 | Z30: 0 | AD30: 0 | AE30: DR2640100038 | AF30: 1800003311 | AG30: 27.08.2026
A31: 670 | B31: Scrap of AAAC Earth wire | C31: 309 | D31: 21979 | E31: KG | F31: 2046 | G31: SAHARA ENTERPRISES | H31: 207030 | I31: 37265 | J31: 244295 | K31: 4886 | L31: 207.03 | M31: 5496.6465 | N31: 93.1635 | O31: 5403.483 | P31: 5611 | Q31: 0 | R31: 0 | S31: 243571 | T31: 51758 | U31: 51758 | V31: 11.08.2026 | W31: 191813 | X31: 191812 | Y31: 21.08.2026 | Z31: 0 | AD31: 1 | AE31: DR2640100041 | AF31: 1800003316 | AG31: 27.08.2026
A32: 2 | B32: Scrap of 220 KV CT | C32: 80006 | D32: 21979 | E32: NO | F32: 2055 | G32: NATIONAL ENTERPRISES | H32: 160012 | I32: 28802 | J32: 188814 | K32: 3776 | L32: 160.012 | M32: 4248.3186 | N32: 72.0054 | O32: 4176.3132 | P32: 4336 | Q32: 0 | R32: 0 | S32: 188254 | T32: 40003 | U32: 40003 | V32: 13.08.2026 | W32: 148251 | X32: 148251 | Y32: 24.08.2026 | Z32: 0 | AD32: 0 | AE32: DR2640100039 | AF32: 1800003312 | AG32: 27.08.2026
A33: 1 | B33: Scrap of 33 KV GCB | C33: 29502 | D33: 21979 | E33: NO | F33: 2059 | G33: NATIONAL ENTERPRISES | H33: 29502 | I33: 5310 | J33: 34812 | K33: 696 | L33: 29.502 | M33: 783.2781 | N33: 13.2759 | O33: 770.0022 | P33: 800 | Q33: 0 | R33: 0 | S33: 34709 | T33: 7376 | U33: 7376 | V33: 13.08.2026 | W33: 27334 | X33: 27332 | Y33: 24.08.2026 | Z33: 0 | AD33: 1 | AE33: DR2640100046 | AF33: 1800003313 | AG33: 27.08.2026
A34: 30 | B34: Scrap of Empty oil Barrels | C34: 702 | D34: 21979 | E34: NO | F34: 2062 | G34: STERLING ENTERPRISES | H34: 21060 | I34: 3791 | J34: 24851 | K34: 497 | L34: 21.06 | M34: 559.143 | N34: 9.477 | O34: 549.666 | P34: 571 | Q34: 0 | R34: 0 | S34: 24777 | T34: 5265 | U34: 5265 | V34: 11.08.2026 | W34: 19512 | X34: 19512 | Y34: 11.08.2026 | Z34: 0 | AD34: 0 | AE34: DR2640100022 | AF34: 1800003161 | AG34: 14.08.2026
A35: 150 | B35: Scrap of empty oil drums | C35: 571 | D35: 21980 | E35: NO | F35: 2067 | G35: WATAN SCRAP TRADERS | H35: 85650 | I35: 15417 | J35: 101067 | K35: 2021 | L35: 85.65 | M35: 2274.0075 | N35: 38.5425 | O35: 2235.465 | P35: 2321 | Q35: 0 | R35: 0 | S35: 100767 | T35: 21413 | U35: 21413 | V35: 14.08.2026 | W35: 79355 | X35: 79354 | Y35: 20.08.2026 | Z35: 0 | AD35: 0 | AE35: DR2640100027 | AF35: 1800003248 | AG35: 20.08.2026
A36: 1 | B36: Scrap of 33 KV CB | C36: 54000 | D36: 21980 | E36: NO | F36: 2069 | G36: STERLING ENTERPRISES | H36: 54000 | I36: 9720 | J36: 63720 | K36: 1274 | L36: 54 | M36: 1433.7 | N36: 24.3 | O36: 1409.4 | P36: 1463 | Q36: 0 | R36: 0 | S36: 63531 | T36: 13500 | U36: 13500 | V36: 11.08.2026 | W36: 50031 | Y36: 0 | Z36: 1911.6 | AD36: 50031
A37: 3 | B37: Scrap of 66 KV Isolater | C37: 25001 | D37: 21980 | E37: NO | F37: 2071 | G37: NATIONAL ENTERPRISES | H37: 75003 | I37: 13501 | J37: 88504 | K37: 1770 | L37: 75.003 | M37: 1991.3296 | N37: 33.75135 | O37: 1957.5783 | P37: 2033 | Q37: 0 | R37: 0 | S37: 88241 | T37: 18751 | U37: 18751 | V37: 13.08.2026 | W37: 69490 | X37: 69491 | Y37: 24.08.2026 | Z37: 0 | AD37: -1 | AE37: DR2640100040 | AF37: 1800003314 | AG37: 27.08.2026
A38: 3 | B38: Scrap of 132 KV CT | C38: 70001 | D38: 21980 | E38: NO | F38: 2086 | G38: KASHYAP TRADING CO | H38: 210003 | I38: 37801 | J38: 247804 | K38: 4956 | L38: 210.003 | M38: 5575.5796 | N38: 94.50135 | O38: 5481.0783 | P38: 5691 | Q38: 0 | R38: 0 | S38: 247069 | T38: 52501 | U38: 52501 | V38: 17.08.2026 | W38: 194568 | X38: 194568 | Y38: 17.08.2026 | Z38: 0 | AD38: 0 | AE38: DR2640100025 | AF38: 1800003226 | AG38: 19.08.2026
A39: 2 | B39: Scrap of 66 kv TBC C & R Panel | C39: 15006 | D39: 21980 | E39: NO | F39: 2089 | G39: S M ENTERPRISES | H39: 30012 | I39: 5402 | J39: 35414 | K39: 708 | L39: 30.012 | M39: 796.8186 | N39: 13.5054 | O39: 783.3132 | P39: 813 | Q39: 0 | R39: 0 | S39: 35309 | T39: 7503 | U39: 7503 | V39: 14.08.2026 | W39: 27806 | X39: 27806 | Y39: 01.09.2026 | Z39: 708.2832 | AD39: 0
A40: 3 | B40: Scrap of 132 KV CT | C40: 40003 | D40: 21980 | E40: NO | F40: 2091 | G40: S M ENTERPRISES | H40: 120009 | I40: 21602 | J40: 141611 | K40: 2832 | L40: 120.009 | M40: 3186.2389 | N40: 54.00405 | O40: 3132.2349 | P40: 3252 | Q40: 0 | R40: 0 | S40: 141191 | T40: 30002 | U40: 30002 | V40: 14.08.2026 | W40: 111188 | X40: 111189 | Y40: 01.09.2026 | Z40: 2832.2124 | AD40: 0
H41: 15130598 | I41: 2723508 | J41: 17854106 | K41: 357082 | L41: 15130.598 | M41: 401717.38 | N41: 6808.7691 | O41: 394908.61 | P41: 410039 | R41: 0 | S41: 17718123 | T41: 3782654 | U41: 3782654 | V41: 0 | W41: 13935473 | X41: 13137293 | Y41: 0 | AD41: 798176
H42: 15130598 | I42: 2723508 | J42: 17854106 | K42: 357082 | L42: 15131 | M42: 401717 | N42: 6809 | O42: 394908 | P42: 410039 | R42: 0 | S42: 17801149 | U42: 0 | X42: 798180
U43: Bal SD O/s | X43: Bal FP O/s

Sheet Buyer Lookup
A1: AL HAMD TRADE CORPORATION | B1: 4 | C1: 1763
A2: F R KHANS ENTERPRISES | B2: 6 | C2: 1874
A3: HIND TRADERS | B3: 15 | C3: 1875
A4: KASHYAP TRADING CO | B4: 38 | C4: 1876
A5: M I SCRAP TRADERS | B5: 27 | C5: 1923
A6: NATIONAL ENTERPRISES | B6: 5 | C6: 1976 | D6: 11 | E6: 12 | F6: 18 | G6: 19 | H6: 22 | I6: 24 | J6: 26 | K6: 30 | L6: 32 | M6: 33 | N6: 37
A7: NATIONAL SCRAP AND BUILDING MATERIAL SUPPLIER | B7: 21 | C7: 2002
A8: OMKAR STEELS | B8: 8 | C8: 2003
A9: S M ENTERPRISES | B9: 39 | C9: 2005
A10: SAHARA ENTERPRISES | B10: 31 | C10: 2006
A11: SHAR JAHAN TRADERS | B11: 9 | C11: 2007
A12: STERLING ENTERPRISES | B12: 13 | C12: 2008 | D12: 17 | E12: 23 | F12: 29 | G12: 34 | H12: 36
A13: WATAN SCRAP TRADERS | B13: 25 | C13: 2011 | D13: 35
C14: 2015
C15: 2018
C16: 2019
C17: 2020
C18: 2022
C19: 2023
C20: 2025
C21: 2027
C22: 2033
C23: 2035
C24: 2036
C25: 2037
... C37: 2091
